Workbook
Name TaskCat: Calc!$AV$2:$AV$2001
Name TaskDone: Calc!$BG$2:$BG$2001
Name TaskDue: Calc!$AW$2:$AW$2001
Name TaskStat: Calc!$AZ$2:$AZ$2001

Sheet Instructions
B2: TASK + HABIT TRACKER
C3: Tasks · planners · decision matrix · habits · mood · gratitude · goals — dark edition
C5: SETUP
C6: Set the planner start date (habit tracker & 1-year recurring horizon), schedule interval, day start time, week start and your categories & people. Yellow cells are inputs everywhere.
C8: RECURRING SCHEDULE
C9: Set up repeating tasks ONCE (daily, weekdays, weekly, bi-weekly, monthly, quarterly, annual or once) with times, priority, importance and person. They auto-fill the Recurring Log.
C11: VARIABLE TASKS
C12: Type one-off tasks here. DAYS LEFT, DURATION and DECISION (Eisenhower) calculate automatically.
C14: RECURRING LOG
C15: Every occurrence of your recurring tasks. Update STATUS, PROGRESS and NOTES only. If you change the schedule later, re-check statuses (rows re-sort by date).
C17: TASKS FILTER
C18: All tasks (recurring + variable) in one view. Sort by due date / priority / category / person / status and filter by date range, name, priority, importance, category, status, person and decision. Click ✎ edit to jump to the exact row.
C20: DASHBOARD
... C36: Built for Microsoft Excel 365 / 2021+. Sample data is included — overwrite or delete it.

Sheet Setup
C2: SETUP
C3: Yellow cells are inputs. Categories, people, statuses & priorities feed every dropdown.
C4: GENERAL | F4: CATEGORIES | H4: PEOPLE | J4: STATUS | L4: PRIORITY
C5: Planner start date | D5: 46266 | F5: colour follows row order
C6: Today (override) | F6: Business | H6: Me | J6: Not Started | L6: 1-Urgent
C7: Today used | D7: =IF(D6="",TODAY(),D6) | F7: Personal | H7: Sam | J7: In Progress | L7: 2-High
C8: Schedule interval (min) | D8: 30 | F8: Family | H8: Lucy | J8: Waiting | L8: 3-Medium
C9: Day starts at | D9: 0.29166667 | F9: Health | H9: Tony | J9: On Hold | L9: 4-Low
C10: Week starts on | D10: Monday | F10: Social | H10: Jamie | J10: Done
F11: Birthdays | H11: Rebecca | J11: Cancelled
C12: Planner start = first day of the habit tracker & recurring-task horizon (1 year).
J17: Status & priority lists are fixed (formulas rely on them).

Sheet Dashboard
W1: CATEGORY | Y1: PERSON
B2: TODAY IS | D2: TODAY'S TASKS | G2: =IFERROR(COUNTIFS(TaskDue,Setup!$D$7,TaskDone,1)/COUNTIFS(TaskDue,Setup!$D$7,TaskStat,"<>Cancelled"),0) | J2: THIS WEEK'S TASKS | M2: =IFERROR(COUNTIFS(TaskDue,">="&$AB$3,TaskDue,"<="&($AB$3+6),TaskDone,1)/COUNTIFS(TaskDue,">="&$AB$3,TaskDue,"<="&($AB$3+6),TaskStat,"<>Cancelled"),0) | P2: TASKS SUMMARY | W2: =IF(INDEX(Setup!$F$6:$F$15,1)="","",INDEX(Setup!$F$6:$F$15,1)) | X2: =IF(W2="","",COUNTIFS(Calc!$AW$2:$AW$2001,">="&$Q$3,Calc!$AW$2:$AW$2001,"<="&$Q$4,Calc!$BH$2:$BH$2001,1,Calc!$AV$2:$AV$2001,IF($Q$5="","*",$Q$5),Calc!$BC$2:$BC$2001,IF($Q$6="","*",$Q$6),Calc!$AV$2:$AV$2001,W2)) | Y2: =IF(INDEX(Setup!$H$6:$H$15,1)="","",INDEX(Setup!$H$6:$H$15,1)) | Z2: =IF(Y2="","",COUNTIFS(Calc!$AW$2:$AW$2001,">="&$Q$3,Calc!$AW$2:$AW$2001,"<="&$Q$4,Calc!$BH$2:$BH$2001,1,Calc!$AV$2:$AV$2001,IF($Q$5="","*",$Q$5),Calc!$BC$2:$BC$2001,IF($Q$6="","*",$Q$6),Calc!$BC$2:$BC$2001,Y2))
B3: =Setup!$D$7 | E3: TASK | F3: CATEGORY | G3: PRIORITY | K3: ="TASK · week of "&TEXT($AB$3,"d mmm") | L3: CATEGORY | M3: DUE | P3: Start date | Q3: =DATE(YEAR(Setup!$D$7),MONTH(Setup!$D$7),1) | S3: blank = all | W3: =IF(INDEX(Setup!$F$6:$F$15,2)="","",INDEX(Setup!$F$6:$F$15,2)) | X3: =IF(W3="","",COUNTIFS(Calc!$AW$2:$AW$2001,">="&$Q$3,Calc!$AW$2:$AW$2001,"<="&$Q$4,Calc!$BH$2:$BH$2001,1,Calc!$AV$2:$AV$2001,IF($Q$5="","*",$Q$5),Calc!$BC$2:$BC$2001,IF($Q$6="","*",$Q$6),Calc!$AV$2:$AV$2001,W3)) | Y3: =IF(INDEX(Setup!$H$6:$H$15,2)="","",INDEX(Setup!$H$6:$H$15,2)) | Z3: =IF(Y3="","",COUNTIFS(Calc!$AW$2:$AW$2001,">="&$Q$3,Calc!$AW$2:$AW$2001,"<="&$Q$4,Calc!$BH$2:$BH$2001,1,Calc!$AV$2:$AV$2001,IF($Q$5="","*",$Q$5),Calc!$BC$2:$BC$2001,IF($Q$6="","*",$Q$6),Calc!$BC$2:$BC$2001,Y3)) | AB3: =Setup!$D$7-MOD(WEEKDAY(Setup!$D$7,IF(Setup!$D$10="Monday",2,1))-1,7)
D4: =IF(H4="","",IF(INDEX(Calc!$BG$2:$BG$2001,H4)=1,"✓","○")) | E4: =IF(H4="","",INDEX(Calc!$AU$2:$AU$2001,H4)&"") | F4: =IF(H4="","",INDEX(Calc!$AV$2:$AV$2001,H4)&"") | G4: =IF(H4="","",INDEX(Calc!$BA$2:$BA$2001,H4)&"") | H4: =IFERROR(MOD(_xlfn.AGGREGATE(15,6,Calc!$BN$2:$BN$2001/(Calc!$AW$2:$AW$2001=Setup!$D$7),1),10000),"") | J4: =IF(N4="","",IF(INDEX(Calc!$BG$2:$BG$2001,N4)=1,"✓","○")) | K4: =IF(N4="","",INDEX(Calc!$AU$2:$AU$2001,N4)&"") | L4: =IF(N4="","",INDEX(Calc!$AV$2:$AV$2001,N4)&"") | M4: =IF(N4="","",INDEX(Calc!$AW$2:$AW$2001,N4)) | N4: =IFERROR(MATCH(SMALL(Calc!$BM$2:$BM$2001,1),Calc!$BM$2:$BM$2001,0),"") | P4: End date | Q4: =EOMONTH(Setup!$D$7,0) | W4: =IF(INDEX(Setup!$F$6:$F$15,3)="","",INDEX(Setup!$F$6:$F$15,3)) | X4: =IF(W4="","",COUNTIFS(Calc!$AW$2:$AW$2001,">="&$Q$3,Calc!$AW$2:$AW$2001,"<="&$Q$4,Calc!$BH$2:$BH$2001,1,Calc!$AV$2:$AV$2001,IF($Q$5="","*",$Q$5),Calc!$BC$2:$BC$2001,IF($Q$6="","*",$Q$6),Calc!$AV$2:$AV$2001,W4)) | Y4: =IF(INDEX(Setup!$H$6:$H$15,3)="","",INDEX(Setup!$H$6:$H$15,3)) | Z4: =IF(Y4="","",COUNTIFS(Calc!$AW$2:$AW$2001,">="&$Q$3,Calc!$AW$2:$AW$2001,"<="&$Q$4,Calc!$BH$2:$BH$2001,1,Calc!$AV$2:$AV$2001,IF($Q$5="","*",$Q$5),Calc!$BC$2:$BC$2001,IF($Q$6="","*",$Q$6),Calc!$BC$2:$BC$2001,Y4))
B5: =HYPERLINK("#'Setup'!A1","› SETUP") | D5: =IF(H5="","",IF(INDEX(Calc!$BG$2:$BG$2001,H5)=1,"✓","○")) | E5: =IF(H5="","",INDEX(Calc!$AU$2:$AU$2001,H5)&"") | F5: =IF(H5="","",INDEX(Calc!$AV$2:$AV$2001,H5)&"") | G5: =IF(H5="","",INDEX(Calc!$BA$2:$BA$2001,H5)&"") | H5: =IFERROR(MOD(_xlfn.AGGREGATE(15,6,Calc!$BN$2:$BN$2001/(Calc!$AW$2:$AW$2001=Setup!$D$7),2),10000),"") | J5: =IF(N5="","",IF(INDEX(Calc!$BG$2:$BG$2001,N5)=1,"✓","○")) | K5: =IF(N5="","",INDEX(Calc!$AU$2:$AU$2001,N5)&"") | L5: =IF(N5="","",INDEX(Calc!$AV$2:$AV$2001,N5)&"") | M5: =IF(N5="","",INDEX(Calc!$AW$2:$AW$2001,N5)) | N5: =IFERROR(MATCH(SMALL(Calc!$BM$2:$BM$2001,2),Calc!$BM$2:$BM$2001,0),"") | P5: Category | W5: =IF(INDEX(Setup!$F$6:$F$15,4)="","",INDEX(Setup!$F$6:$F$15,4)) | X5: =IF(W5="","",COUNTIFS(Calc!$AW$2:$AW$2001,">="&$Q$3,Calc!$AW$2:$AW$2001,"<="&$Q$4,Calc!$BH$2:$BH$2001,1,Calc!$AV$2:$AV$2001,IF($Q$5="","*",$Q$5),Calc!$BC$2:$BC$2001,IF($Q$6="","*",$Q$6),Calc!$AV$2:$AV$2001,W5)) | Y5: =IF(INDEX(Setup!$H$6:$H$15,4)="","",INDEX(Setup!$H$6:$H$15,4)) | Z5: =IF(Y5="","",COUNTIFS(Calc!$AW$2:$AW$2001,">="&$Q$3,Calc!$AW$2:$AW$2001,"<="&$Q$4,Calc!$BH$2:$BH$2001,1,Calc!$AV$2:$AV$2001,IF($Q$5="","*",$Q$5),Calc!$BC$2:$BC$2001,IF($Q$6="","*",$Q$6),Calc!$BC$2:$BC$2001,Y5))
D6: =IF(H6="","",IF(INDEX(Calc!$BG$2:$BG$2001,H6)=1,"✓","○")) | E6: =IF(H6="","",INDEX(Calc!$AU$2:$AU$2001,H6)&"") | F6: =IF(H6="","",INDEX(Calc!$AV$2:$AV$2001,H6)&"") | G6: =IF(H6="","",INDEX(Calc!$BA$2:$BA$2001,H6)&"") | H6: =IFERROR(MOD(_xlfn.AGGREGATE(15,6,Calc!$BN$2:$BN$2001/(Calc!$AW$2:$AW$2001=Setup!$D$7),3),10000),"") | J6: =IF(N6="","",IF(INDEX(Calc!$BG$2:$BG$2001,N6)=1,"✓","○")) | K6: =IF(N6="","",INDEX(Calc!$AU$2:$AU$2001,N6)&"") | L6: =IF(N6="","",INDEX(Calc!$AV$2:$AV$2001,N6)&"") | M6: =IF(N6="","",INDEX(Calc!$AW$2:$AW$2001,N6)) | N6: =IFERROR(MATCH(SMALL(Calc!$BM$2:$BM$2001,3),Calc!$BM$2:$BM$2001,0),"") | P6: Person | W6: =IF(INDEX(Setup!$F$6:$F$15,5)="","",INDEX(Setup!$F$6:$F$15,5)) | X6: =IF(W6="","",COUNTIFS(Calc!$AW$2:$AW$2001,">="&$Q$3,Calc!$AW$2:$AW$2001,"<="&$Q$4,Calc!$BH$2:$BH$2001,1,Calc!$AV$2:$AV$2001,IF($Q$5="","*",$Q$5),Calc!$BC$2:$BC$2001,IF($Q$6="","*",$Q$6),Calc!$AV$2:$AV$2001,W6)) | Y6: =IF(INDEX(Setup!$H$6:$H$15,5)="","",INDEX(Setup!$H$6:$H$15,5)) | Z6: =IF(Y6="","",COUNTIFS(Calc!$AW$2:$AW$2001,">="&$Q$3,Calc!$AW$2:$AW$2001,"<="&$Q$4,Calc!$BH$2:$BH$2001,1,Calc!$AV$2:$AV$2001,IF($Q$5="","*",$Q$5),Calc!$BC$2:$BC$2001,IF($Q$6="","*",$Q$6),Calc!$BC$2:$BC$2001,Y6))
B7: TASK LOG + FILTER | D7: =IF(H7="","",IF(INDEX(Calc!$BG$2:$BG$2001,H7)=1,"✓","○")) | E7: =IF(H7="","",INDEX(Calc!$AU$2:$AU$2001,H7)&"") | F7: =IF(H7="","",INDEX(Calc!$AV$2:$AV$2001,H7)&"") | G7: =IF(H7="","",INDEX(Calc!$BA$2:$BA$2001,H7)&"") | H7: =IFERROR(MOD(_xlfn.AGGREGATE(15,6,Calc!$BN$2:$BN$2001/(Calc!$AW$2:$AW$2001=Setup!$D$7),4),10000),"") | J7: =IF(N7="","",IF(INDEX(Calc!$BG$2:$BG$2001,N7)=1,"✓","○")) | K7: =IF(N7="","",INDEX(Calc!$AU$2:$AU$2001,N7)&"") | L7: =IF(N7="","",INDEX(Calc!$AV$2:$AV$2001,N7)&"") | M7: =IF(N7="","",INDEX(Calc!$AW$2:$AW$2001,N7)) | N7: =IFERROR(MATCH(SMALL(Calc!$BM$2:$BM$2001,4),Calc!$BM$2:$BM$2001,0),"") | W7: =IF(INDEX(Setup!$F$6:$F$15,6)="","",INDEX(Setup!$F$6:$F$15,6)) | X7: =IF(W7="","",COUNTIFS(Calc!$AW$2:$AW$2001,">="&$Q$3,Calc!$AW$2:$AW$2001,"<="&$Q$4,Calc!$BH$2:$BH$2001,1,Calc!$AV$2:$AV$2001,IF($Q$5="","*",$Q$5),Calc!$BC$2:$BC$2001,IF($Q$6="","*",$Q$6),Calc!$AV$2:$AV$2001,W7)) | Y7: =IF(INDEX(Setup!$H$6:$H$15,6)="","",INDEX(Setup!$H$6:$H$15,6)) | Z7: =IF(Y7="","",COUNTIFS(Calc!$AW$2:$AW$2001,">="&$Q$3,Calc!$AW$2:$AW$2001,"<="&$Q$4,Calc!$BH$2:$BH$2001,1,Calc!$AV$2:$AV$2001,IF($Q$5="","*",$Q$5),Calc!$BC$2:$BC$2001,IF($Q$6="","*",$Q$6),Calc!$BC$2:$BC$2001,Y7))
B8: =HYPERLINK("#'Recurring Schedule'!A1","› Recurring Schedule") | D8: =IF(H8="","",IF(INDEX(Calc!$BG$2:$BG$2001,H8)=1,"✓","○")) | E8: =IF(H8="","",INDEX(Calc!$AU$2:$AU$2001,H8)&"") | F8: =IF(H8="","",INDEX(Calc!$AV$2:$AV$2001,H8)&"") | G8: =IF(H8="","",INDEX(Calc!$BA$2:$BA$2001,H8)&"") | H8: =IFERROR(MOD(_xlfn.AGGREGATE(15,6,Calc!$BN$2:$BN$2001/(Calc!$AW$2:$AW$2001=Setup!$D$7),5),10000),"") | J8: =IF(N8="","",IF(INDEX(Calc!$BG$2:$BG$2001,N8)=1,"✓","○")) | K8: =IF(N8="","",INDEX(Calc!$AU$2:$AU$2001,N8)&"") | L8: =IF(N8="","",INDEX(Calc!$AV$2:$AV$2001,N8)&"") | M8: =IF(N8="","",INDEX(Calc!$AW$2:$AW$2001,N8)) | N8: =IFERROR(MATCH(SMALL(Calc!$BM$2:$BM$2001,5),Calc!$BM$2:$BM$2001,0),"") | P8: DECISION MATRIX | S8: BY STATUS | W8: =IF(INDEX(Setup!$F$6:$F$15,7)="","",INDEX(Setup!$F$6:$F$15,7)) | X8: =IF(W8="","",COUNTIFS(Calc!$AW$2:$AW$2001,">="&$Q$3,Calc!$AW$2:$AW$2001,"<="&$Q$4,Calc!$BH$2:$BH$2001,1,Calc!$AV$2:$AV$2001,IF($Q$5="","*",$Q$5),Calc!$BC$2:$BC$2001,IF($Q$6="","*",$Q$6),Calc!$AV$2:$AV$2001,W8)) | Y8: =IF(INDEX(Setup!$H$6:$H$15,7)="","",INDEX(Setup!$H$6:$H$15,7)) | Z8: =IF(Y8="","",COUNTIFS(Calc!$AW$2:$AW$2001,">="&$Q$3,Calc!$AW$2:$AW$2001,"<="&$Q$4,Calc!$BH$2:$BH$2001,1,Calc!$AV$2:$AV$2001,IF($Q$5="","*",$Q$5),Calc!$BC$2:$BC$2001,IF($Q$6="","*",$Q$6),Calc!$BC$2:$BC$2001,Y8))
B9: =HYPERLINK("#'Variable Tasks'!A1","› Variable Tasks") | D9: =IF(H9="","",IF(INDEX(Calc!$BG$2:$BG$2001,H9)=1,"✓","○")) | E9: =IF(H9="","",INDEX(Calc!$AU$2:$AU$2001,H9)&"") | F9: =IF(H9="","",INDEX(Calc!$AV$2:$AV$2001,H9)&"") | G9: =IF(H9="","",INDEX(Calc!$BA$2:$BA$2001,H9)&"") | H9: =IFERROR(MOD(_xlfn.AGGREGATE(15,6,Calc!$BN$2:$BN$2001/(Calc!$AW$2:$AW$2001=Setup!$D$7),6),10000),"") | J9: =IF(N9="","",IF(INDEX(Calc!$BG$2:$BG$2001,N9)=1,"✓","○")) | K9: =IF(N9="","",INDEX(Calc!$AU$2:$AU$2001,N9)&"") | L9: =IF(N9="","",INDEX(Calc!$AV$2:$AV$2001,N9)&"") | M9: =IF(N9="","",INDEX(Calc!$AW$2:$AW$2001,N9)) | N9: =IFERROR(MATCH(SMALL(Calc!$BM$2:$BM$2001,6),Calc!$BM$2:$BM$2001,0),"") | P9: DECISION | Q9: TO DO | R9: DONE | S9: =INDEX(Setup!$J$6:$J$11,1) | U9: =COUNTIFS(Calc!$AW$2:$AW$2001,">="&$Q$3,Calc!$AW$2:$AW$2001,"<="&$Q$4,Calc!$BH$2:$BH$2001,1,Calc!$AV$2:$AV$2001,IF($Q$5="","*",$Q$5),Calc!$BC$2:$BC$2001,IF($Q$6="","*",$Q$6),Calc!$AZ$2:$AZ$2001,S9) | W9: =IF(INDEX(Setup!$F$6:$F$15,8)="","",INDEX(Setup!$F$6:$F$15,8)) | X9: =IF(W9="","",COUNTIFS(Calc!$AW$2:$AW$2001,">="&$Q$3,Calc!$AW$2:$AW$2001,"<="&$Q$4,Calc!$BH$2:$BH$2001,1,Calc!$AV$2:$AV$2001,IF($Q$5="","*",$Q$5),Calc!$BC$2:$BC$2001,IF($Q$6="","*",$Q$6),Calc!$AV$2:$AV$2001,W9)) | Y9: =IF(INDEX(Setup!$H$6:$H$15,8)="","",INDEX(Setup!$H$6:$H$15,8)) | Z9: =IF(Y9="","",COUNTIFS(Calc!$AW$2:$AW$2001,">="&$Q$3,Calc!$AW$2:$AW$2001,"<="&$Q$4,Calc!$BH$2:$BH$2001,1,Calc!$AV$2:$AV$2001,IF($Q$5="","*",$Q$5),Calc!$BC$2:$BC$2001,IF($Q$6="","*",$Q$6),Calc!$BC$2:$BC$2001,Y9))
B10: =HYPERLINK("#'Recurring Log'!A1","› Recurring Log") | D10: =IF(H10="","",IF(INDEX(Calc!$BG$2:$BG$2001,H10)=1,"✓","○")) | E10: =IF(H10="","",INDEX(Calc!$AU$2:$AU$2001,H10)&"") | F10: =IF(H10="","",INDEX(Calc!$AV$2:$AV$2001,H10)&"") | G10: =IF(H10="","",INDEX(Calc!$BA$2:$BA$2001,H10)&"") | H10: =IFERROR(MOD(_xlfn.AGGREGATE(15,6,Calc!$BN$2:$BN$2001/(Calc!$AW$2:$AW$2001=Setup!$D$7),7),10000),"") | J10: =IF(N10="","",IF(INDEX(Calc!$BG$2:$BG$2001,N10)=1,"✓","○")) | K10: =IF(N10="","",INDEX(Calc!$AU$2:$AU$2001,N10)&"") | L10: =IF(N10="","",INDEX(Calc!$AV$2:$AV$2001,N10)&"") | M10: =IF(N10="","",INDEX(Calc!$AW$2:$AW$2001,N10)) | N10: =IFERROR(MATCH(SMALL(Calc!$BM$2:$BM$2001,7),Calc!$BM$2:$BM$2001,0),"") | P10: DO FIRST | Q10: =COUNTIFS(Calc!$AW$2:$AW$2001,">="&$Q$3,Calc!$AW$2:$AW$2001,"<="&$Q$4,Calc!$BH$2:$BH$2001,1,Calc!$AV$2:$AV$2001,IF($Q$5="","*",$Q$5),Calc!$BC$2:$BC$2001,IF($Q$6="","*",$Q$6),Calc!$BD$2:$BD$2001,"DO FIRST",Calc!$BG$2:$BG$2001,0) | R10: =COUNTIFS(Calc!$AW$2:$AW$2001,">="&$Q$3,Calc!$AW$2:$AW$2001,"<="&$Q$4,Calc!$BH$2:$BH$2001,1,Calc!$AV$2:$AV$2001,IF($Q$5="","*",$Q$5),Calc!$BC$2:$BC$2001,IF($Q$6="","*",$Q$6),Calc!$BD$2:$BD$2001,"DO FIRST",Calc!$BG$2:$BG$2001,1) | S10: =INDEX(Setup!$J$6:$J$11,2) | U10: =COUNTIFS(Calc!$AW$2:$AW$2001,">="&$Q$3,Calc!$AW$2:$AW$2001,"<="&$Q$4,Calc!$BH$2:$BH$2001,1,Calc!$AV$2:$AV$2001,IF($Q$5="","*",$Q$5),Calc!$BC$2:$BC$2001,IF($Q$6="","*",$Q$6),Calc!$AZ$2:$AZ$2001,S10) | W10: =IF(INDEX(Setup!$F$6:$F$15,9)="","",INDEX(Setup!$F$6:$F$15,9)) | X10: =IF(W10="","",COUNTIFS(Calc!$AW$2:$AW$2001,">="&$Q$3,Calc!$AW$2:$AW$2001,"<="&$Q$4,Calc!$BH$2:$BH$2001,1,Calc!$AV$2:$AV$2001,IF($Q$5="","*",$Q$5),Calc!$BC$2:$BC$2001,IF($Q$6="","*",$Q$6),Calc!$AV$2:$AV$2001,W10)) | Y10: =IF(INDEX(Setup!$H$6:$H$15,9)="","",INDEX(Setup!$H$6:$H$15,9)) | Z10: =IF(Y10="","",COUNTIFS(Calc!$AW$2:$AW$2001,">="&$Q$3,Calc!$AW$2:$AW$2001,"<="&$Q$4,Calc!$BH$2:$BH$2001,1,Calc!$AV$2:$AV$2001,IF($Q$5="","*",$Q$5),Calc!$BC$2:$BC$2001,IF($Q$6="","*",$Q$6),Calc!$BC$2:$BC$2001,Y10))
B11: =HYPERLINK("#'Tasks Filter'!A1","› Tasks Filter") | D11: =IF(H11="","",IF(INDEX(Calc!$BG$2:$BG$2001,H11)=1,"✓","○")) | E11: =IF(H11="","",INDEX(Calc!$AU$2:$AU$2001,H11)&"") | F11: =IF(H11="","",INDEX(Calc!$AV$2:$AV$2001,H11)&"") | G11: =IF(H11="","",INDEX(Calc!$BA$2:$BA$2001,H11)&"") | H11: =IFERROR(MOD(_xlfn.AGGREGATE(15,6,Calc!$BN$2:$BN$2001/(Calc!$AW$2:$AW$2001=Setup!$D$7),8),10000),"") | J11: =IF(N11="","",IF(INDEX(Calc!$BG$2:$BG$2001,N11)=1,"✓","○")) | K11: =IF(N11="","",INDEX(Calc!$AU$2:$AU$2001,N11)&"") | L11: =IF(N11="","",INDEX(Calc!$AV$2:$AV$2001,N11)&"") | M11: =IF(N11="","",INDEX(Calc!$AW$2:$AW$2001,N11)) | N11: =IFERROR(MATCH(SMALL(Calc!$BM$2:$BM$2001,8),Calc!$BM$2:$BM$2001,0),"") | P11: SCHEDULE | Q11: =COUNTIFS(Calc!$AW$2:$AW$2001,">="&$Q$3,Calc!$AW$2:$AW$2001,"<="&$Q$4,Calc!$BH$2:$BH$2001,1,Calc!$AV$2:$AV$2001,IF($Q$5="","*",$Q$5),Calc!$BC$2:$BC$2001,IF($Q$6="","*",$Q$6),Calc!$BD$2:$BD$2001,"SCHEDULE",Calc!$BG$2:$BG$2001,0) | R11: =COUNTIFS(Calc!$AW$2:$AW$2001,">="&$Q$3,Calc!$AW$2:$AW$2001,"<="&$Q$4,Calc!$BH$2:$BH$2001,1,Calc!$AV$2:$AV$2001,IF($Q$5="","*",$Q$5),Calc!$BC$2:$BC$2001,IF($Q$6="","*",$Q$6),Calc!$BD$2:$BD$2001,"SCHEDULE",Calc!$BG$2:$BG$2001,1) | S11: =INDEX(Setup!$J$6:$J$11,3) | U11: =COUNTIFS(Calc!$AW$2:$AW$2001,">="&$Q$3,Calc!$AW$2:$AW$2001,"<="&$Q$4,Calc!$BH$2:$BH$2001,1,Calc!$AV$2:$AV$2001,IF($Q$5="","*",$Q$5),Calc!$BC$2:$BC$2001,IF($Q$6="","*",$Q$6),Calc!$AZ$2:$AZ$2001,S11) | W11: =IF(INDEX(Setup!$F$6:$F$15,10)="","",INDEX(Setup!$F$6:$F$15,10)) | X11: =IF(W11="","",COUNTIFS(Calc!$AW$2:$AW$2001,">="&$Q$3,Calc!$AW$2:$AW$2001,"<="&$Q$4,Calc!$BH$2:$BH$2001,1,Calc!$AV$2:$AV$2001,IF($Q$5="","*",$Q$5),Calc!$BC$2:$BC$2001,IF($Q$6="","*",$Q$6),Calc!$AV$2:$AV$2001,W11)) | Y11: =IF(INDEX(Setup!$H$6:$H$15,10)="","",INDEX(Setup!$H$6:$H$15,10)) | Z11: =IF(Y11="","",COUNTIFS(Calc!$AW$2:$AW$2001,">="&$Q$3,Calc!$AW$2:$AW$2001,"<="&$Q$4,Calc!$BH$2:$BH$2001,1,Calc!$AV$2:$AV$2001,IF($Q$5="","*",$Q$5),Calc!$BC$2:$BC$2001,IF($Q$6="","*",$Q$6),Calc!$BC$2:$BC$2001,Y11))
B12: =HYPERLINK("#'Gratitude Log'!A1","› Gratitude Log") | D12: =IF(H12="","",IF(INDEX(Calc!$BG$2:$BG$2001,H12)=1,"✓","○")) | E12: =IF(H12="","",INDEX(Calc!$AU$2:$AU$2001,H12)&"") | F12: =IF(H12="","",INDEX(Calc!$AV$2:$AV$2001,H12)&"") | G12: =IF(H12="","",INDEX(Calc!$BA$2:$BA$2001,H12)&"") | H12: =IFERROR(MOD(_xlfn.AGGREGATE(15,6,Calc!$BN$2:$BN$2001/(Calc!$AW$2:$AW$2001=Setup!$D$7),9),10000),"") | J12: =IF(N12="","",IF(INDEX(Calc!$BG$2:$BG$2001,N12)=1,"✓","○")) | K12: =IF(N12="","",INDEX(Calc!$AU$2:$AU$2001,N12)&"") | L12: =IF(N12="","",INDEX(Calc!$AV$2:$AV$2001,N12)&"") | M12: =IF(N12="","",INDEX(Calc!$AW$2:$AW$2001,N12)) | N12: =IFERROR(MATCH(SMALL(Calc!$BM$2:$BM$2001,9),Calc!$BM$2:$BM$2001,0),"") | P12: DELEGATE | Q12: =COUNTIFS(Calc!$AW$2:$AW$2001,">="&$Q$3,Calc!$AW$2:$AW$2001,"<="&$Q$4,Calc!$BH$2:$BH$2001,1,Calc!$AV$2:$AV$2001,IF($Q$5="","*",$Q$5),Calc!$BC$2:$BC$2001,IF($Q$6="","*",$Q$6),Calc!$BD$2:$BD$2001,"DELEGATE",Calc!$BG$2:$BG$2001,0) | R12: =COUNTIFS(Calc!$AW$2:$AW$2001,">="&$Q$3,Calc!$AW$2:$AW$2001,"<="&$Q$4,Calc!$BH$2:$BH$2001,1,Calc!$AV$2:$AV$2001,IF($Q$5="","*",$Q$5),Calc!$BC$2:$BC$2001,IF($Q$6="","*",$Q$6),Calc!$BD$2:$BD$2001,"DELEGATE",Calc!$BG$2:$BG$2001,1) | S12: =INDEX(Setup!$J$6:$J$11,4) | U12: =COUNTIFS(Calc!$AW$2:$AW$2001,">="&$Q$3,Calc!$AW$2:$AW$2001,"<="&$Q$4,Calc!$BH$2:$BH$2001,1,Calc!$AV$2:$AV$2001,IF($Q$5="","*",$Q$5),Calc!$BC$2:$BC$2001,IF($Q$6="","*",$Q$6),Calc!$AZ$2:$AZ$2001,S12)
B13: =HYPERLINK("#'Habit Tracker'!A1","› Habit Tracker") | D13: =IF(H13="","",IF(INDEX(Calc!$BG$2:$BG$2001,H13)=1,"✓","○")) | E13: =IF(H13="","",INDEX(Calc!$AU$2:$AU$2001,H13)&"") | F13: =IF(H13="","",INDEX(Calc!$AV$2:$AV$2001,H13)&"") | G13: =IF(H13="","",INDEX(Calc!$BA$2:$BA$2001,H13)&"") | H13: =IFERROR(MOD(_xlfn.AGGREGATE(15,6,Calc!$BN$2:$BN$2001/(Calc!$AW$2:$AW$2001=Setup!$D$7),10),10000),"") | J13: =IF(N13="","",IF(INDEX(Calc!$BG$2:$BG$2001,N13)=1,"✓","○")) | K13: =IF(N13="","",INDEX(Calc!$AU$2:$AU$2001,N13)&"") | L13: =IF(N13="","",INDEX(Calc!$AV$2:$AV$2001,N13)&"") | M13: =IF(N13="","",INDEX(Calc!$AW$2:$AW$2001,N13)) | N13: =IFERROR(MATCH(SMALL(Calc!$BM$2:$BM$2001,10),Calc!$BM$2:$BM$2001,0),"") | P13: DELETE | Q13: =COUNTIFS(Calc!$AW$2:$AW$2001,">="&$Q$3,Calc!$AW$2:$AW$2001,"<="&$Q$4,Calc!$BH$2:$BH$2001,1,Calc!$AV$2:$AV$2001,IF($Q$5="","*",$Q$5),Calc!$BC$2:$BC$2001,IF($Q$6="","*",$Q$6),Calc!$BD$2:$BD$2001,"DELETE",Calc!$BG$2:$BG$2001,0) | R13: =COUNTIFS(Calc!$AW$2:$AW$2001,">="&$Q$3,Calc!$AW$2:$AW$2001,"<="&$Q$4,Calc!$BH$2:$BH$2001,1,Calc!$AV$2:$AV$2001,IF($Q$5="","*",$Q$5),Calc!$BC$2:$BC$2001,IF($Q$6="","*",$Q$6),Calc!$BD$2:$BD$2001,"DELETE",Calc!$BG$2:$BG$2001,1) | S13: =INDEX(Setup!$J$6:$J$11,5) | U13: =COUNTIFS(Calc!$AW$2:$AW$2001,">="&$Q$3,Calc!$AW$2:$AW$2001,"<="&$Q$4,Calc!$BH$2:$BH$2001,1,Calc!$AV$2:$AV$2001,IF($Q$5="","*",$Q$5),Calc!$BC$2:$BC$2001,IF($Q$6="","*",$Q$6),Calc!$AZ$2:$AZ$2001,S13)
D14: =IF(H14="","",IF(INDEX(Calc!$BG$2:$BG$2001,H14)=1,"✓","○")) | E14: =IF(H14="","",INDEX(Calc!$AU$2:$AU$2001,H14)&"") | F14: =IF(H14="","",INDEX(Calc!$AV$2:$AV$2001,H14)&"") | G14: =IF(H14="","",INDEX(Calc!$BA$2:$BA$2001,H14)&"") | H14: =IFERROR(MOD(_xlfn.AGGREGATE(15,6,Calc!$BN$2:$BN$2001/(Calc!$AW$2:$AW$2001=Setup!$D$7),11),10000),"") | J14: =IF(N14="","",IF(INDEX(Calc!$BG$2:$BG$2001,N14)=1,"✓","○")) | K14: =IF(N14="","",INDEX(Calc!$AU$2:$AU$2001,N14)&"") | L14: =IF(N14="","",INDEX(Calc!$AV$2:$AV$2001,N14)&"") | M14: =IF(N14="","",INDEX(Calc!$AW$2:$AW$2001,N14)) | N14: =IFERROR(MATCH(SMALL(Calc!$BM$2:$BM$2001,11),Calc!$BM$2:$BM$2001,0),"") | S14: =INDEX(Setup!$J$6:$J$11,6) | U14: =COUNTIFS(Calc!$AW$2:$AW$2001,">="&$Q$3,Calc!$AW$2:$AW$2001,"<="&$Q$4,Calc!$BH$2:$BH$2001,1,Calc!$AV$2:$AV$2001,IF($Q$5="","*",$Q$5),Calc!$BC$2:$BC$2001,IF($Q$6="","*",$Q$6),Calc!$AZ$2:$AZ$2001,S14)
B15: DASHBOARDS | D15: =IF(H15="","",IF(INDEX(Calc!$BG$2:$BG$2001,H15)=1,"✓","○")) | E15: =IF(H15="","",INDEX(Calc!$AU$2:$AU$2001,H15)&"") | F15: =IF(H15="","",INDEX(Calc!$AV$2:$AV$2001,H15)&"") | G15: =IF(H15="","",INDEX(Calc!$BA$2:$BA$2001,H15)&"") | H15: =IFERROR(MOD(_xlfn.AGGREGATE(15,6,Calc!$BN$2:$BN$2001/(Calc!$AW$2:$AW$2001=Setup!$D$7),12),10000),"") | J15: =IF(N15="","",IF(INDEX(Calc!$BG$2:$BG$2001,N15)=1,"✓","○")) | K15: =IF(N15="","",INDEX(Calc!$AU$2:$AU$2001,N15)&"") | L15: =IF(N15="","",INDEX(Calc!$AV$2:$AV$2001,N15)&"") | M15: =IF(N15="","",INDEX(Calc!$AW$2:$AW$2001,N15)) | N15: =IFERROR(MATCH(SMALL(Calc!$BM$2:$BM$2001,12),Calc!$BM$2:$BM$2001,0),"")
B16: =HYPERLINK("#'Daily'!A1","› Daily") | D16: =IF(H16="","",IF(INDEX(Calc!$BG$2:$BG$2001,H16)=1,"✓","○")) | E16: =IF(H16="","",INDEX(Calc!$AU$2:$AU$2001,H16)&"") | F16: =IF(H16="","",INDEX(Calc!$AV$2:$AV$2001,H16)&"") | G16: =IF(H16="","",INDEX(Calc!$BA$2:$BA$2001,H16)&"") | H16: =IFERROR(MOD(_xlfn.AGGREGATE(15,6,Calc!$BN$2:$BN$2001/(Calc!$AW$2:$AW$2001=Setup!$D$7),13),10000),"") | J16: =IF(N16="","",IF(INDEX(Calc!$BG$2:$BG$2001,N16)=1,"✓","○")) | K16: =IF(N16="","",INDEX(Calc!$AU$2:$AU$2001,N16)&"") | L16: =IF(N16="","",INDEX(Calc!$AV$2:$AV$2001,N16)&"") | M16: =IF(N16="","",INDEX(Calc!$AW$2:$AW$2001,N16)) | N16: =IFERROR(MATCH(SMALL(Calc!$BM$2:$BM$2001,13),Calc!$BM$2:$BM$2001,0),"") | P16: TASKS BY CATEGORY
B17: =HYPERLINK("#'Weekly'!A1","› Weekly") | D17: =IF(H17="","",IF(INDEX(Calc!$BG$2:$BG$2001,H17)=1,"✓","○")) | E17: =IF(H17="","",INDEX(Calc!$AU$2:$AU$2001,H17)&"") | F17: =IF(H17="","",INDEX(Calc!$AV$2:$AV$2001,H17)&"") | G17: =IF(H17="","",INDEX(Calc!$BA$2:$BA$2001,H17)&"") | H17: =IFERROR(MOD(_xlfn.AGGREGATE(15,6,Calc!$BN$2:$BN$2001/(Calc!$AW$2:$AW$2001=Setup!$D$7),14),10000),"") | J17: =IF(N17="","",IF(INDEX(Calc!$BG$2:$BG$2001,N17)=1,"✓","○")) | K17: =IF(N17="","",INDEX(Calc!$AU$2:$AU$2001,N17)&"") | L17: =IF(N17="","",INDEX(Calc!$AV$2:$AV$2001,N17)&"") | M17: =IF(N17="","",INDEX(Calc!$AW$2:$AW$2001,N17)) | N17: =IFERROR(MATCH(SMALL(Calc!$BM$2:$BM$2001,14),Calc!$BM$2:$BM$2001,0),"")
B18: =HYPERLINK("#'Monthly'!A1","› Monthly") | J18: =IF(N18="","",IF(INDEX(Calc!$BG$2:$BG$2001,N18)=1,"✓","○")) | K18: =IF(N18="","",INDEX(Calc!$AU$2:$AU$2001,N18)&"") | L18: =IF(N18="","",INDEX(Calc!$AV$2:$AV$2001,N18)&"") | M18: =IF(N18="","",INDEX(Calc!$AW$2:$AW$2001,N18)) | N18: =IFERROR(MATCH(SMALL(Calc!$BM$2:$BM$2001,15),Calc!$BM$2:$BM$2001,0),"")
B19: =HYPERLINK("#'Decision Matrix'!A1","› Decision Matrix") | J19: =IF(N19="","",IF(INDEX(Calc!$BG$2:$BG$2001,N19)=1,"✓","○")) | K19: =IF(N19="","",INDEX(Calc!$AU$2:$AU$2001,N19)&"") | L19: =IF(N19="","",INDEX(Calc!$AV$2:$AV$2001,N19)&"") | M19: =IF(N19="","",INDEX(Calc!$AW$2:$AW$2001,N19)) | N19: =IFERROR(MATCH(SMALL(Calc!$BM$2:$BM$2001,16),Calc!$BM$2:$BM$2001,0),"")
D20: OVERDUE TASKS | G20: =COUNT(Calc!$BL$2:$BL$2001) | J20: =IF(N20="","",IF(INDEX(Calc!$BG$2:$BG$2001,N20)=1,"✓","○")) | K20: =IF(N20="","",INDEX(Calc!$AU$2:$AU$2001,N20)&"") | L20: =IF(N20="","",INDEX(Calc!$AV$2:$AV$2001,N20)&"") | M20: =IF(N20="","",INDEX(Calc!$AW$2:$AW$2001,N20)) | N20: =IFERROR(MATCH(SMALL(Calc!$BM$2:$BM$2001,17),Calc!$BM$2:$BM$2001,0),"")
B21: BONUS | E21: TASK | F21: DAYS LATE | G21: PRIORITY | J21: =IF(N21="","",IF(INDEX(Calc!$BG$2:$BG$2001,N21)=1,"✓","○")) | K21: =IF(N21="","",INDEX(Calc!$AU$2:$AU$2001,N21)&"") | L21: =IF(N21="","",INDEX(Calc!$AV$2:$AV$2001,N21)&"") | M21: =IF(N21="","",INDEX(Calc!$AW$2:$AW$2001,N21)) | N21: =IFERROR(MATCH(SMALL(Calc!$BM$2:$BM$2001,18),Calc!$BM$2:$BM$2001,0),"")
B22: =HYPERLINK("#'Goals'!A1","› Goals") | D22: =IF(I22="","",IF(INDEX(Calc!$BG$2:$BG$2001,I22)=1,"✓","○")) | E22: =IF(I22="","",INDEX(Calc!$AU$2:$AU$2001,I22)&"") | F22: =IF(I22="","",Setup!$D$7-INDEX(Calc!$AW$2:$AW$2001,I22)) | G22: =IF(I22="","",INDEX(Calc!$BA$2:$BA$2001,I22)&"") | I22: =IFERROR(MATCH(SMALL(Calc!$BL$2:$BL$2001,1),Calc!$BL$2:$BL$2001,0),"") | J22: =IF(N22="","",IF(INDEX(Calc!$BG$2:$BG$2001,N22)=1,"✓","○")) | K22: =IF(N22="","",INDEX(Calc!$AU$2:$AU$2001,N22)&"") | L22: =IF(N22="","",INDEX(Calc!$AV$2:$AV$2001,N22)&"") | M22: =IF(N22="","",INDEX(Calc!$AW$2:$AW$2001,N22)) | N22: =IFERROR(MATCH(SMALL(Calc!$BM$2:$BM$2001,19),Calc!$BM$2:$BM$2001,0),"")
B23: =HYPERLINK("#'Instructions'!A1","› Instructions") | D23: =IF(I23="","",IF(INDEX(Calc!$BG$2:$BG$2001,I23)=1,"✓","○")) | E23: =IF(I23="","",INDEX(Calc!$AU$2:$AU$2001,I23)&"") | F23: =IF(I23="","",Setup!$D$7-INDEX(Calc!$AW$2:$AW$2001,I23)) | G23: =IF(I23="","",INDEX(Calc!$BA$2:$BA$2001,I23)&"") | I23: =IFERROR(MATCH(SMALL(Calc!$BL$2:$BL$2001,2),Calc!$BL$2:$BL$2001,0),"") | J23: =IF(N23="","",IF(INDEX(Calc!$BG$2:$BG$2001,N23)=1,"✓","○")) | K23: =IF(N23="","",INDEX(Calc!$AU$2:$AU$2001,N23)&"") | L23: =IF(N23="","",INDEX(Calc!$AV$2:$AV$2001,N23)&"") | M23: =IF(N23="","",INDEX(Calc!$AW$2:$AW$2001,N23)) | N23: =IFERROR(MATCH(SMALL(Calc!$BM$2:$BM$2001,20),Calc!$BM$2:$BM$2001,0),"")
D24: =IF(I24="","",IF(INDEX(Calc!$BG$2:$BG$2001,I24)=1,"✓","○")) | E24: =IF(I24="","",INDEX(Calc!$AU$2:$AU$2001,I24)&"") | F24: =IF(I24="","",Setup!$D$7-INDEX(Calc!$AW$2:$AW$2001,I24)) | G24: =IF(I24="","",INDEX(Calc!$BA$2:$BA$2001,I24)&"") | I24: =IFERROR(MATCH(SMALL(Calc!$BL$2:$BL$2001,3),Calc!$BL$2:$BL$2001,0),"") | J24: =IF(N24="","",IF(INDEX(Calc!$BG$2:$BG$2001,N24)=1,"✓","○")) | K24: =IF(N24="","",INDEX(Calc!$AU$2:$AU$2001,N24)&"") | L24: =IF(N24="","",INDEX(Calc!$AV$2:$AV$2001,N24)&"") | M24: =IF(N24="","",INDEX(Calc!$AW$2:$AW$2001,N24)) | N24: =IFERROR(MATCH(SMALL(Calc!$BM$2:$BM$2001,21),Calc!$BM$2:$BM$2001,0),"")
D25: =IF(I25="","",IF(INDEX(Calc!$BG$2:$BG$2001,I25)=1,"✓","○")) | E25: =IF(I25="","",INDEX(Calc!$AU$2:$AU$2001,I25)&"") | F25: =IF(I25="","",Setup!$D$7-INDEX(Calc!$AW$2:$AW$2001,I25)) | G25: =IF(I25="","",INDEX(Calc!$BA$2:$BA$2001,I25)&"") | I25: =IFERROR(MATCH(SMALL(Calc!$BL$2:$BL$2001,4),Calc!$BL$2:$BL$2001,0),"") | J25: =IF(N25="","",IF(INDEX(Calc!$BG$2:$BG$2001,N25)=1,"✓","○")) | K25: =IF(N25="","",INDEX(Calc!$AU$2:$AU$2001,N25)&"") | L25: =IF(N25="","",INDEX(Calc!$AV$2:$AV$2001,N25)&"") | M25: =IF(N25="","",INDEX(Calc!$AW$2:$AW$2001,N25)) | N25: =IFERROR(MATCH(SMALL(Calc!$BM$2:$BM$2001,22),Calc!$BM$2:$BM$2001,0),"")
B26: MY TOP HABITS | D26: =IF(I26="","",IF(INDEX(Calc!$BG$2:$BG$2001,I26)=1,"✓","○")) | E26: =IF(I26="","",INDEX(Calc!$AU$2:$AU$2001,I26)&"") | F26: =IF(I26="","",Setup!$D$7-INDEX(Calc!$AW$2:$AW$2001,I26)) | G26: =IF(I26="","",INDEX(Calc!$BA$2:$BA$2001,I26)&"") | I26: =IFERROR(MATCH(SMALL(Calc!$BL$2:$BL$2001,5),Calc!$BL$2:$BL$2001,0),"") | J26: =IF(N26="","",IF(INDEX(Calc!$BG$2:$BG$2001,N26)=1,"✓","○")) | K26: =IF(N26="","",INDEX(Calc!$AU$2:$AU$2001,N26)&"") | L26: =IF(N26="","",INDEX(Calc!$AV$2:$AV$2001,N26)&"") | M26: =IF(N26="","",INDEX(Calc!$AW$2:$AW$2001,N26)) | N26: =IFERROR(MATCH(SMALL(Calc!$BM$2:$BM$2001,23),Calc!$BM$2:$BM$2001,0),"")
B27: =IF('Habit Tracker'!B9="","","1. "&'Habit Tracker'!B9) | D27: =IF(I27="","",IF(INDEX(Calc!$BG$2:$BG$2001,I27)=1,"✓","○")) | E27: =IF(I27="","",INDEX(Calc!$AU$2:$AU$2001,I27)&"") | F27: =IF(I27="","",Setup!$D$7-INDEX(Calc!$AW$2:$AW$2001,I27)) | G27: =IF(I27="","",INDEX(Calc!$BA$2:$BA$2001,I27)&"") | I27: =IFERROR(MATCH(SMALL(Calc!$BL$2:$BL$2001,6),Calc!$BL$2:$BL$2001,0),"") | J27: =IF(N27="","",IF(INDEX(Calc!$BG$2:$BG$2001,N27)=1,"✓","○")) | K27: =IF(N27="","",INDEX(Calc!$AU$2:$AU$2001,N27)&"") | L27: =IF(N27="","",INDEX(Calc!$AV$2:$AV$2001,N27)&"") | M27: =IF(N27="","",INDEX(Calc!$AW$2:$AW$2001,N27)) | N27: =IFERROR(MATCH(SMALL(Calc!$BM$2:$BM$2001,24),Calc!$BM$2:$BM$2001,0),"")
B28: =IF('Habit Tracker'!B10="","","2. "&'Habit Tracker'!B10) | D28: =IF(I28="","",IF(INDEX(Calc!$BG$2:$BG$2001,I28)=1,"✓","○")) | E28: =IF(I28="","",INDEX(Calc!$AU$2:$AU$2001,I28)&"") | F28: =IF(I28="","",Setup!$D$7-INDEX(Calc!$AW$2:$AW$2001,I28)) | G28: =IF(I28="","",INDEX(Calc!$BA$2:$BA$2001,I28)&"") | I28: =IFERROR(MATCH(SMALL(Calc!$BL$2:$BL$2001,7),Calc!$BL$2:$BL$2001,0),"") | J28: =IF(N28="","",IF(INDEX(Calc!$BG$2:$BG$2001,N28)=1,"✓","○")) | K28: =IF(N28="","",INDEX(Calc!$AU$2:$AU$2001,N28)&"") | L28: =IF(N28="","",INDEX(Calc!$AV$2:$AV$2001,N28)&"") | M28: =IF(N28="","",INDEX(Calc!$AW$2:$AW$2001,N28)) | N28: =IFERROR(MATCH(SMALL(Calc!$BM$2:$BM$2001,25),Calc!$BM$2:$BM$2001,0),"")
B29: =IF('Habit Tracker'!B11="","","3. "&'Habit Tracker'!B11) | D29: =IF(I29="","",IF(INDEX(Calc!$BG$2:$BG$2001,I29)=1,"✓","○")) | E29: =IF(I29="","",INDEX(Calc!$AU$2:$AU$2001,I29)&"") | F29: =IF(I29="","",Setup!$D$7-INDEX(Calc!$AW$2:$AW$2001,I29)) | G29: =IF(I29="","",INDEX(Calc!$BA$2:$BA$2001,I29)&"") | I29: =IFERROR(MATCH(SMALL(Calc!$BL$2:$BL$2001,8),Calc!$BL$2:$BL$2001,0),"") | J29: =IF(N29="","",IF(INDEX(Calc!$BG$2:$BG$2001,N29)=1,"✓","○")) | K29: =IF(N29="","",INDEX(Calc!$AU$2:$AU$2001,N29)&"") | L29: =IF(N29="","",INDEX(Calc!$AV$2:$AV$2001,N29)&"") | M29: =IF(N29="","",INDEX(Calc!$AW$2:$AW$2001,N29)) | N29: =IFERROR(MATCH(SMALL(Calc!$BM$2:$BM$2001,26),Calc!$BM$2:$BM$2001,0),"")
B30: =IF('Habit Tracker'!B12="","","4. "&'Habit Tracker'!B12) | D30: =IF(I30="","",IF(INDEX(Calc!$BG$2:$BG$2001,I30)=1,"✓","○")) | E30: =IF(I30="","",INDEX(Calc!$AU$2:$AU$2001,I30)&"") | F30: =IF(I30="","",Setup!$D$7-INDEX(Calc!$AW$2:$AW$2001,I30)) | G30: =IF(I30="","",INDEX(Calc!$BA$2:$BA$2001,I30)&"") | I30: =IFERROR(MATCH(SMALL(Calc!$BL$2:$BL$2001,9),Calc!$BL$2:$BL$2001,0),"") | J30: =IF(N30="","",IF(INDEX(Calc!$BG$2:$BG$2001,N30)=1,"✓","○")) | K30: =IF(N30="","",INDEX(Calc!$AU$2:$AU$2001,N30)&"") | L30: =IF(N30="","",INDEX(Calc!$AV$2:$AV$2001,N30)&"") | M30: =IF(N30="","",INDEX(Calc!$AW$2:$AW$2001,N30)) | N30: =IFERROR(MATCH(SMALL(Calc!$BM$2:$BM$2001,27),Calc!$BM$2:$BM$2001,0),"")
B31: =IF('Habit Tracker'!B13="","","5. "&'Habit Tracker'!B13) | D31: =IF(I31="","",IF(INDEX(Calc!$BG$2:$BG$2001,I31)=1,"✓","○")) | E31: =IF(I31="","",INDEX(Calc!$AU$2:$AU$2001,I31)&"") | F31: =IF(I31="","",Setup!$D$7-INDEX(Calc!$AW$2:$AW$2001,I31)) | G31: =IF(I31="","",INDEX(Calc!$BA$2:$BA$2001,I31)&"") | I31: =IFERROR(MATCH(SMALL(Calc!$BL$2:$BL$2001,10),Calc!$BL$2:$BL$2001,0),"") | J31: =IF(N31="","",IF(INDEX(Calc!$BG$2:$BG$2001,N31)=1,"✓","○")) | K31: =IF(N31="","",INDEX(Calc!$AU$2:$AU$2001,N31)&"") | L31: =IF(N31="","",INDEX(Calc!$AV$2:$AV$2001,N31)&"") | M31: =IF(N31="","",INDEX(Calc!$AW$2:$AW$2001,N31)) | N31: =IFERROR(MATCH(SMALL(Calc!$BM$2:$BM$2001,28),Calc!$BM$2:$BM$2001,0),"") | P31: TASKS BY PERSON
B32: =IF('Habit Tracker'!B14="","","6. "&'Habit Tracker'!B14) | D32: =IF(I32="","",IF(INDEX(Calc!$BG$2:$BG$2001,I32)=1,"✓","○")) | E32: =IF(I32="","",INDEX(Calc!$AU$2:$AU$2001,I32)&"") | F32: =IF(I32="","",Setup!$D$7-INDEX(Calc!$AW$2:$AW$2001,I32)) | G32: =IF(I32="","",INDEX(Calc!$BA$2:$BA$2001,I32)&"") | I32: =IFERROR(MATCH(SMALL(Calc!$BL$2:$BL$2001,11),Calc!$BL$2:$BL$2001,0),"") | J32: =IF(N32="","",IF(INDEX(Calc!$BG$2:$BG$2001,N32)=1,"✓","○")) | K32: =IF(N32="","",INDEX(Calc!$AU$2:$AU$2001,N32)&"") | L32: =IF(N32="","",INDEX(Calc!$AV$2:$AV$2001,N32)&"") | M32: =IF(N32="","",INDEX(Calc!$AW$2:$AW$2001,N32)) | N32: =IFERROR(MATCH(SMALL(Calc!$BM$2:$BM$2001,29),Calc!$BM$2:$BM$2001,0),"")
B33: =IF('Habit Tracker'!B15="","","7. "&'Habit Tracker'!B15) | D33: =IF(I33="","",IF(INDEX(Calc!$BG$2:$BG$2001,I33)=1,"✓","○")) | E33: =IF(I33="","",INDEX(Calc!$AU$2:$AU$2001,I33)&"") | F33: =IF(I33="","",Setup!$D$7-INDEX(Calc!$AW$2:$AW$2001,I33)) | G33: =IF(I33="","",INDEX(Calc!$BA$2:$BA$2001,I33)&"") | I33: =IFERROR(MATCH(SMALL(Calc!$BL$2:$BL$2001,12),Calc!$BL$2:$BL$2001,0),"") | J33: =IF(N33="","",IF(INDEX(Calc!$BG$2:$BG$2001,N33)=1,"✓","○")) | K33: =IF(N33="","",INDEX(Calc!$AU$2:$AU$2001,N33)&"") | L33: =IF(N33="","",INDEX(Calc!$AV$2:$AV$2001,N33)&"") | M33: =IF(N33="","",INDEX(Calc!$AW$2:$AW$2001,N33)) | N33: =IFERROR(MATCH(SMALL(Calc!$BM$2:$BM$2001,30),Calc!$BM$2:$BM$2001,0),"")
B34: =IF('Habit Tracker'!B16="","","8. "&'Habit Tracker'!B16)
D36: DECISION MATRIX — TO DO vs DONE

Sheet Recurring Schedule
B2: RECURRING TASK SCHEDULE
B3: Set up repeating tasks ONCE — they auto-fill the Recurring Log, Tasks Filter, Dashboard, Daily, Weekly, Monthly & Decision Matrix for a full year.
B4: RECURRING TASKS
B5: # | C5: TASK | D5: CATEGORY | E5: FREQUENCY | F5: 1ST DATE | G5: END DATE | H5: START TIME | I5: END TIME | J5: PRIORITY | K5: IMPORTANT | L5: PERSON | M5: NOTES
B6: 1 | C6: Yoga | D6: Personal | E6: Daily | F6: 46293 | H6: 0.3125 | I6: 0.33333333 | J6: 3-Medium | K6: ✓ | L6: Me | N6: =IFERROR(VLOOKUP(E6,Lists!$A$2:$C$9,2,0),0) | O6: =IFERROR(VLOOKUP(E6,Lists!$A$2:$C$9,3,0),0) | P6: =IF(G6="",Setup!$D$5+365,MIN(G6,Setup!$D$5+365))
B7: 2 | C7: Meditate | D7: Health | E7: Weekdays | F7: 46293 | H7: 0.35416667 | I7: 0.36458333 | J7: 4-Low | L7: Me | N7: =IFERROR(VLOOKUP(E7,Lists!$A$2:$C$9,2,0),0) | O7: =IFERROR(VLOOKUP(E7,Lists!$A$2:$C$9,3,0),0) | P7: =IF(G7="",Setup!$D$5+365,MIN(G7,Setup!$D$5+365))
B8: 3 | C8: Monday Meeting | D8: Business | E8: Weekly | F8: 46293 | H8: 0.375 | I8: 0.41666667 | J8: 2-High | K8: ✓ | L8: Me | N8: =IFERROR(VLOOKUP(E8,Lists!$A$2:$C$9,2,0),0) | O8: =IFERROR(VLOOKUP(E8,Lists!$A$2:$C$9,3,0),0) | P8: =IF(G8="",Setup!$D$5+365,MIN(G8,Setup!$D$5+365))
B9: 4 | C9: Write project proposal | D9: Business | E9: Weekly | F9: 46295 | G9: 46387 | H9: 0.38541667 | I9: 0.45833333 | J9: 1-Urgent | K9: ✓ | L9: Me | N9: =IFERROR(VLOOKUP(E9,Lists!$A$2:$C$9,2,0),0) | O9: =IFERROR(VLOOKUP(E9,Lists!$A$2:$C$9,3,0),0) | P9: =IF(G9="",Setup!$D$5+365,MIN(G9,Setup!$D$5+365))
B10: 5 | C10: Pilates | D10: Health | E10: Weekly | F10: 46296 | H10: 0.75 | I10: 0.79166667 | J10: 3-Medium | K10: ✓ | L10: Me | N10: =IFERROR(VLOOKUP(E10,Lists!$A$2:$C$9,2,0),0) | O10: =IFERROR(VLOOKUP(E10,Lists!$A$2:$C$9,3,0),0) | P10: =IF(G10="",Setup!$D$5+365,MIN(G10,Setup!$D$5+365))
B11: 6 | C11: Amy's Soccer Game | D11: Family | E11: Weekly | F11: 46298 | G11: 46375 | H11: 0.41666667 | I11: 0.47916667 | J11: 2-High | K11: ✓ | L11: Sam | N11: =IFERROR(VLOOKUP(E11,Lists!$A$2:$C$9,2,0),0) | O11: =IFERROR(VLOOKUP(E11,Lists!$A$2:$C$9,3,0),0) | P11: =IF(G11="",Setup!$D$5+365,MIN(G11,Setup!$D$5+365))
B12: 7 | C12: Water Plants | D12: Personal | E12: Weekly | F12: 46299 | H12: 0.70833333 | I12: 0.71875 | J12: 4-Low | L12: Lucy | N12: =IFERROR(VLOOKUP(E12,Lists!$A$2:$C$9,2,0),0) | O12: =IFERROR(VLOOKUP(E12,Lists!$A$2:$C$9,3,0),0) | P12: =IF(G12="",Setup!$D$5+365,MIN(G12,Setup!$D$5+365))
B13: 8 | C13: Friday task review | D13: Business | E13: Weekly | F13: 46297 | H13: 0.66666667 | I13: 0.6875 | J13: 3-Medium | L13: Me | N13: =IFERROR(VLOOKUP(E13,Lists!$A$2:$C$9,2,0),0) | O13: =IFERROR(VLOOKUP(E13,Lists!$A$2:$C$9,3,0),0) | P13: =IF(G13="",Setup!$D$5+365,MIN(G13,Setup!$D$5+365))
B14: 9 | C14: Date Night | D14: Family | E14: Bi-weekly | F14: 46298 | H14: 0.79166667 | I14: 0.875 | J14: 2-High | K14: ✓ | L14: Me | N14: =IFERROR(VLOOKUP(E14,Lists!$A$2:$C$9,2,0),0) | O14: =IFERROR(VLOOKUP(E14,Lists!$A$2:$C$9,3,0),0) | P14: =IF(G14="",Setup!$D$5+365,MIN(G14,Setup!$D$5+365))
B15: 10 | C15: Monthly goal planning | D15: Personal | E15: Monthly | F15: 46296 | H15: 0.83333333 | I15: 0.875 | J15: 2-High | K15: ✓ | L15: Me | N15: =IFERROR(VLOOKUP(E15,Lists!$A$2:$C$9,2,0),0) | O15: =IFERROR(VLOOKUP(E15,Lists!$A$2:$C$9,3,0),0) | P15: =IF(G15="",Setup!$D$5+365,MIN(G15,Setup!$D$5+365))
B16: 11 | C16: Pay credit card | D16: Personal | E16: Monthly | F16: 46305 | J16: 1-Urgent | K16: ✓ | L16: Me | N16: =IFERROR(VLOOKUP(E16,Lists!$A$2:$C$9,2,0),0) | O16: =IFERROR(VLOOKUP(E16,Lists!$A$2:$C$9,3,0),0) | P16: =IF(G16="",Setup!$D$5+365,MIN(G16,Setup!$D$5+365))
B17: 12 | C17: Dentist check-up | D17: Health | E17: Quarterly | F17: 46338 | H17: 0.58333333 | I17: 0.625 | J17: 3-Medium | K17: ✓ | L17: Me | N17: =IFERROR(VLOOKUP(E17,Lists!$A$2:$C$9,2,0),0) | O17: =IFERROR(VLOOKUP(E17,Lists!$A$2:$C$9,3,0),0) | P17: =IF(G17="",Setup!$D$5+365,MIN(G17,Setup!$D$5+365))
B18: 13 | N18: =IFERROR(VLOOKUP(E18,Lists!$A$2:$C$9,2,0),0) | O18: =IFERROR(VLOOKUP(E18,Lists!$A$2:$C$9,3,0),0) | P18: =IF(G18="",Setup!$D$5+365,MIN(G18,Setup!$D$5+365))
B19: 14 | N19: =IFERROR(VLOOKUP(E19,Lists!$A$2:$C$9,2,0),0) | O19: =IFERROR(VLOOKUP(E19,Lists!$A$2:$C$9,3,0),0) | P19: =IF(G19="",Setup!$D$5+365,MIN(G19,Setup!$D$5+365))
B20: 15 | N20: =IFERROR(VLOOKUP(E20,Lists!$A$2:$C$9,2,0),0) | O20: =IFERROR(VLOOKUP(E20,Lists!$A$2:$C$9,3,0),0) | P20: =IF(G20="",Setup!$D$5+365,MIN(G20,Setup!$D$5+365))
B21: 16 | N21: =IFERROR(VLOOKUP(E21,Lists!$A$2:$C$9,2,0),0) | O21: =IFERROR(VLOOKUP(E21,Lists!$A$2:$C$9,3,0),0) | P21: =IF(G21="",Setup!$D$5+365,MIN(G21,Setup!$D$5+365))
B22: 17 | N22: =IFERROR(VLOOKUP(E22,Lists!$A$2:$C$9,2,0),0) | O22: =IFERROR(VLOOKUP(E22,Lists!$A$2:$C$9,3,0),0) | P22: =IF(G22="",Setup!$D$5+365,MIN(G22,Setup!$D$5+365))
B23: 18 | N23: =IFERROR(VLOOKUP(E23,Lists!$A$2:$C$9,2,0),0) | O23: =IFERROR(VLOOKUP(E23,Lists!$A$2:$C$9,3,0),0) | P23: =IF(G23="",Setup!$D$5+365,MIN(G23,Setup!$D$5+365))
B24: 19 | N24: =IFERROR(VLOOKUP(E24,Lists!$A$2:$C$9,2,0),0) | O24: =IFERROR(VLOOKUP(E24,Lists!$A$2:$C$9,3,0),0) | P24: =IF(G24="",Setup!$D$5+365,MIN(G24,Setup!$D$5+365))
B25: 20 | N25: =IFERROR(VLOOKUP(E25,Lists!$A$2:$C$9,2,0),0) | O25: =IFERROR(VLOOKUP(E25,Lists!$A$2:$C$9,3,0),0) | P25: =IF(G25="",Setup!$D$5+365,MIN(G25,Setup!$D$5+365))
B26: 21 | N26: =IFERROR(VLOOKUP(E26,Lists!$A$2:$C$9,2,0),0) | O26: =IFERROR(VLOOKUP(E26,Lists!$A$2:$C$9,3,0),0) | P26: =IF(G26="",Setup!$D$5+365,MIN(G26,Setup!$D$5+365))
B27: 22 | N27: =IFERROR(VLOOKUP(E27,Lists!$A$2:$C$9,2,0),0) | O27: =IFERROR(VLOOKUP(E27,Lists!$A$2:$C$9,3,0),0) | P27: =IF(G27="",Setup!$D$5+365,MIN(G27,Setup!$D$5+365))
B28: 23 | N28: =IFERROR(VLOOKUP(E28,Lists!$A$2:$C$9,2,0),0) | O28: =IFERROR(VLOOKUP(E28,Lists!$A$2:$C$9,3,0),0) | P28: =IF(G28="",Setup!$D$5+365,MIN(G28,Setup!$D$5+365))
B29: 24 | N29: =IFERROR(VLOOKUP(E29,Lists!$A$2:$C$9,2,0),0) | O29: =IFERROR(VLOOKUP(E29,Lists!$A$2:$C$9,3,0),0) | P29: =IF(G29="",Setup!$D$5+365,MIN(G29,Setup!$D$5+365))
... B45: 40 | N45: =IFERROR(VLOOKUP(E45,Lists!$A$2:$C$9,2,0),0) | O45: =IFERROR(VLOOKUP(E45,Lists!$A$2:$C$9,3,0),0) | P45: =IF(G45="",Setup!$D$5+365,MIN(G45,Setup!$D$5+365))

Sheet Variable Tasks
B2: VARIABLE TASKS
B3: One-off tasks — type them here. Pink = overdue · purple = due today · grey = done.
B4: TASK DETAILS | E4: SCHEDULE | J4: STATUS & PROGRESS | L4: EISENHOWER MATRIX | P4: NOTES
B5: # | C5: TASK | D5: CATEGORY | E5: DUE DATE | F5: DAYS LEFT | G5: START | H5: END | I5: DURATION | J5: STATUS | K5: PROGRESS | L5: PRIORITY | M5: IMPORTANT | N5: DELEGATE TO | O5: DECISION | P5: NOTES
B6: 1 | C6: Respond to emails | D6: Business | E6: 46285 | F6: =IF(OR(C6="",E6=""),"",E6-Setup!$D$7) | G6: 0.375 | H6: 0.44791667 | I6: =IF(OR(G6="",H6=""),"",TRIM(IF(HOUR(H6-G6)>0,HOUR(H6-G6)&" hr ","")&IF(MINUTE(H6-G6)>0,MINUTE(H6-G6)&" min",""))) | J6: Not Started | L6: 1-Urgent | N6: Me | O6: =IF(C6="","",IF(AND(OR(L6="1-Urgent",L6="2-High"),M6="✓"),"DO FIRST",IF(M6="✓","SCHEDULE",IF(OR(L6="1-Urgent",L6="2-High"),"DELEGATE","DELETE"))))
B7: 2 | C7: Conduct market research | D7: Business | E7: 46286 | F7: =IF(OR(C7="",E7=""),"",E7-Setup!$D$7) | G7: 0.6875 | H7: 0.72916667 | I7: =IF(OR(G7="",H7=""),"",TRIM(IF(HOUR(H7-G7)>0,HOUR(H7-G7)&" hr ","")&IF(MINUTE(H7-G7)>0,MINUTE(H7-G7)&" min",""))) | J7: Not Started | L7: 2-High | N7: Me | O7: =IF(C7="","",IF(AND(OR(L7="1-Urgent",L7="2-High"),M7="✓"),"DO FIRST",IF(M7="✓","SCHEDULE",IF(OR(L7="1-Urgent",L7="2-High"),"DELEGATE","DELETE"))))
B8: 3 | C8: Organize project files | D8: Business | E8: 46287 | F8: =IF(OR(C8="",E8=""),"",E8-Setup!$D$7) | G8: 0.5625 | H8: 0.64583333 | I8: =IF(OR(G8="",H8=""),"",TRIM(IF(HOUR(H8-G8)>0,HOUR(H8-G8)&" hr ","")&IF(MINUTE(H8-G8)>0,MINUTE(H8-G8)&" min",""))) | J8: Done | K8: 1 | L8: 2-High | N8: Rebecca | O8: =IF(C8="","",IF(AND(OR(L8="1-Urgent",L8="2-High"),M8="✓"),"DO FIRST",IF(M8="✓","SCHEDULE",IF(OR(L8="1-Urgent",L8="2-High"),"DELEGATE","DELETE"))))
B9: 4 | C9: Brief Amanda | D9: Business | E9: 46288 | F9: =IF(OR(C9="",E9=""),"",E9-Setup!$D$7) | G9: 0.625 | H9: 0.65625 | I9: =IF(OR(G9="",H9=""),"",TRIM(IF(HOUR(H9-G9)>0,HOUR(H9-G9)&" hr ","")&IF(MINUTE(H9-G9)>0,MINUTE(H9-G9)&" min",""))) | J9: Done | K9: 1 | L9: 3-Medium | M9: ✓ | N9: Tony | O9: =IF(C9="","",IF(AND(OR(L9="1-Urgent",L9="2-High"),M9="✓"),"DO FIRST",IF(M9="✓","SCHEDULE",IF(OR(L9="1-Urgent",L9="2-High"),"DELEGATE","DELETE"))))
B10: 5 | C10: Track weekly goals | D10: Personal | E10: 46290 | F10: =IF(OR(C10="",E10=""),"",E10-Setup!$D$7) | G10: 0.47916667 | H10: 0.5625 | I10: =IF(OR(G10="",H10=""),"",TRIM(IF(HOUR(H10-G10)>0,HOUR(H10-G10)&" hr ","")&IF(MINUTE(H10-G10)>0,MINUTE(H10-G10)&" min",""))) | J10: In Progress | K10: 0.8 | L10: 2-High | M10: ✓ | N10: Me | O10: =IF(C10="","",IF(AND(OR(L10="1-Urgent",L10="2-High"),M10="✓"),"DO FIRST",IF(M10="✓","SCHEDULE",IF(OR(L10="1-Urgent",L10="2-High"),"DELEGATE","DELETE"))))
B11: 6 | C11: Coffee with Alex | D11: Social | E11: 46291 | F11: =IF(OR(C11="",E11=""),"",E11-Setup!$D$7) | I11: =IF(OR(G11="",H11=""),"",TRIM(IF(HOUR(H11-G11)>0,HOUR(H11-G11)&" hr ","")&IF(MINUTE(H11-G11)>0,MINUTE(H11-G11)&" min",""))) | J11: Done | K11: 1 | L11: 2-High | M11: ✓ | N11: Rebecca | O11: =IF(C11="","",IF(AND(OR(L11="1-Urgent",L11="2-High"),M11="✓"),"DO FIRST",IF(M11="✓","SCHEDULE",IF(OR(L11="1-Urgent",L11="2-High"),"DELEGATE","DELETE"))))
B12: 7 | C12: Declutter desk | D12: Personal | E12: 46292 | F12: =IF(OR(C12="",E12=""),"",E12-Setup!$D$7) | G12: 0.6875 | H12: 0.77083333 | I12: =IF(OR(G12="",H12=""),"",TRIM(IF(HOUR(H12-G12)>0,HOUR(H12-G12)&" hr ","")&IF(MINUTE(H12-G12)>0,MINUTE(H12-G12)&" min",""))) | J12: Not Started | L12: 3-Medium | N12: Rebecca | O12: =IF(C12="","",IF(AND(OR(L12="1-Urgent",L12="2-High"),M12="✓"),"DO FIRST",IF(M12="✓","SCHEDULE",IF(OR(L12="1-Urgent",L12="2-High"),"DELEGATE","DELETE"))))
B13: 8 | C13: Review client feedback | D13: Business | E13: 46294 | F13: =IF(OR(C13="",E13=""),"",E13-Setup!$D$7) | G13: 0.54166667 | H13: 0.61458333 | I13: =IF(OR(G13="",H13=""),"",TRIM(IF(HOUR(H13-G13)>0,HOUR(H13-G13)&" hr ","")&IF(MINUTE(H13-G13)>0,MINUTE(H13-G13)&" min",""))) | J13: Not Started | L13: 2-High | N13: Jamie | O13: =IF(C13="","",IF(AND(OR(L13="1-Urgent",L13="2-High"),M13="✓"),"DO FIRST",IF(M13="✓","SCHEDULE",IF(OR(L13="1-Urgent",L13="2-High"),"DELEGATE","DELETE"))))
B14: 9 | C14: Analyze sales data | D14: Business | E14: 46295 | F14: =IF(OR(C14="",E14=""),"",E14-Setup!$D$7) | G14: 0.54166667 | H14: 0.61458333 | I14: =IF(OR(G14="",H14=""),"",TRIM(IF(HOUR(H14-G14)>0,HOUR(H14-G14)&" hr ","")&IF(MINUTE(H14-G14)>0,MINUTE(H14-G14)&" min",""))) | L14: 3-Medium | M14: ✓ | N14: Me | O14: =IF(C14="","",IF(AND(OR(L14="1-Urgent",L14="2-High"),M14="✓"),"DO FIRST",IF(M14="✓","SCHEDULE",IF(OR(L14="1-Urgent",L14="2-High"),"DELEGATE","DELETE"))))
B15: 10 | C15: Take Sam to Dentist | D15: Family | E15: 46296 | F15: =IF(OR(C15="",E15=""),"",E15-Setup!$D$7) | G15: 0.47916667 | H15: 0.47916667 | I15: =IF(OR(G15="",H15=""),"",TRIM(IF(HOUR(H15-G15)>0,HOUR(H15-G15)&" hr ","")&IF(MINUTE(H15-G15)>0,MINUTE(H15-G15)&" min",""))) | J15: In Progress | K15: 0.25 | L15: 4-Low | M15: ✓ | N15: Me | O15: =IF(C15="","",IF(AND(OR(L15="1-Urgent",L15="2-High"),M15="✓"),"DO FIRST",IF(M15="✓","SCHEDULE",IF(OR(L15="1-Urgent",L15="2-High"),"DELEGATE","DELETE"))))
B16: 11 | C16: Thyroid Check | D16: Health | E16: 46298 | F16: =IF(OR(C16="",E16=""),"",E16-Setup!$D$7) | G16: 0.4375 | H16: 0.52083333 | I16: =IF(OR(G16="",H16=""),"",TRIM(IF(HOUR(H16-G16)>0,HOUR(H16-G16)&" hr ","")&IF(MINUTE(H16-G16)>0,MINUTE(H16-G16)&" min",""))) | J16: Not Started | L16: 1-Urgent | M16: ✓ | N16: Jamie | O16: =IF(C16="","",IF(AND(OR(L16="1-Urgent",L16="2-High"),M16="✓"),"DO FIRST",IF(M16="✓","SCHEDULE",IF(OR(L16="1-Urgent",L16="2-High"),"DELEGATE","DELETE"))))
B17: 12 | C17: Design product logo | D17: Business | E17: 46299 | F17: =IF(OR(C17="",E17=""),"",E17-Setup!$D$7) | G17: 0.5625 | H17: 0.60416667 | I17: =IF(OR(G17="",H17=""),"",TRIM(IF(HOUR(H17-G17)>0,HOUR(H17-G17)&" hr ","")&IF(MINUTE(H17-G17)>0,MINUTE(H17-G17)&" min",""))) | J17: Not Started | L17: 1-Urgent | M17: ✓ | N17: Me | O17: =IF(C17="","",IF(AND(OR(L17="1-Urgent",L17="2-High"),M17="✓"),"DO FIRST",IF(M17="✓","SCHEDULE",IF(OR(L17="1-Urgent",L17="2-High"),"DELEGATE","DELETE"))))
B18: 13 | C18: Draft blog post | D18: Business | E18: 46300 | F18: =IF(OR(C18="",E18=""),"",E18-Setup!$D$7) | G18: 0.54166667 | H18: 0.61458333 | I18: =IF(OR(G18="",H18=""),"",TRIM(IF(HOUR(H18-G18)>0,HOUR(H18-G18)&" hr ","")&IF(MINUTE(H18-G18)>0,MINUTE(H18-G18)&" min",""))) | J18: Waiting | K18: 0.5 | L18: 3-Medium | M18: ✓ | N18: Me | O18: =IF(C18="","",IF(AND(OR(L18="1-Urgent",L18="2-High"),M18="✓"),"DO FIRST",IF(M18="✓","SCHEDULE",IF(OR(L18="1-Urgent",L18="2-High"),"DELEGATE","DELETE"))))
B19: 14 | C19: Dinner with Amy | D19: Social | E19: 46301 | F19: =IF(OR(C19="",E19=""),"",E19-Setup!$D$7) | G19: 0.6875 | H19: 0.72916667 | I19: =IF(OR(G19="",H19=""),"",TRIM(IF(HOUR(H19-G19)>0,HOUR(H19-G19)&" hr ","")&IF(MINUTE(H19-G19)>0,MINUTE(H19-G19)&" min",""))) | J19: In Progress | K19: 0.4 | L19: 4-Low | M19: ✓ | N19: Me | O19: =IF(C19="","",IF(AND(OR(L19="1-Urgent",L19="2-High"),M19="✓"),"DO FIRST",IF(M19="✓","SCHEDULE",IF(OR(L19="1-Urgent",L19="2-High"),"DELEGATE","DELETE"))))
B20: 15 | C20: Plan weekend away | D20: Family | E20: 46303 | F20: =IF(OR(C20="",E20=""),"",E20-Setup!$D$7) | G20: 0.6875 | H20: 0.6875 | I20: =IF(OR(G20="",H20=""),"",TRIM(IF(HOUR(H20-G20)>0,HOUR(H20-G20)&" hr ","")&IF(MINUTE(H20-G20)>0,MINUTE(H20-G20)&" min",""))) | L20: 4-Low | N20: Lucy | O20: =IF(C20="","",IF(AND(OR(L20="1-Urgent",L20="2-High"),M20="✓"),"DO FIRST",IF(M20="✓","SCHEDULE",IF(OR(L20="1-Urgent",L20="2-High"),"DELEGATE","DELETE"))))
B21: 16 | C21: Clean kitchen | D21: Family | E21: 46304 | F21: =IF(OR(C21="",E21=""),"",E21-Setup!$D$7) | G21: 0.4375 | H21: 0.47916667 | I21: =IF(OR(G21="",H21=""),"",TRIM(IF(HOUR(H21-G21)>0,HOUR(H21-G21)&" hr ","")&IF(MINUTE(H21-G21)>0,MINUTE(H21-G21)&" min",""))) | L21: 3-Medium | M21: ✓ | N21: Rebecca | O21: =IF(C21="","",IF(AND(OR(L21="1-Urgent",L21="2-High"),M21="✓"),"DO FIRST",IF(M21="✓","SCHEDULE",IF(OR(L21="1-Urgent",L21="2-High"),"DELEGATE","DELETE"))))
B22: 17 | C22: Family Lunch | D22: Family | E22: 46305 | F22: =IF(OR(C22="",E22=""),"",E22-Setup!$D$7) | G22: 0.5625 | H22: 0.5625 | I22: =IF(OR(G22="",H22=""),"",TRIM(IF(HOUR(H22-G22)>0,HOUR(H22-G22)&" hr ","")&IF(MINUTE(H22-G22)>0,MINUTE(H22-G22)&" min",""))) | J22: Waiting | K22: 0.5 | L22: 1-Urgent | N22: Jamie | O22: =IF(C22="","",IF(AND(OR(L22="1-Urgent",L22="2-High"),M22="✓"),"DO FIRST",IF(M22="✓","SCHEDULE",IF(OR(L22="1-Urgent",L22="2-High"),"DELEGATE","DELETE"))))
B23: 18 | C23: Madison's Bday | D23: Birthdays | E23: 46307 | F23: =IF(OR(C23="",E23=""),"",E23-Setup!$D$7) | G23: 0.47916667 | H23: 0.52083333 | I23: =IF(OR(G23="",H23=""),"",TRIM(IF(HOUR(H23-G23)>0,HOUR(H23-G23)&" hr ","")&IF(MINUTE(H23-G23)>0,MINUTE(H23-G23)&" min",""))) | L23: 4-Low | M23: ✓ | N23: Me | O23: =IF(C23="","",IF(AND(OR(L23="1-Urgent",L23="2-High"),M23="✓"),"DO FIRST",IF(M23="✓","SCHEDULE",IF(OR(L23="1-Urgent",L23="2-High"),"DELEGATE","DELETE"))))
B24: 19 | C24: Client follow-up calls | D24: Business | E24: 46308 | F24: =IF(OR(C24="",E24=""),"",E24-Setup!$D$7) | G24: 0.625 | H24: 0.69791667 | I24: =IF(OR(G24="",H24=""),"",TRIM(IF(HOUR(H24-G24)>0,HOUR(H24-G24)&" hr ","")&IF(MINUTE(H24-G24)>0,MINUTE(H24-G24)&" min",""))) | J24: In Progress | K24: 0.8 | L24: 3-Medium | N24: Jamie | O24: =IF(C24="","",IF(AND(OR(L24="1-Urgent",L24="2-High"),M24="✓"),"DO FIRST",IF(M24="✓","SCHEDULE",IF(OR(L24="1-Urgent",L24="2-High"),"DELEGATE","DELETE"))))
B25: 20 | C25: Schedule team meeting | D25: Business | E25: 46309 | F25: =IF(OR(C25="",E25=""),"",E25-Setup!$D$7) | G25: 0.39583333 | H25: 0.4375 | I25: =IF(OR(G25="",H25=""),"",TRIM(IF(HOUR(H25-G25)>0,HOUR(H25-G25)&" hr ","")&IF(MINUTE(H25-G25)>0,MINUTE(H25-G25)&" min",""))) | J25: In Progress | K25: 0.6 | L25: 3-Medium | M25: ✓ | N25: Rebecca | O25: =IF(C25="","",IF(AND(OR(L25="1-Urgent",L25="2-High"),M25="✓"),"DO FIRST",IF(M25="✓","SCHEDULE",IF(OR(L25="1-Urgent",L25="2-High"),"DELEGATE","DELETE"))))
B26: 21 | C26: Plan marketing campaign | D26: Business | E26: 46311 | F26: =IF(OR(C26="",E26=""),"",E26-Setup!$D$7) | I26: =IF(OR(G26="",H26=""),"",TRIM(IF(HOUR(H26-G26)>0,HOUR(H26-G26)&" hr ","")&IF(MINUTE(H26-G26)>0,MINUTE(H26-G26)&" min",""))) | J26: Not Started | L26: 3-Medium | N26: Lucy | O26: =IF(C26="","",IF(AND(OR(L26="1-Urgent",L26="2-High"),M26="✓"),"DO FIRST",IF(M26="✓","SCHEDULE",IF(OR(L26="1-Urgent",L26="2-High"),"DELEGATE","DELETE"))))
B27: 22 | C27: Review ad performance | D27: Business | E27: 46312 | F27: =IF(OR(C27="",E27=""),"",E27-Setup!$D$7) | G27: 0.64583333 | H27: 0.6875 | I27: =IF(OR(G27="",H27=""),"",TRIM(IF(HOUR(H27-G27)>0,HOUR(H27-G27)&" hr ","")&IF(MINUTE(H27-G27)>0,MINUTE(H27-G27)&" min",""))) | J27: In Progress | K27: 0.4 | L27: 4-Low | N27: Me | O27: =IF(C27="","",IF(AND(OR(L27="1-Urgent",L27="2-High"),M27="✓"),"DO FIRST",IF(M27="✓","SCHEDULE",IF(OR(L27="1-Urgent",L27="2-High"),"DELEGATE","DELETE"))))
B28: 23 | C28: Presentation Project X | D28: Business | E28: 46313 | F28: =IF(OR(C28="",E28=""),"",E28-Setup!$D$7) | I28: =IF(OR(G28="",H28=""),"",TRIM(IF(HOUR(H28-G28)>0,HOUR(H28-G28)&" hr ","")&IF(MINUTE(H28-G28)>0,MINUTE(H28-G28)&" min",""))) | L28: 3-Medium | N28: Lucy | O28: =IF(C28="","",IF(AND(OR(L28="1-Urgent",L28="2-High"),M28="✓"),"DO FIRST",IF(M28="✓","SCHEDULE",IF(OR(L28="1-Urgent",L28="2-High"),"DELEGATE","DELETE"))))
B29: 24 | C29: Mole Check | D29: Health | E29: 46314 | F29: =IF(OR(C29="",E29=""),"",E29-Setup!$D$7) | G29: 0.45833333 | H29: 0.48958333 | I29: =IF(OR(G29="",H29=""),"",TRIM(IF(HOUR(H29-G29)>0,HOUR(H29-G29)&" hr ","")&IF(MINUTE(H29-G29)>0,MINUTE(H29-G29)&" min",""))) | J29: In Progress | K29: 0.4 | L29: 4-Low | M29: ✓ | N29: Lucy | O29: =IF(C29="","",IF(AND(OR(L29="1-Urgent",L29="2-High"),M29="✓"),"DO FIRST",IF(M29="✓","SCHEDULE",IF(OR(L29="1-Urgent",L29="2-High"),"DELEGATE","DELETE"))))
B30: 25 | C30: Running | D30: Personal | E30: 46316 | F30: =IF(OR(C30="",E30=""),"",E30-Setup!$D$7) | G30: 0.66666667 | H30: 0.69791667 | I30: =IF(OR(G30="",H30=""),"",TRIM(IF(HOUR(H30-G30)>0,HOUR(H30-G30)&" hr ","")&IF(MINUTE(H30-G30)>0,MINUTE(H30-G30)&" min",""))) | L30: 3-Medium | N30: Sam | O30: =IF(C30="","",IF(AND(OR(L30="1-Urgent",L30="2-High"),M30="✓"),"DO FIRST",IF(M30="✓","SCHEDULE",IF(OR(L30="1-Urgent",L30="2-High"),"DELEGATE","DELETE"))))
B31: 26 | C31: Doctor Check Up | D31: Health | E31: 46317 | F31: =IF(OR(C31="",E31=""),"",E31-Setup!$D$7) | G31: 0.6875 | H31: 0.72916667 | I31: =IF(OR(G31="",H31=""),"",TRIM(IF(HOUR(H31-G31)>0,HOUR(H31-G31)&" hr ","")&IF(MINUTE(H31-G31)>0,MINUTE(H31-G31)&" min",""))) | J31: Not Started | L31: 2-High | M31: ✓ | N31: Tony | O31: =IF(C31="","",IF(AND(OR(L31="1-Urgent",L31="2-High"),M31="✓"),"DO FIRST",IF(M31="✓","SCHEDULE",IF(OR(L31="1-Urgent",L31="2-High"),"DELEGATE","DELETE"))))
B32: 27 | C32: Buy groceries | D32: Family | E32: 46318 | F32: =IF(OR(C32="",E32=""),"",E32-Setup!$D$7) | G32: 0.5625 | H32: 0.64583333 | I32: =IF(OR(G32="",H32=""),"",TRIM(IF(HOUR(H32-G32)>0,HOUR(H32-G32)&" hr ","")&IF(MINUTE(H32-G32)>0,MINUTE(H32-G32)&" min",""))) | J32: In Progress | K32: 0.8 | L32: 3-Medium | M32: ✓ | N32: Rebecca | O32: =IF(C32="","",IF(AND(OR(L32="1-Urgent",L32="2-High"),M32="✓"),"DO FIRST",IF(M32="✓","SCHEDULE",IF(OR(L32="1-Urgent",L32="2-High"),"DELEGATE","DELETE"))))
B33: 28 | C33: John's Birthday | D33: Birthdays | E33: 46320 | F33: =IF(OR(C33="",E33=""),"",E33-Setup!$D$7) | I33: =IF(OR(G33="",H33=""),"",TRIM(IF(HOUR(H33-G33)>0,HOUR(H33-G33)&" hr ","")&IF(MINUTE(H33-G33)>0,MINUTE(H33-G33)&" min",""))) | J33: Waiting | K33: 0.5 | L33: 2-High | M33: ✓ | N33: Me | O33: =IF(C33="","",IF(AND(OR(L33="1-Urgent",L33="2-High"),M33="✓"),"DO FIRST",IF(M33="✓","SCHEDULE",IF(OR(L33="1-Urgent",L33="2-High"),"DELEGATE","DELETE"))))
B34: 29 | C34: Test product features | D34: Business | E34: 46321 | F34: =IF(OR(C34="",E34=""),"",E34-Setup!$D$7) | G34: 0.6875 | H34: 0.72916667 | I34: =IF(OR(G34="",H34=""),"",TRIM(IF(HOUR(H34-G34)>0,HOUR(H34-G34)&" hr ","")&IF(MINUTE(H34-G34)>0,MINUTE(H34-G34)&" min",""))) | J34: Not Started | L34: 3-Medium | N34: Jamie | O34: =IF(C34="","",IF(AND(OR(L34="1-Urgent",L34="2-High"),M34="✓"),"DO FIRST",IF(M34="✓","SCHEDULE",IF(OR(L34="1-Urgent",L34="2-High"),"DELEGATE","DELETE"))))
B35: 30 | C35: Girls lunch | D35: Social | E35: 46322 | F35: =IF(OR(C35="",E35=""),"",E35-Setup!$D$7) | G35: 0.375 | H35: 0.44791667 | I35: =IF(OR(G35="",H35=""),"",TRIM(IF(HOUR(H35-G35)>0,HOUR(H35-G35)&" hr ","")&IF(MINUTE(H35-G35)>0,MINUTE(H35-G35)&" min",""))) | J35: Not Started | L35: 1-Urgent | M35: ✓ | N35: Lucy | O35: =IF(C35="","",IF(AND(OR(L35="1-Urgent",L35="2-High"),M35="✓"),"DO FIRST",IF(M35="✓","SCHEDULE",IF(OR(L35="1-Urgent",L35="2-High"),"DELEGATE","DELETE"))))
B36: 31 | C36: Facial Treatment | D36: Health | E36: 46324 | F36: =IF(OR(C36="",E36=""),"",E36-Setup!$D$7) | G36: 0.45833333 | H36: 0.48958333 | I36: =IF(OR(G36="",H36=""),"",TRIM(IF(HOUR(H36-G36)>0,HOUR(H36-G36)&" hr ","")&IF(MINUTE(H36-G36)>0,MINUTE(H36-G36)&" min",""))) | J36: Waiting | K36: 0.5 | L36: 2-High | N36: Tony | O36: =IF(C36="","",IF(AND(OR(L36="1-Urgent",L36="2-High"),M36="✓"),"DO FIRST",IF(M36="✓","SCHEDULE",IF(OR(L36="1-Urgent",L36="2-High"),"DELEGATE","DELETE"))))
B37: 32 | C37: Book massage | D37: Personal | E37: 46325 | F37: =IF(OR(C37="",E37=""),"",E37-Setup!$D$7) | G37: 0.375 | H37: 0.48958333 | I37: =IF(OR(G37="",H37=""),"",TRIM(IF(HOUR(H37-G37)>0,HOUR(H37-G37)&" hr ","")&IF(MINUTE(H37-G37)>0,MINUTE(H37-G37)&" min",""))) | J37: Not Started | L37: 3-Medium | M37: ✓ | N37: Tony | O37: =IF(C37="","",IF(AND(OR(L37="1-Urgent",L37="2-High"),M37="✓"),"DO FIRST",IF(M37="✓","SCHEDULE",IF(OR(L37="1-Urgent",L37="2-High"),"DELEGATE","DELETE"))))
B38: 33 | C38: Hair dresser | D38: Personal | E38: 46326 | F38: =IF(OR(C38="",E38=""),"",E38-Setup!$D$7) | G38: 0.6875 | H38: 0.6875 | I38: =IF(OR(G38="",H38=""),"",TRIM(IF(HOUR(H38-G38)>0,HOUR(H38-G38)&" hr ","")&IF(MINUTE(H38-G38)>0,MINUTE(H38-G38)&" min",""))) | J38: In Progress | K38: 0.4 | L38: 2-High | M38: ✓ | N38: Me | O38: =IF(C38="","",IF(AND(OR(L38="1-Urgent",L38="2-High"),M38="✓"),"DO FIRST",IF(M38="✓","SCHEDULE",IF(OR(L38="1-Urgent",L38="2-High"),"DELEGATE","DELETE"))))
B39: 34 | C39: Finalize budget allocation | D39: Business | E39: 46327 | F39: =IF(OR(C39="",E39=""),"",E39-Setup!$D$7) | G39: 0.375 | H39: 0.44791667 | I39: =IF(OR(G39="",H39=""),"",TRIM(IF(HOUR(H39-G39)>0,HOUR(H39-G39)&" hr ","")&IF(MINUTE(H39-G39)>0,MINUTE(H39-G39)&" min",""))) | J39: Not Started | L39: 4-Low | N39: Rebecca | O39: =IF(C39="","",IF(AND(OR(L39="1-Urgent",L39="2-High"),M39="✓"),"DO FIRST",IF(M39="✓","SCHEDULE",IF(OR(L39="1-Urgent",L39="2-High"),"DELEGATE","DELETE"))))
B40: 35 | C40: Call client | D40: Business | E40: 46329 | F40: =IF(OR(C40="",E40=""),"",E40-Setup!$D$7) | I40: =IF(OR(G40="",H40=""),"",TRIM(IF(HOUR(H40-G40)>0,HOUR(H40-G40)&" hr ","")&IF(MINUTE(H40-G40)>0,MINUTE(H40-G40)&" min",""))) | J40: In Progress | K40: 0.4 | L40: 3-Medium | N40: Rebecca | O40: =IF(C40="","",IF(AND(OR(L40="1-Urgent",L40="2-High"),M40="✓"),"DO FIRST",IF(M40="✓","SCHEDULE",IF(OR(L40="1-Urgent",L40="2-High"),"DELEGATE","DELETE"))))
B41: 36 | C41: Prepare launch checklist | D41: Business | E41: 46330 | F41: =IF(OR(C41="",E41=""),"",E41-Setup!$D$7) | I41: =IF(OR(G41="",H41=""),"",TRIM(IF(HOUR(H41-G41)>0,HOUR(H41-G41)&" hr ","")&IF(MINUTE(H41-G41)>0,MINUTE(H41-G41)&" min",""))) | J41: Waiting | K41: 0.5 | L41: 1-Urgent | M41: ✓ | N41: Sam | O41: =IF(C41="","",IF(AND(OR(L41="1-Urgent",L41="2-High"),M41="✓"),"DO FIRST",IF(M41="✓","SCHEDULE",IF(OR(L41="1-Urgent",L41="2-High"),"DELEGATE","DELETE"))))
B42: 37 | C42: Email client re: project X | D42: Business | E42: 46331 | F42: =IF(OR(C42="",E42=""),"",E42-Setup!$D$7) | I42: =IF(OR(G42="",H42=""),"",TRIM(IF(HOUR(H42-G42)>0,HOUR(H42-G42)&" hr ","")&IF(MINUTE(H42-G42)>0,MINUTE(H42-G42)&" min",""))) | J42: Not Started | L42: 1-Urgent | M42: ✓ | N42: Me | O42: =IF(C42="","",IF(AND(OR(L42="1-Urgent",L42="2-High"),M42="✓"),"DO FIRST",IF(M42="✓","SCHEDULE",IF(OR(L42="1-Urgent",L42="2-High"),"DELEGATE","DELETE"))))
B43: 38 | C43: Organize photos | D43: Personal | E43: 46333 | F43: =IF(OR(C43="",E43=""),"",E43-Setup!$D$7) | G43: 0.66666667 | H43: 0.78125 | I43: =IF(OR(G43="",H43=""),"",TRIM(IF(HOUR(H43-G43)>0,HOUR(H43-G43)&" hr ","")&IF(MINUTE(H43-G43)>0,MINUTE(H43-G43)&" min",""))) | J43: In Progress | K43: 0.4 | L43: 3-Medium | M43: ✓ | N43: Jamie | O43: =IF(C43="","",IF(AND(OR(L43="1-Urgent",L43="2-High"),M43="✓"),"DO FIRST",IF(M43="✓","SCHEDULE",IF(OR(L43="1-Urgent",L43="2-High"),"DELEGATE","DELETE"))))
B44: 39 | C44: Car service | D44: Family | E44: 46334 | F44: =IF(OR(C44="",E44=""),"",E44-Setup!$D$7) | G44: 0.47916667 | H44: 0.52083333 | I44: =IF(OR(G44="",H44=""),"",TRIM(IF(HOUR(H44-G44)>0,HOUR(H44-G44)&" hr ","")&IF(MINUTE(H44-G44)>0,MINUTE(H44-G44)&" min",""))) | J44: In Progress | K44: 0.6 | L44: 2-High | M44: ✓ | N44: Rebecca | O44: =IF(C44="","",IF(AND(OR(L44="1-Urgent",L44="2-High"),M44="✓"),"DO FIRST",IF(M44="✓","SCHEDULE",IF(OR(L44="1-Urgent",L44="2-High"),"DELEGATE","DELETE"))))
B45: 40 | C45: Renew passport | D45: Personal | E45: 46335 | F45: =IF(OR(C45="",E45=""),"",E45-Setup!$D$7) | I45: =IF(OR(G45="",H45=""),"",TRIM(IF(HOUR(H45-G45)>0,HOUR(H45-G45)&" hr ","")&IF(MINUTE(H45-G45)>0,MINUTE(H45-G45)&" min",""))) | J45: Not Started | L45: 4-Low | M45: ✓ | N45: Sam | O45: =IF(C45="","",IF(AND(OR(L45="1-Urgent",L45="2-High"),M45="✓"),"DO FIRST",IF(M45="✓","SCHEDULE",IF(OR(L45="1-Urgent",L45="2-High"),"DELEGATE","DELETE"))))
B46: 41 | F46: =IF(OR(C46="",E46=""),"",E46-Setup!$D$7) | I46: =IF(OR(G46="",H46=""),"",TRIM(IF(HOUR(H46-G46)>0,HOUR(H46-G46)&" hr ","")&IF(MINUTE(H46-G46)>0,MINUTE(H46-G46)&" min",""))) | O46: =IF(C46="","",IF(AND(OR(L46="1-Urgent",L46="2-High"),M46="✓"),"DO FIRST",IF(M46="✓","SCHEDULE",IF(OR(L46="1-Urgent",L46="2-High"),"DELEGATE","DELETE"))))
B47: 42 | F47: =IF(OR(C47="",E47=""),"",E47-Setup!$D$7) | I47: =IF(OR(G47="",H47=""),"",TRIM(IF(HOUR(H47-G47)>0,HOUR(H47-G47)&" hr ","")&IF(MINUTE(H47-G47)>0,MINUTE(H47-G47)&" min",""))) | O47: =IF(C47="","",IF(AND(OR(L47="1-Urgent",L47="2-High"),M47="✓"),"DO FIRST",IF(M47="✓","SCHEDULE",IF(OR(L47="1-Urgent",L47="2-High"),"DELEGATE","DELETE"))))
B48: 43 | F48: =IF(OR(C48="",E48=""),"",E48-Setup!$D$7) | I48: =IF(OR(G48="",H48=""),"",TRIM(IF(HOUR(H48-G48)>0,HOUR(H48-G48)&" hr ","")&IF(MINUTE(H48-G48)>0,MINUTE(H48-G48)&" min",""))) | O48: =IF(C48="","",IF(AND(OR(L48="1-Urgent",L48="2-High"),M48="✓"),"DO FIRST",IF(M48="✓","SCHEDULE",IF(OR(L48="1-Urgent",L48="2-High"),"DELEGATE","DELETE"))))
B49: 44 | F49: =IF(OR(C49="",E49=""),"",E49-Setup!$D$7) | I49: =IF(OR(G49="",H49=""),"",TRIM(IF(HOUR(H49-G49)>0,HOUR(H49-G49)&" hr ","")&IF(MINUTE(H49-G49)>0,MINUTE(H49-G49)&" min",""))) | O49: =IF(C49="","",IF(AND(OR(L49="1-Urgent",L49="2-High"),M49="✓"),"DO FIRST",IF(M49="✓","SCHEDULE",IF(OR(L49="1-Urgent",L49="2-High"),"DELEGATE","DELETE"))))
B50: 45 | F50: =IF(OR(C50="",E50=""),"",E50-Setup!$D$7) | I50: =IF(OR(G50="",H50=""),"",TRIM(IF(HOUR(H50-G50)>0,HOUR(H50-G50)&" hr ","")&IF(MINUTE(H50-G50)>0,MINUTE(H50-G50)&" min",""))) | O50: =IF(C50="","",IF(AND(OR(L50="1-Urgent",L50="2-High"),M50="✓"),"DO FIRST",IF(M50="✓","SCHEDULE",IF(OR(L50="1-Urgent",L50="2-High"),"DELEGATE","DELETE"))))
B51: 46 | F51: =IF(OR(C51="",E51=""),"",E51-Setup!$D$7) | I51: =IF(OR(G51="",H51=""),"",TRIM(IF(HOUR(H51-G51)>0,HOUR(H51-G51)&" hr ","")&IF(MINUTE(H51-G51)>0,MINUTE(H51-G51)&" min",""))) | O51: =IF(C51="","",IF(AND(OR(L51="1-Urgent",L51="2-High"),M51="✓"),"DO FIRST",IF(M51="✓","SCHEDULE",IF(OR(L51="1-Urgent",L51="2-High"),"DELEGATE","DELETE"))))
B52: 47 | F52: =IF(OR(C52="",E52=""),"",E52-Setup!$D$7) | I52: =IF(OR(G52="",H52=""),"",TRIM(IF(HOUR(H52-G52)>0,HOUR(H52-G52)&" hr ","")&IF(MINUTE(H52-G52)>0,MINUTE(H52-G52)&" min",""))) | O52: =IF(C52="","",IF(AND(OR(L52="1-Urgent",L52="2-High"),M52="✓"),"DO FIRST",IF(M52="✓","SCHEDULE",IF(OR(L52="1-Urgent",L52="2-High"),"DELEGATE","DELETE"))))
B53: 48 | F53: =IF(OR(C53="",E53=""),"",E53-Setup!$D$7) | I53: =IF(OR(G53="",H53=""),"",TRIM(IF(HOUR(H53-G53)>0,HOUR(H53-G53)&" hr ","")&IF(MINUTE(H53-G53)>0,MINUTE(H53-G53)&" min",""))) | O53: =IF(C53="","",IF(AND(OR(L53="1-Urgent",L53="2-High"),M53="✓"),"DO FIRST",IF(M53="✓","SCHEDULE",IF(OR(L53="1-Urgent",L53="2-High"),"DELEGATE","DELETE"))))
B54: 49 | F54: =IF(OR(C54="",E54=""),"",E54-Setup!$D$7) | I54: =IF(OR(G54="",H54=""),"",TRIM(IF(HOUR(H54-G54)>0,HOUR(H54-G54)&" hr ","")&IF(MINUTE(H54-G54)>0,MINUTE(H54-G54)&" min",""))) | O54: =IF(C54="","",IF(AND(OR(L54="1-Urgent",L54="2-High"),M54="✓"),"DO FIRST",IF(M54="✓","SCHEDULE",IF(OR(L54="1-Urgent",L54="2-High"),"DELEGATE","DELETE"))))
B55: 50 | F55: =IF(OR(C55="",E55=""),"",E55-Setup!$D$7) | I55: =IF(OR(G55="",H55=""),"",TRIM(IF(HOUR(H55-G55)>0,HOUR(H55-G55)&" hr ","")&IF(MINUTE(H55-G55)>0,MINUTE(H55-G55)&" min",""))) | O55: =IF(C55="","",IF(AND(OR(L55="1-Urgent",L55="2-High"),M55="✓"),"DO FIRST",IF(M55="✓","SCHEDULE",IF(OR(L55="1-Urgent",L55="2-High"),"DELEGATE","DELETE"))))
B56: 51 | F56: =IF(OR(C56="",E56=""),"",E56-Setup!$D$7) | I56: =IF(OR(G56="",H56=""),"",TRIM(IF(HOUR(H56-G56)>0,HOUR(H56-G56)&" hr ","")&IF(MINUTE(H56-G56)>0,MINUTE(H56-G56)&" min",""))) | O56: =IF(C56="","",IF(AND(OR(L56="1-Urgent",L56="2-High"),M56="✓"),"DO FIRST",IF(M56="✓","SCHEDULE",IF(OR(L56="1-Urgent",L56="2-High"),"DELEGATE","DELETE"))))
B57: 52 | F57: =IF(OR(C57="",E57=""),"",E57-Setup!$D$7) | I57: =IF(OR(G57="",H57=""),"",TRIM(IF(HOUR(H57-G57)>0,HOUR(H57-G57)&" hr ","")&IF(MINUTE(H57-G57)>0,MINUTE(H57-G57)&" min",""))) | O57: =IF(C57="","",IF(AND(OR(L57="1-Urgent",L57="2-High"),M57="✓"),"DO FIRST",IF(M57="✓","SCHEDULE",IF(OR(L57="1-Urgent",L57="2-High"),"DELEGATE","DELETE"))))
... B505: 500 | F505: =IF(OR(C505="",E505=""),"",E505-Setup!$D$7) | I505: =IF(OR(G505="",H505=""),"",TRIM(IF(HOUR(H505-G505)>0,HOUR(H505-G505)&" hr ","")&IF(MINUTE(H505-G505)>0,MINUTE(H505-G505)&" min",""))) | O505: =IF(C505="","",IF(AND(OR(L505="1-Urgent",L505="2-High"),M505="✓"),"DO FIRST",IF(M505="✓","SCHEDULE",IF(OR(L505="1-Urgent",L505="2-High"),"DELEGATE","DELETE"))))

Sheet Recurring Log
B2: RECURRING LOG
B3: Auto-generated from the Recurring Schedule — only update STATUS, PROGRESS & NOTES here.
B4: TASK DETAILS | E4: SCHEDULE | J4: STATUS & PROGRESS | L4: EISENHOWER MATRIX | P4: NOTES
B5: # | C5: TASK | D5: CATEGORY | E5: DUE DATE | F5: DAYS LEFT | G5: START | H5: END | I5: DURATION | J5: STATUS | K5: PROGRESS | L5: PRIORITY | M5: IMPORTANT | N5: DELEGATE TO | O5: DECISION | P5: NOTES
B6: =IF(R6="","",1) | C6: =IF(R6="","",IF(INDEX('Recurring Schedule'!$C$6:$C$45,R6)="","",INDEX('Recurring Schedule'!$C$6:$C$45,R6))) | D6: =IF(R6="","",IF(INDEX('Recurring Schedule'!$D$6:$D$45,R6)="","",INDEX('Recurring Schedule'!$D$6:$D$45,R6))) | E6: =IF(Q6="","",INDEX(Calc!$A$2:$A$367,Q6)) | F6: =IF(OR(C6="",E6=""),"",E6-Setup!$D$7) | G6: =IF(R6="","",IF(INDEX('Recurring Schedule'!$H$6:$H$45,R6)="","",INDEX('Recurring Schedule'!$H$6:$H$45,R6))) | H6: =IF(R6="","",IF(INDEX('Recurring Schedule'!$I$6:$I$45,R6)="","",INDEX('Recurring Schedule'!$I$6:$I$45,R6))) | I6: =IF(OR(G6="",H6=""),"",TRIM(IF(HOUR(H6-G6)>0,HOUR(H6-G6)&" hr ","")&IF(MINUTE(H6-G6)>0,MINUTE(H6-G6)&" min",""))) | L6: =IF(R6="","",IF(INDEX('Recurring Schedule'!$J$6:$J$45,R6)="","",INDEX('Recurring Schedule'!$J$6:$J$45,R6))) | M6: =IF(R6="","",IF(INDEX('Recurring Schedule'!$K$6:$K$45,R6)="","",INDEX('Recurring Schedule'!$K$6:$K$45,R6))) | N6: =IF(R6="","",IF(INDEX('Recurring Schedule'!$L$6:$L$45,R6)="","",INDEX('Recurring Schedule'!$L$6:$L$45,R6))) | O6: =IF(C6="","",IF(AND(OR(L6="1-Urgent",L6="2-High"),M6="✓"),"DO FIRST",IF(M6="✓","SCHEDULE",IF(OR(L6="1-Urgent",L6="2-High"),"DELEGATE","DELETE")))) | Q6: =IF(1>Calc!$AQ$368,"",MATCH(0,Calc!$AQ$2:$AQ$367,1)) | R6: =IF(Q6="","",SMALL(INDEX(Calc!$B$2:$AO$367,Q6,0),1-INDEX(Calc!$AQ$2:$AQ$367,Q6)))
B7: =IF(R7="","",2) | C7: =IF(R7="","",IF(INDEX('Recurring Schedule'!$C$6:$C$45,R7)="","",INDEX('Recurring Schedule'!$C$6:$C$45,R7))) | D7: =IF(R7="","",IF(INDEX('Recurring Schedule'!$D$6:$D$45,R7)="","",INDEX('Recurring Schedule'!$D$6:$D$45,R7))) | E7: =IF(Q7="","",INDEX(Calc!$A$2:$A$367,Q7)) | F7: =IF(OR(C7="",E7=""),"",E7-Setup!$D$7) | G7: =IF(R7="","",IF(INDEX('Recurring Schedule'!$H$6:$H$45,R7)="","",INDEX('Recurring Schedule'!$H$6:$H$45,R7))) | H7: =IF(R7="","",IF(INDEX('Recurring Schedule'!$I$6:$I$45,R7)="","",INDEX('Recurring Schedule'!$I$6:$I$45,R7))) | I7: =IF(OR(G7="",H7=""),"",TRIM(IF(HOUR(H7-G7)>0,HOUR(H7-G7)&" hr ","")&IF(MINUTE(H7-G7)>0,MINUTE(H7-G7)&" min",""))) | L7: =IF(R7="","",IF(INDEX('Recurring Schedule'!$J$6:$J$45,R7)="","",INDEX('Recurring Schedule'!$J$6:$J$45,R7))) | M7: =IF(R7="","",IF(INDEX('Recurring Schedule'!$K$6:$K$45,R7)="","",INDEX('Recurring Schedule'!$K$6:$K$45,R7))) | N7: =IF(R7="","",IF(INDEX('Recurring Schedule'!$L$6:$L$45,R7)="","",INDEX('Recurring Schedule'!$L$6:$L$45,R7))) | O7: =IF(C7="","",IF(AND(OR(L7="1-Urgent",L7="2-High"),M7="✓"),"DO FIRST",IF(M7="✓","SCHEDULE",IF(OR(L7="1-Urgent",L7="2-High"),"DELEGATE","DELETE")))) | Q7: =IF(2>Calc!$AQ$368,"",MATCH(1,Calc!$AQ$2:$AQ$367,1)) | R7: =IF(Q7="","",SMALL(INDEX(Calc!$B$2:$AO$367,Q7,0),2-INDEX(Calc!$AQ$2:$AQ$367,Q7)))
B8: =IF(R8="","",3) | C8: =IF(R8="","",IF(INDEX('Recurring Schedule'!$C$6:$C$45,R8)="","",INDEX('Recurring Schedule'!$C$6:$C$45,R8))) | D8: =IF(R8="","",IF(INDEX('Recurring Schedule'!$D$6:$D$45,R8)="","",INDEX('Recurring Schedule'!$D$6:$D$45,R8))) | E8: =IF(Q8="","",INDEX(Calc!$A$2:$A$367,Q8)) | F8: =IF(OR(C8="",E8=""),"",E8-Setup!$D$7) | G8: =IF(R8="","",IF(INDEX('Recurring Schedule'!$H$6:$H$45,R8)="","",INDEX('Recurring Schedule'!$H$6:$H$45,R8))) | H8: =IF(R8="","",IF(INDEX('Recurring Schedule'!$I$6:$I$45,R8)="","",INDEX('Recurring Schedule'!$I$6:$I$45,R8))) | I8: =IF(OR(G8="",H8=""),"",TRIM(IF(HOUR(H8-G8)>0,HOUR(H8-G8)&" hr ","")&IF(MINUTE(H8-G8)>0,MINUTE(H8-G8)&" min",""))) | L8: =IF(R8="","",IF(INDEX('Recurring Schedule'!$J$6:$J$45,R8)="","",INDEX('Recurring Schedule'!$J$6:$J$45,R8))) | M8: =IF(R8="","",IF(INDEX('Recurring Schedule'!$K$6:$K$45,R8)="","",INDEX('Recurring Schedule'!$K$6:$K$45,R8))) | N8: =IF(R8="","",IF(INDEX('Recurring Schedule'!$L$6:$L$45,R8)="","",INDEX('Recurring Schedule'!$L$6:$L$45,R8))) | O8: =IF(C8="","",IF(AND(OR(L8="1-Urgent",L8="2-High"),M8="✓"),"DO FIRST",IF(M8="✓","SCHEDULE",IF(OR(L8="1-Urgent",L8="2-High"),"DELEGATE","DELETE")))) | Q8: =IF(3>Calc!$AQ$368,"",MATCH(2,Calc!$AQ$2:$AQ$367,1)) | R8: =IF(Q8="","",SMALL(INDEX(Calc!$B$2:$AO$367,Q8,0),3-INDEX(Calc!$AQ$2:$AQ$367,Q8)))
B9: =IF(R9="","",4) | C9: =IF(R9="","",IF(INDEX('Recurring Schedule'!$C$6:$C$45,R9)="","",INDEX('Recurring Schedule'!$C$6:$C$45,R9))) | D9: =IF(R9="","",IF(INDEX('Recurring Schedule'!$D$6:$D$45,R9)="","",INDEX('Recurring Schedule'!$D$6:$D$45,R9))) | E9: =IF(Q9="","",INDEX(Calc!$A$2:$A$367,Q9)) | F9: =IF(OR(C9="",E9=""),"",E9-Setup!$D$7) | G9: =IF(R9="","",IF(INDEX('Recurring Schedule'!$H$6:$H$45,R9)="","",INDEX('Recurring Schedule'!$H$6:$H$45,R9))) | H9: =IF(R9="","",IF(INDEX('Recurring Schedule'!$I$6:$I$45,R9)="","",INDEX('Recurring Schedule'!$I$6:$I$45,R9))) | I9: =IF(OR(G9="",H9=""),"",TRIM(IF(HOUR(H9-G9)>0,HOUR(H9-G9)&" hr ","")&IF(MINUTE(H9-G9)>0,MINUTE(H9-G9)&" min",""))) | L9: =IF(R9="","",IF(INDEX('Recurring Schedule'!$J$6:$J$45,R9)="","",INDEX('Recurring Schedule'!$J$6:$J$45,R9))) | M9: =IF(R9="","",IF(INDEX('Recurring Schedule'!$K$6:$K$45,R9)="","",INDEX('Recurring Schedule'!$K$6:$K$45,R9))) | N9: =IF(R9="","",IF(INDEX('Recurring Schedule'!$L$6:$L$45,R9)="","",INDEX('Recurring Schedule'!$L$6:$L$45,R9))) | O9: =IF(C9="","",IF(AND(OR(L9="1-Urgent",L9="2-High"),M9="✓"),"DO FIRST",IF(M9="✓","SCHEDULE",IF(OR(L9="1-Urgent",L9="2-High"),"DELEGATE","DELETE")))) | Q9: =IF(4>Calc!$AQ$368,"",MATCH(3,Calc!$AQ$2:$AQ$367,1)) | R9: =IF(Q9="","",SMALL(INDEX(Calc!$B$2:$AO$367,Q9,0),4-INDEX(Calc!$AQ$2:$AQ$367,Q9)))
B10: =IF(R10="","",5) | C10: =IF(R10="","",IF(INDEX('Recurring Schedule'!$C$6:$C$45,R10)="","",INDEX('Recurring Schedule'!$C$6:$C$45,R10))) | D10: =IF(R10="","",IF(INDEX('Recurring Schedule'!$D$6:$D$45,R10)="","",INDEX('Recurring Schedule'!$D$6:$D$45,R10))) | E10: =IF(Q10="","",INDEX(Calc!$A$2:$A$367,Q10)) | F10: =IF(OR(C10="",E10=""),"",E10-Setup!$D$7) | G10: =IF(R10="","",IF(INDEX('Recurring Schedule'!$H$6:$H$45,R10)="","",INDEX('Recurring Schedule'!$H$6:$H$45,R10))) | H10: =IF(R10="","",IF(INDEX('Recurring Schedule'!$I$6:$I$45,R10)="","",INDEX('Recurring Schedule'!$I$6:$I$45,R10))) | I10: =IF(OR(G10="",H10=""),"",TRIM(IF(HOUR(H10-G10)>0,HOUR(H10-G10)&" hr ","")&IF(MINUTE(H10-G10)>0,MINUTE(H10-G10)&" min",""))) | L10: =IF(R10="","",IF(INDEX('Recurring Schedule'!$J$6:$J$45,R10)="","",INDEX('Recurring Schedule'!$J$6:$J$45,R10))) | M10: =IF(R10="","",IF(INDEX('Recurring Schedule'!$K$6:$K$45,R10)="","",INDEX('Recurring Schedule'!$K$6:$K$45,R10))) | N10: =IF(R10="","",IF(INDEX('Recurring Schedule'!$L$6:$L$45,R10)="","",INDEX('Recurring Schedule'!$L$6:$L$45,R10))) | O10: =IF(C10="","",IF(AND(OR(L10="1-Urgent",L10="2-High"),M10="✓"),"DO FIRST",IF(M10="✓","SCHEDULE",IF(OR(L10="1-Urgent",L10="2-High"),"DELEGATE","DELETE")))) | Q10: =IF(5>Calc!$AQ$368,"",MATCH(4,Calc!$AQ$2:$AQ$367,1)) | R10: =IF(Q10="","",SMALL(INDEX(Calc!$B$2:$AO$367,Q10,0),5-INDEX(Calc!$AQ$2:$AQ$367,Q10)))
B11: =IF(R11="","",6) | C11: =IF(R11="","",IF(INDEX('Recurring Schedule'!$C$6:$C$45,R11)="","",INDEX('Recurring Schedule'!$C$6:$C$45,R11))) | D11: =IF(R11="","",IF(INDEX('Recurring Schedule'!$D$6:$D$45,R11)="","",INDEX('Recurring Schedule'!$D$6:$D$45,R11))) | E11: =IF(Q11="","",INDEX(Calc!$A$2:$A$367,Q11)) | F11: =IF(OR(C11="",E11=""),"",E11-Setup!$D$7) | G11: =IF(R11="","",IF(INDEX('Recurring Schedule'!$H$6:$H$45,R11)="","",INDEX('Recurring Schedule'!$H$6:$H$45,R11))) | H11: =IF(R11="","",IF(INDEX('Recurring Schedule'!$I$6:$I$45,R11)="","",INDEX('Recurring Schedule'!$I$6:$I$45,R11))) | I11: =IF(OR(G11="",H11=""),"",TRIM(IF(HOUR(H11-G11)>0,HOUR(H11-G11)&" hr ","")&IF(MINUTE(H11-G11)>0,MINUTE(H11-G11)&" min",""))) | L11: =IF(R11="","",IF(INDEX('Recurring Schedule'!$J$6:$J$45,R11)="","",INDEX('Recurring Schedule'!$J$6:$J$45,R11))) | M11: =IF(R11="","",IF(INDEX('Recurring Schedule'!$K$6:$K$45,R11)="","",INDEX('Recurring Schedule'!$K$6:$K$45,R11))) | N11: =IF(R11="","",IF(INDEX('Recurring Schedule'!$L$6:$L$45,R11)="","",INDEX('Recurring Schedule'!$L$6:$L$45,R11))) | O11: =IF(C11="","",IF(AND(OR(L11="1-Urgent",L11="2-High"),M11="✓"),"DO FIRST",IF(M11="✓","SCHEDULE",IF(OR(L11="1-Urgent",L11="2-High"),"DELEGATE","DELETE")))) | Q11: =IF(6>Calc!$AQ$368,"",MATCH(5,Calc!$AQ$2:$AQ$367,1)) | R11: =IF(Q11="","",SMALL(INDEX(Calc!$B$2:$AO$367,Q11,0),6-INDEX(Calc!$AQ$2:$AQ$367,Q11)))
B12: =IF(R12="","",7) | C12: =IF(R12="","",IF(INDEX('Recurring Schedule'!$C$6:$C$45,R12)="","",INDEX('Recurring Schedule'!$C$6:$C$45,R12))) | D12: =IF(R12="","",IF(INDEX('Recurring Schedule'!$D$6:$D$45,R12)="","",INDEX('Recurring Schedule'!$D$6:$D$45,R12))) | E12: =IF(Q12="","",INDEX(Calc!$A$2:$A$367,Q12)) | F12: =IF(OR(C12="",E12=""),"",E12-Setup!$D$7) | G12: =IF(R12="","",IF(INDEX('Recurring Schedule'!$H$6:$H$45,R12)="","",INDEX('Recurring Schedule'!$H$6:$H$45,R12))) | H12: =IF(R12="","",IF(INDEX('Recurring Schedule'!$I$6:$I$45,R12)="","",INDEX('Recurring Schedule'!$I$6:$I$45,R12))) | I12: =IF(OR(G12="",H12=""),"",TRIM(IF(HOUR(H12-G12)>0,HOUR(H12-G12)&" hr ","")&IF(MINUTE(H12-G12)>0,MINUTE(H12-G12)&" min",""))) | L12: =IF(R12="","",IF(INDEX('Recurring Schedule'!$J$6:$J$45,R12)="","",INDEX('Recurring Schedule'!$J$6:$J$45,R12))) | M12: =IF(R12="","",IF(INDEX('Recurring Schedule'!$K$6:$K$45,R12)="","",INDEX('Recurring Schedule'!$K$6:$K$45,R12))) | N12: =IF(R12="","",IF(INDEX('Recurring Schedule'!$L$6:$L$45,R12)="","",INDEX('Recurring Schedule'!$L$6:$L$45,R12))) | O12: =IF(C12="","",IF(AND(OR(L12="1-Urgent",L12="2-High"),M12="✓"),"DO FIRST",IF(M12="✓","SCHEDULE",IF(OR(L12="1-Urgent",L12="2-High"),"DELEGATE","DELETE")))) | Q12: =IF(7>Calc!$AQ$368,"",MATCH(6,Calc!$AQ$2:$AQ$367,1)) | R12: =IF(Q12="","",SMALL(INDEX(Calc!$B$2:$AO$367,Q12,0),7-INDEX(Calc!$AQ$2:$AQ$367,Q12)))
B13: =IF(R13="","",8) | C13: =IF(R13="","",IF(INDEX('Recurring Schedule'!$C$6:$C$45,R13)="","",INDEX('Recurring Schedule'!$C$6:$C$45,R13))) | D13: =IF(R13="","",IF(INDEX('Recurring Schedule'!$D$6:$D$45,R13)="","",INDEX('Recurring Schedule'!$D$6:$D$45,R13))) | E13: =IF(Q13="","",INDEX(Calc!$A$2:$A$367,Q13)) | F13: =IF(OR(C13="",E13=""),"",E13-Setup!$D$7) | G13: =IF(R13="","",IF(INDEX('Recurring Schedule'!$H$6:$H$45,R13)="","",INDEX('Recurring Schedule'!$H$6:$H$45,R13))) | H13: =IF(R13="","",IF(INDEX('Recurring Schedule'!$I$6:$I$45,R13)="","",INDEX('Recurring Schedule'!$I$6:$I$45,R13))) | I13: =IF(OR(G13="",H13=""),"",TRIM(IF(HOUR(H13-G13)>0,HOUR(H13-G13)&" hr ","")&IF(MINUTE(H13-G13)>0,MINUTE(H13-G13)&" min",""))) | L13: =IF(R13="","",IF(INDEX('Recurring Schedule'!$J$6:$J$45,R13)="","",INDEX('Recurring Schedule'!$J$6:$J$45,R13))) | M13: =IF(R13="","",IF(INDEX('Recurring Schedule'!$K$6:$K$45,R13)="","",INDEX('Recurring Schedule'!$K$6:$K$45,R13))) | N13: =IF(R13="","",IF(INDEX('Recurring Schedule'!$L$6:$L$45,R13)="","",INDEX('Recurring Schedule'!$L$6:$L$45,R13))) | O13: =IF(C13="","",IF(AND(OR(L13="1-Urgent",L13="2-High"),M13="✓"),"DO FIRST",IF(M13="✓","SCHEDULE",IF(OR(L13="1-Urgent",L13="2-High"),"DELEGATE","DELETE")))) | Q13: =IF(8>Calc!$AQ$368,"",MATCH(7,Calc!$AQ$2:$AQ$367,1)) | R13: =IF(Q13="","",SMALL(INDEX(Calc!$B$2:$AO$367,Q13,0),8-INDEX(Calc!$AQ$2:$AQ$367,Q13)))
B14: =IF(R14="","",9) | C14: =IF(R14="","",IF(INDEX('Recurring Schedule'!$C$6:$C$45,R14)="","",INDEX('Recurring Schedule'!$C$6:$C$45,R14))) | D14: =IF(R14="","",IF(INDEX('Recurring Schedule'!$D$6:$D$45,R14)="","",INDEX('Recurring Schedule'!$D$6:$D$45,R14))) | E14: =IF(Q14="","",INDEX(Calc!$A$2:$A$367,Q14)) | F14: =IF(OR(C14="",E14=""),"",E14-Setup!$D$7) | G14: =IF(R14="","",IF(INDEX('Recurring Schedule'!$H$6:$H$45,R14)="","",INDEX('Recurring Schedule'!$H$6:$H$45,R14))) | H14: =IF(R14="","",IF(INDEX('Recurring Schedule'!$I$6:$I$45,R14)="","",INDEX('Recurring Schedule'!$I$6:$I$45,R14))) | I14: =IF(OR(G14="",H14=""),"",TRIM(IF(HOUR(H14-G14)>0,HOUR(H14-G14)&" hr ","")&IF(MINUTE(H14-G14)>0,MINUTE(H14-G14)&" min",""))) | L14: =IF(R14="","",IF(INDEX('Recurring Schedule'!$J$6:$J$45,R14)="","",INDEX('Recurring Schedule'!$J$6:$J$45,R14))) | M14: =IF(R14="","",IF(INDEX('Recurring Schedule'!$K$6:$K$45,R14)="","",INDEX('Recurring Schedule'!$K$6:$K$45,R14))) | N14: =IF(R14="","",IF(INDEX('Recurring Schedule'!$L$6:$L$45,R14)="","",INDEX('Recurring Schedule'!$L$6:$L$45,R14))) | O14: =IF(C14="","",IF(AND(OR(L14="1-Urgent",L14="2-High"),M14="✓"),"DO FIRST",IF(M14="✓","SCHEDULE",IF(OR(L14="1-Urgent",L14="2-High"),"DELEGATE","DELETE")))) | Q14: =IF(9>Calc!$AQ$368,"",MATCH(8,Calc!$AQ$2:$AQ$367,1)) | R14: =IF(Q14="","",SMALL(INDEX(Calc!$B$2:$AO$367,Q14,0),9-INDEX(Calc!$AQ$2:$AQ$367,Q14)))
B15: =IF(R15="","",10) | C15: =IF(R15="","",IF(INDEX('Recurring Schedule'!$C$6:$C$45,R15)="","",INDEX('Recurring Schedule'!$C$6:$C$45,R15))) | D15: =IF(R15="","",IF(INDEX('Recurring Schedule'!$D$6:$D$45,R15)="","",INDEX('Recurring Schedule'!$D$6:$D$45,R15))) | E15: =IF(Q15="","",INDEX(Calc!$A$2:$A$367,Q15)) | F15: =IF(OR(C15="",E15=""),"",E15-Setup!$D$7) | G15: =IF(R15="","",IF(INDEX('Recurring Schedule'!$H$6:$H$45,R15)="","",INDEX('Recurring Schedule'!$H$6:$H$45,R15))) | H15: =IF(R15="","",IF(INDEX('Recurring Schedule'!$I$6:$I$45,R15)="","",INDEX('Recurring Schedule'!$I$6:$I$45,R15))) | I15: =IF(OR(G15="",H15=""),"",TRIM(IF(HOUR(H15-G15)>0,HOUR(H15-G15)&" hr ","")&IF(MINUTE(H15-G15)>0,MINUTE(H15-G15)&" min",""))) | L15: =IF(R15="","",IF(INDEX('Recurring Schedule'!$J$6:$J$45,R15)="","",INDEX('Recurring Schedule'!$J$6:$J$45,R15))) | M15: =IF(R15="","",IF(INDEX('Recurring Schedule'!$K$6:$K$45,R15)="","",INDEX('Recurring Schedule'!$K$6:$K$45,R15))) | N15: =IF(R15="","",IF(INDEX('Recurring Schedule'!$L$6:$L$45,R15)="","",INDEX('Recurring Schedule'!$L$6:$L$45,R15))) | O15: =IF(C15="","",IF(AND(OR(L15="1-Urgent",L15="2-High"),M15="✓"),"DO FIRST",IF(M15="✓","SCHEDULE",IF(OR(L15="1-Urgent",L15="2-High"),"DELEGATE","DELETE")))) | Q15: =IF(10>Calc!$AQ$368,"",MATCH(9,Calc!$AQ$2:$AQ$367,1)) | R15: =IF(Q15="","",SMALL(INDEX(Calc!$B$2:$AO$367,Q15,0),10-INDEX(Calc!$AQ$2:$AQ$367,Q15)))
B16: =IF(R16="","",11) | C16: =IF(R16="","",IF(INDEX('Recurring Schedule'!$C$6:$C$45,R16)="","",INDEX('Recurring Schedule'!$C$6:$C$45,R16))) | D16: =IF(R16="","",IF(INDEX('Recurring Schedule'!$D$6:$D$45,R16)="","",INDEX('Recurring Schedule'!$D$6:$D$45,R16))) | E16: =IF(Q16="","",INDEX(Calc!$A$2:$A$367,Q16)) | F16: =IF(OR(C16="",E16=""),"",E16-Setup!$D$7) | G16: =IF(R16="","",IF(INDEX('Recurring Schedule'!$H$6:$H$45,R16)="","",INDEX('Recurring Schedule'!$H$6:$H$45,R16))) | H16: =IF(R16="","",IF(INDEX('Recurring Schedule'!$I$6:$I$45,R16)="","",INDEX('Recurring Schedule'!$I$6:$I$45,R16))) | I16: =IF(OR(G16="",H16=""),"",TRIM(IF(HOUR(H16-G16)>0,HOUR(H16-G16)&" hr ","")&IF(MINUTE(H16-G16)>0,MINUTE(H16-G16)&" min",""))) | L16: =IF(R16="","",IF(INDEX('Recurring Schedule'!$J$6:$J$45,R16)="","",INDEX('Recurring Schedule'!$J$6:$J$45,R16))) | M16: =IF(R16="","",IF(INDEX('Recurring Schedule'!$K$6:$K$45,R16)="","",INDEX('Recurring Schedule'!$K$6:$K$45,R16))) | N16: =IF(R16="","",IF(INDEX('Recurring Schedule'!$L$6:$L$45,R16)="","",INDEX('Recurring Schedule'!$L$6:$L$45,R16))) | O16: =IF(C16="","",IF(AND(OR(L16="1-Urgent",L16="2-High"),M16="✓"),"DO FIRST",IF(M16="✓","SCHEDULE",IF(OR(L16="1-Urgent",L16="2-High"),"DELEGATE","DELETE")))) | Q16: =IF(11>Calc!$AQ$368,"",MATCH(10,Calc!$AQ$2:$AQ$367,1)) | R16: =IF(Q16="","",SMALL(INDEX(Calc!$B$2:$AO$367,Q16,0),11-INDEX(Calc!$AQ$2:$AQ$367,Q16)))
B17: =IF(R17="","",12) | C17: =IF(R17="","",IF(INDEX('Recurring Schedule'!$C$6:$C$45,R17)="","",INDEX('Recurring Schedule'!$C$6:$C$45,R17))) | D17: =IF(R17="","",IF(INDEX('Recurring Schedule'!$D$6:$D$45,R17)="","",INDEX('Recurring Schedule'!$D$6:$D$45,R17))) | E17: =IF(Q17="","",INDEX(Calc!$A$2:$A$367,Q17)) | F17: =IF(OR(C17="",E17=""),"",E17-Setup!$D$7) | G17: =IF(R17="","",IF(INDEX('Recurring Schedule'!$H$6:$H$45,R17)="","",INDEX('Recurring Schedule'!$H$6:$H$45,R17))) | H17: =IF(R17="","",IF(INDEX('Recurring Schedule'!$I$6:$I$45,R17)="","",INDEX('Recurring Schedule'!$I$6:$I$45,R17))) | I17: =IF(OR(G17="",H17=""),"",TRIM(IF(HOUR(H17-G17)>0,HOUR(H17-G17)&" hr ","")&IF(MINUTE(H17-G17)>0,MINUTE(H17-G17)&" min",""))) | L17: =IF(R17="","",IF(INDEX('Recurring Schedule'!$J$6:$J$45,R17)="","",INDEX('Recurring Schedule'!$J$6:$J$45,R17))) | M17: =IF(R17="","",IF(INDEX('Recurring Schedule'!$K$6:$K$45,R17)="","",INDEX('Recurring Schedule'!$K$6:$K$45,R17))) | N17: =IF(R17="","",IF(INDEX('Recurring Schedule'!$L$6:$L$45,R17)="","",INDEX('Recurring Schedule'!$L$6:$L$45,R17))) | O17: =IF(C17="","",IF(AND(OR(L17="1-Urgent",L17="2-High"),M17="✓"),"DO FIRST",IF(M17="✓","SCHEDULE",IF(OR(L17="1-Urgent",L17="2-High"),"DELEGATE","DELETE")))) | Q17: =IF(12>Calc!$AQ$368,"",MATCH(11,Calc!$AQ$2:$AQ$367,1)) | R17: =IF(Q17="","",SMALL(INDEX(Calc!$B$2:$AO$367,Q17,0),12-INDEX(Calc!$AQ$2:$AQ$367,Q17)))
B18: =IF(R18="","",13) | C18: =IF(R18="","",IF(INDEX('Recurring Schedule'!$C$6:$C$45,R18)="","",INDEX('Recurring Schedule'!$C$6:$C$45,R18))) | D18: =IF(R18="","",IF(INDEX('Recurring Schedule'!$D$6:$D$45,R18)="","",INDEX('Recurring Schedule'!$D$6:$D$45,R18))) | E18: =IF(Q18="","",INDEX(Calc!$A$2:$A$367,Q18)) | F18: =IF(OR(C18="",E18=""),"",E18-Setup!$D$7) | G18: =IF(R18="","",IF(INDEX('Recurring Schedule'!$H$6:$H$45,R18)="","",INDEX('Recurring Schedule'!$H$6:$H$45,R18))) | H18: =IF(R18="","",IF(INDEX('Recurring Schedule'!$I$6:$I$45,R18)="","",INDEX('Recurring Schedule'!$I$6:$I$45,R18))) | I18: =IF(OR(G18="",H18=""),"",TRIM(IF(HOUR(H18-G18)>0,HOUR(H18-G18)&" hr ","")&IF(MINUTE(H18-G18)>0,MINUTE(H18-G18)&" min",""))) | L18: =IF(R18="","",IF(INDEX('Recurring Schedule'!$J$6:$J$45,R18)="","",INDEX('Recurring Schedule'!$J$6:$J$45,R18))) | M18: =IF(R18="","",IF(INDEX('Recurring Schedule'!$K$6:$K$45,R18)="","",INDEX('Recurring Schedule'!$K$6:$K$45,R18))) | N18: =IF(R18="","",IF(INDEX('Recurring Schedule'!$L$6:$L$45,R18)="","",INDEX('Recurring Schedule'!$L$6:$L$45,R18))) | O18: =IF(C18="","",IF(AND(OR(L18="1-Urgent",L18="2-High"),M18="✓"),"DO FIRST",IF(M18="✓","SCHEDULE",IF(OR(L18="1-Urgent",L18="2-High"),"DELEGATE","DELETE")))) | Q18: =IF(13>Calc!$AQ$368,"",MATCH(12,Calc!$AQ$2:$AQ$367,1)) | R18: =IF(Q18="","",SMALL(INDEX(Calc!$B$2:$AO$367,Q18,0),13-INDEX(Calc!$AQ$2:$AQ$367,Q18)))
B19: =IF(R19="","",14) | C19: =IF(R19="","",IF(INDEX('Recurring Schedule'!$C$6:$C$45,R19)="","",INDEX('Recurring Schedule'!$C$6:$C$45,R19))) | D19: =IF(R19="","",IF(INDEX('Recurring Schedule'!$D$6:$D$45,R19)="","",INDEX('Recurring Schedule'!$D$6:$D$45,R19))) | E19: =IF(Q19="","",INDEX(Calc!$A$2:$A$367,Q19)) | F19: =IF(OR(C19="",E19=""),"",E19-Setup!$D$7) | G19: =IF(R19="","",IF(INDEX('Recurring Schedule'!$H$6:$H$45,R19)="","",INDEX('Recurring Schedule'!$H$6:$H$45,R19))) | H19: =IF(R19="","",IF(INDEX('Recurring Schedule'!$I$6:$I$45,R19)="","",INDEX('Recurring Schedule'!$I$6:$I$45,R19))) | I19: =IF(OR(G19="",H19=""),"",TRIM(IF(HOUR(H19-G19)>0,HOUR(H19-G19)&" hr ","")&IF(MINUTE(H19-G19)>0,MINUTE(H19-G19)&" min",""))) | L19: =IF(R19="","",IF(INDEX('Recurring Schedule'!$J$6:$J$45,R19)="","",INDEX('Recurring Schedule'!$J$6:$J$45,R19))) | M19: =IF(R19="","",IF(INDEX('Recurring Schedule'!$K$6:$K$45,R19)="","",INDEX('Recurring Schedule'!$K$6:$K$45,R19))) | N19: =IF(R19="","",IF(INDEX('Recurring Schedule'!$L$6:$L$45,R19)="","",INDEX('Recurring Schedule'!$L$6:$L$45,R19))) | O19: =IF(C19="","",IF(AND(OR(L19="1-Urgent",L19="2-High"),M19="✓"),"DO FIRST",IF(M19="✓","SCHEDULE",IF(OR(L19="1-Urgent",L19="2-High"),"DELEGATE","DELETE")))) | Q19: =IF(14>Calc!$AQ$368,"",MATCH(13,Calc!$AQ$2:$AQ$367,1)) | R19: =IF(Q19="","",SMALL(INDEX(Calc!$B$2:$AO$367,Q19,0),14-INDEX(Calc!$AQ$2:$AQ$367,Q19)))
B20: =IF(R20="","",15) | C20: =IF(R20="","",IF(INDEX('Recurring Schedule'!$C$6:$C$45,R20)="","",INDEX('Recurring Schedule'!$C$6:$C$45,R20))) | D20: =IF(R20="","",IF(INDEX('Recurring Schedule'!$D$6:$D$45,R20)="","",INDEX('Recurring Schedule'!$D$6:$D$45,R20))) | E20: =IF(Q20="","",INDEX(Calc!$A$2:$A$367,Q20)) | F20: =IF(OR(C20="",E20=""),"",E20-Setup!$D$7) | G20: =IF(R20="","",IF(INDEX('Recurring Schedule'!$H$6:$H$45,R20)="","",INDEX('Recurring Schedule'!$H$6:$H$45,R20))) | H20: =IF(R20="","",IF(INDEX('Recurring Schedule'!$I$6:$I$45,R20)="","",INDEX('Recurring Schedule'!$I$6:$I$45,R20))) | I20: =IF(OR(G20="",H20=""),"",TRIM(IF(HOUR(H20-G20)>0,HOUR(H20-G20)&" hr ","")&IF(MINUTE(H20-G20)>0,MINUTE(H20-G20)&" min",""))) | L20: =IF(R20="","",IF(INDEX('Recurring Schedule'!$J$6:$J$45,R20)="","",INDEX('Recurring Schedule'!$J$6:$J$45,R20))) | M20: =IF(R20="","",IF(INDEX('Recurring Schedule'!$K$6:$K$45,R20)="","",INDEX('Recurring Schedule'!$K$6:$K$45,R20))) | N20: =IF(R20="","",IF(INDEX('Recurring Schedule'!$L$6:$L$45,R20)="","",INDEX('Recurring Schedule'!$L$6:$L$45,R20))) | O20: =IF(C20="","",IF(AND(OR(L20="1-Urgent",L20="2-High"),M20="✓"),"DO FIRST",IF(M20="✓","SCHEDULE",IF(OR(L20="1-Urgent",L20="2-High"),"DELEGATE","DELETE")))) | Q20: =IF(15>Calc!$AQ$368,"",MATCH(14,Calc!$AQ$2:$AQ$367,1)) | R20: =IF(Q20="","",SMALL(INDEX(Calc!$B$2:$AO$367,Q20,0),15-INDEX(Calc!$AQ$2:$AQ$367,Q20)))
B21: =IF(R21="","",16) | C21: =IF(R21="","",IF(INDEX('Recurring Schedule'!$C$6:$C$45,R21)="","",INDEX('Recurring Schedule'!$C$6:$C$45,R21))) | D21: =IF(R21="","",IF(INDEX('Recurring Schedule'!$D$6:$D$45,R21)="","",INDEX('Recurring Schedule'!$D$6:$D$45,R21))) | E21: =IF(Q21="","",INDEX(Calc!$A$2:$A$367,Q21)) | F21: =IF(OR(C21="",E21=""),"",E21-Setup!$D$7) | G21: =IF(R21="","",IF(INDEX('Recurring Schedule'!$H$6:$H$45,R21)="","",INDEX('Recurring Schedule'!$H$6:$H$45,R21))) | H21: =IF(R21="","",IF(INDEX('Recurring Schedule'!$I$6:$I$45,R21)="","",INDEX('Recurring Schedule'!$I$6:$I$45,R21))) | I21: =IF(OR(G21="",H21=""),"",TRIM(IF(HOUR(H21-G21)>0,HOUR(H21-G21)&" hr ","")&IF(MINUTE(H21-G21)>0,MINUTE(H21-G21)&" min",""))) | L21: =IF(R21="","",IF(INDEX('Recurring Schedule'!$J$6:$J$45,R21)="","",INDEX('Recurring Schedule'!$J$6:$J$45,R21))) | M21: =IF(R21="","",IF(INDEX('Recurring Schedule'!$K$6:$K$45,R21)="","",INDEX('Recurring Schedule'!$K$6:$K$45,R21))) | N21: =IF(R21="","",IF(INDEX('Recurring Schedule'!$L$6:$L$45,R21)="","",INDEX('Recurring Schedule'!$L$6:$L$45,R21))) | O21: =IF(C21="","",IF(AND(OR(L21="1-Urgent",L21="2-High"),M21="✓"),"DO FIRST",IF(M21="✓","SCHEDULE",IF(OR(L21="1-Urgent",L21="2-High"),"DELEGATE","DELETE")))) | Q21: =IF(16>Calc!$AQ$368,"",MATCH(15,Calc!$AQ$2:$AQ$367,1)) | R21: =IF(Q21="","",SMALL(INDEX(Calc!$B$2:$AO$367,Q21,0),16-INDEX(Calc!$AQ$2:$AQ$367,Q21)))
B22: =IF(R22="","",17) | C22: =IF(R22="","",IF(INDEX('Recurring Schedule'!$C$6:$C$45,R22)="","",INDEX('Recurring Schedule'!$C$6:$C$45,R22))) | D22: =IF(R22="","",IF(INDEX('Recurring Schedule'!$D$6:$D$45,R22)="","",INDEX('Recurring Schedule'!$D$6:$D$45,R22))) | E22: =IF(Q22="","",INDEX(Calc!$A$2:$A$367,Q22)) | F22: =IF(OR(C22="",E22=""),"",E22-Setup!$D$7) | G22: =IF(R22="","",IF(INDEX('Recurring Schedule'!$H$6:$H$45,R22)="","",INDEX('Recurring Schedule'!$H$6:$H$45,R22))) | H22: =IF(R22="","",IF(INDEX('Recurring Schedule'!$I$6:$I$45,R22)="","",INDEX('Recurring Schedule'!$I$6:$I$45,R22))) | I22: =IF(OR(G22="",H22=""),"",TRIM(IF(HOUR(H22-G22)>0,HOUR(H22-G22)&" hr ","")&IF(MINUTE(H22-G22)>0,MINUTE(H22-G22)&" min",""))) | L22: =IF(R22="","",IF(INDEX('Recurring Schedule'!$J$6:$J$45,R22)="","",INDEX('Recurring Schedule'!$J$6:$J$45,R22))) | M22: =IF(R22="","",IF(INDEX('Recurring Schedule'!$K$6:$K$45,R22)="","",INDEX('Recurring Schedule'!$K$6:$K$45,R22))) | N22: =IF(R22="","",IF(INDEX('Recurring Schedule'!$L$6:$L$45,R22)="","",INDEX('Recurring Schedule'!$L$6:$L$45,R22))) | O22: =IF(C22="","",IF(AND(OR(L22="1-Urgent",L22="2-High"),M22="✓"),"DO FIRST",IF(M22="✓","SCHEDULE",IF(OR(L22="1-Urgent",L22="2-High"),"DELEGATE","DELETE")))) | Q22: =IF(17>Calc!$AQ$368,"",MATCH(16,Calc!$AQ$2:$AQ$367,1)) | R22: =IF(Q22="","",SMALL(INDEX(Calc!$B$2:$AO$367,Q22,0),17-INDEX(Calc!$AQ$2:$AQ$367,Q22)))
B23: =IF(R23="","",18) | C23: =IF(R23="","",IF(INDEX('Recurring Schedule'!$C$6:$C$45,R23)="","",INDEX('Recurring Schedule'!$C$6:$C$45,R23))) | D23: =IF(R23="","",IF(INDEX('Recurring Schedule'!$D$6:$D$45,R23)="","",INDEX('Recurring Schedule'!$D$6:$D$45,R23))) | E23: =IF(Q23="","",INDEX(Calc!$A$2:$A$367,Q23)) | F23: =IF(OR(C23="",E23=""),"",E23-Setup!$D$7) | G23: =IF(R23="","",IF(INDEX('Recurring Schedule'!$H$6:$H$45,R23)="","",INDEX('Recurring Schedule'!$H$6:$H$45,R23))) | H23: =IF(R23="","",IF(INDEX('Recurring Schedule'!$I$6:$I$45,R23)="","",INDEX('Recurring Schedule'!$I$6:$I$45,R23))) | I23: =IF(OR(G23="",H23=""),"",TRIM(IF(HOUR(H23-G23)>0,HOUR(H23-G23)&" hr ","")&IF(MINUTE(H23-G23)>0,MINUTE(H23-G23)&" min",""))) | L23: =IF(R23="","",IF(INDEX('Recurring Schedule'!$J$6:$J$45,R23)="","",INDEX('Recurring Schedule'!$J$6:$J$45,R23))) | M23: =IF(R23="","",IF(INDEX('Recurring Schedule'!$K$6:$K$45,R23)="","",INDEX('Recurring Schedule'!$K$6:$K$45,R23))) | N23: =IF(R23="","",IF(INDEX('Recurring Schedule'!$L$6:$L$45,R23)="","",INDEX('Recurring Schedule'!$L$6:$L$45,R23))) | O23: =IF(C23="","",IF(AND(OR(L23="1-Urgent",L23="2-High"),M23="✓"),"DO FIRST",IF(M23="✓","SCHEDULE",IF(OR(L23="1-Urgent",L23="2-High"),"DELEGATE","DELETE")))) | Q23: =IF(18>Calc!$AQ$368,"",MATCH(17,Calc!$AQ$2:$AQ$367,1)) | R23: =IF(Q23="","",SMALL(INDEX(Calc!$B$2:$AO$367,Q23,0),18-INDEX(Calc!$AQ$2:$AQ$367,Q23)))
B24: =IF(R24="","",19) | C24: =IF(R24="","",IF(INDEX('Recurring Schedule'!$C$6:$C$45,R24)="","",INDEX('Recurring Schedule'!$C$6:$C$45,R24))) | D24: =IF(R24="","",IF(INDEX('Recurring Schedule'!$D$6:$D$45,R24)="","",INDEX('Recurring Schedule'!$D$6:$D$45,R24))) | E24: =IF(Q24="","",INDEX(Calc!$A$2:$A$367,Q24)) | F24: =IF(OR(C24="",E24=""),"",E24-Setup!$D$7) | G24: =IF(R24="","",IF(INDEX('Recurring Schedule'!$H$6:$H$45,R24)="","",INDEX('Recurring Schedule'!$H$6:$H$45,R24))) | H24: =IF(R24="","",IF(INDEX('Recurring Schedule'!$I$6:$I$45,R24)="","",INDEX('Recurring Schedule'!$I$6:$I$45,R24))) | I24: =IF(OR(G24="",H24=""),"",TRIM(IF(HOUR(H24-G24)>0,HOUR(H24-G24)&" hr ","")&IF(MINUTE(H24-G24)>0,MINUTE(H24-G24)&" min",""))) | L24: =IF(R24="","",IF(INDEX('Recurring Schedule'!$J$6:$J$45,R24)="","",INDEX('Recurring Schedule'!$J$6:$J$45,R24))) | M24: =IF(R24="","",IF(INDEX('Recurring Schedule'!$K$6:$K$45,R24)="","",INDEX('Recurring Schedule'!$K$6:$K$45,R24))) | N24: =IF(R24="","",IF(INDEX('Recurring Schedule'!$L$6:$L$45,R24)="","",INDEX('Recurring Schedule'!$L$6:$L$45,R24))) | O24: =IF(C24="","",IF(AND(OR(L24="1-Urgent",L24="2-High"),M24="✓"),"DO FIRST",IF(M24="✓","SCHEDULE",IF(OR(L24="1-Urgent",L24="2-High"),"DELEGATE","DELETE")))) | Q24: =IF(19>Calc!$AQ$368,"",MATCH(18,Calc!$AQ$2:$AQ$367,1)) | R24: =IF(Q24="","",SMALL(INDEX(Calc!$B$2:$AO$367,Q24,0),19-INDEX(Calc!$AQ$2:$AQ$367,Q24)))
B25: =IF(R25="","",20) | C25: =IF(R25="","",IF(INDEX('Recurring Schedule'!$C$6:$C$45,R25)="","",INDEX('Recurring Schedule'!$C$6:$C$45,R25))) | D25: =IF(R25="","",IF(INDEX('Recurring Schedule'!$D$6:$D$45,R25)="","",INDEX('Recurring Schedule'!$D$6:$D$45,R25))) | E25: =IF(Q25="","",INDEX(Calc!$A$2:$A$367,Q25)) | F25: =IF(OR(C25="",E25=""),"",E25-Setup!$D$7) | G25: =IF(R25="","",IF(INDEX('Recurring Schedule'!$H$6:$H$45,R25)="","",INDEX('Recurring Schedule'!$H$6:$H$45,R25))) | H25: =IF(R25="","",IF(INDEX('Recurring Schedule'!$I$6:$I$45,R25)="","",INDEX('Recurring Schedule'!$I$6:$I$45,R25))) | I25: =IF(OR(G25="",H25=""),"",TRIM(IF(HOUR(H25-G25)>0,HOUR(H25-G25)&" hr ","")&IF(MINUTE(H25-G25)>0,MINUTE(H25-G25)&" min",""))) | L25: =IF(R25="","",IF(INDEX('Recurring Schedule'!$J$6:$J$45,R25)="","",INDEX('Recurring Schedule'!$J$6:$J$45,R25))) | M25: =IF(R25="","",IF(INDEX('Recurring Schedule'!$K$6:$K$45,R25)="","",INDEX('Recurring Schedule'!$K$6:$K$45,R25))) | N25: =IF(R25="","",IF(INDEX('Recurring Schedule'!$L$6:$L$45,R25)="","",INDEX('Recurring Schedule'!$L$6:$L$45,R25))) | O25: =IF(C25="","",IF(AND(OR(L25="1-Urgent",L25="2-High"),M25="✓"),"DO FIRST",IF(M25="✓","SCHEDULE",IF(OR(L25="1-Urgent",L25="2-High"),"DELEGATE","DELETE")))) | Q25: =IF(20>Calc!$AQ$368,"",MATCH(19,Calc!$AQ$2:$AQ$367,1)) | R25: =IF(Q25="","",SMALL(INDEX(Calc!$B$2:$AO$367,Q25,0),20-INDEX(Calc!$AQ$2:$AQ$367,Q25)))
B26: =IF(R26="","",21) | C26: =IF(R26="","",IF(INDEX('Recurring Schedule'!$C$6:$C$45,R26)="","",INDEX('Recurring Schedule'!$C$6:$C$45,R26))) | D26: =IF(R26="","",IF(INDEX('Recurring Schedule'!$D$6:$D$45,R26)="","",INDEX('Recurring Schedule'!$D$6:$D$45,R26))) | E26: =IF(Q26="","",INDEX(Calc!$A$2:$A$367,Q26)) | F26: =IF(OR(C26="",E26=""),"",E26-Setup!$D$7) | G26: =IF(R26="","",IF(INDEX('Recurring Schedule'!$H$6:$H$45,R26)="","",INDEX('Recurring Schedule'!$H$6:$H$45,R26))) | H26: =IF(R26="","",IF(INDEX('Recurring Schedule'!$I$6:$I$45,R26)="","",INDEX('Recurring Schedule'!$I$6:$I$45,R26))) | I26: =IF(OR(G26="",H26=""),"",TRIM(IF(HOUR(H26-G26)>0,HOUR(H26-G26)&" hr ","")&IF(MINUTE(H26-G26)>0,MINUTE(H26-G26)&" min",""))) | L26: =IF(R26="","",IF(INDEX('Recurring Schedule'!$J$6:$J$45,R26)="","",INDEX('Recurring Schedule'!$J$6:$J$45,R26))) | M26: =IF(R26="","",IF(INDEX('Recurring Schedule'!$K$6:$K$45,R26)="","",INDEX('Recurring Schedule'!$K$6:$K$45,R26))) | N26: =IF(R26="","",IF(INDEX('Recurring Schedule'!$L$6:$L$45,R26)="","",INDEX('Recurring Schedule'!$L$6:$L$45,R26))) | O26: =IF(C26="","",IF(AND(OR(L26="1-Urgent",L26="2-High"),M26="✓"),"DO FIRST",IF(M26="✓","SCHEDULE",IF(OR(L26="1-Urgent",L26="2-High"),"DELEGATE","DELETE")))) | Q26: =IF(21>Calc!$AQ$368,"",MATCH(20,Calc!$AQ$2:$AQ$367,1)) | R26: =IF(Q26="","",SMALL(INDEX(Calc!$B$2:$AO$367,Q26,0),21-INDEX(Calc!$AQ$2:$AQ$367,Q26)))
B27: =IF(R27="","",22) | C27: =IF(R27="","",IF(INDEX('Recurring Schedule'!$C$6:$C$45,R27)="","",INDEX('Recurring Schedule'!$C$6:$C$45,R27))) | D27: =IF(R27="","",IF(INDEX('Recurring Schedule'!$D$6:$D$45,R27)="","",INDEX('Recurring Schedule'!$D$6:$D$45,R27))) | E27: =IF(Q27="","",INDEX(Calc!$A$2:$A$367,Q27)) | F27: =IF(OR(C27="",E27=""),"",E27-Setup!$D$7) | G27: =IF(R27="","",IF(INDEX('Recurring Schedule'!$H$6:$H$45,R27)="","",INDEX('Recurring Schedule'!$H$6:$H$45,R27))) | H27: =IF(R27="","",IF(INDEX('Recurring Schedule'!$I$6:$I$45,R27)="","",INDEX('Recurring Schedule'!$I$6:$I$45,R27))) | I27: =IF(OR(G27="",H27=""),"",TRIM(IF(HOUR(H27-G27)>0,HOUR(H27-G27)&" hr ","")&IF(MINUTE(H27-G27)>0,MINUTE(H27-G27)&" min",""))) | L27: =IF(R27="","",IF(INDEX('Recurring Schedule'!$J$6:$J$45,R27)="","",INDEX('Recurring Schedule'!$J$6:$J$45,R27))) | M27: =IF(R27="","",IF(INDEX('Recurring Schedule'!$K$6:$K$45,R27)="","",INDEX('Recurring Schedule'!$K$6:$K$45,R27))) | N27: =IF(R27="","",IF(INDEX('Recurring Schedule'!$L$6:$L$45,R27)="","",INDEX('Recurring Schedule'!$L$6:$L$45,R27))) | O27: =IF(C27="","",IF(AND(OR(L27="1-Urgent",L27="2-High"),M27="✓"),"DO FIRST",IF(M27="✓","SCHEDULE",IF(OR(L27="1-Urgent",L27="2-High"),"DELEGATE","DELETE")))) | Q27: =IF(22>Calc!$AQ$368,"",MATCH(21,Calc!$AQ$2:$AQ$367,1)) | R27: =IF(Q27="","",SMALL(INDEX(Calc!$B$2:$AO$367,Q27,0),22-INDEX(Calc!$AQ$2:$AQ$367,Q27)))
B28: =IF(R28="","",23) | C28: =IF(R28="","",IF(INDEX('Recurring Schedule'!$C$6:$C$45,R28)="","",INDEX('Recurring Schedule'!$C$6:$C$45,R28))) | D28: =IF(R28="","",IF(INDEX('Recurring Schedule'!$D$6:$D$45,R28)="","",INDEX('Recurring Schedule'!$D$6:$D$45,R28))) | E28: =IF(Q28="","",INDEX(Calc!$A$2:$A$367,Q28)) | F28: =IF(OR(C28="",E28=""),"",E28-Setup!$D$7) | G28: =IF(R28="","",IF(INDEX('Recurring Schedule'!$H$6:$H$45,R28)="","",INDEX('Recurring Schedule'!$H$6:$H$45,R28))) | H28: =IF(R28="","",IF(INDEX('Recurring Schedule'!$I$6:$I$45,R28)="","",INDEX('Recurring Schedule'!$I$6:$I$45,R28))) | I28: =IF(OR(G28="",H28=""),"",TRIM(IF(HOUR(H28-G28)>0,HOUR(H28-G28)&" hr ","")&IF(MINUTE(H28-G28)>0,MINUTE(H28-G28)&" min",""))) | L28: =IF(R28="","",IF(INDEX('Recurring Schedule'!$J$6:$J$45,R28)="","",INDEX('Recurring Schedule'!$J$6:$J$45,R28))) | M28: =IF(R28="","",IF(INDEX('Recurring Schedule'!$K$6:$K$45,R28)="","",INDEX('Recurring Schedule'!$K$6:$K$45,R28))) | N28: =IF(R28="","",IF(INDEX('Recurring Schedule'!$L$6:$L$45,R28)="","",INDEX('Recurring Schedule'!$L$6:$L$45,R28))) | O28: =IF(C28="","",IF(AND(OR(L28="1-Urgent",L28="2-High"),M28="✓"),"DO FIRST",IF(M28="✓","SCHEDULE",IF(OR(L28="1-Urgent",L28="2-High"),"DELEGATE","DELETE")))) | Q28: =IF(23>Calc!$AQ$368,"",MATCH(22,Calc!$AQ$2:$AQ$367,1)) | R28: =IF(Q28="","",SMALL(INDEX(Calc!$B$2:$AO$367,Q28,0),23-INDEX(Calc!$AQ$2:$AQ$367,Q28)))
B29: =IF(R29="","",24) | C29: =IF(R29="","",IF(INDEX('Recurring Schedule'!$C$6:$C$45,R29)="","",INDEX('Recurring Schedule'!$C$6:$C$45,R29))) | D29: =IF(R29="","",IF(INDEX('Recurring Schedule'!$D$6:$D$45,R29)="","",INDEX('Recurring Schedule'!$D$6:$D$45,R29))) | E29: =IF(Q29="","",INDEX(Calc!$A$2:$A$367,Q29)) | F29: =IF(OR(C29="",E29=""),"",E29-Setup!$D$7) | G29: =IF(R29="","",IF(INDEX('Recurring Schedule'!$H$6:$H$45,R29)="","",INDEX('Recurring Schedule'!$H$6:$H$45,R29))) | H29: =IF(R29="","",IF(INDEX('Recurring Schedule'!$I$6:$I$45,R29)="","",INDEX('Recurring Schedule'!$I$6:$I$45,R29))) | I29: =IF(OR(G29="",H29=""),"",TRIM(IF(HOUR(H29-G29)>0,HOUR(H29-G29)&" hr ","")&IF(MINUTE(H29-G29)>0,MINUTE(H29-G29)&" min",""))) | L29: =IF(R29="","",IF(INDEX('Recurring Schedule'!$J$6:$J$45,R29)="","",INDEX('Recurring Schedule'!$J$6:$J$45,R29))) | M29: =IF(R29="","",IF(INDEX('Recurring Schedule'!$K$6:$K$45,R29)="","",INDEX('Recurring Schedule'!$K$6:$K$45,R29))) | N29: =IF(R29="","",IF(INDEX('Recurring Schedule'!$L$6:$L$45,R29)="","",INDEX('Recurring Schedule'!$L$6:$L$45,R29))) | O29: =IF(C29="","",IF(AND(OR(L29="1-Urgent",L29="2-High"),M29="✓"),"DO FIRST",IF(M29="✓","SCHEDULE",IF(OR(L29="1-Urgent",L29="2-High"),"DELEGATE","DELETE")))) | Q29: =IF(24>Calc!$AQ$368,"",MATCH(23,Calc!$AQ$2:$AQ$367,1)) | R29: =IF(Q29="","",SMALL(INDEX(Calc!$B$2:$AO$367,Q29,0),24-INDEX(Calc!$AQ$2:$AQ$367,Q29)))
B30: =IF(R30="","",25) | C30: =IF(R30="","",IF(INDEX('Recurring Schedule'!$C$6:$C$45,R30)="","",INDEX('Recurring Schedule'!$C$6:$C$45,R30))) | D30: =IF(R30="","",IF(INDEX('Recurring Schedule'!$D$6:$D$45,R30)="","",INDEX('Recurring Schedule'!$D$6:$D$45,R30))) | E30: =IF(Q30="","",INDEX(Calc!$A$2:$A$367,Q30)) | F30: =IF(OR(C30="",E30=""),"",E30-Setup!$D$7) | G30: =IF(R30="","",IF(INDEX('Recurring Schedule'!$H$6:$H$45,R30)="","",INDEX('Recurring Schedule'!$H$6:$H$45,R30))) | H30: =IF(R30="","",IF(INDEX('Recurring Schedule'!$I$6:$I$45,R30)="","",INDEX('Recurring Schedule'!$I$6:$I$45,R30))) | I30: =IF(OR(G30="",H30=""),"",TRIM(IF(HOUR(H30-G30)>0,HOUR(H30-G30)&" hr ","")&IF(MINUTE(H30-G30)>0,MINUTE(H30-G30)&" min",""))) | L30: =IF(R30="","",IF(INDEX('Recurring Schedule'!$J$6:$J$45,R30)="","",INDEX('Recurring Schedule'!$J$6:$J$45,R30))) | M30: =IF(R30="","",IF(INDEX('Recurring Schedule'!$K$6:$K$45,R30)="","",INDEX('Recurring Schedule'!$K$6:$K$45,R30))) | N30: =IF(R30="","",IF(INDEX('Recurring Schedule'!$L$6:$L$45,R30)="","",INDEX('Recurring Schedule'!$L$6:$L$45,R30))) | O30: =IF(C30="","",IF(AND(OR(L30="1-Urgent",L30="2-High"),M30="✓"),"DO FIRST",IF(M30="✓","SCHEDULE",IF(OR(L30="1-Urgent",L30="2-High"),"DELEGATE","DELETE")))) | Q30: =IF(25>Calc!$AQ$368,"",MATCH(24,Calc!$AQ$2:$AQ$367,1)) | R30: =IF(Q30="","",SMALL(INDEX(Calc!$B$2:$AO$367,Q30,0),25-INDEX(Calc!$AQ$2:$AQ$367,Q30)))
B31: =IF(R31="","",26) | C31: =IF(R31="","",IF(INDEX('Recurring Schedule'!$C$6:$C$45,R31)="","",INDEX('Recurring Schedule'!$C$6:$C$45,R31))) | D31: =IF(R31="","",IF(INDEX('Recurring Schedule'!$D$6:$D$45,R31)="","",INDEX('Recurring Schedule'!$D$6:$D$45,R31))) | E31: =IF(Q31="","",INDEX(Calc!$A$2:$A$367,Q31)) | F31: =IF(OR(C31="",E31=""),"",E31-Setup!$D$7) | G31: =IF(R31="","",IF(INDEX('Recurring Schedule'!$H$6:$H$45,R31)="","",INDEX('Recurring Schedule'!$H$6:$H$45,R31))) | H31: =IF(R31="","",IF(INDEX('Recurring Schedule'!$I$6:$I$45,R31)="","",INDEX('Recurring Schedule'!$I$6:$I$45,R31))) | I31: =IF(OR(G31="",H31=""),"",TRIM(IF(HOUR(H31-G31)>0,HOUR(H31-G31)&" hr ","")&IF(MINUTE(H31-G31)>0,MINUTE(H31-G31)&" min",""))) | L31: =IF(R31="","",IF(INDEX('Recurring Schedule'!$J$6:$J$45,R31)="","",INDEX('Recurring Schedule'!$J$6:$J$45,R31))) | M31: =IF(R31="","",IF(INDEX('Recurring Schedule'!$K$6:$K$45,R31)="","",INDEX('Recurring Schedule'!$K$6:$K$45,R31))) | N31: =IF(R31="","",IF(INDEX('Recurring Schedule'!$L$6:$L$45,R31)="","",INDEX('Recurring Schedule'!$L$6:$L$45,R31))) | O31: =IF(C31="","",IF(AND(OR(L31="1-Urgent",L31="2-High"),M31="✓"),"DO FIRST",IF(M31="✓","SCHEDULE",IF(OR(L31="1-Urgent",L31="2-High"),"DELEGATE","DELETE")))) | Q31: =IF(26>Calc!$AQ$368,"",MATCH(25,Calc!$AQ$2:$AQ$367,1)) | R31: =IF(Q31="","",SMALL(INDEX(Calc!$B$2:$AO$367,Q31,0),26-INDEX(Calc!$AQ$2:$AQ$367,Q31)))
B32: =IF(R32="","",27) | C32: =IF(R32="","",IF(INDEX('Recurring Schedule'!$C$6:$C$45,R32)="","",INDEX('Recurring Schedule'!$C$6:$C$45,R32))) | D32: =IF(R32="","",IF(INDEX('Recurring Schedule'!$D$6:$D$45,R32)="","",INDEX('Recurring Schedule'!$D$6:$D$45,R32))) | E32: =IF(Q32="","",INDEX(Calc!$A$2:$A$367,Q32)) | F32: =IF(OR(C32="",E32=""),"",E32-Setup!$D$7) | G32: =IF(R32="","",IF(INDEX('Recurring Schedule'!$H$6:$H$45,R32)="","",INDEX('Recurring Schedule'!$H$6:$H$45,R32))) | H32: =IF(R32="","",IF(INDEX('Recurring Schedule'!$I$6:$I$45,R32)="","",INDEX('Recurring Schedule'!$I$6:$I$45,R32))) | I32: =IF(OR(G32="",H32=""),"",TRIM(IF(HOUR(H32-G32)>0,HOUR(H32-G32)&" hr ","")&IF(MINUTE(H32-G32)>0,MINUTE(H32-G32)&" min",""))) | L32: =IF(R32="","",IF(INDEX('Recurring Schedule'!$J$6:$J$45,R32)="","",INDEX('Recurring Schedule'!$J$6:$J$45,R32))) | M32: =IF(R32="","",IF(INDEX('Recurring Schedule'!$K$6:$K$45,R32)="","",INDEX('Recurring Schedule'!$K$6:$K$45,R32))) | N32: =IF(R32="","",IF(INDEX('Recurring Schedule'!$L$6:$L$45,R32)="","",INDEX('Recurring Schedule'!$L$6:$L$45,R32))) | O32: =IF(C32="","",IF(AND(OR(L32="1-Urgent",L32="2-High"),M32="✓"),"DO FIRST",IF(M32="✓","SCHEDULE",IF(OR(L32="1-Urgent",L32="2-High"),"DELEGATE","DELETE")))) | Q32: =IF(27>Calc!$AQ$368,"",MATCH(26,Calc!$AQ$2:$AQ$367,1)) | R32: =IF(Q32="","",SMALL(INDEX(Calc!$B$2:$AO$367,Q32,0),27-INDEX(Calc!$AQ$2:$AQ$367,Q32)))
B33: =IF(R33="","",28) | C33: =IF(R33="","",IF(INDEX('Recurring Schedule'!$C$6:$C$45,R33)="","",INDEX('Recurring Schedule'!$C$6:$C$45,R33))) | D33: =IF(R33="","",IF(INDEX('Recurring Schedule'!$D$6:$D$45,R33)="","",INDEX('Recurring Schedule'!$D$6:$D$45,R33))) | E33: =IF(Q33="","",INDEX(Calc!$A$2:$A$367,Q33)) | F33: =IF(OR(C33="",E33=""),"",E33-Setup!$D$7) | G33: =IF(R33="","",IF(INDEX('Recurring Schedule'!$H$6:$H$45,R33)="","",INDEX('Recurring Schedule'!$H$6:$H$45,R33))) | H33: =IF(R33="","",IF(INDEX('Recurring Schedule'!$I$6:$I$45,R33)="","",INDEX('Recurring Schedule'!$I$6:$I$45,R33))) | I33: =IF(OR(G33="",H33=""),"",TRIM(IF(HOUR(H33-G33)>0,HOUR(H33-G33)&" hr ","")&IF(MINUTE(H33-G33)>0,MINUTE(H33-G33)&" min",""))) | L33: =IF(R33="","",IF(INDEX('Recurring Schedule'!$J$6:$J$45,R33)="","",INDEX('Recurring Schedule'!$J$6:$J$45,R33))) | M33: =IF(R33="","",IF(INDEX('Recurring Schedule'!$K$6:$K$45,R33)="","",INDEX('Recurring Schedule'!$K$6:$K$45,R33))) | N33: =IF(R33="","",IF(INDEX('Recurring Schedule'!$L$6:$L$45,R33)="","",INDEX('Recurring Schedule'!$L$6:$L$45,R33))) | O33: =IF(C33="","",IF(AND(OR(L33="1-Urgent",L33="2-High"),M33="✓"),"DO FIRST",IF(M33="✓","SCHEDULE",IF(OR(L33="1-Urgent",L33="2-High"),"DELEGATE","DELETE")))) | Q33: =IF(28>Calc!$AQ$368,"",MATCH(27,Calc!$AQ$2:$AQ$367,1)) | R33: =IF(Q33="","",SMALL(INDEX(Calc!$B$2:$AO$367,Q33,0),28-INDEX(Calc!$AQ$2:$AQ$367,Q33)))
B34: =IF(R34="","",29) | C34: =IF(R34="","",IF(INDEX('Recurring Schedule'!$C$6:$C$45,R34)="","",INDEX('Recurring Schedule'!$C$6:$C$45,R34))) | D34: =IF(R34="","",IF(INDEX('Recurring Schedule'!$D$6:$D$45,R34)="","",INDEX('Recurring Schedule'!$D$6:$D$45,R34))) | E34: =IF(Q34="","",INDEX(Calc!$A$2:$A$367,Q34)) | F34: =IF(OR(C34="",E34=""),"",E34-Setup!$D$7) | G34: =IF(R34="","",IF(INDEX('Recurring Schedule'!$H$6:$H$45,R34)="","",INDEX('Recurring Schedule'!$H$6:$H$45,R34))) | H34: =IF(R34="","",IF(INDEX('Recurring Schedule'!$I$6:$I$45,R34)="","",INDEX('Recurring Schedule'!$I$6:$I$45,R34))) | I34: =IF(OR(G34="",H34=""),"",TRIM(IF(HOUR(H34-G34)>0,HOUR(H34-G34)&" hr ","")&IF(MINUTE(H34-G34)>0,MINUTE(H34-G34)&" min",""))) | L34: =IF(R34="","",IF(INDEX('Recurring Schedule'!$J$6:$J$45,R34)="","",INDEX('Recurring Schedule'!$J$6:$J$45,R34))) | M34: =IF(R34="","",IF(INDEX('Recurring Schedule'!$K$6:$K$45,R34)="","",INDEX('Recurring Schedule'!$K$6:$K$45,R34))) | N34: =IF(R34="","",IF(INDEX('Recurring Schedule'!$L$6:$L$45,R34)="","",INDEX('Recurring Schedule'!$L$6:$L$45,R34))) | O34: =IF(C34="","",IF(AND(OR(L34="1-Urgent",L34="2-High"),M34="✓"),"DO FIRST",IF(M34="✓","SCHEDULE",IF(OR(L34="1-Urgent",L34="2-High"),"DELEGATE","DELETE")))) | Q34: =IF(29>Calc!$AQ$368,"",MATCH(28,Calc!$AQ$2:$AQ$367,1)) | R34: =IF(Q34="","",SMALL(INDEX(Calc!$B$2:$AO$367,Q34,0),29-INDEX(Calc!$AQ$2:$AQ$367,Q34)))
B35: =IF(R35="","",30) | C35: =IF(R35="","",IF(INDEX('Recurring Schedule'!$C$6:$C$45,R35)="","",INDEX('Recurring Schedule'!$C$6:$C$45,R35))) | D35: =IF(R35="","",IF(INDEX('Recurring Schedule'!$D$6:$D$45,R35)="","",INDEX('Recurring Schedule'!$D$6:$D$45,R35))) | E35: =IF(Q35="","",INDEX(Calc!$A$2:$A$367,Q35)) | F35: =IF(OR(C35="",E35=""),"",E35-Setup!$D$7) | G35: =IF(R35="","",IF(INDEX('Recurring Schedule'!$H$6:$H$45,R35)="","",INDEX('Recurring Schedule'!$H$6:$H$45,R35))) | H35: =IF(R35="","",IF(INDEX('Recurring Schedule'!$I$6:$I$45,R35)="","",INDEX('Recurring Schedule'!$I$6:$I$45,R35))) | I35: =IF(OR(G35="",H35=""),"",TRIM(IF(HOUR(H35-G35)>0,HOUR(H35-G35)&" hr ","")&IF(MINUTE(H35-G35)>0,MINUTE(H35-G35)&" min",""))) | L35: =IF(R35="","",IF(INDEX('Recurring Schedule'!$J$6:$J$45,R35)="","",INDEX('Recurring Schedule'!$J$6:$J$45,R35))) | M35: =IF(R35="","",IF(INDEX('Recurring Schedule'!$K$6:$K$45,R35)="","",INDEX('Recurring Schedule'!$K$6:$K$45,R35))) | N35: =IF(R35="","",IF(INDEX('Recurring Schedule'!$L$6:$L$45,R35)="","",INDEX('Recurring Schedule'!$L$6:$L$45,R35))) | O35: =IF(C35="","",IF(AND(OR(L35="1-Urgent",L35="2-High"),M35="✓"),"DO FIRST",IF(M35="✓","SCHEDULE",IF(OR(L35="1-Urgent",L35="2-High"),"DELEGATE","DELETE")))) | Q35: =IF(30>Calc!$AQ$368,"",MATCH(29,Calc!$AQ$2:$AQ$367,1)) | R35: =IF(Q35="","",SMALL(INDEX(Calc!$B$2:$AO$367,Q35,0),30-INDEX(Calc!$AQ$2:$AQ$367,Q35)))
B36: =IF(R36="","",31) | C36: =IF(R36="","",IF(INDEX('Recurring Schedule'!$C$6:$C$45,R36)="","",INDEX('Recurring Schedule'!$C$6:$C$45,R36))) | D36: =IF(R36="","",IF(INDEX('Recurring Schedule'!$D$6:$D$45,R36)="","",INDEX('Recurring Schedule'!$D$6:$D$45,R36))) | E36: =IF(Q36="","",INDEX(Calc!$A$2:$A$367,Q36)) | F36: =IF(OR(C36="",E36=""),"",E36-Setup!$D$7) | G36: =IF(R36="","",IF(INDEX('Recurring Schedule'!$H$6:$H$45,R36)="","",INDEX('Recurring Schedule'!$H$6:$H$45,R36))) | H36: =IF(R36="","",IF(INDEX('Recurring Schedule'!$I$6:$I$45,R36)="","",INDEX('Recurring Schedule'!$I$6:$I$45,R36))) | I36: =IF(OR(G36="",H36=""),"",TRIM(IF(HOUR(H36-G36)>0,HOUR(H36-G36)&" hr ","")&IF(MINUTE(H36-G36)>0,MINUTE(H36-G36)&" min",""))) | L36: =IF(R36="","",IF(INDEX('Recurring Schedule'!$J$6:$J$45,R36)="","",INDEX('Recurring Schedule'!$J$6:$J$45,R36))) | M36: =IF(R36="","",IF(INDEX('Recurring Schedule'!$K$6:$K$45,R36)="","",INDEX('Recurring Schedule'!$K$6:$K$45,R36))) | N36: =IF(R36="","",IF(INDEX('Recurring Schedule'!$L$6:$L$45,R36)="","",INDEX('Recurring Schedule'!$L$6:$L$45,R36))) | O36: =IF(C36="","",IF(AND(OR(L36="1-Urgent",L36="2-High"),M36="✓"),"DO FIRST",IF(M36="✓","SCHEDULE",IF(OR(L36="1-Urgent",L36="2-High"),"DELEGATE","DELETE")))) | Q36: =IF(31>Calc!$AQ$368,"",MATCH(30,Calc!$AQ$2:$AQ$367,1)) | R36: =IF(Q36="","",SMALL(INDEX(Calc!$B$2:$AO$367,Q36,0),31-INDEX(Calc!$AQ$2:$AQ$367,Q36)))
B37: =IF(R37="","",32) | C37: =IF(R37="","",IF(INDEX('Recurring Schedule'!$C$6:$C$45,R37)="","",INDEX('Recurring Schedule'!$C$6:$C$45,R37))) | D37: =IF(R37="","",IF(INDEX('Recurring Schedule'!$D$6:$D$45,R37)="","",INDEX('Recurring Schedule'!$D$6:$D$45,R37))) | E37: =IF(Q37="","",INDEX(Calc!$A$2:$A$367,Q37)) | F37: =IF(OR(C37="",E37=""),"",E37-Setup!$D$7) | G37: =IF(R37="","",IF(INDEX('Recurring Schedule'!$H$6:$H$45,R37)="","",INDEX('Recurring Schedule'!$H$6:$H$45,R37))) | H37: =IF(R37="","",IF(INDEX('Recurring Schedule'!$I$6:$I$45,R37)="","",INDEX('Recurring Schedule'!$I$6:$I$45,R37))) | I37: =IF(OR(G37="",H37=""),"",TRIM(IF(HOUR(H37-G37)>0,HOUR(H37-G37)&" hr ","")&IF(MINUTE(H37-G37)>0,MINUTE(H37-G37)&" min",""))) | L37: =IF(R37="","",IF(INDEX('Recurring Schedule'!$J$6:$J$45,R37)="","",INDEX('Recurring Schedule'!$J$6:$J$45,R37))) | M37: =IF(R37="","",IF(INDEX('Recurring Schedule'!$K$6:$K$45,R37)="","",INDEX('Recurring Schedule'!$K$6:$K$45,R37))) | N37: =IF(R37="","",IF(INDEX('Recurring Schedule'!$L$6:$L$45,R37)="","",INDEX('Recurring Schedule'!$L$6:$L$45,R37))) | O37: =IF(C37="","",IF(AND(OR(L37="1-Urgent",L37="2-High"),M37="✓"),"DO FIRST",IF(M37="✓","SCHEDULE",IF(OR(L37="1-Urgent",L37="2-High"),"DELEGATE","DELETE")))) | Q37: =IF(32>Calc!$AQ$368,"",MATCH(31,Calc!$AQ$2:$AQ$367,1)) | R37: =IF(Q37="","",SMALL(INDEX(Calc!$B$2:$AO$367,Q37,0),32-INDEX(Calc!$AQ$2:$AQ$367,Q37)))
B38: =IF(R38="","",33) | C38: =IF(R38="","",IF(INDEX('Recurring Schedule'!$C$6:$C$45,R38)="","",INDEX('Recurring Schedule'!$C$6:$C$45,R38))) | D38: =IF(R38="","",IF(INDEX('Recurring Schedule'!$D$6:$D$45,R38)="","",INDEX('Recurring Schedule'!$D$6:$D$45,R38))) | E38: =IF(Q38="","",INDEX(Calc!$A$2:$A$367,Q38)) | F38: =IF(OR(C38="",E38=""),"",E38-Setup!$D$7) | G38: =IF(R38="","",IF(INDEX('Recurring Schedule'!$H$6:$H$45,R38)="","",INDEX('Recurring Schedule'!$H$6:$H$45,R38))) | H38: =IF(R38="","",IF(INDEX('Recurring Schedule'!$I$6:$I$45,R38)="","",INDEX('Recurring Schedule'!$I$6:$I$45,R38))) | I38: =IF(OR(G38="",H38=""),"",TRIM(IF(HOUR(H38-G38)>0,HOUR(H38-G38)&" hr ","")&IF(MINUTE(H38-G38)>0,MINUTE(H38-G38)&" min",""))) | L38: =IF(R38="","",IF(INDEX('Recurring Schedule'!$J$6:$J$45,R38)="","",INDEX('Recurring Schedule'!$J$6:$J$45,R38))) | M38: =IF(R38="","",IF(INDEX('Recurring Schedule'!$K$6:$K$45,R38)="","",INDEX('Recurring Schedule'!$K$6:$K$45,R38))) | N38: =IF(R38="","",IF(INDEX('Recurring Schedule'!$L$6:$L$45,R38)="","",INDEX('Recurring Schedule'!$L$6:$L$45,R38))) | O38: =IF(C38="","",IF(AND(OR(L38="1-Urgent",L38="2-High"),M38="✓"),"DO FIRST",IF(M38="✓","SCHEDULE",IF(OR(L38="1-Urgent",L38="2-High"),"DELEGATE","DELETE")))) | Q38: =IF(33>Calc!$AQ$368,"",MATCH(32,Calc!$AQ$2:$AQ$367,1)) | R38: =IF(Q38="","",SMALL(INDEX(Calc!$B$2:$AO$367,Q38,0),33-INDEX(Calc!$AQ$2:$AQ$367,Q38)))
B39: =IF(R39="","",34) | C39: =IF(R39="","",IF(INDEX('Recurring Schedule'!$C$6:$C$45,R39)="","",INDEX('Recurring Schedule'!$C$6:$C$45,R39))) | D39: =IF(R39="","",IF(INDEX('Recurring Schedule'!$D$6:$D$45,R39)="","",INDEX('Recurring Schedule'!$D$6:$D$45,R39))) | E39: =IF(Q39="","",INDEX(Calc!$A$2:$A$367,Q39)) | F39: =IF(OR(C39="",E39=""),"",E39-Setup!$D$7) | G39: =IF(R39="","",IF(INDEX('Recurring Schedule'!$H$6:$H$45,R39)="","",INDEX('Recurring Schedule'!$H$6:$H$45,R39))) | H39: =IF(R39="","",IF(INDEX('Recurring Schedule'!$I$6:$I$45,R39)="","",INDEX('Recurring Schedule'!$I$6:$I$45,R39))) | I39: =IF(OR(G39="",H39=""),"",TRIM(IF(HOUR(H39-G39)>0,HOUR(H39-G39)&" hr ","")&IF(MINUTE(H39-G39)>0,MINUTE(H39-G39)&" min",""))) | L39: =IF(R39="","",IF(INDEX('Recurring Schedule'!$J$6:$J$45,R39)="","",INDEX('Recurring Schedule'!$J$6:$J$45,R39))) | M39: =IF(R39="","",IF(INDEX('Recurring Schedule'!$K$6:$K$45,R39)="","",INDEX('Recurring Schedule'!$K$6:$K$45,R39))) | N39: =IF(R39="","",IF(INDEX('Recurring Schedule'!$L$6:$L$45,R39)="","",INDEX('Recurring Schedule'!$L$6:$L$45,R39))) | O39: =IF(C39="","",IF(AND(OR(L39="1-Urgent",L39="2-High"),M39="✓"),"DO FIRST",IF(M39="✓","SCHEDULE",IF(OR(L39="1-Urgent",L39="2-High"),"DELEGATE","DELETE")))) | Q39: =IF(34>Calc!$AQ$368,"",MATCH(33,Calc!$AQ$2:$AQ$367,1)) | R39: =IF(Q39="","",SMALL(INDEX(Calc!$B$2:$AO$367,Q39,0),34-INDEX(Calc!$AQ$2:$AQ$367,Q39)))
B40: =IF(R40="","",35) | C40: =IF(R40="","",IF(INDEX('Recurring Schedule'!$C$6:$C$45,R40)="","",INDEX('Recurring Schedule'!$C$6:$C$45,R40))) | D40: =IF(R40="","",IF(INDEX('Recurring Schedule'!$D$6:$D$45,R40)="","",INDEX('Recurring Schedule'!$D$6:$D$45,R40))) | E40: =IF(Q40="","",INDEX(Calc!$A$2:$A$367,Q40)) | F40: =IF(OR(C40="",E40=""),"",E40-Setup!$D$7) | G40: =IF(R40="","",IF(INDEX('Recurring Schedule'!$H$6:$H$45,R40)="","",INDEX('Recurring Schedule'!$H$6:$H$45,R40))) | H40: =IF(R40="","",IF(INDEX('Recurring Schedule'!$I$6:$I$45,R40)="","",INDEX('Recurring Schedule'!$I$6:$I$45,R40))) | I40: =IF(OR(G40="",H40=""),"",TRIM(IF(HOUR(H40-G40)>0,HOUR(H40-G40)&" hr ","")&IF(MINUTE(H40-G40)>0,MINUTE(H40-G40)&" min",""))) | L40: =IF(R40="","",IF(INDEX('Recurring Schedule'!$J$6:$J$45,R40)="","",INDEX('Recurring Schedule'!$J$6:$J$45,R40))) | M40: =IF(R40="","",IF(INDEX('Recurring Schedule'!$K$6:$K$45,R40)="","",INDEX('Recurring Schedule'!$K$6:$K$45,R40))) | N40: =IF(R40="","",IF(INDEX('Recurring Schedule'!$L$6:$L$45,R40)="","",INDEX('Recurring Schedule'!$L$6:$L$45,R40))) | O40: =IF(C40="","",IF(AND(OR(L40="1-Urgent",L40="2-High"),M40="✓"),"DO FIRST",IF(M40="✓","SCHEDULE",IF(OR(L40="1-Urgent",L40="2-High"),"DELEGATE","DELETE")))) | Q40: =IF(35>Calc!$AQ$368,"",MATCH(34,Calc!$AQ$2:$AQ$367,1)) | R40: =IF(Q40="","",SMALL(INDEX(Calc!$B$2:$AO$367,Q40,0),35-INDEX(Calc!$AQ$2:$AQ$367,Q40)))
B41: =IF(R41="","",36) | C41: =IF(R41="","",IF(INDEX('Recurring Schedule'!$C$6:$C$45,R41)="","",INDEX('Recurring Schedule'!$C$6:$C$45,R41))) | D41: =IF(R41="","",IF(INDEX('Recurring Schedule'!$D$6:$D$45,R41)="","",INDEX('Recurring Schedule'!$D$6:$D$45,R41))) | E41: =IF(Q41="","",INDEX(Calc!$A$2:$A$367,Q41)) | F41: =IF(OR(C41="",E41=""),"",E41-Setup!$D$7) | G41: =IF(R41="","",IF(INDEX('Recurring Schedule'!$H$6:$H$45,R41)="","",INDEX('Recurring Schedule'!$H$6:$H$45,R41))) | H41: =IF(R41="","",IF(INDEX('Recurring Schedule'!$I$6:$I$45,R41)="","",INDEX('Recurring Schedule'!$I$6:$I$45,R41))) | I41: =IF(OR(G41="",H41=""),"",TRIM(IF(HOUR(H41-G41)>0,HOUR(H41-G41)&" hr ","")&IF(MINUTE(H41-G41)>0,MINUTE(H41-G41)&" min",""))) | L41: =IF(R41="","",IF(INDEX('Recurring Schedule'!$J$6:$J$45,R41)="","",INDEX('Recurring Schedule'!$J$6:$J$45,R41))) | M41: =IF(R41="","",IF(INDEX('Recurring Schedule'!$K$6:$K$45,R41)="","",INDEX('Recurring Schedule'!$K$6:$K$45,R41))) | N41: =IF(R41="","",IF(INDEX('Recurring Schedule'!$L$6:$L$45,R41)="","",INDEX('Recurring Schedule'!$L$6:$L$45,R41))) | O41: =IF(C41="","",IF(AND(OR(L41="1-Urgent",L41="2-High"),M41="✓"),"DO FIRST",IF(M41="✓","SCHEDULE",IF(OR(L41="1-Urgent",L41="2-High"),"DELEGATE","DELETE")))) | Q41: =IF(36>Calc!$AQ$368,"",MATCH(35,Calc!$AQ$2:$AQ$367,1)) | R41: =IF(Q41="","",SMALL(INDEX(Calc!$B$2:$AO$367,Q41,0),36-INDEX(Calc!$AQ$2:$AQ$367,Q41)))
B42: =IF(R42="","",37) | C42: =IF(R42="","",IF(INDEX('Recurring Schedule'!$C$6:$C$45,R42)="","",INDEX('Recurring Schedule'!$C$6:$C$45,R42))) | D42: =IF(R42="","",IF(INDEX('Recurring Schedule'!$D$6:$D$45,R42)="","",INDEX('Recurring Schedule'!$D$6:$D$45,R42))) | E42: =IF(Q42="","",INDEX(Calc!$A$2:$A$367,Q42)) | F42: =IF(OR(C42="",E42=""),"",E42-Setup!$D$7) | G42: =IF(R42="","",IF(INDEX('Recurring Schedule'!$H$6:$H$45,R42)="","",INDEX('Recurring Schedule'!$H$6:$H$45,R42))) | H42: =IF(R42="","",IF(INDEX('Recurring Schedule'!$I$6:$I$45,R42)="","",INDEX('Recurring Schedule'!$I$6:$I$45,R42))) | I42: =IF(OR(G42="",H42=""),"",TRIM(IF(HOUR(H42-G42)>0,HOUR(H42-G42)&" hr ","")&IF(MINUTE(H42-G42)>0,MINUTE(H42-G42)&" min",""))) | L42: =IF(R42="","",IF(INDEX('Recurring Schedule'!$J$6:$J$45,R42)="","",INDEX('Recurring Schedule'!$J$6:$J$45,R42))) | M42: =IF(R42="","",IF(INDEX('Recurring Schedule'!$K$6:$K$45,R42)="","",INDEX('Recurring Schedule'!$K$6:$K$45,R42))) | N42: =IF(R42="","",IF(INDEX('Recurring Schedule'!$L$6:$L$45,R42)="","",INDEX('Recurring Schedule'!$L$6:$L$45,R42))) | O42: =IF(C42="","",IF(AND(OR(L42="1-Urgent",L42="2-High"),M42="✓"),"DO FIRST",IF(M42="✓","SCHEDULE",IF(OR(L42="1-Urgent",L42="2-High"),"DELEGATE","DELETE")))) | Q42: =IF(37>Calc!$AQ$368,"",MATCH(36,Calc!$AQ$2:$AQ$367,1)) | R42: =IF(Q42="","",SMALL(INDEX(Calc!$B$2:$AO$367,Q42,0),37-INDEX(Calc!$AQ$2:$AQ$367,Q42)))
B43: =IF(R43="","",38) | C43: =IF(R43="","",IF(INDEX('Recurring Schedule'!$C$6:$C$45,R43)="","",INDEX('Recurring Schedule'!$C$6:$C$45,R43))) | D43: =IF(R43="","",IF(INDEX('Recurring Schedule'!$D$6:$D$45,R43)="","",INDEX('Recurring Schedule'!$D$6:$D$45,R43))) | E43: =IF(Q43="","",INDEX(Calc!$A$2:$A$367,Q43)) | F43: =IF(OR(C43="",E43=""),"",E43-Setup!$D$7) | G43: =IF(R43="","",IF(INDEX('Recurring Schedule'!$H$6:$H$45,R43)="","",INDEX('Recurring Schedule'!$H$6:$H$45,R43))) | H43: =IF(R43="","",IF(INDEX('Recurring Schedule'!$I$6:$I$45,R43)="","",INDEX('Recurring Schedule'!$I$6:$I$45,R43))) | I43: =IF(OR(G43="",H43=""),"",TRIM(IF(HOUR(H43-G43)>0,HOUR(H43-G43)&" hr ","")&IF(MINUTE(H43-G43)>0,MINUTE(H43-G43)&" min",""))) | L43: =IF(R43="","",IF(INDEX('Recurring Schedule'!$J$6:$J$45,R43)="","",INDEX('Recurring Schedule'!$J$6:$J$45,R43))) | M43: =IF(R43="","",IF(INDEX('Recurring Schedule'!$K$6:$K$45,R43)="","",INDEX('Recurring Schedule'!$K$6:$K$45,R43))) | N43: =IF(R43="","",IF(INDEX('Recurring Schedule'!$L$6:$L$45,R43)="","",INDEX('Recurring Schedule'!$L$6:$L$45,R43))) | O43: =IF(C43="","",IF(AND(OR(L43="1-Urgent",L43="2-High"),M43="✓"),"DO FIRST",IF(M43="✓","SCHEDULE",IF(OR(L43="1-Urgent",L43="2-High"),"DELEGATE","DELETE")))) | Q43: =IF(38>Calc!$AQ$368,"",MATCH(37,Calc!$AQ$2:$AQ$367,1)) | R43: =IF(Q43="","",SMALL(INDEX(Calc!$B$2:$AO$367,Q43,0),38-INDEX(Calc!$AQ$2:$AQ$367,Q43)))
B44: =IF(R44="","",39) | C44: =IF(R44="","",IF(INDEX('Recurring Schedule'!$C$6:$C$45,R44)="","",INDEX('Recurring Schedule'!$C$6:$C$45,R44))) | D44: =IF(R44="","",IF(INDEX('Recurring Schedule'!$D$6:$D$45,R44)="","",INDEX('Recurring Schedule'!$D$6:$D$45,R44))) | E44: =IF(Q44="","",INDEX(Calc!$A$2:$A$367,Q44)) | F44: =IF(OR(C44="",E44=""),"",E44-Setup!$D$7) | G44: =IF(R44="","",IF(INDEX('Recurring Schedule'!$H$6:$H$45,R44)="","",INDEX('Recurring Schedule'!$H$6:$H$45,R44))) | H44: =IF(R44="","",IF(INDEX('Recurring Schedule'!$I$6:$I$45,R44)="","",INDEX('Recurring Schedule'!$I$6:$I$45,R44))) | I44: =IF(OR(G44="",H44=""),"",TRIM(IF(HOUR(H44-G44)>0,HOUR(H44-G44)&" hr ","")&IF(MINUTE(H44-G44)>0,MINUTE(H44-G44)&" min",""))) | L44: =IF(R44="","",IF(INDEX('Recurring Schedule'!$J$6:$J$45,R44)="","",INDEX('Recurring Schedule'!$J$6:$J$45,R44))) | M44: =IF(R44="","",IF(INDEX('Recurring Schedule'!$K$6:$K$45,R44)="","",INDEX('Recurring Schedule'!$K$6:$K$45,R44))) | N44: =IF(R44="","",IF(INDEX('Recurring Schedule'!$L$6:$L$45,R44)="","",INDEX('Recurring Schedule'!$L$6:$L$45,R44))) | O44: =IF(C44="","",IF(AND(OR(L44="1-Urgent",L44="2-High"),M44="✓"),"DO FIRST",IF(M44="✓","SCHEDULE",IF(OR(L44="1-Urgent",L44="2-High"),"DELEGATE","DELETE")))) | Q44: =IF(39>Calc!$AQ$368,"",MATCH(38,Calc!$AQ$2:$AQ$367,1)) | R44: =IF(Q44="","",SMALL(INDEX(Calc!$B$2:$AO$367,Q44,0),39-INDEX(Calc!$AQ$2:$AQ$367,Q44)))
B45: =IF(R45="","",40) | C45: =IF(R45="","",IF(INDEX('Recurring Schedule'!$C$6:$C$45,R45)="","",INDEX('Recurring Schedule'!$C$6:$C$45,R45))) | D45: =IF(R45="","",IF(INDEX('Recurring Schedule'!$D$6:$D$45,R45)="","",INDEX('Recurring Schedule'!$D$6:$D$45,R45))) | E45: =IF(Q45="","",INDEX(Calc!$A$2:$A$367,Q45)) | F45: =IF(OR(C45="",E45=""),"",E45-Setup!$D$7) | G45: =IF(R45="","",IF(INDEX('Recurring Schedule'!$H$6:$H$45,R45)="","",INDEX('Recurring Schedule'!$H$6:$H$45,R45))) | H45: =IF(R45="","",IF(INDEX('Recurring Schedule'!$I$6:$I$45,R45)="","",INDEX('Recurring Schedule'!$I$6:$I$45,R45))) | I45: =IF(OR(G45="",H45=""),"",TRIM(IF(HOUR(H45-G45)>0,HOUR(H45-G45)&" hr ","")&IF(MINUTE(H45-G45)>0,MINUTE(H45-G45)&" min",""))) | L45: =IF(R45="","",IF(INDEX('Recurring Schedule'!$J$6:$J$45,R45)="","",INDEX('Recurring Schedule'!$J$6:$J$45,R45))) | M45: =IF(R45="","",IF(INDEX('Recurring Schedule'!$K$6:$K$45,R45)="","",INDEX('Recurring Schedule'!$K$6:$K$45,R45))) | N45: =IF(R45="","",IF(INDEX('Recurring Schedule'!$L$6:$L$45,R45)="","",INDEX('Recurring Schedule'!$L$6:$L$45,R45))) | O45: =IF(C45="","",IF(AND(OR(L45="1-Urgent",L45="2-High"),M45="✓"),"DO FIRST",IF(M45="✓","SCHEDULE",IF(OR(L45="1-Urgent",L45="2-High"),"DELEGATE","DELETE")))) | Q45: =IF(40>Calc!$AQ$368,"",MATCH(39,Calc!$AQ$2:$AQ$367,1)) | R45: =IF(Q45="","",SMALL(INDEX(Calc!$B$2:$AO$367,Q45,0),40-INDEX(Calc!$AQ$2:$AQ$367,Q45)))
B46: =IF(R46="","",41) | C46: =IF(R46="","",IF(INDEX('Recurring Schedule'!$C$6:$C$45,R46)="","",INDEX('Recurring Schedule'!$C$6:$C$45,R46))) | D46: =IF(R46="","",IF(INDEX('Recurring Schedule'!$D$6:$D$45,R46)="","",INDEX('Recurring Schedule'!$D$6:$D$45,R46))) | E46: =IF(Q46="","",INDEX(Calc!$A$2:$A$367,Q46)) | F46: =IF(OR(C46="",E46=""),"",E46-Setup!$D$7) | G46: =IF(R46="","",IF(INDEX('Recurring Schedule'!$H$6:$H$45,R46)="","",INDEX('Recurring Schedule'!$H$6:$H$45,R46))) | H46: =IF(R46="","",IF(INDEX('Recurring Schedule'!$I$6:$I$45,R46)="","",INDEX('Recurring Schedule'!$I$6:$I$45,R46))) | I46: =IF(OR(G46="",H46=""),"",TRIM(IF(HOUR(H46-G46)>0,HOUR(H46-G46)&" hr ","")&IF(MINUTE(H46-G46)>0,MINUTE(H46-G46)&" min",""))) | L46: =IF(R46="","",IF(INDEX('Recurring Schedule'!$J$6:$J$45,R46)="","",INDEX('Recurring Schedule'!$J$6:$J$45,R46))) | M46: =IF(R46="","",IF(INDEX('Recurring Schedule'!$K$6:$K$45,R46)="","",INDEX('Recurring Schedule'!$K$6:$K$45,R46))) | N46: =IF(R46="","",IF(INDEX('Recurring Schedule'!$L$6:$L$45,R46)="","",INDEX('Recurring Schedule'!$L$6:$L$45,R46))) | O46: =IF(C46="","",IF(AND(OR(L46="1-Urgent",L46="2-High"),M46="✓"),"DO FIRST",IF(M46="✓","SCHEDULE",IF(OR(L46="1-Urgent",L46="2-High"),"DELEGATE","DELETE")))) | Q46: =IF(41>Calc!$AQ$368,"",MATCH(40,Calc!$AQ$2:$AQ$367,1)) | R46: =IF(Q46="","",SMALL(INDEX(Calc!$B$2:$AO$367,Q46,0),41-INDEX(Calc!$AQ$2:$AQ$367,Q46)))
B47: =IF(R47="","",42) | C47: =IF(R47="","",IF(INDEX('Recurring Schedule'!$C$6:$C$45,R47)="","",INDEX('Recurring Schedule'!$C$6:$C$45,R47))) | D47: =IF(R47="","",IF(INDEX('Recurring Schedule'!$D$6:$D$45,R47)="","",INDEX('Recurring Schedule'!$D$6:$D$45,R47))) | E47: =IF(Q47="","",INDEX(Calc!$A$2:$A$367,Q47)) | F47: =IF(OR(C47="",E47=""),"",E47-Setup!$D$7) | G47: =IF(R47="","",IF(INDEX('Recurring Schedule'!$H$6:$H$45,R47)="","",INDEX('Recurring Schedule'!$H$6:$H$45,R47))) | H47: =IF(R47="","",IF(INDEX('Recurring Schedule'!$I$6:$I$45,R47)="","",INDEX('Recurring Schedule'!$I$6:$I$45,R47))) | I47: =IF(OR(G47="",H47=""),"",TRIM(IF(HOUR(H47-G47)>0,HOUR(H47-G47)&" hr ","")&IF(MINUTE(H47-G47)>0,MINUTE(H47-G47)&" min",""))) | L47: =IF(R47="","",IF(INDEX('Recurring Schedule'!$J$6:$J$45,R47)="","",INDEX('Recurring Schedule'!$J$6:$J$45,R47))) | M47: =IF(R47="","",IF(INDEX('Recurring Schedule'!$K$6:$K$45,R47)="","",INDEX('Recurring Schedule'!$K$6:$K$45,R47))) | N47: =IF(R47="","",IF(INDEX('Recurring Schedule'!$L$6:$L$45,R47)="","",INDEX('Recurring Schedule'!$L$6:$L$45,R47))) | O47: =IF(C47="","",IF(AND(OR(L47="1-Urgent",L47="2-High"),M47="✓"),"DO FIRST",IF(M47="✓","SCHEDULE",IF(OR(L47="1-Urgent",L47="2-High"),"DELEGATE","DELETE")))) | Q47: =IF(42>Calc!$AQ$368,"",MATCH(41,Calc!$AQ$2:$AQ$367,1)) | R47: =IF(Q47="","",SMALL(INDEX(Calc!$B$2:$AO$367,Q47,0),42-INDEX(Calc!$AQ$2:$AQ$367,Q47)))
B48: =IF(R48="","",43) | C48: =IF(R48="","",IF(INDEX('Recurring Schedule'!$C$6:$C$45,R48)="","",INDEX('Recurring Schedule'!$C$6:$C$45,R48))) | D48: =IF(R48="","",IF(INDEX('Recurring Schedule'!$D$6:$D$45,R48)="","",INDEX('Recurring Schedule'!$D$6:$D$45,R48))) | E48: =IF(Q48="","",INDEX(Calc!$A$2:$A$367,Q48)) | F48: =IF(OR(C48="",E48=""),"",E48-Setup!$D$7) | G48: =IF(R48="","",IF(INDEX('Recurring Schedule'!$H$6:$H$45,R48)="","",INDEX('Recurring Schedule'!$H$6:$H$45,R48))) | H48: =IF(R48="","",IF(INDEX('Recurring Schedule'!$I$6:$I$45,R48)="","",INDEX('Recurring Schedule'!$I$6:$I$45,R48))) | I48: =IF(OR(G48="",H48=""),"",TRIM(IF(HOUR(H48-G48)>0,HOUR(H48-G48)&" hr ","")&IF(MINUTE(H48-G48)>0,MINUTE(H48-G48)&" min",""))) | L48: =IF(R48="","",IF(INDEX('Recurring Schedule'!$J$6:$J$45,R48)="","",INDEX('Recurring Schedule'!$J$6:$J$45,R48))) | M48: =IF(R48="","",IF(INDEX('Recurring Schedule'!$K$6:$K$45,R48)="","",INDEX('Recurring Schedule'!$K$6:$K$45,R48))) | N48: =IF(R48="","",IF(INDEX('Recurring Schedule'!$L$6:$L$45,R48)="","",INDEX('Recurring Schedule'!$L$6:$L$45,R48))) | O48: =IF(C48="","",IF(AND(OR(L48="1-Urgent",L48="2-High"),M48="✓"),"DO FIRST",IF(M48="✓","SCHEDULE",IF(OR(L48="1-Urgent",L48="2-High"),"DELEGATE","DELETE")))) | Q48: =IF(43>Calc!$AQ$368,"",MATCH(42,Calc!$AQ$2:$AQ$367,1)) | R48: =IF(Q48="","",SMALL(INDEX(Calc!$B$2:$AO$367,Q48,0),43-INDEX(Calc!$AQ$2:$AQ$367,Q48)))
B49: =IF(R49="","",44) | C49: =IF(R49="","",IF(INDEX('Recurring Schedule'!$C$6:$C$45,R49)="","",INDEX('Recurring Schedule'!$C$6:$C$45,R49))) | D49: =IF(R49="","",IF(INDEX('Recurring Schedule'!$D$6:$D$45,R49)="","",INDEX('Recurring Schedule'!$D$6:$D$45,R49))) | E49: =IF(Q49="","",INDEX(Calc!$A$2:$A$367,Q49)) | F49: =IF(OR(C49="",E49=""),"",E49-Setup!$D$7) | G49: =IF(R49="","",IF(INDEX('Recurring Schedule'!$H$6:$H$45,R49)="","",INDEX('Recurring Schedule'!$H$6:$H$45,R49))) | H49: =IF(R49="","",IF(INDEX('Recurring Schedule'!$I$6:$I$45,R49)="","",INDEX('Recurring Schedule'!$I$6:$I$45,R49))) | I49: =IF(OR(G49="",H49=""),"",TRIM(IF(HOUR(H49-G49)>0,HOUR(H49-G49)&" hr ","")&IF(MINUTE(H49-G49)>0,MINUTE(H49-G49)&" min",""))) | L49: =IF(R49="","",IF(INDEX('Recurring Schedule'!$J$6:$J$45,R49)="","",INDEX('Recurring Schedule'!$J$6:$J$45,R49))) | M49: =IF(R49="","",IF(INDEX('Recurring Schedule'!$K$6:$K$45,R49)="","",INDEX('Recurring Schedule'!$K$6:$K$45,R49))) | N49: =IF(R49="","",IF(INDEX('Recurring Schedule'!$L$6:$L$45,R49)="","",INDEX('Recurring Schedule'!$L$6:$L$45,R49))) | O49: =IF(C49="","",IF(AND(OR(L49="1-Urgent",L49="2-High"),M49="✓"),"DO FIRST",IF(M49="✓","SCHEDULE",IF(OR(L49="1-Urgent",L49="2-High"),"DELEGATE","DELETE")))) | Q49: =IF(44>Calc!$AQ$368,"",MATCH(43,Calc!$AQ$2:$AQ$367,1)) | R49: =IF(Q49="","",SMALL(INDEX(Calc!$B$2:$AO$367,Q49,0),44-INDEX(Calc!$AQ$2:$AQ$367,Q49)))
B50: =IF(R50="","",45) | C50: =IF(R50="","",IF(INDEX('Recurring Schedule'!$C$6:$C$45,R50)="","",INDEX('Recurring Schedule'!$C$6:$C$45,R50))) | D50: =IF(R50="","",IF(INDEX('Recurring Schedule'!$D$6:$D$45,R50)="","",INDEX('Recurring Schedule'!$D$6:$D$45,R50))) | E50: =IF(Q50="","",INDEX(Calc!$A$2:$A$367,Q50)) | F50: =IF(OR(C50="",E50=""),"",E50-Setup!$D$7) | G50: =IF(R50="","",IF(INDEX('Recurring Schedule'!$H$6:$H$45,R50)="","",INDEX('Recurring Schedule'!$H$6:$H$45,R50))) | H50: =IF(R50="","",IF(INDEX('Recurring Schedule'!$I$6:$I$45,R50)="","",INDEX('Recurring Schedule'!$I$6:$I$45,R50))) | I50: =IF(OR(G50="",H50=""),"",TRIM(IF(HOUR(H50-G50)>0,HOUR(H50-G50)&" hr ","")&IF(MINUTE(H50-G50)>0,MINUTE(H50-G50)&" min",""))) | L50: =IF(R50="","",IF(INDEX('Recurring Schedule'!$J$6:$J$45,R50)="","",INDEX('Recurring Schedule'!$J$6:$J$45,R50))) | M50: =IF(R50="","",IF(INDEX('Recurring Schedule'!$K$6:$K$45,R50)="","",INDEX('Recurring Schedule'!$K$6:$K$45,R50))) | N50: =IF(R50="","",IF(INDEX('Recurring Schedule'!$L$6:$L$45,R50)="","",INDEX('Recurring Schedule'!$L$6:$L$45,R50))) | O50: =IF(C50="","",IF(AND(OR(L50="1-Urgent",L50="2-High"),M50="✓"),"DO FIRST",IF(M50="✓","SCHEDULE",IF(OR(L50="1-Urgent",L50="2-High"),"DELEGATE","DELETE")))) | Q50: =IF(45>Calc!$AQ$368,"",MATCH(44,Calc!$AQ$2:$AQ$367,1)) | R50: =IF(Q50="","",SMALL(INDEX(Calc!$B$2:$AO$367,Q50,0),45-INDEX(Calc!$AQ$2:$AQ$367,Q50)))
B51: =IF(R51="","",46) | C51: =IF(R51="","",IF(INDEX('Recurring Schedule'!$C$6:$C$45,R51)="","",INDEX('Recurring Schedule'!$C$6:$C$45,R51))) | D51: =IF(R51="","",IF(INDEX('Recurring Schedule'!$D$6:$D$45,R51)="","",INDEX('Recurring Schedule'!$D$6:$D$45,R51))) | E51: =IF(Q51="","",INDEX(Calc!$A$2:$A$367,Q51)) | F51: =IF(OR(C51="",E51=""),"",E51-Setup!$D$7) | G51: =IF(R51="","",IF(INDEX('Recurring Schedule'!$H$6:$H$45,R51)="","",INDEX('Recurring Schedule'!$H$6:$H$45,R51))) | H51: =IF(R51="","",IF(INDEX('Recurring Schedule'!$I$6:$I$45,R51)="","",INDEX('Recurring Schedule'!$I$6:$I$45,R51))) | I51: =IF(OR(G51="",H51=""),"",TRIM(IF(HOUR(H51-G51)>0,HOUR(H51-G51)&" hr ","")&IF(MINUTE(H51-G51)>0,MINUTE(H51-G51)&" min",""))) | L51: =IF(R51="","",IF(INDEX('Recurring Schedule'!$J$6:$J$45,R51)="","",INDEX('Recurring Schedule'!$J$6:$J$45,R51))) | M51: =IF(R51="","",IF(INDEX('Recurring Schedule'!$K$6:$K$45,R51)="","",INDEX('Recurring Schedule'!$K$6:$K$45,R51))) | N51: =IF(R51="","",IF(INDEX('Recurring Schedule'!$L$6:$L$45,R51)="","",INDEX('Recurring Schedule'!$L$6:$L$45,R51))) | O51: =IF(C51="","",IF(AND(OR(L51="1-Urgent",L51="2-High"),M51="✓"),"DO FIRST",IF(M51="✓","SCHEDULE",IF(OR(L51="1-Urgent",L51="2-High"),"DELEGATE","DELETE")))) | Q51: =IF(46>Calc!$AQ$368,"",MATCH(45,Calc!$AQ$2:$AQ$367,1)) | R51: =IF(Q51="","",SMALL(INDEX(Calc!$B$2:$AO$367,Q51,0),46-INDEX(Calc!$AQ$2:$AQ$367,Q51)))
B52: =IF(R52="","",47) | C52: =IF(R52="","",IF(INDEX('Recurring Schedule'!$C$6:$C$45,R52)="","",INDEX('Recurring Schedule'!$C$6:$C$45,R52))) | D52: =IF(R52="","",IF(INDEX('Recurring Schedule'!$D$6:$D$45,R52)="","",INDEX('Recurring Schedule'!$D$6:$D$45,R52))) | E52: =IF(Q52="","",INDEX(Calc!$A$2:$A$367,Q52)) | F52: =IF(OR(C52="",E52=""),"",E52-Setup!$D$7) | G52: =IF(R52="","",IF(INDEX('Recurring Schedule'!$H$6:$H$45,R52)="","",INDEX('Recurring Schedule'!$H$6:$H$45,R52))) | H52: =IF(R52="","",IF(INDEX('Recurring Schedule'!$I$6:$I$45,R52)="","",INDEX('Recurring Schedule'!$I$6:$I$45,R52))) | I52: =IF(OR(G52="",H52=""),"",TRIM(IF(HOUR(H52-G52)>0,HOUR(H52-G52)&" hr ","")&IF(MINUTE(H52-G52)>0,MINUTE(H52-G52)&" min",""))) | L52: =IF(R52="","",IF(INDEX('Recurring Schedule'!$J$6:$J$45,R52)="","",INDEX('Recurring Schedule'!$J$6:$J$45,R52))) | M52: =IF(R52="","",IF(INDEX('Recurring Schedule'!$K$6:$K$45,R52)="","",INDEX('Recurring Schedule'!$K$6:$K$45,R52))) | N52: =IF(R52="","",IF(INDEX('Recurring Schedule'!$L$6:$L$45,R52)="","",INDEX('Recurring Schedule'!$L$6:$L$45,R52))) | O52: =IF(C52="","",IF(AND(OR(L52="1-Urgent",L52="2-High"),M52="✓"),"DO FIRST",IF(M52="✓","SCHEDULE",IF(OR(L52="1-Urgent",L52="2-High"),"DELEGATE","DELETE")))) | Q52: =IF(47>Calc!$AQ$368,"",MATCH(46,Calc!$AQ$2:$AQ$367,1)) | R52: =IF(Q52="","",SMALL(INDEX(Calc!$B$2:$AO$367,Q52,0),47-INDEX(Calc!$AQ$2:$AQ$367,Q52)))
B53: =IF(R53="","",48) | C53: =IF(R53="","",IF(INDEX('Recurring Schedule'!$C$6:$C$45,R53)="","",INDEX('Recurring Schedule'!$C$6:$C$45,R53))) | D53: =IF(R53="","",IF(INDEX('Recurring Schedule'!$D$6:$D$45,R53)="","",INDEX('Recurring Schedule'!$D$6:$D$45,R53))) | E53: =IF(Q53="","",INDEX(Calc!$A$2:$A$367,Q53)) | F53: =IF(OR(C53="",E53=""),"",E53-Setup!$D$7) | G53: =IF(R53="","",IF(INDEX('Recurring Schedule'!$H$6:$H$45,R53)="","",INDEX('Recurring Schedule'!$H$6:$H$45,R53))) | H53: =IF(R53="","",IF(INDEX('Recurring Schedule'!$I$6:$I$45,R53)="","",INDEX('Recurring Schedule'!$I$6:$I$45,R53))) | I53: =IF(OR(G53="",H53=""),"",TRIM(IF(HOUR(H53-G53)>0,HOUR(H53-G53)&" hr ","")&IF(MINUTE(H53-G53)>0,MINUTE(H53-G53)&" min",""))) | L53: =IF(R53="","",IF(INDEX('Recurring Schedule'!$J$6:$J$45,R53)="","",INDEX('Recurring Schedule'!$J$6:$J$45,R53))) | M53: =IF(R53="","",IF(INDEX('Recurring Schedule'!$K$6:$K$45,R53)="","",INDEX('Recurring Schedule'!$K$6:$K$45,R53))) | N53: =IF(R53="","",IF(INDEX('Recurring Schedule'!$L$6:$L$45,R53)="","",INDEX('Recurring Schedule'!$L$6:$L$45,R53))) | O53: =IF(C53="","",IF(AND(OR(L53="1-Urgent",L53="2-High"),M53="✓"),"DO FIRST",IF(M53="✓","SCHEDULE",IF(OR(L53="1-Urgent",L53="2-High"),"DELEGATE","DELETE")))) | Q53: =IF(48>Calc!$AQ$368,"",MATCH(47,Calc!$AQ$2:$AQ$367,1)) | R53: =IF(Q53="","",SMALL(INDEX(Calc!$B$2:$AO$367,Q53,0),48-INDEX(Calc!$AQ$2:$AQ$367,Q53)))
B54: =IF(R54="","",49) | C54: =IF(R54="","",IF(INDEX('Recurring Schedule'!$C$6:$C$45,R54)="","",INDEX('Recurring Schedule'!$C$6:$C$45,R54))) | D54: =IF(R54="","",IF(INDEX('Recurring Schedule'!$D$6:$D$45,R54)="","",INDEX('Recurring Schedule'!$D$6:$D$45,R54))) | E54: =IF(Q54="","",INDEX(Calc!$A$2:$A$367,Q54)) | F54: =IF(OR(C54="",E54=""),"",E54-Setup!$D$7) | G54: =IF(R54="","",IF(INDEX('Recurring Schedule'!$H$6:$H$45,R54)="","",INDEX('Recurring Schedule'!$H$6:$H$45,R54))) | H54: =IF(R54="","",IF(INDEX('Recurring Schedule'!$I$6:$I$45,R54)="","",INDEX('Recurring Schedule'!$I$6:$I$45,R54))) | I54: =IF(OR(G54="",H54=""),"",TRIM(IF(HOUR(H54-G54)>0,HOUR(H54-G54)&" hr ","")&IF(MINUTE(H54-G54)>0,MINUTE(H54-G54)&" min",""))) | L54: =IF(R54="","",IF(INDEX('Recurring Schedule'!$J$6:$J$45,R54)="","",INDEX('Recurring Schedule'!$J$6:$J$45,R54))) | M54: =IF(R54="","",IF(INDEX('Recurring Schedule'!$K$6:$K$45,R54)="","",INDEX('Recurring Schedule'!$K$6:$K$45,R54))) | N54: =IF(R54="","",IF(INDEX('Recurring Schedule'!$L$6:$L$45,R54)="","",INDEX('Recurring Schedule'!$L$6:$L$45,R54))) | O54: =IF(C54="","",IF(AND(OR(L54="1-Urgent",L54="2-High"),M54="✓"),"DO FIRST",IF(M54="✓","SCHEDULE",IF(OR(L54="1-Urgent",L54="2-High"),"DELEGATE","DELETE")))) | Q54: =IF(49>Calc!$AQ$368,"",MATCH(48,Calc!$AQ$2:$AQ$367,1)) | R54: =IF(Q54="","",SMALL(INDEX(Calc!$B$2:$AO$367,Q54,0),49-INDEX(Calc!$AQ$2:$AQ$367,Q54)))
B55: =IF(R55="","",50) | C55: =IF(R55="","",IF(INDEX('Recurring Schedule'!$C$6:$C$45,R55)="","",INDEX('Recurring Schedule'!$C$6:$C$45,R55))) | D55: =IF(R55="","",IF(INDEX('Recurring Schedule'!$D$6:$D$45,R55)="","",INDEX('Recurring Schedule'!$D$6:$D$45,R55))) | E55: =IF(Q55="","",INDEX(Calc!$A$2:$A$367,Q55)) | F55: =IF(OR(C55="",E55=""),"",E55-Setup!$D$7) | G55: =IF(R55="","",IF(INDEX('Recurring Schedule'!$H$6:$H$45,R55)="","",INDEX('Recurring Schedule'!$H$6:$H$45,R55))) | H55: =IF(R55="","",IF(INDEX('Recurring Schedule'!$I$6:$I$45,R55)="","",INDEX('Recurring Schedule'!$I$6:$I$45,R55))) | I55: =IF(OR(G55="",H55=""),"",TRIM(IF(HOUR(H55-G55)>0,HOUR(H55-G55)&" hr ","")&IF(MINUTE(H55-G55)>0,MINUTE(H55-G55)&" min",""))) | L55: =IF(R55="","",IF(INDEX('Recurring Schedule'!$J$6:$J$45,R55)="","",INDEX('Recurring Schedule'!$J$6:$J$45,R55))) | M55: =IF(R55="","",IF(INDEX('Recurring Schedule'!$K$6:$K$45,R55)="","",INDEX('Recurring Schedule'!$K$6:$K$45,R55))) | N55: =IF(R55="","",IF(INDEX('Recurring Schedule'!$L$6:$L$45,R55)="","",INDEX('Recurring Schedule'!$L$6:$L$45,R55))) | O55: =IF(C55="","",IF(AND(OR(L55="1-Urgent",L55="2-High"),M55="✓"),"DO FIRST",IF(M55="✓","SCHEDULE",IF(OR(L55="1-Urgent",L55="2-High"),"DELEGATE","DELETE")))) | Q55: =IF(50>Calc!$AQ$368,"",MATCH(49,Calc!$AQ$2:$AQ$367,1)) | R55: =IF(Q55="","",SMALL(INDEX(Calc!$B$2:$AO$367,Q55,0),50-INDEX(Calc!$AQ$2:$AQ$367,Q55)))
B56: =IF(R56="","",51) | C56: =IF(R56="","",IF(INDEX('Recurring Schedule'!$C$6:$C$45,R56)="","",INDEX('Recurring Schedule'!$C$6:$C$45,R56))) | D56: =IF(R56="","",IF(INDEX('Recurring Schedule'!$D$6:$D$45,R56)="","",INDEX('Recurring Schedule'!$D$6:$D$45,R56))) | E56: =IF(Q56="","",INDEX(Calc!$A$2:$A$367,Q56)) | F56: =IF(OR(C56="",E56=""),"",E56-Setup!$D$7) | G56: =IF(R56="","",IF(INDEX('Recurring Schedule'!$H$6:$H$45,R56)="","",INDEX('Recurring Schedule'!$H$6:$H$45,R56))) | H56: =IF(R56="","",IF(INDEX('Recurring Schedule'!$I$6:$I$45,R56)="","",INDEX('Recurring Schedule'!$I$6:$I$45,R56))) | I56: =IF(OR(G56="",H56=""),"",TRIM(IF(HOUR(H56-G56)>0,HOUR(H56-G56)&" hr ","")&IF(MINUTE(H56-G56)>0,MINUTE(H56-G56)&" min",""))) | L56: =IF(R56="","",IF(INDEX('Recurring Schedule'!$J$6:$J$45,R56)="","",INDEX('Recurring Schedule'!$J$6:$J$45,R56))) | M56: =IF(R56="","",IF(INDEX('Recurring Schedule'!$K$6:$K$45,R56)="","",INDEX('Recurring Schedule'!$K$6:$K$45,R56))) | N56: =IF(R56="","",IF(INDEX('Recurring Schedule'!$L$6:$L$45,R56)="","",INDEX('Recurring Schedule'!$L$6:$L$45,R56))) | O56: =IF(C56="","",IF(AND(OR(L56="1-Urgent",L56="2-High"),M56="✓"),"DO FIRST",IF(M56="✓","SCHEDULE",IF(OR(L56="1-Urgent",L56="2-High"),"DELEGATE","DELETE")))) | Q56: =IF(51>Calc!$AQ$368,"",MATCH(50,Calc!$AQ$2:$AQ$367,1)) | R56: =IF(Q56="","",SMALL(INDEX(Calc!$B$2:$AO$367,Q56,0),51-INDEX(Calc!$AQ$2:$AQ$367,Q56)))
B57: =IF(R57="","",52) | C57: =IF(R57="","",IF(INDEX('Recurring Schedule'!$C$6:$C$45,R57)="","",INDEX('Recurring Schedule'!$C$6:$C$45,R57))) | D57: =IF(R57="","",IF(INDEX('Recurring Schedule'!$D$6:$D$45,R57)="","",INDEX('Recurring Schedule'!$D$6:$D$45,R57))) | E57: =IF(Q57="","",INDEX(Calc!$A$2:$A$367,Q57)) | F57: =IF(OR(C57="",E57=""),"",E57-Setup!$D$7) | G57: =IF(R57="","",IF(INDEX('Recurring Schedule'!$H$6:$H$45,R57)="","",INDEX('Recurring Schedule'!$H$6:$H$45,R57))) | H57: =IF(R57="","",IF(INDEX('Recurring Schedule'!$I$6:$I$45,R57)="","",INDEX('Recurring Schedule'!$I$6:$I$45,R57))) | I57: =IF(OR(G57="",H57=""),"",TRIM(IF(HOUR(H57-G57)>0,HOUR(H57-G57)&" hr ","")&IF(MINUTE(H57-G57)>0,MINUTE(H57-G57)&" min",""))) | L57: =IF(R57="","",IF(INDEX('Recurring Schedule'!$J$6:$J$45,R57)="","",INDEX('Recurring Schedule'!$J$6:$J$45,R57))) | M57: =IF(R57="","",IF(INDEX('Recurring Schedule'!$K$6:$K$45,R57)="","",INDEX('Recurring Schedule'!$K$6:$K$45,R57))) | N57: =IF(R57="","",IF(INDEX('Recurring Schedule'!$L$6:$L$45,R57)="","",INDEX('Recurring Schedule'!$L$6:$L$45,R57))) | O57: =IF(C57="","",IF(AND(OR(L57="1-Urgent",L57="2-High"),M57="✓"),"DO FIRST",IF(M57="✓","SCHEDULE",IF(OR(L57="1-Urgent",L57="2-High"),"DELEGATE","DELETE")))) | Q57: =IF(52>Calc!$AQ$368,"",MATCH(51,Calc!$AQ$2:$AQ$367,1)) | R57: =IF(Q57="","",SMALL(INDEX(Calc!$B$2:$AO$367,Q57,0),52-INDEX(Calc!$AQ$2:$AQ$367,Q57)))
B58: =IF(R58="","",53) | C58: =IF(R58="","",IF(INDEX('Recurring Schedule'!$C$6:$C$45,R58)="","",INDEX('Recurring Schedule'!$C$6:$C$45,R58))) | D58: =IF(R58="","",IF(INDEX('Recurring Schedule'!$D$6:$D$45,R58)="","",INDEX('Recurring Schedule'!$D$6:$D$45,R58))) | E58: =IF(Q58="","",INDEX(Calc!$A$2:$A$367,Q58)) | F58: =IF(OR(C58="",E58=""),"",E58-Setup!$D$7) | G58: =IF(R58="","",IF(INDEX('Recurring Schedule'!$H$6:$H$45,R58)="","",INDEX('Recurring Schedule'!$H$6:$H$45,R58))) | H58: =IF(R58="","",IF(INDEX('Recurring Schedule'!$I$6:$I$45,R58)="","",INDEX('Recurring Schedule'!$I$6:$I$45,R58))) | I58: =IF(OR(G58="",H58=""),"",TRIM(IF(HOUR(H58-G58)>0,HOUR(H58-G58)&" hr ","")&IF(MINUTE(H58-G58)>0,MINUTE(H58-G58)&" min",""))) | L58: =IF(R58="","",IF(INDEX('Recurring Schedule'!$J$6:$J$45,R58)="","",INDEX('Recurring Schedule'!$J$6:$J$45,R58))) | M58: =IF(R58="","",IF(INDEX('Recurring Schedule'!$K$6:$K$45,R58)="","",INDEX('Recurring Schedule'!$K$6:$K$45,R58))) | N58: =IF(R58="","",IF(INDEX('Recurring Schedule'!$L$6:$L$45,R58)="","",INDEX('Recurring Schedule'!$L$6:$L$45,R58))) | O58: =IF(C58="","",IF(AND(OR(L58="1-Urgent",L58="2-High"),M58="✓"),"DO FIRST",IF(M58="✓","SCHEDULE",IF(OR(L58="1-Urgent",L58="2-High"),"DELEGATE","DELETE")))) | Q58: =IF(53>Calc!$AQ$368,"",MATCH(52,Calc!$AQ$2:$AQ$367,1)) | R58: =IF(Q58="","",SMALL(INDEX(Calc!$B$2:$AO$367,Q58,0),53-INDEX(Calc!$AQ$2:$AQ$367,Q58)))
B59: =IF(R59="","",54) | C59: =IF(R59="","",IF(INDEX('Recurring Schedule'!$C$6:$C$45,R59)="","",INDEX('Recurring Schedule'!$C$6:$C$45,R59))) | D59: =IF(R59="","",IF(INDEX('Recurring Schedule'!$D$6:$D$45,R59)="","",INDEX('Recurring Schedule'!$D$6:$D$45,R59))) | E59: =IF(Q59="","",INDEX(Calc!$A$2:$A$367,Q59)) | F59: =IF(OR(C59="",E59=""),"",E59-Setup!$D$7) | G59: =IF(R59="","",IF(INDEX('Recurring Schedule'!$H$6:$H$45,R59)="","",INDEX('Recurring Schedule'!$H$6:$H$45,R59))) | H59: =IF(R59="","",IF(INDEX('Recurring Schedule'!$I$6:$I$45,R59)="","",INDEX('Recurring Schedule'!$I$6:$I$45,R59))) | I59: =IF(OR(G59="",H59=""),"",TRIM(IF(HOUR(H59-G59)>0,HOUR(H59-G59)&" hr ","")&IF(MINUTE(H59-G59)>0,MINUTE(H59-G59)&" min",""))) | L59: =IF(R59="","",IF(INDEX('Recurring Schedule'!$J$6:$J$45,R59)="","",INDEX('Recurring Schedule'!$J$6:$J$45,R59))) | M59: =IF(R59="","",IF(INDEX('Recurring Schedule'!$K$6:$K$45,R59)="","",INDEX('Recurring Schedule'!$K$6:$K$45,R59))) | N59: =IF(R59="","",IF(INDEX('Recurring Schedule'!$L$6:$L$45,R59)="","",INDEX('Recurring Schedule'!$L$6:$L$45,R59))) | O59: =IF(C59="","",IF(AND(OR(L59="1-Urgent",L59="2-High"),M59="✓"),"DO FIRST",IF(M59="✓","SCHEDULE",IF(OR(L59="1-Urgent",L59="2-High"),"DELEGATE","DELETE")))) | Q59: =IF(54>Calc!$AQ$368,"",MATCH(53,Calc!$AQ$2:$AQ$367,1)) | R59: =IF(Q59="","",SMALL(INDEX(Calc!$B$2:$AO$367,Q59,0),54-INDEX(Calc!$AQ$2:$AQ$367,Q59)))
B60: =IF(R60="","",55) | C60: =IF(R60="","",IF(INDEX('Recurring Schedule'!$C$6:$C$45,R60)="","",INDEX('Recurring Schedule'!$C$6:$C$45,R60))) | D60: =IF(R60="","",IF(INDEX('Recurring Schedule'!$D$6:$D$45,R60)="","",INDEX('Recurring Schedule'!$D$6:$D$45,R60))) | E60: =IF(Q60="","",INDEX(Calc!$A$2:$A$367,Q60)) | F60: =IF(OR(C60="",E60=""),"",E60-Setup!$D$7) | G60: =IF(R60="","",IF(INDEX('Recurring Schedule'!$H$6:$H$45,R60)="","",INDEX('Recurring Schedule'!$H$6:$H$45,R60))) | H60: =IF(R60="","",IF(INDEX('Recurring Schedule'!$I$6:$I$45,R60)="","",INDEX('Recurring Schedule'!$I$6:$I$45,R60))) | I60: =IF(OR(G60="",H60=""),"",TRIM(IF(HOUR(H60-G60)>0,HOUR(H60-G60)&" hr ","")&IF(MINUTE(H60-G60)>0,MINUTE(H60-G60)&" min",""))) | L60: =IF(R60="","",IF(INDEX('Recurring Schedule'!$J$6:$J$45,R60)="","",INDEX('Recurring Schedule'!$J$6:$J$45,R60))) | M60: =IF(R60="","",IF(INDEX('Recurring Schedule'!$K$6:$K$45,R60)="","",INDEX('Recurring Schedule'!$K$6:$K$45,R60))) | N60: =IF(R60="","",IF(INDEX('Recurring Schedule'!$L$6:$L$45,R60)="","",INDEX('Recurring Schedule'!$L$6:$L$45,R60))) | O60: =IF(C60="","",IF(AND(OR(L60="1-Urgent",L60="2-High"),M60="✓"),"DO FIRST",IF(M60="✓","SCHEDULE",IF(OR(L60="1-Urgent",L60="2-High"),"DELEGATE","DELETE")))) | Q60: =IF(55>Calc!$AQ$368,"",MATCH(54,Calc!$AQ$2:$AQ$367,1)) | R60: =IF(Q60="","",SMALL(INDEX(Calc!$B$2:$AO$367,Q60,0),55-INDEX(Calc!$AQ$2:$AQ$367,Q60)))
B61: =IF(R61="","",56) | C61: =IF(R61="","",IF(INDEX('Recurring Schedule'!$C$6:$C$45,R61)="","",INDEX('Recurring Schedule'!$C$6:$C$45,R61))) | D61: =IF(R61="","",IF(INDEX('Recurring Schedule'!$D$6:$D$45,R61)="","",INDEX('Recurring Schedule'!$D$6:$D$45,R61))) | E61: =IF(Q61="","",INDEX(Calc!$A$2:$A$367,Q61)) | F61: =IF(OR(C61="",E61=""),"",E61-Setup!$D$7) | G61: =IF(R61="","",IF(INDEX('Recurring Schedule'!$H$6:$H$45,R61)="","",INDEX('Recurring Schedule'!$H$6:$H$45,R61))) | H61: =IF(R61="","",IF(INDEX('Recurring Schedule'!$I$6:$I$45,R61)="","",INDEX('Recurring Schedule'!$I$6:$I$45,R61))) | I61: =IF(OR(G61="",H61=""),"",TRIM(IF(HOUR(H61-G61)>0,HOUR(H61-G61)&" hr ","")&IF(MINUTE(H61-G61)>0,MINUTE(H61-G61)&" min",""))) | L61: =IF(R61="","",IF(INDEX('Recurring Schedule'!$J$6:$J$45,R61)="","",INDEX('Recurring Schedule'!$J$6:$J$45,R61))) | M61: =IF(R61="","",IF(INDEX('Recurring Schedule'!$K$6:$K$45,R61)="","",INDEX('Recurring Schedule'!$K$6:$K$45,R61))) | N61: =IF(R61="","",IF(INDEX('Recurring Schedule'!$L$6:$L$45,R61)="","",INDEX('Recurring Schedule'!$L$6:$L$45,R61))) | O61: =IF(C61="","",IF(AND(OR(L61="1-Urgent",L61="2-High"),M61="✓"),"DO FIRST",IF(M61="✓","SCHEDULE",IF(OR(L61="1-Urgent",L61="2-High"),"DELEGATE","DELETE")))) | Q61: =IF(56>Calc!$AQ$368,"",MATCH(55,Calc!$AQ$2:$AQ$367,1)) | R61: =IF(Q61="","",SMALL(INDEX(Calc!$B$2:$AO$367,Q61,0),56-INDEX(Calc!$AQ$2:$AQ$367,Q61)))
B62: =IF(R62="","",57) | C62: =IF(R62="","",IF(INDEX('Recurring Schedule'!$C$6:$C$45,R62)="","",INDEX('Recurring Schedule'!$C$6:$C$45,R62))) | D62: =IF(R62="","",IF(INDEX('Recurring Schedule'!$D$6:$D$45,R62)="","",INDEX('Recurring Schedule'!$D$6:$D$45,R62))) | E62: =IF(Q62="","",INDEX(Calc!$A$2:$A$367,Q62)) | F62: =IF(OR(C62="",E62=""),"",E62-Setup!$D$7) | G62: =IF(R62="","",IF(INDEX('Recurring Schedule'!$H$6:$H$45,R62)="","",INDEX('Recurring Schedule'!$H$6:$H$45,R62))) | H62: =IF(R62="","",IF(INDEX('Recurring Schedule'!$I$6:$I$45,R62)="","",INDEX('Recurring Schedule'!$I$6:$I$45,R62))) | I62: =IF(OR(G62="",H62=""),"",TRIM(IF(HOUR(H62-G62)>0,HOUR(H62-G62)&" hr ","")&IF(MINUTE(H62-G62)>0,MINUTE(H62-G62)&" min",""))) | L62: =IF(R62="","",IF(INDEX('Recurring Schedule'!$J$6:$J$45,R62)="","",INDEX('Recurring Schedule'!$J$6:$J$45,R62))) | M62: =IF(R62="","",IF(INDEX('Recurring Schedule'!$K$6:$K$45,R62)="","",INDEX('Recurring Schedule'!$K$6:$K$45,R62))) | N62: =IF(R62="","",IF(INDEX('Recurring Schedule'!$L$6:$L$45,R62)="","",INDEX('Recurring Schedule'!$L$6:$L$45,R62))) | O62: =IF(C62="","",IF(AND(OR(L62="1-Urgent",L62="2-High"),M62="✓"),"DO FIRST",IF(M62="✓","SCHEDULE",IF(OR(L62="1-Urgent",L62="2-High"),"DELEGATE","DELETE")))) | Q62: =IF(57>Calc!$AQ$368,"",MATCH(56,Calc!$AQ$2:$AQ$367,1)) | R62: =IF(Q62="","",SMALL(INDEX(Calc!$B$2:$AO$367,Q62,0),57-INDEX(Calc!$AQ$2:$AQ$367,Q62)))
B63: =IF(R63="","",58) | C63: =IF(R63="","",IF(INDEX('Recurring Schedule'!$C$6:$C$45,R63)="","",INDEX('Recurring Schedule'!$C$6:$C$45,R63))) | D63: =IF(R63="","",IF(INDEX('Recurring Schedule'!$D$6:$D$45,R63)="","",INDEX('Recurring Schedule'!$D$6:$D$45,R63))) | E63: =IF(Q63="","",INDEX(Calc!$A$2:$A$367,Q63)) | F63: =IF(OR(C63="",E63=""),"",E63-Setup!$D$7) | G63: =IF(R63="","",IF(INDEX('Recurring Schedule'!$H$6:$H$45,R63)="","",INDEX('Recurring Schedule'!$H$6:$H$45,R63))) | H63: =IF(R63="","",IF(INDEX('Recurring Schedule'!$I$6:$I$45,R63)="","",INDEX('Recurring Schedule'!$I$6:$I$45,R63))) | I63: =IF(OR(G63="",H63=""),"",TRIM(IF(HOUR(H63-G63)>0,HOUR(H63-G63)&" hr ","")&IF(MINUTE(H63-G63)>0,MINUTE(H63-G63)&" min",""))) | L63: =IF(R63="","",IF(INDEX('Recurring Schedule'!$J$6:$J$45,R63)="","",INDEX('Recurring Schedule'!$J$6:$J$45,R63))) | M63: =IF(R63="","",IF(INDEX('Recurring Schedule'!$K$6:$K$45,R63)="","",INDEX('Recurring Schedule'!$K$6:$K$45,R63))) | N63: =IF(R63="","",IF(INDEX('Recurring Schedule'!$L$6:$L$45,R63)="","",INDEX('Recurring Schedule'!$L$6:$L$45,R63))) | O63: =IF(C63="","",IF(AND(OR(L63="1-Urgent",L63="2-High"),M63="✓"),"DO FIRST",IF(M63="✓","SCHEDULE",IF(OR(L63="1-Urgent",L63="2-High"),"DELEGATE","DELETE")))) | Q63: =IF(58>Calc!$AQ$368,"",MATCH(57,Calc!$AQ$2:$AQ$367,1)) | R63: =IF(Q63="","",SMALL(INDEX(Calc!$B$2:$AO$367,Q63,0),58-INDEX(Calc!$AQ$2:$AQ$367,Q63)))
B64: =IF(R64="","",59) | C64: =IF(R64="","",IF(INDEX('Recurring Schedule'!$C$6:$C$45,R64)="","",INDEX('Recurring Schedule'!$C$6:$C$45,R64))) | D64: =IF(R64="","",IF(INDEX('Recurring Schedule'!$D$6:$D$45,R64)="","",INDEX('Recurring Schedule'!$D$6:$D$45,R64))) | E64: =IF(Q64="","",INDEX(Calc!$A$2:$A$367,Q64)) | F64: =IF(OR(C64="",E64=""),"",E64-Setup!$D$7) | G64: =IF(R64="","",IF(INDEX('Recurring Schedule'!$H$6:$H$45,R64)="","",INDEX('Recurring Schedule'!$H$6:$H$45,R64))) | H64: =IF(R64="","",IF(INDEX('Recurring Schedule'!$I$6:$I$45,R64)="","",INDEX('Recurring Schedule'!$I$6:$I$45,R64))) | I64: =IF(OR(G64="",H64=""),"",TRIM(IF(HOUR(H64-G64)>0,HOUR(H64-G64)&" hr ","")&IF(MINUTE(H64-G64)>0,MINUTE(H64-G64)&" min",""))) | L64: =IF(R64="","",IF(INDEX('Recurring Schedule'!$J$6:$J$45,R64)="","",INDEX('Recurring Schedule'!$J$6:$J$45,R64))) | M64: =IF(R64="","",IF(INDEX('Recurring Schedule'!$K$6:$K$45,R64)="","",INDEX('Recurring Schedule'!$K$6:$K$45,R64))) | N64: =IF(R64="","",IF(INDEX('Recurring Schedule'!$L$6:$L$45,R64)="","",INDEX('Recurring Schedule'!$L$6:$L$45,R64))) | O64: =IF(C64="","",IF(AND(OR(L64="1-Urgent",L64="2-High"),M64="✓"),"DO FIRST",IF(M64="✓","SCHEDULE",IF(OR(L64="1-Urgent",L64="2-High"),"DELEGATE","DELETE")))) | Q64: =IF(59>Calc!$AQ$368,"",MATCH(58,Calc!$AQ$2:$AQ$367,1)) | R64: =IF(Q64="","",SMALL(INDEX(Calc!$B$2:$AO$367,Q64,0),59-INDEX(Calc!$AQ$2:$AQ$367,Q64)))
B65: =IF(R65="","",60) | C65: =IF(R65="","",IF(INDEX('Recurring Schedule'!$C$6:$C$45,R65)="","",INDEX('Recurring Schedule'!$C$6:$C$45,R65))) | D65: =IF(R65="","",IF(INDEX('Recurring Schedule'!$D$6:$D$45,R65)="","",INDEX('Recurring Schedule'!$D$6:$D$45,R65))) | E65: =IF(Q65="","",INDEX(Calc!$A$2:$A$367,Q65)) | F65: =IF(OR(C65="",E65=""),"",E65-Setup!$D$7) | G65: =IF(R65="","",IF(INDEX('Recurring Schedule'!$H$6:$H$45,R65)="","",INDEX('Recurring Schedule'!$H$6:$H$45,R65))) | H65: =IF(R65="","",IF(INDEX('Recurring Schedule'!$I$6:$I$45,R65)="","",INDEX('Recurring Schedule'!$I$6:$I$45,R65))) | I65: =IF(OR(G65="",H65=""),"",TRIM(IF(HOUR(H65-G65)>0,HOUR(H65-G65)&" hr ","")&IF(MINUTE(H65-G65)>0,MINUTE(H65-G65)&" min",""))) | L65: =IF(R65="","",IF(INDEX('Recurring Schedule'!$J$6:$J$45,R65)="","",INDEX('Recurring Schedule'!$J$6:$J$45,R65))) | M65: =IF(R65="","",IF(INDEX('Recurring Schedule'!$K$6:$K$45,R65)="","",INDEX('Recurring Schedule'!$K$6:$K$45,R65))) | N65: =IF(R65="","",IF(INDEX('Recurring Schedule'!$L$6:$L$45,R65)="","",INDEX('Recurring Schedule'!$L$6:$L$45,R65))) | O65: =IF(C65="","",IF(AND(OR(L65="1-Urgent",L65="2-High"),M65="✓"),"DO FIRST",IF(M65="✓","SCHEDULE",IF(OR(L65="1-Urgent",L65="2-High"),"DELEGATE","DELETE")))) | Q65: =IF(60>Calc!$AQ$368,"",MATCH(59,Calc!$AQ$2:$AQ$367,1)) | R65: =IF(Q65="","",SMALL(INDEX(Calc!$B$2:$AO$367,Q65,0),60-INDEX(Calc!$AQ$2:$AQ$367,Q65)))
B66: =IF(R66="","",61) | C66: =IF(R66="","",IF(INDEX('Recurring Schedule'!$C$6:$C$45,R66)="","",INDEX('Recurring Schedule'!$C$6:$C$45,R66))) | D66: =IF(R66="","",IF(INDEX('Recurring Schedule'!$D$6:$D$45,R66)="","",INDEX('Recurring Schedule'!$D$6:$D$45,R66))) | E66: =IF(Q66="","",INDEX(Calc!$A$2:$A$367,Q66)) | F66: =IF(OR(C66="",E66=""),"",E66-Setup!$D$7) | G66: =IF(R66="","",IF(INDEX('Recurring Schedule'!$H$6:$H$45,R66)="","",INDEX('Recurring Schedule'!$H$6:$H$45,R66))) | H66: =IF(R66="","",IF(INDEX('Recurring Schedule'!$I$6:$I$45,R66)="","",INDEX('Recurring Schedule'!$I$6:$I$45,R66))) | I66: =IF(OR(G66="",H66=""),"",TRIM(IF(HOUR(H66-G66)>0,HOUR(H66-G66)&" hr ","")&IF(MINUTE(H66-G66)>0,MINUTE(H66-G66)&" min",""))) | L66: =IF(R66="","",IF(INDEX('Recurring Schedule'!$J$6:$J$45,R66)="","",INDEX('Recurring Schedule'!$J$6:$J$45,R66))) | M66: =IF(R66="","",IF(INDEX('Recurring Schedule'!$K$6:$K$45,R66)="","",INDEX('Recurring Schedule'!$K$6:$K$45,R66))) | N66: =IF(R66="","",IF(INDEX('Recurring Schedule'!$L$6:$L$45,R66)="","",INDEX('Recurring Schedule'!$L$6:$L$45,R66))) | O66: =IF(C66="","",IF(AND(OR(L66="1-Urgent",L66="2-High"),M66="✓"),"DO FIRST",IF(M66="✓","SCHEDULE",IF(OR(L66="1-Urgent",L66="2-High"),"DELEGATE","DELETE")))) | Q66: =IF(61>Calc!$AQ$368,"",MATCH(60,Calc!$AQ$2:$AQ$367,1)) | R66: =IF(Q66="","",SMALL(INDEX(Calc!$B$2:$AO$367,Q66,0),61-INDEX(Calc!$AQ$2:$AQ$367,Q66)))
B67: =IF(R67="","",62) | C67: =IF(R67="","",IF(INDEX('Recurring Schedule'!$C$6:$C$45,R67)="","",INDEX('Recurring Schedule'!$C$6:$C$45,R67))) | D67: =IF(R67="","",IF(INDEX('Recurring Schedule'!$D$6:$D$45,R67)="","",INDEX('Recurring Schedule'!$D$6:$D$45,R67))) | E67: =IF(Q67="","",INDEX(Calc!$A$2:$A$367,Q67)) | F67: =IF(OR(C67="",E67=""),"",E67-Setup!$D$7) | G67: =IF(R67="","",IF(INDEX('Recurring Schedule'!$H$6:$H$45,R67)="","",INDEX('Recurring Schedule'!$H$6:$H$45,R67))) | H67: =IF(R67="","",IF(INDEX('Recurring Schedule'!$I$6:$I$45,R67)="","",INDEX('Recurring Schedule'!$I$6:$I$45,R67))) | I67: =IF(OR(G67="",H67=""),"",TRIM(IF(HOUR(H67-G67)>0,HOUR(H67-G67)&" hr ","")&IF(MINUTE(H67-G67)>0,MINUTE(H67-G67)&" min",""))) | L67: =IF(R67="","",IF(INDEX('Recurring Schedule'!$J$6:$J$45,R67)="","",INDEX('Recurring Schedule'!$J$6:$J$45,R67))) | M67: =IF(R67="","",IF(INDEX('Recurring Schedule'!$K$6:$K$45,R67)="","",INDEX('Recurring Schedule'!$K$6:$K$45,R67))) | N67: =IF(R67="","",IF(INDEX('Recurring Schedule'!$L$6:$L$45,R67)="","",INDEX('Recurring Schedule'!$L$6:$L$45,R67))) | O67: =IF(C67="","",IF(AND(OR(L67="1-Urgent",L67="2-High"),M67="✓"),"DO FIRST",IF(M67="✓","SCHEDULE",IF(OR(L67="1-Urgent",L67="2-High"),"DELEGATE","DELETE")))) | Q67: =IF(62>Calc!$AQ$368,"",MATCH(61,Calc!$AQ$2:$AQ$367,1)) | R67: =IF(Q67="","",SMALL(INDEX(Calc!$B$2:$AO$367,Q67,0),62-INDEX(Calc!$AQ$2:$AQ$367,Q67)))
B68: =IF(R68="","",63) | C68: =IF(R68="","",IF(INDEX('Recurring Schedule'!$C$6:$C$45,R68)="","",INDEX('Recurring Schedule'!$C$6:$C$45,R68))) | D68: =IF(R68="","",IF(INDEX('Recurring Schedule'!$D$6:$D$45,R68)="","",INDEX('Recurring Schedule'!$D$6:$D$45,R68))) | E68: =IF(Q68="","",INDEX(Calc!$A$2:$A$367,Q68)) | F68: =IF(OR(C68="",E68=""),"",E68-Setup!$D$7) | G68: =IF(R68="","",IF(INDEX('Recurring Schedule'!$H$6:$H$45,R68)="","",INDEX('Recurring Schedule'!$H$6:$H$45,R68))) | H68: =IF(R68="","",IF(INDEX('Recurring Schedule'!$I$6:$I$45,R68)="","",INDEX('Recurring Schedule'!$I$6:$I$45,R68))) | I68: =IF(OR(G68="",H68=""),"",TRIM(IF(HOUR(H68-G68)>0,HOUR(H68-G68)&" hr ","")&IF(MINUTE(H68-G68)>0,MINUTE(H68-G68)&" min",""))) | L68: =IF(R68="","",IF(INDEX('Recurring Schedule'!$J$6:$J$45,R68)="","",INDEX('Recurring Schedule'!$J$6:$J$45,R68))) | M68: =IF(R68="","",IF(INDEX('Recurring Schedule'!$K$6:$K$45,R68)="","",INDEX('Recurring Schedule'!$K$6:$K$45,R68))) | N68: =IF(R68="","",IF(INDEX('Recurring Schedule'!$L$6:$L$45,R68)="","",INDEX('Recurring Schedule'!$L$6:$L$45,R68))) | O68: =IF(C68="","",IF(AND(OR(L68="1-Urgent",L68="2-High"),M68="✓"),"DO FIRST",IF(M68="✓","SCHEDULE",IF(OR(L68="1-Urgent",L68="2-High"),"DELEGATE","DELETE")))) | Q68: =IF(63>Calc!$AQ$368,"",MATCH(62,Calc!$AQ$2:$AQ$367,1)) | R68: =IF(Q68="","",SMALL(INDEX(Calc!$B$2:$AO$367,Q68,0),63-INDEX(Calc!$AQ$2:$AQ$367,Q68)))
B69: =IF(R69="","",64) | C69: =IF(R69="","",IF(INDEX('Recurring Schedule'!$C$6:$C$45,R69)="","",INDEX('Recurring Schedule'!$C$6:$C$45,R69))) | D69: =IF(R69="","",IF(INDEX('Recurring Schedule'!$D$6:$D$45,R69)="","",INDEX('Recurring Schedule'!$D$6:$D$45,R69))) | E69: =IF(Q69="","",INDEX(Calc!$A$2:$A$367,Q69)) | F69: =IF(OR(C69="",E69=""),"",E69-Setup!$D$7) | G69: =IF(R69="","",IF(INDEX('Recurring Schedule'!$H$6:$H$45,R69)="","",INDEX('Recurring Schedule'!$H$6:$H$45,R69))) | H69: =IF(R69="","",IF(INDEX('Recurring Schedule'!$I$6:$I$45,R69)="","",INDEX('Recurring Schedule'!$I$6:$I$45,R69))) | I69: =IF(OR(G69="",H69=""),"",TRIM(IF(HOUR(H69-G69)>0,HOUR(H69-G69)&" hr ","")&IF(MINUTE(H69-G69)>0,MINUTE(H69-G69)&" min",""))) | L69: =IF(R69="","",IF(INDEX('Recurring Schedule'!$J$6:$J$45,R69)="","",INDEX('Recurring Schedule'!$J$6:$J$45,R69))) | M69: =IF(R69="","",IF(INDEX('Recurring Schedule'!$K$6:$K$45,R69)="","",INDEX('Recurring Schedule'!$K$6:$K$45,R69))) | N69: =IF(R69="","",IF(INDEX('Recurring Schedule'!$L$6:$L$45,R69)="","",INDEX('Recurring Schedule'!$L$6:$L$45,R69))) | O69: =IF(C69="","",IF(AND(OR(L69="1-Urgent",L69="2-High"),M69="✓"),"DO FIRST",IF(M69="✓","SCHEDULE",IF(OR(L69="1-Urgent",L69="2-High"),"DELEGATE","DELETE")))) | Q69: =IF(64>Calc!$AQ$368,"",MATCH(63,Calc!$AQ$2:$AQ$367,1)) | R69: =IF(Q69="","",SMALL(INDEX(Calc!$B$2:$AO$367,Q69,0),64-INDEX(Calc!$AQ$2:$AQ$367,Q69)))
B70: =IF(R70="","",65) | C70: =IF(R70="","",IF(INDEX('Recurring Schedule'!$C$6:$C$45,R70)="","",INDEX('Recurring Schedule'!$C$6:$C$45,R70))) | D70: =IF(R70="","",IF(INDEX('Recurring Schedule'!$D$6:$D$45,R70)="","",INDEX('Recurring Schedule'!$D$6:$D$45,R70))) | E70: =IF(Q70="","",INDEX(Calc!$A$2:$A$367,Q70)) | F70: =IF(OR(C70="",E70=""),"",E70-Setup!$D$7) | G70: =IF(R70="","",IF(INDEX('Recurring Schedule'!$H$6:$H$45,R70)="","",INDEX('Recurring Schedule'!$H$6:$H$45,R70))) | H70: =IF(R70="","",IF(INDEX('Recurring Schedule'!$I$6:$I$45,R70)="","",INDEX('Recurring Schedule'!$I$6:$I$45,R70))) | I70: =IF(OR(G70="",H70=""),"",TRIM(IF(HOUR(H70-G70)>0,HOUR(H70-G70)&" hr ","")&IF(MINUTE(H70-G70)>0,MINUTE(H70-G70)&" min",""))) | L70: =IF(R70="","",IF(INDEX('Recurring Schedule'!$J$6:$J$45,R70)="","",INDEX('Recurring Schedule'!$J$6:$J$45,R70))) | M70: =IF(R70="","",IF(INDEX('Recurring Schedule'!$K$6:$K$45,R70)="","",INDEX('Recurring Schedule'!$K$6:$K$45,R70))) | N70: =IF(R70="","",IF(INDEX('Recurring Schedule'!$L$6:$L$45,R70)="","",INDEX('Recurring Schedule'!$L$6:$L$45,R70))) | O70: =IF(C70="","",IF(AND(OR(L70="1-Urgent",L70="2-High"),M70="✓"),"DO FIRST",IF(M70="✓","SCHEDULE",IF(OR(L70="1-Urgent",L70="2-High"),"DELEGATE","DELETE")))) | Q70: =IF(65>Calc!$AQ$368,"",MATCH(64,Calc!$AQ$2:$AQ$367,1)) | R70: =IF(Q70="","",SMALL(INDEX(Calc!$B$2:$AO$367,Q70,0),65-INDEX(Calc!$AQ$2:$AQ$367,Q70)))
B71: =IF(R71="","",66) | C71: =IF(R71="","",IF(INDEX('Recurring Schedule'!$C$6:$C$45,R71)="","",INDEX('Recurring Schedule'!$C$6:$C$45,R71))) | D71: =IF(R71="","",IF(INDEX('Recurring Schedule'!$D$6:$D$45,R71)="","",INDEX('Recurring Schedule'!$D$6:$D$45,R71))) | E71: =IF(Q71="","",INDEX(Calc!$A$2:$A$367,Q71)) | F71: =IF(OR(C71="",E71=""),"",E71-Setup!$D$7) | G71: =IF(R71="","",IF(INDEX('Recurring Schedule'!$H$6:$H$45,R71)="","",INDEX('Recurring Schedule'!$H$6:$H$45,R71))) | H71: =IF(R71="","",IF(INDEX('Recurring Schedule'!$I$6:$I$45,R71)="","",INDEX('Recurring Schedule'!$I$6:$I$45,R71))) | I71: =IF(OR(G71="",H71=""),"",TRIM(IF(HOUR(H71-G71)>0,HOUR(H71-G71)&" hr ","")&IF(MINUTE(H71-G71)>0,MINUTE(H71-G71)&" min",""))) | L71: =IF(R71="","",IF(INDEX('Recurring Schedule'!$J$6:$J$45,R71)="","",INDEX('Recurring Schedule'!$J$6:$J$45,R71))) | M71: =IF(R71="","",IF(INDEX('Recurring Schedule'!$K$6:$K$45,R71)="","",INDEX('Recurring Schedule'!$K$6:$K$45,R71))) | N71: =IF(R71="","",IF(INDEX('Recurring Schedule'!$L$6:$L$45,R71)="","",INDEX('Recurring Schedule'!$L$6:$L$45,R71))) | O71: =IF(C71="","",IF(AND(OR(L71="1-Urgent",L71="2-High"),M71="✓"),"DO FIRST",IF(M71="✓","SCHEDULE",IF(OR(L71="1-Urgent",L71="2-High"),"DELEGATE","DELETE")))) | Q71: =IF(66>Calc!$AQ$368,"",MATCH(65,Calc!$AQ$2:$AQ$367,1)) | R71: =IF(Q71="","",SMALL(INDEX(Calc!$B$2:$AO$367,Q71,0),66-INDEX(Calc!$AQ$2:$AQ$367,Q71)))
B72: =IF(R72="","",67) | C72: =IF(R72="","",IF(INDEX('Recurring Schedule'!$C$6:$C$45,R72)="","",INDEX('Recurring Schedule'!$C$6:$C$45,R72))) | D72: =IF(R72="","",IF(INDEX('Recurring Schedule'!$D$6:$D$45,R72)="","",INDEX('Recurring Schedule'!$D$6:$D$45,R72))) | E72: =IF(Q72="","",INDEX(Calc!$A$2:$A$367,Q72)) | F72: =IF(OR(C72="",E72=""),"",E72-Setup!$D$7) | G72: =IF(R72="","",IF(INDEX('Recurring Schedule'!$H$6:$H$45,R72)="","",INDEX('Recurring Schedule'!$H$6:$H$45,R72))) | H72: =IF(R72="","",IF(INDEX('Recurring Schedule'!$I$6:$I$45,R72)="","",INDEX('Recurring Schedule'!$I$6:$I$45,R72))) | I72: =IF(OR(G72="",H72=""),"",TRIM(IF(HOUR(H72-G72)>0,HOUR(H72-G72)&" hr ","")&IF(MINUTE(H72-G72)>0,MINUTE(H72-G72)&" min",""))) | L72: =IF(R72="","",IF(INDEX('Recurring Schedule'!$J$6:$J$45,R72)="","",INDEX('Recurring Schedule'!$J$6:$J$45,R72))) | M72: =IF(R72="","",IF(INDEX('Recurring Schedule'!$K$6:$K$45,R72)="","",INDEX('Recurring Schedule'!$K$6:$K$45,R72))) | N72: =IF(R72="","",IF(INDEX('Recurring Schedule'!$L$6:$L$45,R72)="","",INDEX('Recurring Schedule'!$L$6:$L$45,R72))) | O72: =IF(C72="","",IF(AND(OR(L72="1-Urgent",L72="2-High"),M72="✓"),"DO FIRST",IF(M72="✓","SCHEDULE",IF(OR(L72="1-Urgent",L72="2-High"),"DELEGATE","DELETE")))) | Q72: =IF(67>Calc!$AQ$368,"",MATCH(66,Calc!$AQ$2:$AQ$367,1)) | R72: =IF(Q72="","",SMALL(INDEX(Calc!$B$2:$AO$367,Q72,0),67-INDEX(Calc!$AQ$2:$AQ$367,Q72)))
B73: =IF(R73="","",68) | C73: =IF(R73="","",IF(INDEX('Recurring Schedule'!$C$6:$C$45,R73)="","",INDEX('Recurring Schedule'!$C$6:$C$45,R73))) | D73: =IF(R73="","",IF(INDEX('Recurring Schedule'!$D$6:$D$45,R73)="","",INDEX('Recurring Schedule'!$D$6:$D$45,R73))) | E73: =IF(Q73="","",INDEX(Calc!$A$2:$A$367,Q73)) | F73: =IF(OR(C73="",E73=""),"",E73-Setup!$D$7) | G73: =IF(R73="","",IF(INDEX('Recurring Schedule'!$H$6:$H$45,R73)="","",INDEX('Recurring Schedule'!$H$6:$H$45,R73))) | H73: =IF(R73="","",IF(INDEX('Recurring Schedule'!$I$6:$I$45,R73)="","",INDEX('Recurring Schedule'!$I$6:$I$45,R73))) | I73: =IF(OR(G73="",H73=""),"",TRIM(IF(HOUR(H73-G73)>0,HOUR(H73-G73)&" hr ","")&IF(MINUTE(H73-G73)>0,MINUTE(H73-G73)&" min",""))) | L73: =IF(R73="","",IF(INDEX('Recurring Schedule'!$J$6:$J$45,R73)="","",INDEX('Recurring Schedule'!$J$6:$J$45,R73))) | M73: =IF(R73="","",IF(INDEX('Recurring Schedule'!$K$6:$K$45,R73)="","",INDEX('Recurring Schedule'!$K$6:$K$45,R73))) | N73: =IF(R73="","",IF(INDEX('Recurring Schedule'!$L$6:$L$45,R73)="","",INDEX('Recurring Schedule'!$L$6:$L$45,R73))) | O73: =IF(C73="","",IF(AND(OR(L73="1-Urgent",L73="2-High"),M73="✓"),"DO FIRST",IF(M73="✓","SCHEDULE",IF(OR(L73="1-Urgent",L73="2-High"),"DELEGATE","DELETE")))) | Q73: =IF(68>Calc!$AQ$368,"",MATCH(67,Calc!$AQ$2:$AQ$367,1)) | R73: =IF(Q73="","",SMALL(INDEX(Calc!$B$2:$AO$367,Q73,0),68-INDEX(Calc!$AQ$2:$AQ$367,Q73)))
B74: =IF(R74="","",69) | C74: =IF(R74="","",IF(INDEX('Recurring Schedule'!$C$6:$C$45,R74)="","",INDEX('Recurring Schedule'!$C$6:$C$45,R74))) | D74: =IF(R74="","",IF(INDEX('Recurring Schedule'!$D$6:$D$45,R74)="","",INDEX('Recurring Schedule'!$D$6:$D$45,R74))) | E74: =IF(Q74="","",INDEX(Calc!$A$2:$A$367,Q74)) | F74: =IF(OR(C74="",E74=""),"",E74-Setup!$D$7) | G74: =IF(R74="","",IF(INDEX('Recurring Schedule'!$H$6:$H$45,R74)="","",INDEX('Recurring Schedule'!$H$6:$H$45,R74))) | H74: =IF(R74="","",IF(INDEX('Recurring Schedule'!$I$6:$I$45,R74)="","",INDEX('Recurring Schedule'!$I$6:$I$45,R74))) | I74: =IF(OR(G74="",H74=""),"",TRIM(IF(HOUR(H74-G74)>0,HOUR(H74-G74)&" hr ","")&IF(MINUTE(H74-G74)>0,MINUTE(H74-G74)&" min",""))) | L74: =IF(R74="","",IF(INDEX('Recurring Schedule'!$J$6:$J$45,R74)="","",INDEX('Recurring Schedule'!$J$6:$J$45,R74))) | M74: =IF(R74="","",IF(INDEX('Recurring Schedule'!$K$6:$K$45,R74)="","",INDEX('Recurring Schedule'!$K$6:$K$45,R74))) | N74: =IF(R74="","",IF(INDEX('Recurring Schedule'!$L$6:$L$45,R74)="","",INDEX('Recurring Schedule'!$L$6:$L$45,R74))) | O74: =IF(C74="","",IF(AND(OR(L74="1-Urgent",L74="2-High"),M74="✓"),"DO FIRST",IF(M74="✓","SCHEDULE",IF(OR(L74="1-Urgent",L74="2-High"),"DELEGATE","DELETE")))) | Q74: =IF(69>Calc!$AQ$368,"",MATCH(68,Calc!$AQ$2:$AQ$367,1)) | R74: =IF(Q74="","",SMALL(INDEX(Calc!$B$2:$AO$367,Q74,0),69-INDEX(Calc!$AQ$2:$AQ$367,Q74)))
B75: =IF(R75="","",70) | C75: =IF(R75="","",IF(INDEX('Recurring Schedule'!$C$6:$C$45,R75)="","",INDEX('Recurring Schedule'!$C$6:$C$45,R75))) | D75: =IF(R75="","",IF(INDEX('Recurring Schedule'!$D$6:$D$45,R75)="","",INDEX('Recurring Schedule'!$D$6:$D$45,R75))) | E75: =IF(Q75="","",INDEX(Calc!$A$2:$A$367,Q75)) | F75: =IF(OR(C75="",E75=""),"",E75-Setup!$D$7) | G75: =IF(R75="","",IF(INDEX('Recurring Schedule'!$H$6:$H$45,R75)="","",INDEX('Recurring Schedule'!$H$6:$H$45,R75))) | H75: =IF(R75="","",IF(INDEX('Recurring Schedule'!$I$6:$I$45,R75)="","",INDEX('Recurring Schedule'!$I$6:$I$45,R75))) | I75: =IF(OR(G75="",H75=""),"",TRIM(IF(HOUR(H75-G75)>0,HOUR(H75-G75)&" hr ","")&IF(MINUTE(H75-G75)>0,MINUTE(H75-G75)&" min",""))) | L75: =IF(R75="","",IF(INDEX('Recurring Schedule'!$J$6:$J$45,R75)="","",INDEX('Recurring Schedule'!$J$6:$J$45,R75))) | M75: =IF(R75="","",IF(INDEX('Recurring Schedule'!$K$6:$K$45,R75)="","",INDEX('Recurring Schedule'!$K$6:$K$45,R75))) | N75: =IF(R75="","",IF(INDEX('Recurring Schedule'!$L$6:$L$45,R75)="","",INDEX('Recurring Schedule'!$L$6:$L$45,R75))) | O75: =IF(C75="","",IF(AND(OR(L75="1-Urgent",L75="2-High"),M75="✓"),"DO FIRST",IF(M75="✓","SCHEDULE",IF(OR(L75="1-Urgent",L75="2-High"),"DELEGATE","DELETE")))) | Q75: =IF(70>Calc!$AQ$368,"",MATCH(69,Calc!$AQ$2:$AQ$367,1)) | R75: =IF(Q75="","",SMALL(INDEX(Calc!$B$2:$AO$367,Q75,0),70-INDEX(Calc!$AQ$2:$AQ$367,Q75)))
B76: =IF(R76="","",71) | C76: =IF(R76="","",IF(INDEX('Recurring Schedule'!$C$6:$C$45,R76)="","",INDEX('Recurring Schedule'!$C$6:$C$45,R76))) | D76: =IF(R76="","",IF(INDEX('Recurring Schedule'!$D$6:$D$45,R76)="","",INDEX('Recurring Schedule'!$D$6:$D$45,R76))) | E76: =IF(Q76="","",INDEX(Calc!$A$2:$A$367,Q76)) | F76: =IF(OR(C76="",E76=""),"",E76-Setup!$D$7) | G76: =IF(R76="","",IF(INDEX('Recurring Schedule'!$H$6:$H$45,R76)="","",INDEX('Recurring Schedule'!$H$6:$H$45,R76))) | H76: =IF(R76="","",IF(INDEX('Recurring Schedule'!$I$6:$I$45,R76)="","",INDEX('Recurring Schedule'!$I$6:$I$45,R76))) | I76: =IF(OR(G76="",H76=""),"",TRIM(IF(HOUR(H76-G76)>0,HOUR(H76-G76)&" hr ","")&IF(MINUTE(H76-G76)>0,MINUTE(H76-G76)&" min",""))) | L76: =IF(R76="","",IF(INDEX('Recurring Schedule'!$J$6:$J$45,R76)="","",INDEX('Recurring Schedule'!$J$6:$J$45,R76))) | M76: =IF(R76="","",IF(INDEX('Recurring Schedule'!$K$6:$K$45,R76)="","",INDEX('Recurring Schedule'!$K$6:$K$45,R76))) | N76: =IF(R76="","",IF(INDEX('Recurring Schedule'!$L$6:$L$45,R76)="","",INDEX('Recurring Schedule'!$L$6:$L$45,R76))) | O76: =IF(C76="","",IF(AND(OR(L76="1-Urgent",L76="2-High"),M76="✓"),"DO FIRST",IF(M76="✓","SCHEDULE",IF(OR(L76="1-Urgent",L76="2-High"),"DELEGATE","DELETE")))) | Q76: =IF(71>Calc!$AQ$368,"",MATCH(70,Calc!$AQ$2:$AQ$367,1)) | R76: =IF(Q76="","",SMALL(INDEX(Calc!$B$2:$AO$367,Q76,0),71-INDEX(Calc!$AQ$2:$AQ$367,Q76)))
B77: =IF(R77="","",72) | C77: =IF(R77="","",IF(INDEX('Recurring Schedule'!$C$6:$C$45,R77)="","",INDEX('Recurring Schedule'!$C$6:$C$45,R77))) | D77: =IF(R77="","",IF(INDEX('Recurring Schedule'!$D$6:$D$45,R77)="","",INDEX('Recurring Schedule'!$D$6:$D$45,R77))) | E77: =IF(Q77="","",INDEX(Calc!$A$2:$A$367,Q77)) | F77: =IF(OR(C77="",E77=""),"",E77-Setup!$D$7) | G77: =IF(R77="","",IF(INDEX('Recurring Schedule'!$H$6:$H$45,R77)="","",INDEX('Recurring Schedule'!$H$6:$H$45,R77))) | H77: =IF(R77="","",IF(INDEX('Recurring Schedule'!$I$6:$I$45,R77)="","",INDEX('Recurring Schedule'!$I$6:$I$45,R77))) | I77: =IF(OR(G77="",H77=""),"",TRIM(IF(HOUR(H77-G77)>0,HOUR(H77-G77)&" hr ","")&IF(MINUTE(H77-G77)>0,MINUTE(H77-G77)&" min",""))) | L77: =IF(R77="","",IF(INDEX('Recurring Schedule'!$J$6:$J$45,R77)="","",INDEX('Recurring Schedule'!$J$6:$J$45,R77))) | M77: =IF(R77="","",IF(INDEX('Recurring Schedule'!$K$6:$K$45,R77)="","",INDEX('Recurring Schedule'!$K$6:$K$45,R77))) | N77: =IF(R77="","",IF(INDEX('Recurring Schedule'!$L$6:$L$45,R77)="","",INDEX('Recurring Schedule'!$L$6:$L$45,R77))) | O77: =IF(C77="","",IF(AND(OR(L77="1-Urgent",L77="2-High"),M77="✓"),"DO FIRST",IF(M77="✓","SCHEDULE",IF(OR(L77="1-Urgent",L77="2-High"),"DELEGATE","DELETE")))) | Q77: =IF(72>Calc!$AQ$368,"",MATCH(71,Calc!$AQ$2:$AQ$367,1)) | R77: =IF(Q77="","",SMALL(INDEX(Calc!$B$2:$AO$367,Q77,0),72-INDEX(Calc!$AQ$2:$AQ$367,Q77)))
B78: =IF(R78="","",73) | C78: =IF(R78="","",IF(INDEX('Recurring Schedule'!$C$6:$C$45,R78)="","",INDEX('Recurring Schedule'!$C$6:$C$45,R78))) | D78: =IF(R78="","",IF(INDEX('Recurring Schedule'!$D$6:$D$45,R78)="","",INDEX('Recurring Schedule'!$D$6:$D$45,R78))) | E78: =IF(Q78="","",INDEX(Calc!$A$2:$A$367,Q78)) | F78: =IF(OR(C78="",E78=""),"",E78-Setup!$D$7) | G78: =IF(R78="","",IF(INDEX('Recurring Schedule'!$H$6:$H$45,R78)="","",INDEX('Recurring Schedule'!$H$6:$H$45,R78))) | H78: =IF(R78="","",IF(INDEX('Recurring Schedule'!$I$6:$I$45,R78)="","",INDEX('Recurring Schedule'!$I$6:$I$45,R78))) | I78: =IF(OR(G78="",H78=""),"",TRIM(IF(HOUR(H78-G78)>0,HOUR(H78-G78)&" hr ","")&IF(MINUTE(H78-G78)>0,MINUTE(H78-G78)&" min",""))) | L78: =IF(R78="","",IF(INDEX('Recurring Schedule'!$J$6:$J$45,R78)="","",INDEX('Recurring Schedule'!$J$6:$J$45,R78))) | M78: =IF(R78="","",IF(INDEX('Recurring Schedule'!$K$6:$K$45,R78)="","",INDEX('Recurring Schedule'!$K$6:$K$45,R78))) | N78: =IF(R78="","",IF(INDEX('Recurring Schedule'!$L$6:$L$45,R78)="","",INDEX('Recurring Schedule'!$L$6:$L$45,R78))) | O78: =IF(C78="","",IF(AND(OR(L78="1-Urgent",L78="2-High"),M78="✓"),"DO FIRST",IF(M78="✓","SCHEDULE",IF(OR(L78="1-Urgent",L78="2-High"),"DELEGATE","DELETE")))) | Q78: =IF(73>Calc!$AQ$368,"",MATCH(72,Calc!$AQ$2:$AQ$367,1)) | R78: =IF(Q78="","",SMALL(INDEX(Calc!$B$2:$AO$367,Q78,0),73-INDEX(Calc!$AQ$2:$AQ$367,Q78)))
B79: =IF(R79="","",74) | C79: =IF(R79="","",IF(INDEX('Recurring Schedule'!$C$6:$C$45,R79)="","",INDEX('Recurring Schedule'!$C$6:$C$45,R79))) | D79: =IF(R79="","",IF(INDEX('Recurring Schedule'!$D$6:$D$45,R79)="","",INDEX('Recurring Schedule'!$D$6:$D$45,R79))) | E79: =IF(Q79="","",INDEX(Calc!$A$2:$A$367,Q79)) | F79: =IF(OR(C79="",E79=""),"",E79-Setup!$D$7) | G79: =IF(R79="","",IF(INDEX('Recurring Schedule'!$H$6:$H$45,R79)="","",INDEX('Recurring Schedule'!$H$6:$H$45,R79))) | H79: =IF(R79="","",IF(INDEX('Recurring Schedule'!$I$6:$I$45,R79)="","",INDEX('Recurring Schedule'!$I$6:$I$45,R79))) | I79: =IF(OR(G79="",H79=""),"",TRIM(IF(HOUR(H79-G79)>0,HOUR(H79-G79)&" hr ","")&IF(MINUTE(H79-G79)>0,MINUTE(H79-G79)&" min",""))) | L79: =IF(R79="","",IF(INDEX('Recurring Schedule'!$J$6:$J$45,R79)="","",INDEX('Recurring Schedule'!$J$6:$J$45,R79))) | M79: =IF(R79="","",IF(INDEX('Recurring Schedule'!$K$6:$K$45,R79)="","",INDEX('Recurring Schedule'!$K$6:$K$45,R79))) | N79: =IF(R79="","",IF(INDEX('Recurring Schedule'!$L$6:$L$45,R79)="","",INDEX('Recurring Schedule'!$L$6:$L$45,R79))) | O79: =IF(C79="","",IF(AND(OR(L79="1-Urgent",L79="2-High"),M79="✓"),"DO FIRST",IF(M79="✓","SCHEDULE",IF(OR(L79="1-Urgent",L79="2-High"),"DELEGATE","DELETE")))) | Q79: =IF(74>Calc!$AQ$368,"",MATCH(73,Calc!$AQ$2:$AQ$367,1)) | R79: =IF(Q79="","",SMALL(INDEX(Calc!$B$2:$AO$367,Q79,0),74-INDEX(Calc!$AQ$2:$AQ$367,Q79)))
B80: =IF(R80="","",75) | C80: =IF(R80="","",IF(INDEX('Recurring Schedule'!$C$6:$C$45,R80)="","",INDEX('Recurring Schedule'!$C$6:$C$45,R80))) | D80: =IF(R80="","",IF(INDEX('Recurring Schedule'!$D$6:$D$45,R80)="","",INDEX('Recurring Schedule'!$D$6:$D$45,R80))) | E80: =IF(Q80="","",INDEX(Calc!$A$2:$A$367,Q80)) | F80: =IF(OR(C80="",E80=""),"",E80-Setup!$D$7) | G80: =IF(R80="","",IF(INDEX('Recurring Schedule'!$H$6:$H$45,R80)="","",INDEX('Recurring Schedule'!$H$6:$H$45,R80))) | H80: =IF(R80="","",IF(INDEX('Recurring Schedule'!$I$6:$I$45,R80)="","",INDEX('Recurring Schedule'!$I$6:$I$45,R80))) | I80: =IF(OR(G80="",H80=""),"",TRIM(IF(HOUR(H80-G80)>0,HOUR(H80-G80)&" hr ","")&IF(MINUTE(H80-G80)>0,MINUTE(H80-G80)&" min",""))) | L80: =IF(R80="","",IF(INDEX('Recurring Schedule'!$J$6:$J$45,R80)="","",INDEX('Recurring Schedule'!$J$6:$J$45,R80))) | M80: =IF(R80="","",IF(INDEX('Recurring Schedule'!$K$6:$K$45,R80)="","",INDEX('Recurring Schedule'!$K$6:$K$45,R80))) | N80: =IF(R80="","",IF(INDEX('Recurring Schedule'!$L$6:$L$45,R80)="","",INDEX('Recurring Schedule'!$L$6:$L$45,R80))) | O80: =IF(C80="","",IF(AND(OR(L80="1-Urgent",L80="2-High"),M80="✓"),"DO FIRST",IF(M80="✓","SCHEDULE",IF(OR(L80="1-Urgent",L80="2-High"),"DELEGATE","DELETE")))) | Q80: =IF(75>Calc!$AQ$368,"",MATCH(74,Calc!$AQ$2:$AQ$367,1)) | R80: =IF(Q80="","",SMALL(INDEX(Calc!$B$2:$AO$367,Q80,0),75-INDEX(Calc!$AQ$2:$AQ$367,Q80)))
B81: =IF(R81="","",76) | C81: =IF(R81="","",IF(INDEX('Recurring Schedule'!$C$6:$C$45,R81)="","",INDEX('Recurring Schedule'!$C$6:$C$45,R81))) | D81: =IF(R81="","",IF(INDEX('Recurring Schedule'!$D$6:$D$45,R81)="","",INDEX('Recurring Schedule'!$D$6:$D$45,R81))) | E81: =IF(Q81="","",INDEX(Calc!$A$2:$A$367,Q81)) | F81: =IF(OR(C81="",E81=""),"",E81-Setup!$D$7) | G81: =IF(R81="","",IF(INDEX('Recurring Schedule'!$H$6:$H$45,R81)="","",INDEX('Recurring Schedule'!$H$6:$H$45,R81))) | H81: =IF(R81="","",IF(INDEX('Recurring Schedule'!$I$6:$I$45,R81)="","",INDEX('Recurring Schedule'!$I$6:$I$45,R81))) | I81: =IF(OR(G81="",H81=""),"",TRIM(IF(HOUR(H81-G81)>0,HOUR(H81-G81)&" hr ","")&IF(MINUTE(H81-G81)>0,MINUTE(H81-G81)&" min",""))) | L81: =IF(R81="","",IF(INDEX('Recurring Schedule'!$J$6:$J$45,R81)="","",INDEX('Recurring Schedule'!$J$6:$J$45,R81))) | M81: =IF(R81="","",IF(INDEX('Recurring Schedule'!$K$6:$K$45,R81)="","",INDEX('Recurring Schedule'!$K$6:$K$45,R81))) | N81: =IF(R81="","",IF(INDEX('Recurring Schedule'!$L$6:$L$45,R81)="","",INDEX('Recurring Schedule'!$L$6:$L$45,R81))) | O81: =IF(C81="","",IF(AND(OR(L81="1-Urgent",L81="2-High"),M81="✓"),"DO FIRST",IF(M81="✓","SCHEDULE",IF(OR(L81="1-Urgent",L81="2-High"),"DELEGATE","DELETE")))) | Q81: =IF(76>Calc!$AQ$368,"",MATCH(75,Calc!$AQ$2:$AQ$367,1)) | R81: =IF(Q81="","",SMALL(INDEX(Calc!$B$2:$AO$367,Q81,0),76-INDEX(Calc!$AQ$2:$AQ$367,Q81)))
B82: =IF(R82="","",77) | C82: =IF(R82="","",IF(INDEX('Recurring Schedule'!$C$6:$C$45,R82)="","",INDEX('Recurring Schedule'!$C$6:$C$45,R82))) | D82: =IF(R82="","",IF(INDEX('Recurring Schedule'!$D$6:$D$45,R82)="","",INDEX('Recurring Schedule'!$D$6:$D$45,R82))) | E82: =IF(Q82="","",INDEX(Calc!$A$2:$A$367,Q82)) | F82: =IF(OR(C82="",E82=""),"",E82-Setup!$D$7) | G82: =IF(R82="","",IF(INDEX('Recurring Schedule'!$H$6:$H$45,R82)="","",INDEX('Recurring Schedule'!$H$6:$H$45,R82))) | H82: =IF(R82="","",IF(INDEX('Recurring Schedule'!$I$6:$I$45,R82)="","",INDEX('Recurring Schedule'!$I$6:$I$45,R82))) | I82: =IF(OR(G82="",H82=""),"",TRIM(IF(HOUR(H82-G82)>0,HOUR(H82-G82)&" hr ","")&IF(MINUTE(H82-G82)>0,MINUTE(H82-G82)&" min",""))) | L82: =IF(R82="","",IF(INDEX('Recurring Schedule'!$J$6:$J$45,R82)="","",INDEX('Recurring Schedule'!$J$6:$J$45,R82))) | M82: =IF(R82="","",IF(INDEX('Recurring Schedule'!$K$6:$K$45,R82)="","",INDEX('Recurring Schedule'!$K$6:$K$45,R82))) | N82: =IF(R82="","",IF(INDEX('Recurring Schedule'!$L$6:$L$45,R82)="","",INDEX('Recurring Schedule'!$L$6:$L$45,R82))) | O82: =IF(C82="","",IF(AND(OR(L82="1-Urgent",L82="2-High"),M82="✓"),"DO FIRST",IF(M82="✓","SCHEDULE",IF(OR(L82="1-Urgent",L82="2-High"),"DELEGATE","DELETE")))) | Q82: =IF(77>Calc!$AQ$368,"",MATCH(76,Calc!$AQ$2:$AQ$367,1)) | R82: =IF(Q82="","",SMALL(INDEX(Calc!$B$2:$AO$367,Q82,0),77-INDEX(Calc!$AQ$2:$AQ$367,Q82)))
B83: =IF(R83="","",78) | C83: =IF(R83="","",IF(INDEX('Recurring Schedule'!$C$6:$C$45,R83)="","",INDEX('Recurring Schedule'!$C$6:$C$45,R83))) | D83: =IF(R83="","",IF(INDEX('Recurring Schedule'!$D$6:$D$45,R83)="","",INDEX('Recurring Schedule'!$D$6:$D$45,R83))) | E83: =IF(Q83="","",INDEX(Calc!$A$2:$A$367,Q83)) | F83: =IF(OR(C83="",E83=""),"",E83-Setup!$D$7) | G83: =IF(R83="","",IF(INDEX('Recurring Schedule'!$H$6:$H$45,R83)="","",INDEX('Recurring Schedule'!$H$6:$H$45,R83))) | H83: =IF(R83="","",IF(INDEX('Recurring Schedule'!$I$6:$I$45,R83)="","",INDEX('Recurring Schedule'!$I$6:$I$45,R83))) | I83: =IF(OR(G83="",H83=""),"",TRIM(IF(HOUR(H83-G83)>0,HOUR(H83-G83)&" hr ","")&IF(MINUTE(H83-G83)>0,MINUTE(H83-G83)&" min",""))) | L83: =IF(R83="","",IF(INDEX('Recurring Schedule'!$J$6:$J$45,R83)="","",INDEX('Recurring Schedule'!$J$6:$J$45,R83))) | M83: =IF(R83="","",IF(INDEX('Recurring Schedule'!$K$6:$K$45,R83)="","",INDEX('Recurring Schedule'!$K$6:$K$45,R83))) | N83: =IF(R83="","",IF(INDEX('Recurring Schedule'!$L$6:$L$45,R83)="","",INDEX('Recurring Schedule'!$L$6:$L$45,R83))) | O83: =IF(C83="","",IF(AND(OR(L83="1-Urgent",L83="2-High"),M83="✓"),"DO FIRST",IF(M83="✓","SCHEDULE",IF(OR(L83="1-Urgent",L83="2-High"),"DELEGATE","DELETE")))) | Q83: =IF(78>Calc!$AQ$368,"",MATCH(77,Calc!$AQ$2:$AQ$367,1)) | R83: =IF(Q83="","",SMALL(INDEX(Calc!$B$2:$AO$367,Q83,0),78-INDEX(Calc!$AQ$2:$AQ$367,Q83)))
B84: =IF(R84="","",79) | C84: =IF(R84="","",IF(INDEX('Recurring Schedule'!$C$6:$C$45,R84)="","",INDEX('Recurring Schedule'!$C$6:$C$45,R84))) | D84: =IF(R84="","",IF(INDEX('Recurring Schedule'!$D$6:$D$45,R84)="","",INDEX('Recurring Schedule'!$D$6:$D$45,R84))) | E84: =IF(Q84="","",INDEX(Calc!$A$2:$A$367,Q84)) | F84: =IF(OR(C84="",E84=""),"",E84-Setup!$D$7) | G84: =IF(R84="","",IF(INDEX('Recurring Schedule'!$H$6:$H$45,R84)="","",INDEX('Recurring Schedule'!$H$6:$H$45,R84))) | H84: =IF(R84="","",IF(INDEX('Recurring Schedule'!$I$6:$I$45,R84)="","",INDEX('Recurring Schedule'!$I$6:$I$45,R84))) | I84: =IF(OR(G84="",H84=""),"",TRIM(IF(HOUR(H84-G84)>0,HOUR(H84-G84)&" hr ","")&IF(MINUTE(H84-G84)>0,MINUTE(H84-G84)&" min",""))) | L84: =IF(R84="","",IF(INDEX('Recurring Schedule'!$J$6:$J$45,R84)="","",INDEX('Recurring Schedule'!$J$6:$J$45,R84))) | M84: =IF(R84="","",IF(INDEX('Recurring Schedule'!$K$6:$K$45,R84)="","",INDEX('Recurring Schedule'!$K$6:$K$45,R84))) | N84: =IF(R84="","",IF(INDEX('Recurring Schedule'!$L$6:$L$45,R84)="","",INDEX('Recurring Schedule'!$L$6:$L$45,R84))) | O84: =IF(C84="","",IF(AND(OR(L84="1-Urgent",L84="2-High"),M84="✓"),"DO FIRST",IF(M84="✓","SCHEDULE",IF(OR(L84="1-Urgent",L84="2-High"),"DELEGATE","DELETE")))) | Q84: =IF(79>Calc!$AQ$368,"",MATCH(78,Calc!$AQ$2:$AQ$367,1)) | R84: =IF(Q84="","",SMALL(INDEX(Calc!$B$2:$AO$367,Q84,0),79-INDEX(Calc!$AQ$2:$AQ$367,Q84)))
B85: =IF(R85="","",80) | C85: =IF(R85="","",IF(INDEX('Recurring Schedule'!$C$6:$C$45,R85)="","",INDEX('Recurring Schedule'!$C$6:$C$45,R85))) | D85: =IF(R85="","",IF(INDEX('Recurring Schedule'!$D$6:$D$45,R85)="","",INDEX('Recurring Schedule'!$D$6:$D$45,R85))) | E85: =IF(Q85="","",INDEX(Calc!$A$2:$A$367,Q85)) | F85: =IF(OR(C85="",E85=""),"",E85-Setup!$D$7) | G85: =IF(R85="","",IF(INDEX('Recurring Schedule'!$H$6:$H$45,R85)="","",INDEX('Recurring Schedule'!$H$6:$H$45,R85))) | H85: =IF(R85="","",IF(INDEX('Recurring Schedule'!$I$6:$I$45,R85)="","",INDEX('Recurring Schedule'!$I$6:$I$45,R85))) | I85: =IF(OR(G85="",H85=""),"",TRIM(IF(HOUR(H85-G85)>0,HOUR(H85-G85)&" hr ","")&IF(MINUTE(H85-G85)>0,MINUTE(H85-G85)&" min",""))) | L85: =IF(R85="","",IF(INDEX('Recurring Schedule'!$J$6:$J$45,R85)="","",INDEX('Recurring Schedule'!$J$6:$J$45,R85))) | M85: =IF(R85="","",IF(INDEX('Recurring Schedule'!$K$6:$K$45,R85)="","",INDEX('Recurring Schedule'!$K$6:$K$45,R85))) | N85: =IF(R85="","",IF(INDEX('Recurring Schedule'!$L$6:$L$45,R85)="","",INDEX('Recurring Schedule'!$L$6:$L$45,R85))) | O85: =IF(C85="","",IF(AND(OR(L85="1-Urgent",L85="2-High"),M85="✓"),"DO FIRST",IF(M85="✓","SCHEDULE",IF(OR(L85="1-Urgent",L85="2-High"),"DELEGATE","DELETE")))) | Q85: =IF(80>Calc!$AQ$368,"",MATCH(79,Calc!$AQ$2:$AQ$367,1)) | R85: =IF(Q85="","",SMALL(INDEX(Calc!$B$2:$AO$367,Q85,0),80-INDEX(Calc!$AQ$2:$AQ$367,Q85)))
B86: =IF(R86="","",81) | C86: =IF(R86="","",IF(INDEX('Recurring Schedule'!$C$6:$C$45,R86)="","",INDEX('Recurring Schedule'!$C$6:$C$45,R86))) | D86: =IF(R86="","",IF(INDEX('Recurring Schedule'!$D$6:$D$45,R86)="","",INDEX('Recurring Schedule'!$D$6:$D$45,R86))) | E86: =IF(Q86="","",INDEX(Calc!$A$2:$A$367,Q86)) | F86: =IF(OR(C86="",E86=""),"",E86-Setup!$D$7) | G86: =IF(R86="","",IF(INDEX('Recurring Schedule'!$H$6:$H$45,R86)="","",INDEX('Recurring Schedule'!$H$6:$H$45,R86))) | H86: =IF(R86="","",IF(INDEX('Recurring Schedule'!$I$6:$I$45,R86)="","",INDEX('Recurring Schedule'!$I$6:$I$45,R86))) | I86: =IF(OR(G86="",H86=""),"",TRIM(IF(HOUR(H86-G86)>0,HOUR(H86-G86)&" hr ","")&IF(MINUTE(H86-G86)>0,MINUTE(H86-G86)&" min",""))) | L86: =IF(R86="","",IF(INDEX('Recurring Schedule'!$J$6:$J$45,R86)="","",INDEX('Recurring Schedule'!$J$6:$J$45,R86))) | M86: =IF(R86="","",IF(INDEX('Recurring Schedule'!$K$6:$K$45,R86)="","",INDEX('Recurring Schedule'!$K$6:$K$45,R86))) | N86: =IF(R86="","",IF(INDEX('Recurring Schedule'!$L$6:$L$45,R86)="","",INDEX('Recurring Schedule'!$L$6:$L$45,R86))) | O86: =IF(C86="","",IF(AND(OR(L86="1-Urgent",L86="2-High"),M86="✓"),"DO FIRST",IF(M86="✓","SCHEDULE",IF(OR(L86="1-Urgent",L86="2-High"),"DELEGATE","DELETE")))) | Q86: =IF(81>Calc!$AQ$368,"",MATCH(80,Calc!$AQ$2:$AQ$367,1)) | R86: =IF(Q86="","",SMALL(INDEX(Calc!$B$2:$AO$367,Q86,0),81-INDEX(Calc!$AQ$2:$AQ$367,Q86)))
B87: =IF(R87="","",82) | C87: =IF(R87="","",IF(INDEX('Recurring Schedule'!$C$6:$C$45,R87)="","",INDEX('Recurring Schedule'!$C$6:$C$45,R87))) | D87: =IF(R87="","",IF(INDEX('Recurring Schedule'!$D$6:$D$45,R87)="","",INDEX('Recurring Schedule'!$D$6:$D$45,R87))) | E87: =IF(Q87="","",INDEX(Calc!$A$2:$A$367,Q87)) | F87: =IF(OR(C87="",E87=""),"",E87-Setup!$D$7) | G87: =IF(R87="","",IF(INDEX('Recurring Schedule'!$H$6:$H$45,R87)="","",INDEX('Recurring Schedule'!$H$6:$H$45,R87))) | H87: =IF(R87="","",IF(INDEX('Recurring Schedule'!$I$6:$I$45,R87)="","",INDEX('Recurring Schedule'!$I$6:$I$45,R87))) | I87: =IF(OR(G87="",H87=""),"",TRIM(IF(HOUR(H87-G87)>0,HOUR(H87-G87)&" hr ","")&IF(MINUTE(H87-G87)>0,MINUTE(H87-G87)&" min",""))) | L87: =IF(R87="","",IF(INDEX('Recurring Schedule'!$J$6:$J$45,R87)="","",INDEX('Recurring Schedule'!$J$6:$J$45,R87))) | M87: =IF(R87="","",IF(INDEX('Recurring Schedule'!$K$6:$K$45,R87)="","",INDEX('Recurring Schedule'!$K$6:$K$45,R87))) | N87: =IF(R87="","",IF(INDEX('Recurring Schedule'!$L$6:$L$45,R87)="","",INDEX('Recurring Schedule'!$L$6:$L$45,R87))) | O87: =IF(C87="","",IF(AND(OR(L87="1-Urgent",L87="2-High"),M87="✓"),"DO FIRST",IF(M87="✓","SCHEDULE",IF(OR(L87="1-Urgent",L87="2-High"),"DELEGATE","DELETE")))) | Q87: =IF(82>Calc!$AQ$368,"",MATCH(81,Calc!$AQ$2:$AQ$367,1)) | R87: =IF(Q87="","",SMALL(INDEX(Calc!$B$2:$AO$367,Q87,0),82-INDEX(Calc!$AQ$2:$AQ$367,Q87)))
B88: =IF(R88="","",83) | C88: =IF(R88="","",IF(INDEX('Recurring Schedule'!$C$6:$C$45,R88)="","",INDEX('Recurring Schedule'!$C$6:$C$45,R88))) | D88: =IF(R88="","",IF(INDEX('Recurring Schedule'!$D$6:$D$45,R88)="","",INDEX('Recurring Schedule'!$D$6:$D$45,R88))) | E88: =IF(Q88="","",INDEX(Calc!$A$2:$A$367,Q88)) | F88: =IF(OR(C88="",E88=""),"",E88-Setup!$D$7) | G88: =IF(R88="","",IF(INDEX('Recurring Schedule'!$H$6:$H$45,R88)="","",INDEX('Recurring Schedule'!$H$6:$H$45,R88))) | H88: =IF(R88="","",IF(INDEX('Recurring Schedule'!$I$6:$I$45,R88)="","",INDEX('Recurring Schedule'!$I$6:$I$45,R88))) | I88: =IF(OR(G88="",H88=""),"",TRIM(IF(HOUR(H88-G88)>0,HOUR(H88-G88)&" hr ","")&IF(MINUTE(H88-G88)>0,MINUTE(H88-G88)&" min",""))) | L88: =IF(R88="","",IF(INDEX('Recurring Schedule'!$J$6:$J$45,R88)="","",INDEX('Recurring Schedule'!$J$6:$J$45,R88))) | M88: =IF(R88="","",IF(INDEX('Recurring Schedule'!$K$6:$K$45,R88)="","",INDEX('Recurring Schedule'!$K$6:$K$45,R88))) | N88: =IF(R88="","",IF(INDEX('Recurring Schedule'!$L$6:$L$45,R88)="","",INDEX('Recurring Schedule'!$L$6:$L$45,R88))) | O88: =IF(C88="","",IF(AND(OR(L88="1-Urgent",L88="2-High"),M88="✓"),"DO FIRST",IF(M88="✓","SCHEDULE",IF(OR(L88="1-Urgent",L88="2-High"),"DELEGATE","DELETE")))) | Q88: =IF(83>Calc!$AQ$368,"",MATCH(82,Calc!$AQ$2:$AQ$367,1)) | R88: =IF(Q88="","",SMALL(INDEX(Calc!$B$2:$AO$367,Q88,0),83-INDEX(Calc!$AQ$2:$AQ$367,Q88)))
B89: =IF(R89="","",84) | C89: =IF(R89="","",IF(INDEX('Recurring Schedule'!$C$6:$C$45,R89)="","",INDEX('Recurring Schedule'!$C$6:$C$45,R89))) | D89: =IF(R89="","",IF(INDEX('Recurring Schedule'!$D$6:$D$45,R89)="","",INDEX('Recurring Schedule'!$D$6:$D$45,R89))) | E89: =IF(Q89="","",INDEX(Calc!$A$2:$A$367,Q89)) | F89: =IF(OR(C89="",E89=""),"",E89-Setup!$D$7) | G89: =IF(R89="","",IF(INDEX('Recurring Schedule'!$H$6:$H$45,R89)="","",INDEX('Recurring Schedule'!$H$6:$H$45,R89))) | H89: =IF(R89="","",IF(INDEX('Recurring Schedule'!$I$6:$I$45,R89)="","",INDEX('Recurring Schedule'!$I$6:$I$45,R89))) | I89: =IF(OR(G89="",H89=""),"",TRIM(IF(HOUR(H89-G89)>0,HOUR(H89-G89)&" hr ","")&IF(MINUTE(H89-G89)>0,MINUTE(H89-G89)&" min",""))) | L89: =IF(R89="","",IF(INDEX('Recurring Schedule'!$J$6:$J$45,R89)="","",INDEX('Recurring Schedule'!$J$6:$J$45,R89))) | M89: =IF(R89="","",IF(INDEX('Recurring Schedule'!$K$6:$K$45,R89)="","",INDEX('Recurring Schedule'!$K$6:$K$45,R89))) | N89: =IF(R89="","",IF(INDEX('Recurring Schedule'!$L$6:$L$45,R89)="","",INDEX('Recurring Schedule'!$L$6:$L$45,R89))) | O89: =IF(C89="","",IF(AND(OR(L89="1-Urgent",L89="2-High"),M89="✓"),"DO FIRST",IF(M89="✓","SCHEDULE",IF(OR(L89="1-Urgent",L89="2-High"),"DELEGATE","DELETE")))) | Q89: =IF(84>Calc!$AQ$368,"",MATCH(83,Calc!$AQ$2:$AQ$367,1)) | R89: =IF(Q89="","",SMALL(INDEX(Calc!$B$2:$AO$367,Q89,0),84-INDEX(Calc!$AQ$2:$AQ$367,Q89)))
B90: =IF(R90="","",85) | C90: =IF(R90="","",IF(INDEX('Recurring Schedule'!$C$6:$C$45,R90)="","",INDEX('Recurring Schedule'!$C$6:$C$45,R90))) | D90: =IF(R90="","",IF(INDEX('Recurring Schedule'!$D$6:$D$45,R90)="","",INDEX('Recurring Schedule'!$D$6:$D$45,R90))) | E90: =IF(Q90="","",INDEX(Calc!$A$2:$A$367,Q90)) | F90: =IF(OR(C90="",E90=""),"",E90-Setup!$D$7) | G90: =IF(R90="","",IF(INDEX('Recurring Schedule'!$H$6:$H$45,R90)="","",INDEX('Recurring Schedule'!$H$6:$H$45,R90))) | H90: =IF(R90="","",IF(INDEX('Recurring Schedule'!$I$6:$I$45,R90)="","",INDEX('Recurring Schedule'!$I$6:$I$45,R90))) | I90: =IF(OR(G90="",H90=""),"",TRIM(IF(HOUR(H90-G90)>0,HOUR(H90-G90)&" hr ","")&IF(MINUTE(H90-G90)>0,MINUTE(H90-G90)&" min",""))) | L90: =IF(R90="","",IF(INDEX('Recurring Schedule'!$J$6:$J$45,R90)="","",INDEX('Recurring Schedule'!$J$6:$J$45,R90))) | M90: =IF(R90="","",IF(INDEX('Recurring Schedule'!$K$6:$K$45,R90)="","",INDEX('Recurring Schedule'!$K$6:$K$45,R90))) | N90: =IF(R90="","",IF(INDEX('Recurring Schedule'!$L$6:$L$45,R90)="","",INDEX('Recurring Schedule'!$L$6:$L$45,R90))) | O90: =IF(C90="","",IF(AND(OR(L90="1-Urgent",L90="2-High"),M90="✓"),"DO FIRST",IF(M90="✓","SCHEDULE",IF(OR(L90="1-Urgent",L90="2-High"),"DELEGATE","DELETE")))) | Q90: =IF(85>Calc!$AQ$368,"",MATCH(84,Calc!$AQ$2:$AQ$367,1)) | R90: =IF(Q90="","",SMALL(INDEX(Calc!$B$2:$AO$367,Q90,0),85-INDEX(Calc!$AQ$2:$AQ$367,Q90)))
B91: =IF(R91="","",86) | C91: =IF(R91="","",IF(INDEX('Recurring Schedule'!$C$6:$C$45,R91)="","",INDEX('Recurring Schedule'!$C$6:$C$45,R91))) | D91: =IF(R91="","",IF(INDEX('Recurring Schedule'!$D$6:$D$45,R91)="","",INDEX('Recurring Schedule'!$D$6:$D$45,R91))) | E91: =IF(Q91="","",INDEX(Calc!$A$2:$A$367,Q91)) | F91: =IF(OR(C91="",E91=""),"",E91-Setup!$D$7) | G91: =IF(R91="","",IF(INDEX('Recurring Schedule'!$H$6:$H$45,R91)="","",INDEX('Recurring Schedule'!$H$6:$H$45,R91))) | H91: =IF(R91="","",IF(INDEX('Recurring Schedule'!$I$6:$I$45,R91)="","",INDEX('Recurring Schedule'!$I$6:$I$45,R91))) | I91: =IF(OR(G91="",H91=""),"",TRIM(IF(HOUR(H91-G91)>0,HOUR(H91-G91)&" hr ","")&IF(MINUTE(H91-G91)>0,MINUTE(H91-G91)&" min",""))) | L91: =IF(R91="","",IF(INDEX('Recurring Schedule'!$J$6:$J$45,R91)="","",INDEX('Recurring Schedule'!$J$6:$J$45,R91))) | M91: =IF(R91="","",IF(INDEX('Recurring Schedule'!$K$6:$K$45,R91)="","",INDEX('Recurring Schedule'!$K$6:$K$45,R91))) | N91: =IF(R91="","",IF(INDEX('Recurring Schedule'!$L$6:$L$45,R91)="","",INDEX('Recurring Schedule'!$L$6:$L$45,R91))) | O91: =IF(C91="","",IF(AND(OR(L91="1-Urgent",L91="2-High"),M91="✓"),"DO FIRST",IF(M91="✓","SCHEDULE",IF(OR(L91="1-Urgent",L91="2-High"),"DELEGATE","DELETE")))) | Q91: =IF(86>Calc!$AQ$368,"",MATCH(85,Calc!$AQ$2:$AQ$367,1)) | R91: =IF(Q91="","",SMALL(INDEX(Calc!$B$2:$AO$367,Q91,0),86-INDEX(Calc!$AQ$2:$AQ$367,Q91)))
B92: =IF(R92="","",87) | C92: =IF(R92="","",IF(INDEX('Recurring Schedule'!$C$6:$C$45,R92)="","",INDEX('Recurring Schedule'!$C$6:$C$45,R92))) | D92: =IF(R92="","",IF(INDEX('Recurring Schedule'!$D$6:$D$45,R92)="","",INDEX('Recurring Schedule'!$D$6:$D$45,R92))) | E92: =IF(Q92="","",INDEX(Calc!$A$2:$A$367,Q92)) | F92: =IF(OR(C92="",E92=""),"",E92-Setup!$D$7) | G92: =IF(R92="","",IF(INDEX('Recurring Schedule'!$H$6:$H$45,R92)="","",INDEX('Recurring Schedule'!$H$6:$H$45,R92))) | H92: =IF(R92="","",IF(INDEX('Recurring Schedule'!$I$6:$I$45,R92)="","",INDEX('Recurring Schedule'!$I$6:$I$45,R92))) | I92: =IF(OR(G92="",H92=""),"",TRIM(IF(HOUR(H92-G92)>0,HOUR(H92-G92)&" hr ","")&IF(MINUTE(H92-G92)>0,MINUTE(H92-G92)&" min",""))) | L92: =IF(R92="","",IF(INDEX('Recurring Schedule'!$J$6:$J$45,R92)="","",INDEX('Recurring Schedule'!$J$6:$J$45,R92))) | M92: =IF(R92="","",IF(INDEX('Recurring Schedule'!$K$6:$K$45,R92)="","",INDEX('Recurring Schedule'!$K$6:$K$45,R92))) | N92: =IF(R92="","",IF(INDEX('Recurring Schedule'!$L$6:$L$45,R92)="","",INDEX('Recurring Schedule'!$L$6:$L$45,R92))) | O92: =IF(C92="","",IF(AND(OR(L92="1-Urgent",L92="2-High"),M92="✓"),"DO FIRST",IF(M92="✓","SCHEDULE",IF(OR(L92="1-Urgent",L92="2-High"),"DELEGATE","DELETE")))) | Q92: =IF(87>Calc!$AQ$368,"",MATCH(86,Calc!$AQ$2:$AQ$367,1)) | R92: =IF(Q92="","",SMALL(INDEX(Calc!$B$2:$AO$367,Q92,0),87-INDEX(Calc!$AQ$2:$AQ$367,Q92)))
B93: =IF(R93="","",88) | C93: =IF(R93="","",IF(INDEX('Recurring Schedule'!$C$6:$C$45,R93)="","",INDEX('Recurring Schedule'!$C$6:$C$45,R93))) | D93: =IF(R93="","",IF(INDEX('Recurring Schedule'!$D$6:$D$45,R93)="","",INDEX('Recurring Schedule'!$D$6:$D$45,R93))) | E93: =IF(Q93="","",INDEX(Calc!$A$2:$A$367,Q93)) | F93: =IF(OR(C93="",E93=""),"",E93-Setup!$D$7) | G93: =IF(R93="","",IF(INDEX('Recurring Schedule'!$H$6:$H$45,R93)="","",INDEX('Recurring Schedule'!$H$6:$H$45,R93))) | H93: =IF(R93="","",IF(INDEX('Recurring Schedule'!$I$6:$I$45,R93)="","",INDEX('Recurring Schedule'!$I$6:$I$45,R93))) | I93: =IF(OR(G93="",H93=""),"",TRIM(IF(HOUR(H93-G93)>0,HOUR(H93-G93)&" hr ","")&IF(MINUTE(H93-G93)>0,MINUTE(H93-G93)&" min",""))) | L93: =IF(R93="","",IF(INDEX('Recurring Schedule'!$J$6:$J$45,R93)="","",INDEX('Recurring Schedule'!$J$6:$J$45,R93))) | M93: =IF(R93="","",IF(INDEX('Recurring Schedule'!$K$6:$K$45,R93)="","",INDEX('Recurring Schedule'!$K$6:$K$45,R93))) | N93: =IF(R93="","",IF(INDEX('Recurring Schedule'!$L$6:$L$45,R93)="","",INDEX('Recurring Schedule'!$L$6:$L$45,R93))) | O93: =IF(C93="","",IF(AND(OR(L93="1-Urgent",L93="2-High"),M93="✓"),"DO FIRST",IF(M93="✓","SCHEDULE",IF(OR(L93="1-Urgent",L93="2-High"),"DELEGATE","DELETE")))) | Q93: =IF(88>Calc!$AQ$368,"",MATCH(87,Calc!$AQ$2:$AQ$367,1)) | R93: =IF(Q93="","",SMALL(INDEX(Calc!$B$2:$AO$367,Q93,0),88-INDEX(Calc!$AQ$2:$AQ$367,Q93)))
B94: =IF(R94="","",89) | C94: =IF(R94="","",IF(INDEX('Recurring Schedule'!$C$6:$C$45,R94)="","",INDEX('Recurring Schedule'!$C$6:$C$45,R94))) | D94: =IF(R94="","",IF(INDEX('Recurring Schedule'!$D$6:$D$45,R94)="","",INDEX('Recurring Schedule'!$D$6:$D$45,R94))) | E94: =IF(Q94="","",INDEX(Calc!$A$2:$A$367,Q94)) | F94: =IF(OR(C94="",E94=""),"",E94-Setup!$D$7) | G94: =IF(R94="","",IF(INDEX('Recurring Schedule'!$H$6:$H$45,R94)="","",INDEX('Recurring Schedule'!$H$6:$H$45,R94))) | H94: =IF(R94="","",IF(INDEX('Recurring Schedule'!$I$6:$I$45,R94)="","",INDEX('Recurring Schedule'!$I$6:$I$45,R94))) | I94: =IF(OR(G94="",H94=""),"",TRIM(IF(HOUR(H94-G94)>0,HOUR(H94-G94)&" hr ","")&IF(MINUTE(H94-G94)>0,MINUTE(H94-G94)&" min",""))) | L94: =IF(R94="","",IF(INDEX('Recurring Schedule'!$J$6:$J$45,R94)="","",INDEX('Recurring Schedule'!$J$6:$J$45,R94))) | M94: =IF(R94="","",IF(INDEX('Recurring Schedule'!$K$6:$K$45,R94)="","",INDEX('Recurring Schedule'!$K$6:$K$45,R94))) | N94: =IF(R94="","",IF(INDEX('Recurring Schedule'!$L$6:$L$45,R94)="","",INDEX('Recurring Schedule'!$L$6:$L$45,R94))) | O94: =IF(C94="","",IF(AND(OR(L94="1-Urgent",L94="2-High"),M94="✓"),"DO FIRST",IF(M94="✓","SCHEDULE",IF(OR(L94="1-Urgent",L94="2-High"),"DELEGATE","DELETE")))) | Q94: =IF(89>Calc!$AQ$368,"",MATCH(88,Calc!$AQ$2:$AQ$367,1)) | R94: =IF(Q94="","",SMALL(INDEX(Calc!$B$2:$AO$367,Q94,0),89-INDEX(Calc!$AQ$2:$AQ$367,Q94)))
B95: =IF(R95="","",90) | C95: =IF(R95="","",IF(INDEX('Recurring Schedule'!$C$6:$C$45,R95)="","",INDEX('Recurring Schedule'!$C$6:$C$45,R95))) | D95: =IF(R95="","",IF(INDEX('Recurring Schedule'!$D$6:$D$45,R95)="","",INDEX('Recurring Schedule'!$D$6:$D$45,R95))) | E95: =IF(Q95="","",INDEX(Calc!$A$2:$A$367,Q95)) | F95: =IF(OR(C95="",E95=""),"",E95-Setup!$D$7) | G95: =IF(R95="","",IF(INDEX('Recurring Schedule'!$H$6:$H$45,R95)="","",INDEX('Recurring Schedule'!$H$6:$H$45,R95))) | H95: =IF(R95="","",IF(INDEX('Recurring Schedule'!$I$6:$I$45,R95)="","",INDEX('Recurring Schedule'!$I$6:$I$45,R95))) | I95: =IF(OR(G95="",H95=""),"",TRIM(IF(HOUR(H95-G95)>0,HOUR(H95-G95)&" hr ","")&IF(MINUTE(H95-G95)>0,MINUTE(H95-G95)&" min",""))) | L95: =IF(R95="","",IF(INDEX('Recurring Schedule'!$J$6:$J$45,R95)="","",INDEX('Recurring Schedule'!$J$6:$J$45,R95))) | M95: =IF(R95="","",IF(INDEX('Recurring Schedule'!$K$6:$K$45,R95)="","",INDEX('Recurring Schedule'!$K$6:$K$45,R95))) | N95: =IF(R95="","",IF(INDEX('Recurring Schedule'!$L$6:$L$45,R95)="","",INDEX('Recurring Schedule'!$L$6:$L$45,R95))) | O95: =IF(C95="","",IF(AND(OR(L95="1-Urgent",L95="2-High"),M95="✓"),"DO FIRST",IF(M95="✓","SCHEDULE",IF(OR(L95="1-Urgent",L95="2-High"),"DELEGATE","DELETE")))) | Q95: =IF(90>Calc!$AQ$368,"",MATCH(89,Calc!$AQ$2:$AQ$367,1)) | R95: =IF(Q95="","",SMALL(INDEX(Calc!$B$2:$AO$367,Q95,0),90-INDEX(Calc!$AQ$2:$AQ$367,Q95)))
B96: =IF(R96="","",91) | C96: =IF(R96="","",IF(INDEX('Recurring Schedule'!$C$6:$C$45,R96)="","",INDEX('Recurring Schedule'!$C$6:$C$45,R96))) | D96: =IF(R96="","",IF(INDEX('Recurring Schedule'!$D$6:$D$45,R96)="","",INDEX('Recurring Schedule'!$D$6:$D$45,R96))) | E96: =IF(Q96="","",INDEX(Calc!$A$2:$A$367,Q96)) | F96: =IF(OR(C96="",E96=""),"",E96-Setup!$D$7) | G96: =IF(R96="","",IF(INDEX('Recurring Schedule'!$H$6:$H$45,R96)="","",INDEX('Recurring Schedule'!$H$6:$H$45,R96))) | H96: =IF(R96="","",IF(INDEX('Recurring Schedule'!$I$6:$I$45,R96)="","",INDEX('Recurring Schedule'!$I$6:$I$45,R96))) | I96: =IF(OR(G96="",H96=""),"",TRIM(IF(HOUR(H96-G96)>0,HOUR(H96-G96)&" hr ","")&IF(MINUTE(H96-G96)>0,MINUTE(H96-G96)&" min",""))) | L96: =IF(R96="","",IF(INDEX('Recurring Schedule'!$J$6:$J$45,R96)="","",INDEX('Recurring Schedule'!$J$6:$J$45,R96))) | M96: =IF(R96="","",IF(INDEX('Recurring Schedule'!$K$6:$K$45,R96)="","",INDEX('Recurring Schedule'!$K$6:$K$45,R96))) | N96: =IF(R96="","",IF(INDEX('Recurring Schedule'!$L$6:$L$45,R96)="","",INDEX('Recurring Schedule'!$L$6:$L$45,R96))) | O96: =IF(C96="","",IF(AND(OR(L96="1-Urgent",L96="2-High"),M96="✓"),"DO FIRST",IF(M96="✓","SCHEDULE",IF(OR(L96="1-Urgent",L96="2-High"),"DELEGATE","DELETE")))) | Q96: =IF(91>Calc!$AQ$368,"",MATCH(90,Calc!$AQ$2:$AQ$367,1)) | R96: =IF(Q96="","",SMALL(INDEX(Calc!$B$2:$AO$367,Q96,0),91-INDEX(Calc!$AQ$2:$AQ$367,Q96)))
B97: =IF(R97="","",92) | C97: =IF(R97="","",IF(INDEX('Recurring Schedule'!$C$6:$C$45,R97)="","",INDEX('Recurring Schedule'!$C$6:$C$45,R97))) | D97: =IF(R97="","",IF(INDEX('Recurring Schedule'!$D$6:$D$45,R97)="","",INDEX('Recurring Schedule'!$D$6:$D$45,R97))) | E97: =IF(Q97="","",INDEX(Calc!$A$2:$A$367,Q97)) | F97: =IF(OR(C97="",E97=""),"",E97-Setup!$D$7) | G97: =IF(R97="","",IF(INDEX('Recurring Schedule'!$H$6:$H$45,R97)="","",INDEX('Recurring Schedule'!$H$6:$H$45,R97))) | H97: =IF(R97="","",IF(INDEX('Recurring Schedule'!$I$6:$I$45,R97)="","",INDEX('Recurring Schedule'!$I$6:$I$45,R97))) | I97: =IF(OR(G97="",H97=""),"",TRIM(IF(HOUR(H97-G97)>0,HOUR(H97-G97)&" hr ","")&IF(MINUTE(H97-G97)>0,MINUTE(H97-G97)&" min",""))) | L97: =IF(R97="","",IF(INDEX('Recurring Schedule'!$J$6:$J$45,R97)="","",INDEX('Recurring Schedule'!$J$6:$J$45,R97))) | M97: =IF(R97="","",IF(INDEX('Recurring Schedule'!$K$6:$K$45,R97)="","",INDEX('Recurring Schedule'!$K$6:$K$45,R97))) | N97: =IF(R97="","",IF(INDEX('Recurring Schedule'!$L$6:$L$45,R97)="","",INDEX('Recurring Schedule'!$L$6:$L$45,R97))) | O97: =IF(C97="","",IF(AND(OR(L97="1-Urgent",L97="2-High"),M97="✓"),"DO FIRST",IF(M97="✓","SCHEDULE",IF(OR(L97="1-Urgent",L97="2-High"),"DELEGATE","DELETE")))) | Q97: =IF(92>Calc!$AQ$368,"",MATCH(91,Calc!$AQ$2:$AQ$367,1)) | R97: =IF(Q97="","",SMALL(INDEX(Calc!$B$2:$AO$367,Q97,0),92-INDEX(Calc!$AQ$2:$AQ$367,Q97)))
B98: =IF(R98="","",93) | C98: =IF(R98="","",IF(INDEX('Recurring Schedule'!$C$6:$C$45,R98)="","",INDEX('Recurring Schedule'!$C$6:$C$45,R98))) | D98: =IF(R98="","",IF(INDEX('Recurring Schedule'!$D$6:$D$45,R98)="","",INDEX('Recurring Schedule'!$D$6:$D$45,R98))) | E98: =IF(Q98="","",INDEX(Calc!$A$2:$A$367,Q98)) | F98: =IF(OR(C98="",E98=""),"",E98-Setup!$D$7) | G98: =IF(R98="","",IF(INDEX('Recurring Schedule'!$H$6:$H$45,R98)="","",INDEX('Recurring Schedule'!$H$6:$H$45,R98))) | H98: =IF(R98="","",IF(INDEX('Recurring Schedule'!$I$6:$I$45,R98)="","",INDEX('Recurring Schedule'!$I$6:$I$45,R98))) | I98: =IF(OR(G98="",H98=""),"",TRIM(IF(HOUR(H98-G98)>0,HOUR(H98-G98)&" hr ","")&IF(MINUTE(H98-G98)>0,MINUTE(H98-G98)&" min",""))) | L98: =IF(R98="","",IF(INDEX('Recurring Schedule'!$J$6:$J$45,R98)="","",INDEX('Recurring Schedule'!$J$6:$J$45,R98))) | M98: =IF(R98="","",IF(INDEX('Recurring Schedule'!$K$6:$K$45,R98)="","",INDEX('Recurring Schedule'!$K$6:$K$45,R98))) | N98: =IF(R98="","",IF(INDEX('Recurring Schedule'!$L$6:$L$45,R98)="","",INDEX('Recurring Schedule'!$L$6:$L$45,R98))) | O98: =IF(C98="","",IF(AND(OR(L98="1-Urgent",L98="2-High"),M98="✓"),"DO FIRST",IF(M98="✓","SCHEDULE",IF(OR(L98="1-Urgent",L98="2-High"),"DELEGATE","DELETE")))) | Q98: =IF(93>Calc!$AQ$368,"",MATCH(92,Calc!$AQ$2:$AQ$367,1)) | R98: =IF(Q98="","",SMALL(INDEX(Calc!$B$2:$AO$367,Q98,0),93-INDEX(Calc!$AQ$2:$AQ$367,Q98)))
B99: =IF(R99="","",94) | C99: =IF(R99="","",IF(INDEX('Recurring Schedule'!$C$6:$C$45,R99)="","",INDEX('Recurring Schedule'!$C$6:$C$45,R99))) | D99: =IF(R99="","",IF(INDEX('Recurring Schedule'!$D$6:$D$45,R99)="","",INDEX('Recurring Schedule'!$D$6:$D$45,R99))) | E99: =IF(Q99="","",INDEX(Calc!$A$2:$A$367,Q99)) | F99: =IF(OR(C99="",E99=""),"",E99-Setup!$D$7) | G99: =IF(R99="","",IF(INDEX('Recurring Schedule'!$H$6:$H$45,R99)="","",INDEX('Recurring Schedule'!$H$6:$H$45,R99))) | H99: =IF(R99="","",IF(INDEX('Recurring Schedule'!$I$6:$I$45,R99)="","",INDEX('Recurring Schedule'!$I$6:$I$45,R99))) | I99: =IF(OR(G99="",H99=""),"",TRIM(IF(HOUR(H99-G99)>0,HOUR(H99-G99)&" hr ","")&IF(MINUTE(H99-G99)>0,MINUTE(H99-G99)&" min",""))) | L99: =IF(R99="","",IF(INDEX('Recurring Schedule'!$J$6:$J$45,R99)="","",INDEX('Recurring Schedule'!$J$6:$J$45,R99))) | M99: =IF(R99="","",IF(INDEX('Recurring Schedule'!$K$6:$K$45,R99)="","",INDEX('Recurring Schedule'!$K$6:$K$45,R99))) | N99: =IF(R99="","",IF(INDEX('Recurring Schedule'!$L$6:$L$45,R99)="","",INDEX('Recurring Schedule'!$L$6:$L$45,R99))) | O99: =IF(C99="","",IF(AND(OR(L99="1-Urgent",L99="2-High"),M99="✓"),"DO FIRST",IF(M99="✓","SCHEDULE",IF(OR(L99="1-Urgent",L99="2-High"),"DELEGATE","DELETE")))) | Q99: =IF(94>Calc!$AQ$368,"",MATCH(93,Calc!$AQ$2:$AQ$367,1)) | R99: =IF(Q99="","",SMALL(INDEX(Calc!$B$2:$AO$367,Q99,0),94-INDEX(Calc!$AQ$2:$AQ$367,Q99)))
B100: =IF(R100="","",95) | C100: =IF(R100="","",IF(INDEX('Recurring Schedule'!$C$6:$C$45,R100)="","",INDEX('Recurring Schedule'!$C$6:$C$45,R100))) | D100: =IF(R100="","",IF(INDEX('Recurring Schedule'!$D$6:$D$45,R100)="","",INDEX('Recurring Schedule'!$D$6:$D$45,R100))) | E100: =IF(Q100="","",INDEX(Calc!$A$2:$A$367,Q100)) | F100: =IF(OR(C100="",E100=""),"",E100-Setup!$D$7) | G100: =IF(R100="","",IF(INDEX('Recurring Schedule'!$H$6:$H$45,R100)="","",INDEX('Recurring Schedule'!$H$6:$H$45,R100))) | H100: =IF(R100="","",IF(INDEX('Recurring Schedule'!$I$6:$I$45,R100)="","",INDEX('Recurring Schedule'!$I$6:$I$45,R100))) | I100: =IF(OR(G100="",H100=""),"",TRIM(IF(HOUR(H100-G100)>0,HOUR(H100-G100)&" hr ","")&IF(MINUTE(H100-G100)>0,MINUTE(H100-G100)&" min",""))) | L100: =IF(R100="","",IF(INDEX('Recurring Schedule'!$J$6:$J$45,R100)="","",INDEX('Recurring Schedule'!$J$6:$J$45,R100))) | M100: =IF(R100="","",IF(INDEX('Recurring Schedule'!$K$6:$K$45,R100)="","",INDEX('Recurring Schedule'!$K$6:$K$45,R100))) | N100: =IF(R100="","",IF(INDEX('Recurring Schedule'!$L$6:$L$45,R100)="","",INDEX('Recurring Schedule'!$L$6:$L$45,R100))) | O100: =IF(C100="","",IF(AND(OR(L100="1-Urgent",L100="2-High"),M100="✓"),"DO FIRST",IF(M100="✓","SCHEDULE",IF(OR(L100="1-Urgent",L100="2-High"),"DELEGATE","DELETE")))) | Q100: =IF(95>Calc!$AQ$368,"",MATCH(94,Calc!$AQ$2:$AQ$367,1)) | R100: =IF(Q100="","",SMALL(INDEX(Calc!$B$2:$AO$367,Q100,0),95-INDEX(Calc!$AQ$2:$AQ$367,Q100)))
B101: =IF(R101="","",96) | C101: =IF(R101="","",IF(INDEX('Recurring Schedule'!$C$6:$C$45,R101)="","",INDEX('Recurring Schedule'!$C$6:$C$45,R101))) | D101: =IF(R101="","",IF(INDEX('Recurring Schedule'!$D$6:$D$45,R101)="","",INDEX('Recurring Schedule'!$D$6:$D$45,R101))) | E101: =IF(Q101="","",INDEX(Calc!$A$2:$A$367,Q101)) | F101: =IF(OR(C101="",E101=""),"",E101-Setup!$D$7) | G101: =IF(R101="","",IF(INDEX('Recurring Schedule'!$H$6:$H$45,R101)="","",INDEX('Recurring Schedule'!$H$6:$H$45,R101))) | H101: =IF(R101="","",IF(INDEX('Recurring Schedule'!$I$6:$I$45,R101)="","",INDEX('Recurring Schedule'!$I$6:$I$45,R101))) | I101: =IF(OR(G101="",H101=""),"",TRIM(IF(HOUR(H101-G101)>0,HOUR(H101-G101)&" hr ","")&IF(MINUTE(H101-G101)>0,MINUTE(H101-G101)&" min",""))) | L101: =IF(R101="","",IF(INDEX('Recurring Schedule'!$J$6:$J$45,R101)="","",INDEX('Recurring Schedule'!$J$6:$J$45,R101))) | M101: =IF(R101="","",IF(INDEX('Recurring Schedule'!$K$6:$K$45,R101)="","",INDEX('Recurring Schedule'!$K$6:$K$45,R101))) | N101: =IF(R101="","",IF(INDEX('Recurring Schedule'!$L$6:$L$45,R101)="","",INDEX('Recurring Schedule'!$L$6:$L$45,R101))) | O101: =IF(C101="","",IF(AND(OR(L101="1-Urgent",L101="2-High"),M101="✓"),"DO FIRST",IF(M101="✓","SCHEDULE",IF(OR(L101="1-Urgent",L101="2-High"),"DELEGATE","DELETE")))) | Q101: =IF(96>Calc!$AQ$368,"",MATCH(95,Calc!$AQ$2:$AQ$367,1)) | R101: =IF(Q101="","",SMALL(INDEX(Calc!$B$2:$AO$367,Q101,0),96-INDEX(Calc!$AQ$2:$AQ$367,Q101)))
...

Sheet Tasks Filter
B2: Tasks Filter | E2: DATE RANGE · SORT · FILTER (blank = all)
E3: From | F3: =Setup!$D$7-30 | H3: Task name | K3: Category | N3: Decision | P3: SHOWN | Q3: OVERDUE
B4: =TEXT(Setup!$D$7,"dddd, mmmm d, yyyy") | E4: To | F4: =Setup!$D$7+90 | H4: Priority | K4: Status | N4: Show done | O4: Yes | P4: =COUNT(Calc!$BK$2:$BK$2001) | Q4: =COUNT(Calc!$BL$2:$BL$2001)
E5: Sort by | F5: Due date | H5: Important | I5: Both | K5: Person
E6: Order | F6: Ascending | P6: DUE TODAY | Q6: DONE
P7: =COUNTIFS(Calc!$AW$2:$AW$2001,Setup!$D$7,Calc!$BH$2:$BH$2001,1) | Q7: =SUMPRODUCT((Calc!$BI$2:$BI$2001=1)*(Calc!$BG$2:$BG$2001=1))
B8: TASK DETAILS | E8: SCHEDULE | J8: STATUS & PROGRESS | L8: EISENHOWER MATRIX | P8: EDIT
B9: # | C9: TASK | D9: CATEGORY | E9: DUE DATE | F9: DAYS LEFT | G9: START | H9: END | I9: DURATION | J9: STATUS | K9: PROGRESS | L9: PRIORITY | M9: IMPORTANT | N9: DELEGATE TO | O9: DECISION | P9: EDIT TASK
B10: =IF(R10="","",1) | C10: =IF($R10="","",IF(INDEX(Calc!$AU$2:$AU$2001,$R10)="","",INDEX(Calc!$AU$2:$AU$2001,$R10))) | D10: =IF($R10="","",IF(INDEX(Calc!$AV$2:$AV$2001,$R10)="","",INDEX(Calc!$AV$2:$AV$2001,$R10))) | E10: =IF($R10="","",IF(INDEX(Calc!$AW$2:$AW$2001,$R10)="","",INDEX(Calc!$AW$2:$AW$2001,$R10))) | F10: =IF(OR(C10="",E10=""),"",E10-Setup!$D$7) | G10: =IF($R10="","",IF(INDEX(Calc!$AX$2:$AX$2001,$R10)="","",INDEX(Calc!$AX$2:$AX$2001,$R10))) | H10: =IF($R10="","",IF(INDEX(Calc!$AY$2:$AY$2001,$R10)="","",INDEX(Calc!$AY$2:$AY$2001,$R10))) | I10: =IF(OR(G10="",H10=""),"",TRIM(IF(HOUR(H10-G10)>0,HOUR(H10-G10)&" hr ","")&IF(MINUTE(H10-G10)>0,MINUTE(H10-G10)&" min",""))) | J10: =IF($R10="","",IF(INDEX(Calc!$AZ$2:$AZ$2001,$R10)="","",INDEX(Calc!$AZ$2:$AZ$2001,$R10))) | K10: =IF($R10="","",IF(INDEX(Calc!$BE$2:$BE$2001,$R10)="","",INDEX(Calc!$BE$2:$BE$2001,$R10))) | L10: =IF($R10="","",IF(INDEX(Calc!$BA$2:$BA$2001,$R10)="","",INDEX(Calc!$BA$2:$BA$2001,$R10))) | M10: =IF($R10="","",IF(INDEX(Calc!$BB$2:$BB$2001,$R10)="","",INDEX(Calc!$BB$2:$BB$2001,$R10))) | N10: =IF($R10="","",IF(INDEX(Calc!$BC$2:$BC$2001,$R10)="","",INDEX(Calc!$BC$2:$BC$2001,$R10))) | O10: =IF($R10="","",IF(INDEX(Calc!$BD$2:$BD$2001,$R10)="","",INDEX(Calc!$BD$2:$BD$2001,$R10))) | P10: =IF(R10="","",HYPERLINK("#'"&IF(INDEX(Calc!$AS$2:$AS$2001,R10)="R","Recurring Log","Variable Tasks")&"'!J"&INDEX(Calc!$AT$2:$AT$2001,R10),"✎ edit")) | R10: =IFERROR(MATCH(SMALL(Calc!$BK$2:$BK$2001,1),Calc!$BK$2:$BK$2001,0),"")
B11: =IF(R11="","",2) | C11: =IF($R11="","",IF(INDEX(Calc!$AU$2:$AU$2001,$R11)="","",INDEX(Calc!$AU$2:$AU$2001,$R11))) | D11: =IF($R11="","",IF(INDEX(Calc!$AV$2:$AV$2001,$R11)="","",INDEX(Calc!$AV$2:$AV$2001,$R11))) | E11: =IF($R11="","",IF(INDEX(Calc!$AW$2:$AW$2001,$R11)="","",INDEX(Calc!$AW$2:$AW$2001,$R11))) | F11: =IF(OR(C11="",E11=""),"",E11-Setup!$D$7) | G11: =IF($R11="","",IF(INDEX(Calc!$AX$2:$AX$2001,$R11)="","",INDEX(Calc!$AX$2:$AX$2001,$R11))) | H11: =IF($R11="","",IF(INDEX(Calc!$AY$2:$AY$2001,$R11)="","",INDEX(Calc!$AY$2:$AY$2001,$R11))) | I11: =IF(OR(G11="",H11=""),"",TRIM(IF(HOUR(H11-G11)>0,HOUR(H11-G11)&" hr ","")&IF(MINUTE(H11-G11)>0,MINUTE(H11-G11)&" min",""))) | J11: =IF($R11="","",IF(INDEX(Calc!$AZ$2:$AZ$2001,$R11)="","",INDEX(Calc!$AZ$2:$AZ$2001,$R11))) | K11: =IF($R11="","",IF(INDEX(Calc!$BE$2:$BE$2001,$R11)="","",INDEX(Calc!$BE$2:$BE$2001,$R11))) | L11: =IF($R11="","",IF(INDEX(Calc!$BA$2:$BA$2001,$R11)="","",INDEX(Calc!$BA$2:$BA$2001,$R11))) | M11: =IF($R11="","",IF(INDEX(Calc!$BB$2:$BB$2001,$R11)="","",INDEX(Calc!$BB$2:$BB$2001,$R11))) | N11: =IF($R11="","",IF(INDEX(Calc!$BC$2:$BC$2001,$R11)="","",INDEX(Calc!$BC$2:$BC$2001,$R11))) | O11: =IF($R11="","",IF(INDEX(Calc!$BD$2:$BD$2001,$R11)="","",INDEX(Calc!$BD$2:$BD$2001,$R11))) | P11: =IF(R11="","",HYPERLINK("#'"&IF(INDEX(Calc!$AS$2:$AS$2001,R11)="R","Recurring Log","Variable Tasks")&"'!J"&INDEX(Calc!$AT$2:$AT$2001,R11),"✎ edit")) | R11: =IFERROR(MATCH(SMALL(Calc!$BK$2:$BK$2001,2),Calc!$BK$2:$BK$2001,0),"")
