Workbook
Name PayCat: Payments!$I$6:$I$1205
Name PayAct: Payments!$Q$6:$Q$1205

Sheet Instructions
B2: ULTIMATE BUDGET PLANNER
C3: Annual · Monthly · Paycheck / any period — dark edition
C5: SETUP
C6: Enter your budget start date, opening balance, accounts, variable-expense budgets and every recurring income, bill, debt payment, subscription and savings transfer ONCE (sample data included — overwrite or delete it). Yellow cells are inputs everywhere.
C8: PAYMENTS
C9: Every recurring item auto-repeats here for 12 months, sorted by date and coloured by category. Mark ✓ paid / ✗ skipped (or leave 'Auto-mark paid' = Yes on Setup). Enter one-off changes in the VARIATION columns (new date, amount or account). Use the filter arrows to sort / filter.
C11: MANUAL LOG
C12: Log variable spending, irregular income, extra bills and transfers between accounts. Tip: sub-categories must match the names in Setup to land in the right table.
C14: ACCOUNTS
C15: Live balance of each account and your net worth.
C17: DASHBOARD
C18: Switch between Weekly / Bi-weekly / 4-weekly (paycheck) / Monthly / Quarterly / 6-month / Annual / Custom and pick a start date — the whole dashboard recalculates for that period.
C20: JAN – DEC
... C36: Built for Microsoft Excel 365 / 2021+. Don't type over white/black formula cells. If you edit recurring items after marking payments, re-check the ✓ marks (rows re-sort by date).

Sheet Setup
B2: BUDGET SETUP
B3: Yellow cells are inputs. Fill this sheet once — Payments, Calendar, every monthly tab and the dashboards update automatically.
C4: GENERAL | F4: ACCOUNTS | I4: VARIABLE EXPENSES
C5: Budget start date | D5: 46023 | F5: Account | G5: Opening bal. | I5: Category | J5: Monthly budget
C6: Opening balance | D6: 2500 | F6: Checking 1 | G6: 1500 | I6: Groceries | J6: 600
C7: Auto-mark paid | D7: Yes | F7: Checking 2 | G7: 1000 | I7: Eating Out | J7: 400
F8: Savings 1 | G8: 3000 | I8: Shopping | J8: 300
C9: Year end | D9: =EDATE(D5,12)-1 | F9: Savings 2 | G9: 500 | I9: Entertainment | J9: 150
C10: Auto-mark paid = Yes counts a scheduled item as paid once its date has passed (mark ✗ in Payments to skip one). | F10: Credit Card 1 | G10: -450 | I10: Transportation | J10: 250
C11: Opening balance = cash available at the start of month 1. | F11: Credit Card 2 | G11: -800 | I11: School | J11: 200
F12: Credit Card 3 | G12: -300 | I12: Pets | J12: 80
F13: Car Loan 1 | G13: -8000 | I13: Hair/Beauty | J13: 60
F14: Capital One | G14: -2400 | I14: Gifts | J14: 100
I15: Other | J15: 100
B23: RECURRING TRANSACTIONS — set up once, auto-repeats into Payments, Calendar & all tabs
B24: # | C24: Category | D24: Sub-category | E24: Amount | F24: Frequency | G24: Start date | H24: End date (opt.) | I24: From account | J24: To account | K24: Notes | L24: key | M24: days | N24: mths | O24: n0 | P24: end
B25: 1 | C25: Income | D25: Sam's Salary | E25: 1600 | F25: Bi-weekly | G25: 46024 | I25: N/A | J25: Checking 1 | L25: =IF(C25="","",C25&"|"&COUNTIF($C$25:C25,C25)) | M25: =IFERROR(VLOOKUP(F25,Lists!$C$2:$E$10,2,0),0) | N25: =IFERROR(VLOOKUP(F25,Lists!$C$2:$E$10,3,0),0) | O25: =IF(OR(G25="",F25="",F25="Once"),0,IF(M25>0,MAX(0,ROUNDUP(($D$5-G25)/M25,0)),IF(N25=0,0,MAX(0,ROUNDUP(((YEAR($D$5)-YEAR(G25))*12+MONTH($D$5)-MONTH(G25))/N25,0))+IF(EDATE(G25,MAX(0,ROUNDUP(((YEAR($D$5)-YEAR(G25))*12+MONTH($D$5)-MONTH(G25))/N25,0))*N25)<$D$5,1,0)))) | P25: =IF(H25="",$D$9,MIN(H25,$D$9))
B26: 2 | C26: Income | D26: Lisa's Salary | E26: 3200 | F26: Monthly | G26: 46036 | I26: N/A | J26: Checking 2 | L26: =IF(C26="","",C26&"|"&COUNTIF($C$25:C26,C26)) | M26: =IFERROR(VLOOKUP(F26,Lists!$C$2:$E$10,2,0),0) | N26: =IFERROR(VLOOKUP(F26,Lists!$C$2:$E$10,3,0),0) | O26: =IF(OR(G26="",F26="",F26="Once"),0,IF(M26>0,MAX(0,ROUNDUP(($D$5-G26)/M26,0)),IF(N26=0,0,MAX(0,ROUNDUP(((YEAR($D$5)-YEAR(G26))*12+MONTH($D$5)-MONTH(G26))/N26,0))+IF(EDATE(G26,MAX(0,ROUNDUP(((YEAR($D$5)-YEAR(G26))*12+MONTH($D$5)-MONTH(G26))/N26,0))*N26)<$D$5,1,0)))) | P26: =IF(H26="",$D$9,MIN(H26,$D$9))
B27: 3 | C27: Income | D27: Side Hustle | E27: 450 | F27: Monthly | G27: 46028 | I27: N/A | J27: Checking 1 | L27: =IF(C27="","",C27&"|"&COUNTIF($C$25:C27,C27)) | M27: =IFERROR(VLOOKUP(F27,Lists!$C$2:$E$10,2,0),0) | N27: =IFERROR(VLOOKUP(F27,Lists!$C$2:$E$10,3,0),0) | O27: =IF(OR(G27="",F27="",F27="Once"),0,IF(M27>0,MAX(0,ROUNDUP(($D$5-G27)/M27,0)),IF(N27=0,0,MAX(0,ROUNDUP(((YEAR($D$5)-YEAR(G27))*12+MONTH($D$5)-MONTH(G27))/N27,0))+IF(EDATE(G27,MAX(0,ROUNDUP(((YEAR($D$5)-YEAR(G27))*12+MONTH($D$5)-MONTH(G27))/N27,0))*N27)<$D$5,1,0)))) | P27: =IF(H27="",$D$9,MIN(H27,$D$9))
B28: 4 | C28: Bills | D28: Rent | E28: 1600 | F28: Monthly | G28: 46023 | I28: Checking 1 | J28: N/A | L28: =IF(C28="","",C28&"|"&COUNTIF($C$25:C28,C28)) | M28: =IFERROR(VLOOKUP(F28,Lists!$C$2:$E$10,2,0),0) | N28: =IFERROR(VLOOKUP(F28,Lists!$C$2:$E$10,3,0),0) | O28: =IF(OR(G28="",F28="",F28="Once"),0,IF(M28>0,MAX(0,ROUNDUP(($D$5-G28)/M28,0)),IF(N28=0,0,MAX(0,ROUNDUP(((YEAR($D$5)-YEAR(G28))*12+MONTH($D$5)-MONTH(G28))/N28,0))+IF(EDATE(G28,MAX(0,ROUNDUP(((YEAR($D$5)-YEAR(G28))*12+MONTH($D$5)-MONTH(G28))/N28,0))*N28)<$D$5,1,0)))) | P28: =IF(H28="",$D$9,MIN(H28,$D$9))
B29: 5 | C29: Bills | D29: Electricity Bill | E29: 140 | F29: Monthly | G29: 46024 | I29: Credit Card 1 | J29: N/A | L29: =IF(C29="","",C29&"|"&COUNTIF($C$25:C29,C29)) | M29: =IFERROR(VLOOKUP(F29,Lists!$C$2:$E$10,2,0),0) | N29: =IFERROR(VLOOKUP(F29,Lists!$C$2:$E$10,3,0),0) | O29: =IF(OR(G29="",F29="",F29="Once"),0,IF(M29>0,MAX(0,ROUNDUP(($D$5-G29)/M29,0)),IF(N29=0,0,MAX(0,ROUNDUP(((YEAR($D$5)-YEAR(G29))*12+MONTH($D$5)-MONTH(G29))/N29,0))+IF(EDATE(G29,MAX(0,ROUNDUP(((YEAR($D$5)-YEAR(G29))*12+MONTH($D$5)-MONTH(G29))/N29,0))*N29)<$D$5,1,0)))) | P29: =IF(H29="",$D$9,MIN(H29,$D$9))
B30: 6 | C30: Bills | D30: Gas Bill | E30: 50 | F30: Monthly | G30: 46024 | I30: Credit Card 1 | J30: N/A | L30: =IF(C30="","",C30&"|"&COUNTIF($C$25:C30,C30)) | M30: =IFERROR(VLOOKUP(F30,Lists!$C$2:$E$10,2,0),0) | N30: =IFERROR(VLOOKUP(F30,Lists!$C$2:$E$10,3,0),0) | O30: =IF(OR(G30="",F30="",F30="Once"),0,IF(M30>0,MAX(0,ROUNDUP(($D$5-G30)/M30,0)),IF(N30=0,0,MAX(0,ROUNDUP(((YEAR($D$5)-YEAR(G30))*12+MONTH($D$5)-MONTH(G30))/N30,0))+IF(EDATE(G30,MAX(0,ROUNDUP(((YEAR($D$5)-YEAR(G30))*12+MONTH($D$5)-MONTH(G30))/N30,0))*N30)<$D$5,1,0)))) | P30: =IF(H30="",$D$9,MIN(H30,$D$9))
B31: 7 | C31: Bills | D31: Water Bill | E31: 60 | F31: Monthly | G31: 46025 | I31: Credit Card 3 | J31: N/A | L31: =IF(C31="","",C31&"|"&COUNTIF($C$25:C31,C31)) | M31: =IFERROR(VLOOKUP(F31,Lists!$C$2:$E$10,2,0),0) | N31: =IFERROR(VLOOKUP(F31,Lists!$C$2:$E$10,3,0),0) | O31: =IF(OR(G31="",F31="",F31="Once"),0,IF(M31>0,MAX(0,ROUNDUP(($D$5-G31)/M31,0)),IF(N31=0,0,MAX(0,ROUNDUP(((YEAR($D$5)-YEAR(G31))*12+MONTH($D$5)-MONTH(G31))/N31,0))+IF(EDATE(G31,MAX(0,ROUNDUP(((YEAR($D$5)-YEAR(G31))*12+MONTH($D$5)-MONTH(G31))/N31,0))*N31)<$D$5,1,0)))) | P31: =IF(H31="",$D$9,MIN(H31,$D$9))
B32: 8 | C32: Bills | D32: Internet | E32: 75 | F32: Monthly | G32: 46031 | I32: Credit Card 2 | J32: N/A | L32: =IF(C32="","",C32&"|"&COUNTIF($C$25:C32,C32)) | M32: =IFERROR(VLOOKUP(F32,Lists!$C$2:$E$10,2,0),0) | N32: =IFERROR(VLOOKUP(F32,Lists!$C$2:$E$10,3,0),0) | O32: =IF(OR(G32="",F32="",F32="Once"),0,IF(M32>0,MAX(0,ROUNDUP(($D$5-G32)/M32,0)),IF(N32=0,0,MAX(0,ROUNDUP(((YEAR($D$5)-YEAR(G32))*12+MONTH($D$5)-MONTH(G32))/N32,0))+IF(EDATE(G32,MAX(0,ROUNDUP(((YEAR($D$5)-YEAR(G32))*12+MONTH($D$5)-MONTH(G32))/N32,0))*N32)<$D$5,1,0)))) | P32: =IF(H32="",$D$9,MIN(H32,$D$9))
B33: 9 | C33: Bills | D33: Phone Bill | E33: 75 | F33: Monthly | G33: 46031 | I33: Credit Card 1 | J33: N/A | L33: =IF(C33="","",C33&"|"&COUNTIF($C$25:C33,C33)) | M33: =IFERROR(VLOOKUP(F33,Lists!$C$2:$E$10,2,0),0) | N33: =IFERROR(VLOOKUP(F33,Lists!$C$2:$E$10,3,0),0) | O33: =IF(OR(G33="",F33="",F33="Once"),0,IF(M33>0,MAX(0,ROUNDUP(($D$5-G33)/M33,0)),IF(N33=0,0,MAX(0,ROUNDUP(((YEAR($D$5)-YEAR(G33))*12+MONTH($D$5)-MONTH(G33))/N33,0))+IF(EDATE(G33,MAX(0,ROUNDUP(((YEAR($D$5)-YEAR(G33))*12+MONTH($D$5)-MONTH(G33))/N33,0))*N33)<$D$5,1,0)))) | P33: =IF(H33="",$D$9,MIN(H33,$D$9))
B34: 10 | C34: Bills | D34: Health Insurance | E34: 150 | F34: Monthly | G34: 46024 | I34: Credit Card 2 | J34: N/A | L34: =IF(C34="","",C34&"|"&COUNTIF($C$25:C34,C34)) | M34: =IFERROR(VLOOKUP(F34,Lists!$C$2:$E$10,2,0),0) | N34: =IFERROR(VLOOKUP(F34,Lists!$C$2:$E$10,3,0),0) | O34: =IF(OR(G34="",F34="",F34="Once"),0,IF(M34>0,MAX(0,ROUNDUP(($D$5-G34)/M34,0)),IF(N34=0,0,MAX(0,ROUNDUP(((YEAR($D$5)-YEAR(G34))*12+MONTH($D$5)-MONTH(G34))/N34,0))+IF(EDATE(G34,MAX(0,ROUNDUP(((YEAR($D$5)-YEAR(G34))*12+MONTH($D$5)-MONTH(G34))/N34,0))*N34)<$D$5,1,0)))) | P34: =IF(H34="",$D$9,MIN(H34,$D$9))
B35: 11 | C35: Bills | D35: Car Insurance | E35: 60 | F35: Monthly | G35: 46028 | I35: Credit Card 2 | J35: N/A | L35: =IF(C35="","",C35&"|"&COUNTIF($C$25:C35,C35)) | M35: =IFERROR(VLOOKUP(F35,Lists!$C$2:$E$10,2,0),0) | N35: =IFERROR(VLOOKUP(F35,Lists!$C$2:$E$10,3,0),0) | O35: =IF(OR(G35="",F35="",F35="Once"),0,IF(M35>0,MAX(0,ROUNDUP(($D$5-G35)/M35,0)),IF(N35=0,0,MAX(0,ROUNDUP(((YEAR($D$5)-YEAR(G35))*12+MONTH($D$5)-MONTH(G35))/N35,0))+IF(EDATE(G35,MAX(0,ROUNDUP(((YEAR($D$5)-YEAR(G35))*12+MONTH($D$5)-MONTH(G35))/N35,0))*N35)<$D$5,1,0)))) | P35: =IF(H35="",$D$9,MIN(H35,$D$9))
B36: 12 | C36: Bills | D36: Home Insurance | E36: 55 | F36: Monthly | G36: 46033 | I36: Credit Card 2 | J36: N/A | L36: =IF(C36="","",C36&"|"&COUNTIF($C$25:C36,C36)) | M36: =IFERROR(VLOOKUP(F36,Lists!$C$2:$E$10,2,0),0) | N36: =IFERROR(VLOOKUP(F36,Lists!$C$2:$E$10,3,0),0) | O36: =IF(OR(G36="",F36="",F36="Once"),0,IF(M36>0,MAX(0,ROUNDUP(($D$5-G36)/M36,0)),IF(N36=0,0,MAX(0,ROUNDUP(((YEAR($D$5)-YEAR(G36))*12+MONTH($D$5)-MONTH(G36))/N36,0))+IF(EDATE(G36,MAX(0,ROUNDUP(((YEAR($D$5)-YEAR(G36))*12+MONTH($D$5)-MONTH(G36))/N36,0))*N36)<$D$5,1,0)))) | P36: =IF(H36="",$D$9,MIN(H36,$D$9))
... B53: 29 | C53: Savings | D53: Emergency Fund | E53: 300 | F53: Monthly | G53: 46037 | I53: Checking 2 | J53: Savings 1 | L53: =IF(C53="","",C53&"|"&COUNTIF($C$25:C53,C53)) | M53: =IFERROR(VLOOKUP(F53,Lists!$C$2:$E$10,2,0),0) | N53: =IFERROR(VLOOKUP(F53,Lists!$C$2:$E$10,3,0),0) | O53: =IF(OR(G53="",F53="",F53="Once"),0,IF(M53>0,MAX(0,ROUNDUP(($D$5-G53)/M53,0)),IF(N53=0,0,MAX(0,ROUNDUP(((YEAR($D$5)-YEAR(G53))*12+MONTH($D$5)-MONTH(G53))/N53,0))+IF(EDATE(G53,MAX(0,ROUNDUP(((YEAR($D$5)-YEAR(G53))*12+MONTH($D$5)-MONTH(G53))/N53,0))*N53)<$D$5,1,0)))) | P53: =IF(H53="",$D$9,MIN(H53,$D$9))
B54: 30 | C54: Savings | D54: New Laptop | E54: 150 | F54: Monthly | G54: 46037 | H54: 46326 | I54: Checking 2 | J54: Savings 2 | L54: =IF(C54="","",C54&"|"&COUNTIF($C$25:C54,C54)) | M54: =IFERROR(VLOOKUP(F54,Lists!$C$2:$E$10,2,0),0) | N54: =IFERROR(VLOOKUP(F54,Lists!$C$2:$E$10,3,0),0) | O54: =IF(OR(G54="",F54="",F54="Once"),0,IF(M54>0,MAX(0,ROUNDUP(($D$5-G54)/M54,0)),IF(N54=0,0,MAX(0,ROUNDUP(((YEAR($D$5)-YEAR(G54))*12+MONTH($D$5)-MONTH(G54))/N54,0))+IF(EDATE(G54,MAX(0,ROUNDUP(((YEAR($D$5)-YEAR(G54))*12+MONTH($D$5)-MONTH(G54))/N54,0))*N54)<$D$5,1,0)))) | P54: =IF(H54="",$D$9,MIN(H54,$D$9))
B55: 31 | C55: Savings | D55: Home Repairs | E55: 150 | F55: Monthly | G55: 46042 | I55: Checking 2 | J55: Savings 1 | L55: =IF(C55="","",C55&"|"&COUNTIF($C$25:C55,C55)) | M55: =IFERROR(VLOOKUP(F55,Lists!$C$2:$E$10,2,0),0) | N55: =IFERROR(VLOOKUP(F55,Lists!$C$2:$E$10,3,0),0) | O55: =IF(OR(G55="",F55="",F55="Once"),0,IF(M55>0,MAX(0,ROUNDUP(($D$5-G55)/M55,0)),IF(N55=0,0,MAX(0,ROUNDUP(((YEAR($D$5)-YEAR(G55))*12+MONTH($D$5)-MONTH(G55))/N55,0))+IF(EDATE(G55,MAX(0,ROUNDUP(((YEAR($D$5)-YEAR(G55))*12+MONTH($D$5)-MONTH(G55))/N55,0))*N55)<$D$5,1,0)))) | P55: =IF(H55="",$D$9,MIN(H55,$D$9))
B56: 32 | C56: Savings | D56: Wedding | E56: 200 | F56: Monthly | G56: 46028 | I56: Checking 1 | J56: Savings 2 | L56: =IF(C56="","",C56&"|"&COUNTIF($C$25:C56,C56)) | M56: =IFERROR(VLOOKUP(F56,Lists!$C$2:$E$10,2,0),0) | N56: =IFERROR(VLOOKUP(F56,Lists!$C$2:$E$10,3,0),0) | O56: =IF(OR(G56="",F56="",F56="Once"),0,IF(M56>0,MAX(0,ROUNDUP(($D$5-G56)/M56,0)),IF(N56=0,0,MAX(0,ROUNDUP(((YEAR($D$5)-YEAR(G56))*12+MONTH($D$5)-MONTH(G56))/N56,0))+IF(EDATE(G56,MAX(0,ROUNDUP(((YEAR($D$5)-YEAR(G56))*12+MONTH($D$5)-MONTH(G56))/N56,0))*N56)<$D$5,1,0)))) | P56: =IF(H56="",$D$9,MIN(H56,$D$9))
B57: 33 | L57: =IF(C57="","",C57&"|"&COUNTIF($C$25:C57,C57)) | M57: =IFERROR(VLOOKUP(F57,Lists!$C$2:$E$10,2,0),0) | N57: =IFERROR(VLOOKUP(F57,Lists!$C$2:$E$10,3,0),0) | O57: =IF(OR(G57="",F57="",F57="Once"),0,IF(M57>0,MAX(0,ROUNDUP(($D$5-G57)/M57,0)),IF(N57=0,0,MAX(0,ROUNDUP(((YEAR($D$5)-YEAR(G57))*12+MONTH($D$5)-MONTH(G57))/N57,0))+IF(EDATE(G57,MAX(0,ROUNDUP(((YEAR($D$5)-YEAR(G57))*12+MONTH($D$5)-MONTH(G57))/N57,0))*N57)<$D$5,1,0)))) | P57: =IF(H57="",$D$9,MIN(H57,$D$9))
B58: 34 | L58: =IF(C58="","",C58&"|"&COUNTIF($C$25:C58,C58)) | M58: =IFERROR(VLOOKUP(F58,Lists!$C$2:$E$10,2,0),0) | N58: =IFERROR(VLOOKUP(F58,Lists!$C$2:$E$10,3,0),0) | O58: =IF(OR(G58="",F58="",F58="Once"),0,IF(M58>0,MAX(0,ROUNDUP(($D$5-G58)/M58,0)),IF(N58=0,0,MAX(0,ROUNDUP(((YEAR($D$5)-YEAR(G58))*12+MONTH($D$5)-MONTH(G58))/N58,0))+IF(EDATE(G58,MAX(0,ROUNDUP(((YEAR($D$5)-YEAR(G58))*12+MONTH($D$5)-MONTH(G58))/N58,0))*N58)<$D$5,1,0)))) | P58: =IF(H58="",$D$9,MIN(H58,$D$9))
B59: 35 | L59: =IF(C59="","",C59&"|"&COUNTIF($C$25:C59,C59)) | M59: =IFERROR(VLOOKUP(F59,Lists!$C$2:$E$10,2,0),0) | N59: =IFERROR(VLOOKUP(F59,Lists!$C$2:$E$10,3,0),0) | O59: =IF(OR(G59="",F59="",F59="Once"),0,IF(M59>0,MAX(0,ROUNDUP(($D$5-G59)/M59,0)),IF(N59=0,0,MAX(0,ROUNDUP(((YEAR($D$5)-YEAR(G59))*12+MONTH($D$5)-MONTH(G59))/N59,0))+IF(EDATE(G59,MAX(0,ROUNDUP(((YEAR($D$5)-YEAR(G59))*12+MONTH($D$5)-MONTH(G59))/N59,0))*N59)<$D$5,1,0)))) | P59: =IF(H59="",$D$9,MIN(H59,$D$9))
B60: 36 | L60: =IF(C60="","",C60&"|"&COUNTIF($C$25:C60,C60)) | M60: =IFERROR(VLOOKUP(F60,Lists!$C$2:$E$10,2,0),0) | N60: =IFERROR(VLOOKUP(F60,Lists!$C$2:$E$10,3,0),0) | O60: =IF(OR(G60="",F60="",F60="Once"),0,IF(M60>0,MAX(0,ROUNDUP(($D$5-G60)/M60,0)),IF(N60=0,0,MAX(0,ROUNDUP(((YEAR($D$5)-YEAR(G60))*12+MONTH($D$5)-MONTH(G60))/N60,0))+IF(EDATE(G60,MAX(0,ROUNDUP(((YEAR($D$5)-YEAR(G60))*12+MONTH($D$5)-MONTH(G60))/N60,0))*N60)<$D$5,1,0)))) | P60: =IF(H60="",$D$9,MIN(H60,$D$9))
B61: 37 | L61: =IF(C61="","",C61&"|"&COUNTIF($C$25:C61,C61)) | M61: =IFERROR(VLOOKUP(F61,Lists!$C$2:$E$10,2,0),0) | N61: =IFERROR(VLOOKUP(F61,Lists!$C$2:$E$10,3,0),0) | O61: =IF(OR(G61="",F61="",F61="Once"),0,IF(M61>0,MAX(0,ROUNDUP(($D$5-G61)/M61,0)),IF(N61=0,0,MAX(0,ROUNDUP(((YEAR($D$5)-YEAR(G61))*12+MONTH($D$5)-MONTH(G61))/N61,0))+IF(EDATE(G61,MAX(0,ROUNDUP(((YEAR($D$5)-YEAR(G61))*12+MONTH($D$5)-MONTH(G61))/N61,0))*N61)<$D$5,1,0)))) | P61: =IF(H61="",$D$9,MIN(H61,$D$9))
B62: 38 | L62: =IF(C62="","",C62&"|"&COUNTIF($C$25:C62,C62)) | M62: =IFERROR(VLOOKUP(F62,Lists!$C$2:$E$10,2,0),0) | N62: =IFERROR(VLOOKUP(F62,Lists!$C$2:$E$10,3,0),0) | O62: =IF(OR(G62="",F62="",F62="Once"),0,IF(M62>0,MAX(0,ROUNDUP(($D$5-G62)/M62,0)),IF(N62=0,0,MAX(0,ROUNDUP(((YEAR($D$5)-YEAR(G62))*12+MONTH($D$5)-MONTH(G62))/N62,0))+IF(EDATE(G62,MAX(0,ROUNDUP(((YEAR($D$5)-YEAR(G62))*12+MONTH($D$5)-MONTH(G62))/N62,0))*N62)<$D$5,1,0)))) | P62: =IF(H62="",$D$9,MIN(H62,$D$9))
B63: 39 | L63: =IF(C63="","",C63&"|"&COUNTIF($C$25:C63,C63)) | M63: =IFERROR(VLOOKUP(F63,Lists!$C$2:$E$10,2,0),0) | N63: =IFERROR(VLOOKUP(F63,Lists!$C$2:$E$10,3,0),0) | O63: =IF(OR(G63="",F63="",F63="Once"),0,IF(M63>0,MAX(0,ROUNDUP(($D$5-G63)/M63,0)),IF(N63=0,0,MAX(0,ROUNDUP(((YEAR($D$5)-YEAR(G63))*12+MONTH($D$5)-MONTH(G63))/N63,0))+IF(EDATE(G63,MAX(0,ROUNDUP(((YEAR($D$5)-YEAR(G63))*12+MONTH($D$5)-MONTH(G63))/N63,0))*N63)<$D$5,1,0)))) | P63: =IF(H63="",$D$9,MIN(H63,$D$9))
B64: 40 | L64: =IF(C64="","",C64&"|"&COUNTIF($C$25:C64,C64)) | M64: =IFERROR(VLOOKUP(F64,Lists!$C$2:$E$10,2,0),0) | N64: =IFERROR(VLOOKUP(F64,Lists!$C$2:$E$10,3,0),0) | O64: =IF(OR(G64="",F64="",F64="Once"),0,IF(M64>0,MAX(0,ROUNDUP(($D$5-G64)/M64,0)),IF(N64=0,0,MAX(0,ROUNDUP(((YEAR($D$5)-YEAR(G64))*12+MONTH($D$5)-MONTH(G64))/N64,0))+IF(EDATE(G64,MAX(0,ROUNDUP(((YEAR($D$5)-YEAR(G64))*12+MONTH($D$5)-MONTH(G64))/N64,0))*N64)<$D$5,1,0)))) | P64: =IF(H64="",$D$9,MIN(H64,$D$9))
B65: 41 | L65: =IF(C65="","",C65&"|"&COUNTIF($C$25:C65,C65)) | M65: =IFERROR(VLOOKUP(F65,Lists!$C$2:$E$10,2,0),0) | N65: =IFERROR(VLOOKUP(F65,Lists!$C$2:$E$10,3,0),0) | O65: =IF(OR(G65="",F65="",F65="Once"),0,IF(M65>0,MAX(0,ROUNDUP(($D$5-G65)/M65,0)),IF(N65=0,0,MAX(0,ROUNDUP(((YEAR($D$5)-YEAR(G65))*12+MONTH($D$5)-MONTH(G65))/N65,0))+IF(EDATE(G65,MAX(0,ROUNDUP(((YEAR($D$5)-YEAR(G65))*12+MONTH($D$5)-MONTH(G65))/N65,0))*N65)<$D$5,1,0)))) | P65: =IF(H65="",$D$9,MIN(H65,$D$9))
B66: 42 | L66: =IF(C66="","",C66&"|"&COUNTIF($C$25:C66,C66)) | M66: =IFERROR(VLOOKUP(F66,Lists!$C$2:$E$10,2,0),0) | N66: =IFERROR(VLOOKUP(F66,Lists!$C$2:$E$10,3,0),0) | O66: =IF(OR(G66="",F66="",F66="Once"),0,IF(M66>0,MAX(0,ROUNDUP(($D$5-G66)/M66,0)),IF(N66=0,0,MAX(0,ROUNDUP(((YEAR($D$5)-YEAR(G66))*12+MONTH($D$5)-MONTH(G66))/N66,0))+IF(EDATE(G66,MAX(0,ROUNDUP(((YEAR($D$5)-YEAR(G66))*12+MONTH($D$5)-MONTH(G66))/N66,0))*N66)<$D$5,1,0)))) | P66: =IF(H66="",$D$9,MIN(H66,$D$9))
B67: 43 | L67: =IF(C67="","",C67&"|"&COUNTIF($C$25:C67,C67)) | M67: =IFERROR(VLOOKUP(F67,Lists!$C$2:$E$10,2,0),0) | N67: =IFERROR(VLOOKUP(F67,Lists!$C$2:$E$10,3,0),0) | O67: =IF(OR(G67="",F67="",F67="Once"),0,IF(M67>0,MAX(0,ROUNDUP(($D$5-G67)/M67,0)),IF(N67=0,0,MAX(0,ROUNDUP(((YEAR($D$5)-YEAR(G67))*12+MONTH($D$5)-MONTH(G67))/N67,0))+IF(EDATE(G67,MAX(0,ROUNDUP(((YEAR($D$5)-YEAR(G67))*12+MONTH($D$5)-MONTH(G67))/N67,0))*N67)<$D$5,1,0)))) | P67: =IF(H67="",$D$9,MIN(H67,$D$9))
B68: 44 | L68: =IF(C68="","",C68&"|"&COUNTIF($C$25:C68,C68)) | M68: =IFERROR(VLOOKUP(F68,Lists!$C$2:$E$10,2,0),0) | N68: =IFERROR(VLOOKUP(F68,Lists!$C$2:$E$10,3,0),0) | O68: =IF(OR(G68="",F68="",F68="Once"),0,IF(M68>0,MAX(0,ROUNDUP(($D$5-G68)/M68,0)),IF(N68=0,0,MAX(0,ROUNDUP(((YEAR($D$5)-YEAR(G68))*12+MONTH($D$5)-MONTH(G68))/N68,0))+IF(EDATE(G68,MAX(0,ROUNDUP(((YEAR($D$5)-YEAR(G68))*12+MONTH($D$5)-MONTH(G68))/N68,0))*N68)<$D$5,1,0)))) | P68: =IF(H68="",$D$9,MIN(H68,$D$9))
... B84: 60 | L84: =IF(C84="","",C84&"|"&COUNTIF($C$25:C84,C84)) | M84: =IFERROR(VLOOKUP(F84,Lists!$C$2:$E$10,2,0),0) | N84: =IFERROR(VLOOKUP(F84,Lists!$C$2:$E$10,3,0),0) | O84: =IF(OR(G84="",F84="",F84="Once"),0,IF(M84>0,MAX(0,ROUNDUP(($D$5-G84)/M84,0)),IF(N84=0,0,MAX(0,ROUNDUP(((YEAR($D$5)-YEAR(G84))*12+MONTH($D$5)-MONTH(G84))/N84,0))+IF(EDATE(G84,MAX(0,ROUNDUP(((YEAR($D$5)-YEAR(G84))*12+MONTH($D$5)-MONTH(G84))/N84,0))*N84)<$D$5,1,0)))) | P84: =IF(H84="",$D$9,MIN(H84,$D$9))

Sheet Payments
C2: PAYMENT SCHEDULE
C3: Auto-generated from Setup. Mark ✓ paid / ✗ skipped, use the filter arrows to sort & filter. Row colours follow the category.
C4: PAYMENT SCHEDULE | K4: VARIATION — enter any change for one payment here | P4: RESULT
A5: key | B5: idx | C5: PAID | D5: DATE | E5: SUB-CATEGORY | F5: AMOUNT | G5: FROM ACCOUNT | H5: TO ACCOUNT | I5: CATEGORY | K5: NEW DATE | L5: NEW AMOUNT | M5: NEW FROM | N5: NEW TO | P5: EFF. DATE | Q5: ACTUAL PAID | R5: EFF. FROM | S5: EFF. TO | T5: STATUS | U5: SCHEDULED
A6: =IFERROR(SMALL(Calc!$B$2:$BB$61,1),"") | B6: =IF(A6="","",ROUND(MOD(A6,1)*1000,0)) | D6: =IF(A6="","",INT(A6)) | E6: =IF(B6="","",INDEX(Setup!$D$25:$D$84,B6)) | F6: =IF(B6="","",INDEX(Setup!$E$25:$E$84,B6)) | G6: =IF(B6="","",INDEX(Setup!$I$25:$I$84,B6)&"") | H6: =IF(B6="","",INDEX(Setup!$J$25:$J$84,B6)&"") | I6: =IF(B6="","",INDEX(Setup!$C$25:$C$84,B6)) | P6: =IF(A6="","",IF(K6<>"",K6,D6)) | Q6: =IF(A6="",0,IF(C6="✗",0,IF(OR(C6="✓",AND(Setup!$D$7="Yes",P6<=TODAY())),IF(L6<>"",L6,F6),0))) | R6: =IF(A6="","",IF(M6<>"",M6,G6)) | S6: =IF(A6="","",IF(N6<>"",N6,H6)) | T6: =IF(A6="","",IF(C6="✗","Skipped",IF(Q6>0,"Paid","Upcoming"))) | U6: =IF(A6="",0,IF(C6="✗",0,IF(L6<>"",L6,F6)))
A7: =IFERROR(SMALL(Calc!$B$2:$BB$61,2),"") | B7: =IF(A7="","",ROUND(MOD(A7,1)*1000,0)) | D7: =IF(A7="","",INT(A7)) | E7: =IF(B7="","",INDEX(Setup!$D$25:$D$84,B7)) | F7: =IF(B7="","",INDEX(Setup!$E$25:$E$84,B7)) | G7: =IF(B7="","",INDEX(Setup!$I$25:$I$84,B7)&"") | H7: =IF(B7="","",INDEX(Setup!$J$25:$J$84,B7)&"") | I7: =IF(B7="","",INDEX(Setup!$C$25:$C$84,B7)) | P7: =IF(A7="","",IF(K7<>"",K7,D7)) | Q7: =IF(A7="",0,IF(C7="✗",0,IF(OR(C7="✓",AND(Setup!$D$7="Yes",P7<=TODAY())),IF(L7<>"",L7,F7),0))) | R7: =IF(A7="","",IF(M7<>"",M7,G7)) | S7: =IF(A7="","",IF(N7<>"",N7,H7)) | T7: =IF(A7="","",IF(C7="✗","Skipped",IF(Q7>0,"Paid","Upcoming"))) | U7: =IF(A7="",0,IF(C7="✗",0,IF(L7<>"",L7,F7)))
A8: =IFERROR(SMALL(Calc!$B$2:$BB$61,3),"") | B8: =IF(A8="","",ROUND(MOD(A8,1)*1000,0)) | D8: =IF(A8="","",INT(A8)) | E8: =IF(B8="","",INDEX(Setup!$D$25:$D$84,B8)) | F8: =IF(B8="","",INDEX(Setup!$E$25:$E$84,B8)) | G8: =IF(B8="","",INDEX(Setup!$I$25:$I$84,B8)&"") | H8: =IF(B8="","",INDEX(Setup!$J$25:$J$84,B8)&"") | I8: =IF(B8="","",INDEX(Setup!$C$25:$C$84,B8)) | P8: =IF(A8="","",IF(K8<>"",K8,D8)) | Q8: =IF(A8="",0,IF(C8="✗",0,IF(OR(C8="✓",AND(Setup!$D$7="Yes",P8<=TODAY())),IF(L8<>"",L8,F8),0))) | R8: =IF(A8="","",IF(M8<>"",M8,G8)) | S8: =IF(A8="","",IF(N8<>"",N8,H8)) | T8: =IF(A8="","",IF(C8="✗","Skipped",IF(Q8>0,"Paid","Upcoming"))) | U8: =IF(A8="",0,IF(C8="✗",0,IF(L8<>"",L8,F8)))
A9: =IFERROR(SMALL(Calc!$B$2:$BB$61,4),"") | B9: =IF(A9="","",ROUND(MOD(A9,1)*1000,0)) | D9: =IF(A9="","",INT(A9)) | E9: =IF(B9="","",INDEX(Setup!$D$25:$D$84,B9)) | F9: =IF(B9="","",INDEX(Setup!$E$25:$E$84,B9)) | G9: =IF(B9="","",INDEX(Setup!$I$25:$I$84,B9)&"") | H9: =IF(B9="","",INDEX(Setup!$J$25:$J$84,B9)&"") | I9: =IF(B9="","",INDEX(Setup!$C$25:$C$84,B9)) | P9: =IF(A9="","",IF(K9<>"",K9,D9)) | Q9: =IF(A9="",0,IF(C9="✗",0,IF(OR(C9="✓",AND(Setup!$D$7="Yes",P9<=TODAY())),IF(L9<>"",L9,F9),0))) | R9: =IF(A9="","",IF(M9<>"",M9,G9)) | S9: =IF(A9="","",IF(N9<>"",N9,H9)) | T9: =IF(A9="","",IF(C9="✗","Skipped",IF(Q9>0,"Paid","Upcoming"))) | U9: =IF(A9="",0,IF(C9="✗",0,IF(L9<>"",L9,F9)))
A10: =IFERROR(SMALL(Calc!$B$2:$BB$61,5),"") | B10: =IF(A10="","",ROUND(MOD(A10,1)*1000,0)) | D10: =IF(A10="","",INT(A10)) | E10: =IF(B10="","",INDEX(Setup!$D$25:$D$84,B10)) | F10: =IF(B10="","",INDEX(Setup!$E$25:$E$84,B10)) | G10: =IF(B10="","",INDEX(Setup!$I$25:$I$84,B10)&"") | H10: =IF(B10="","",INDEX(Setup!$J$25:$J$84,B10)&"") | I10: =IF(B10="","",INDEX(Setup!$C$25:$C$84,B10)) | P10: =IF(A10="","",IF(K10<>"",K10,D10)) | Q10: =IF(A10="",0,IF(C10="✗",0,IF(OR(C10="✓",AND(Setup!$D$7="Yes",P10<=TODAY())),IF(L10<>"",L10,F10),0))) | R10: =IF(A10="","",IF(M10<>"",M10,G10)) | S10: =IF(A10="","",IF(N10<>"",N10,H10)) | T10: =IF(A10="","",IF(C10="✗","Skipped",IF(Q10>0,"Paid","Upcoming"))) | U10: =IF(A10="",0,IF(C10="✗",0,IF(L10<>"",L10,F10)))
A11: =IFERROR(SMALL(Calc!$B$2:$BB$61,6),"") | B11: =IF(A11="","",ROUND(MOD(A11,1)*1000,0)) | D11: =IF(A11="","",INT(A11)) | E11: =IF(B11="","",INDEX(Setup!$D$25:$D$84,B11)) | F11: =IF(B11="","",INDEX(Setup!$E$25:$E$84,B11)) | G11: =IF(B11="","",INDEX(Setup!$I$25:$I$84,B11)&"") | H11: =IF(B11="","",INDEX(Setup!$J$25:$J$84,B11)&"") | I11: =IF(B11="","",INDEX(Setup!$C$25:$C$84,B11)) | P11: =IF(A11="","",IF(K11<>"",K11,D11)) | Q11: =IF(A11="",0,IF(C11="✗",0,IF(OR(C11="✓",AND(Setup!$D$7="Yes",P11<=TODAY())),IF(L11<>"",L11,F11),0))) | R11: =IF(A11="","",IF(M11<>"",M11,G11)) | S11: =IF(A11="","",IF(N11<>"",N11,H11)) | T11: =IF(A11="","",IF(C11="✗","Skipped",IF(Q11>0,"Paid","Upcoming"))) | U11: =IF(A11="",0,IF(C11="✗",0,IF(L11<>"",L11,F11)))
A12: =IFERROR(SMALL(Calc!$B$2:$BB$61,7),"") | B12: =IF(A12="","",ROUND(MOD(A12,1)*1000,0)) | D12: =IF(A12="","",INT(A12)) | E12: =IF(B12="","",INDEX(Setup!$D$25:$D$84,B12)) | F12: =IF(B12="","",INDEX(Setup!$E$25:$E$84,B12)) | G12: =IF(B12="","",INDEX(Setup!$I$25:$I$84,B12)&"") | H12: =IF(B12="","",INDEX(Setup!$J$25:$J$84,B12)&"") | I12: =IF(B12="","",INDEX(Setup!$C$25:$C$84,B12)) | P12: =IF(A12="","",IF(K12<>"",K12,D12)) | Q12: =IF(A12="",0,IF(C12="✗",0,IF(OR(C12="✓",AND(Setup!$D$7="Yes",P12<=TODAY())),IF(L12<>"",L12,F12),0))) | R12: =IF(A12="","",IF(M12<>"",M12,G12)) | S12: =IF(A12="","",IF(N12<>"",N12,H12)) | T12: =IF(A12="","",IF(C12="✗","Skipped",IF(Q12>0,"Paid","Upcoming"))) | U12: =IF(A12="",0,IF(C12="✗",0,IF(L12<>"",L12,F12)))
A13: =IFERROR(SMALL(Calc!$B$2:$BB$61,8),"") | B13: =IF(A13="","",ROUND(MOD(A13,1)*1000,0)) | D13: =IF(A13="","",INT(A13)) | E13: =IF(B13="","",INDEX(Setup!$D$25:$D$84,B13)) | F13: =IF(B13="","",INDEX(Setup!$E$25:$E$84,B13)) | G13: =IF(B13="","",INDEX(Setup!$I$25:$I$84,B13)&"") | H13: =IF(B13="","",INDEX(Setup!$J$25:$J$84,B13)&"") | I13: =IF(B13="","",INDEX(Setup!$C$25:$C$84,B13)) | P13: =IF(A13="","",IF(K13<>"",K13,D13)) | Q13: =IF(A13="",0,IF(C13="✗",0,IF(OR(C13="✓",AND(Setup!$D$7="Yes",P13<=TODAY())),IF(L13<>"",L13,F13),0))) | R13: =IF(A13="","",IF(M13<>"",M13,G13)) | S13: =IF(A13="","",IF(N13<>"",N13,H13)) | T13: =IF(A13="","",IF(C13="✗","Skipped",IF(Q13>0,"Paid","Upcoming"))) | U13: =IF(A13="",0,IF(C13="✗",0,IF(L13<>"",L13,F13)))
A14: =IFERROR(SMALL(Calc!$B$2:$BB$61,9),"") | B14: =IF(A14="","",ROUND(MOD(A14,1)*1000,0)) | D14: =IF(A14="","",INT(A14)) | E14: =IF(B14="","",INDEX(Setup!$D$25:$D$84,B14)) | F14: =IF(B14="","",INDEX(Setup!$E$25:$E$84,B14)) | G14: =IF(B14="","",INDEX(Setup!$I$25:$I$84,B14)&"") | H14: =IF(B14="","",INDEX(Setup!$J$25:$J$84,B14)&"") | I14: =IF(B14="","",INDEX(Setup!$C$25:$C$84,B14)) | P14: =IF(A14="","",IF(K14<>"",K14,D14)) | Q14: =IF(A14="",0,IF(C14="✗",0,IF(OR(C14="✓",AND(Setup!$D$7="Yes",P14<=TODAY())),IF(L14<>"",L14,F14),0))) | R14: =IF(A14="","",IF(M14<>"",M14,G14)) | S14: =IF(A14="","",IF(N14<>"",N14,H14)) | T14: =IF(A14="","",IF(C14="✗","Skipped",IF(Q14>0,"Paid","Upcoming"))) | U14: =IF(A14="",0,IF(C14="✗",0,IF(L14<>"",L14,F14)))
A15: =IFERROR(SMALL(Calc!$B$2:$BB$61,10),"") | B15: =IF(A15="","",ROUND(MOD(A15,1)*1000,0)) | D15: =IF(A15="","",INT(A15)) | E15: =IF(B15="","",INDEX(Setup!$D$25:$D$84,B15)) | F15: =IF(B15="","",INDEX(Setup!$E$25:$E$84,B15)) | G15: =IF(B15="","",INDEX(Setup!$I$25:$I$84,B15)&"") | H15: =IF(B15="","",INDEX(Setup!$J$25:$J$84,B15)&"") | I15: =IF(B15="","",INDEX(Setup!$C$25:$C$84,B15)) | P15: =IF(A15="","",IF(K15<>"",K15,D15)) | Q15: =IF(A15="",0,IF(C15="✗",0,IF(OR(C15="✓",AND(Setup!$D$7="Yes",P15<=TODAY())),IF(L15<>"",L15,F15),0))) | R15: =IF(A15="","",IF(M15<>"",M15,G15)) | S15: =IF(A15="","",IF(N15<>"",N15,H15)) | T15: =IF(A15="","",IF(C15="✗","Skipped",IF(Q15>0,"Paid","Upcoming"))) | U15: =IF(A15="",0,IF(C15="✗",0,IF(L15<>"",L15,F15)))
A16: =IFERROR(SMALL(Calc!$B$2:$BB$61,11),"") | B16: =IF(A16="","",ROUND(MOD(A16,1)*1000,0)) | D16: =IF(A16="","",INT(A16)) | E16: =IF(B16="","",INDEX(Setup!$D$25:$D$84,B16)) | F16: =IF(B16="","",INDEX(Setup!$E$25:$E$84,B16)) | G16: =IF(B16="","",INDEX(Setup!$I$25:$I$84,B16)&"") | H16: =IF(B16="","",INDEX(Setup!$J$25:$J$84,B16)&"") | I16: =IF(B16="","",INDEX(Setup!$C$25:$C$84,B16)) | P16: =IF(A16="","",IF(K16<>"",K16,D16)) | Q16: =IF(A16="",0,IF(C16="✗",0,IF(OR(C16="✓",AND(Setup!$D$7="Yes",P16<=TODAY())),IF(L16<>"",L16,F16),0))) | R16: =IF(A16="","",IF(M16<>"",M16,G16)) | S16: =IF(A16="","",IF(N16<>"",N16,H16)) | T16: =IF(A16="","",IF(C16="✗","Skipped",IF(Q16>0,"Paid","Upcoming"))) | U16: =IF(A16="",0,IF(C16="✗",0,IF(L16<>"",L16,F16)))
A17: =IFERROR(SMALL(Calc!$B$2:$BB$61,12),"") | B17: =IF(A17="","",ROUND(MOD(A17,1)*1000,0)) | D17: =IF(A17="","",INT(A17)) | E17: =IF(B17="","",INDEX(Setup!$D$25:$D$84,B17)) | F17: =IF(B17="","",INDEX(Setup!$E$25:$E$84,B17)) | G17: =IF(B17="","",INDEX(Setup!$I$25:$I$84,B17)&"") | H17: =IF(B17="","",INDEX(Setup!$J$25:$J$84,B17)&"") | I17: =IF(B17="","",INDEX(Setup!$C$25:$C$84,B17)) | P17: =IF(A17="","",IF(K17<>"",K17,D17)) | Q17: =IF(A17="",0,IF(C17="✗",0,IF(OR(C17="✓",AND(Setup!$D$7="Yes",P17<=TODAY())),IF(L17<>"",L17,F17),0))) | R17: =IF(A17="","",IF(M17<>"",M17,G17)) | S17: =IF(A17="","",IF(N17<>"",N17,H17)) | T17: =IF(A17="","",IF(C17="✗","Skipped",IF(Q17>0,"Paid","Upcoming"))) | U17: =IF(A17="",0,IF(C17="✗",0,IF(L17<>"",L17,F17)))
A18: =IFERROR(SMALL(Calc!$B$2:$BB$61,13),"") | B18: =IF(A18="","",ROUND(MOD(A18,1)*1000,0)) | D18: =IF(A18="","",INT(A18)) | E18: =IF(B18="","",INDEX(Setup!$D$25:$D$84,B18)) | F18: =IF(B18="","",INDEX(Setup!$E$25:$E$84,B18)) | G18: =IF(B18="","",INDEX(Setup!$I$25:$I$84,B18)&"") | H18: =IF(B18="","",INDEX(Setup!$J$25:$J$84,B18)&"") | I18: =IF(B18="","",INDEX(Setup!$C$25:$C$84,B18)) | P18: =IF(A18="","",IF(K18<>"",K18,D18)) | Q18: =IF(A18="",0,IF(C18="✗",0,IF(OR(C18="✓",AND(Setup!$D$7="Yes",P18<=TODAY())),IF(L18<>"",L18,F18),0))) | R18: =IF(A18="","",IF(M18<>"",M18,G18)) | S18: =IF(A18="","",IF(N18<>"",N18,H18)) | T18: =IF(A18="","",IF(C18="✗","Skipped",IF(Q18>0,"Paid","Upcoming"))) | U18: =IF(A18="",0,IF(C18="✗",0,IF(L18<>"",L18,F18)))
A19: =IFERROR(SMALL(Calc!$B$2:$BB$61,14),"") | B19: =IF(A19="","",ROUND(MOD(A19,1)*1000,0)) | D19: =IF(A19="","",INT(A19)) | E19: =IF(B19="","",INDEX(Setup!$D$25:$D$84,B19)) | F19: =IF(B19="","",INDEX(Setup!$E$25:$E$84,B19)) | G19: =IF(B19="","",INDEX(Setup!$I$25:$I$84,B19)&"") | H19: =IF(B19="","",INDEX(Setup!$J$25:$J$84,B19)&"") | I19: =IF(B19="","",INDEX(Setup!$C$25:$C$84,B19)) | P19: =IF(A19="","",IF(K19<>"",K19,D19)) | Q19: =IF(A19="",0,IF(C19="✗",0,IF(OR(C19="✓",AND(Setup!$D$7="Yes",P19<=TODAY())),IF(L19<>"",L19,F19),0))) | R19: =IF(A19="","",IF(M19<>"",M19,G19)) | S19: =IF(A19="","",IF(N19<>"",N19,H19)) | T19: =IF(A19="","",IF(C19="✗","Skipped",IF(Q19>0,"Paid","Upcoming"))) | U19: =IF(A19="",0,IF(C19="✗",0,IF(L19<>"",L19,F19)))
A20: =IFERROR(SMALL(Calc!$B$2:$BB$61,15),"") | B20: =IF(A20="","",ROUND(MOD(A20,1)*1000,0)) | D20: =IF(A20="","",INT(A20)) | E20: =IF(B20="","",INDEX(Setup!$D$25:$D$84,B20)) | F20: =IF(B20="","",INDEX(Setup!$E$25:$E$84,B20)) | G20: =IF(B20="","",INDEX(Setup!$I$25:$I$84,B20)&"") | H20: =IF(B20="","",INDEX(Setup!$J$25:$J$84,B20)&"") | I20: =IF(B20="","",INDEX(Setup!$C$25:$C$84,B20)) | P20: =IF(A20="","",IF(K20<>"",K20,D20)) | Q20: =IF(A20="",0,IF(C20="✗",0,IF(OR(C20="✓",AND(Setup!$D$7="Yes",P20<=TODAY())),IF(L20<>"",L20,F20),0))) | R20: =IF(A20="","",IF(M20<>"",M20,G20)) | S20: =IF(A20="","",IF(N20<>"",N20,H20)) | T20: =IF(A20="","",IF(C20="✗","Skipped",IF(Q20>0,"Paid","Upcoming"))) | U20: =IF(A20="",0,IF(C20="✗",0,IF(L20<>"",L20,F20)))
A21: =IFERROR(SMALL(Calc!$B$2:$BB$61,16),"") | B21: =IF(A21="","",ROUND(MOD(A21,1)*1000,0)) | D21: =IF(A21="","",INT(A21)) | E21: =IF(B21="","",INDEX(Setup!$D$25:$D$84,B21)) | F21: =IF(B21="","",INDEX(Setup!$E$25:$E$84,B21)) | G21: =IF(B21="","",INDEX(Setup!$I$25:$I$84,B21)&"") | H21: =IF(B21="","",INDEX(Setup!$J$25:$J$84,B21)&"") | I21: =IF(B21="","",INDEX(Setup!$C$25:$C$84,B21)) | P21: =IF(A21="","",IF(K21<>"",K21,D21)) | Q21: =IF(A21="",0,IF(C21="✗",0,IF(OR(C21="✓",AND(Setup!$D$7="Yes",P21<=TODAY())),IF(L21<>"",L21,F21),0))) | R21: =IF(A21="","",IF(M21<>"",M21,G21)) | S21: =IF(A21="","",IF(N21<>"",N21,H21)) | T21: =IF(A21="","",IF(C21="✗","Skipped",IF(Q21>0,"Paid","Upcoming"))) | U21: =IF(A21="",0,IF(C21="✗",0,IF(L21<>"",L21,F21)))
A22: =IFERROR(SMALL(Calc!$B$2:$BB$61,17),"") | B22: =IF(A22="","",ROUND(MOD(A22,1)*1000,0)) | D22: =IF(A22="","",INT(A22)) | E22: =IF(B22="","",INDEX(Setup!$D$25:$D$84,B22)) | F22: =IF(B22="","",INDEX(Setup!$E$25:$E$84,B22)) | G22: =IF(B22="","",INDEX(Setup!$I$25:$I$84,B22)&"") | H22: =IF(B22="","",INDEX(Setup!$J$25:$J$84,B22)&"") | I22: =IF(B22="","",INDEX(Setup!$C$25:$C$84,B22)) | P22: =IF(A22="","",IF(K22<>"",K22,D22)) | Q22: =IF(A22="",0,IF(C22="✗",0,IF(OR(C22="✓",AND(Setup!$D$7="Yes",P22<=TODAY())),IF(L22<>"",L22,F22),0))) | R22: =IF(A22="","",IF(M22<>"",M22,G22)) | S22: =IF(A22="","",IF(N22<>"",N22,H22)) | T22: =IF(A22="","",IF(C22="✗","Skipped",IF(Q22>0,"Paid","Upcoming"))) | U22: =IF(A22="",0,IF(C22="✗",0,IF(L22<>"",L22,F22)))
A23: =IFERROR(SMALL(Calc!$B$2:$BB$61,18),"") | B23: =IF(A23="","",ROUND(MOD(A23,1)*1000,0)) | D23: =IF(A23="","",INT(A23)) | E23: =IF(B23="","",INDEX(Setup!$D$25:$D$84,B23)) | F23: =IF(B23="","",INDEX(Setup!$E$25:$E$84,B23)) | G23: =IF(B23="","",INDEX(Setup!$I$25:$I$84,B23)&"") | H23: =IF(B23="","",INDEX(Setup!$J$25:$J$84,B23)&"") | I23: =IF(B23="","",INDEX(Setup!$C$25:$C$84,B23)) | P23: =IF(A23="","",IF(K23<>"",K23,D23)) | Q23: =IF(A23="",0,IF(C23="✗",0,IF(OR(C23="✓",AND(Setup!$D$7="Yes",P23<=TODAY())),IF(L23<>"",L23,F23),0))) | R23: =IF(A23="","",IF(M23<>"",M23,G23)) | S23: =IF(A23="","",IF(N23<>"",N23,H23)) | T23: =IF(A23="","",IF(C23="✗","Skipped",IF(Q23>0,"Paid","Upcoming"))) | U23: =IF(A23="",0,IF(C23="✗",0,IF(L23<>"",L23,F23)))
A24: =IFERROR(SMALL(Calc!$B$2:$BB$61,19),"") | B24: =IF(A24="","",ROUND(MOD(A24,1)*1000,0)) | D24: =IF(A24="","",INT(A24)) | E24: =IF(B24="","",INDEX(Setup!$D$25:$D$84,B24)) | F24: =IF(B24="","",INDEX(Setup!$E$25:$E$84,B24)) | G24: =IF(B24="","",INDEX(Setup!$I$25:$I$84,B24)&"") | H24: =IF(B24="","",INDEX(Setup!$J$25:$J$84,B24)&"") | I24: =IF(B24="","",INDEX(Setup!$C$25:$C$84,B24)) | P24: =IF(A24="","",IF(K24<>"",K24,D24)) | Q24: =IF(A24="",0,IF(C24="✗",0,IF(OR(C24="✓",AND(Setup!$D$7="Yes",P24<=TODAY())),IF(L24<>"",L24,F24),0))) | R24: =IF(A24="","",IF(M24<>"",M24,G24)) | S24: =IF(A24="","",IF(N24<>"",N24,H24)) | T24: =IF(A24="","",IF(C24="✗","Skipped",IF(Q24>0,"Paid","Upcoming"))) | U24: =IF(A24="",0,IF(C24="✗",0,IF(L24<>"",L24,F24)))
A25: =IFERROR(SMALL(Calc!$B$2:$BB$61,20),"") | B25: =IF(A25="","",ROUND(MOD(A25,1)*1000,0)) | D25: =IF(A25="","",INT(A25)) | E25: =IF(B25="","",INDEX(Setup!$D$25:$D$84,B25)) | F25: =IF(B25="","",INDEX(Setup!$E$25:$E$84,B25)) | G25: =IF(B25="","",INDEX(Setup!$I$25:$I$84,B25)&"") | H25: =IF(B25="","",INDEX(Setup!$J$25:$J$84,B25)&"") | I25: =IF(B25="","",INDEX(Setup!$C$25:$C$84,B25)) | P25: =IF(A25="","",IF(K25<>"",K25,D25)) | Q25: =IF(A25="",0,IF(C25="✗",0,IF(OR(C25="✓",AND(Setup!$D$7="Yes",P25<=TODAY())),IF(L25<>"",L25,F25),0))) | R25: =IF(A25="","",IF(M25<>"",M25,G25)) | S25: =IF(A25="","",IF(N25<>"",N25,H25)) | T25: =IF(A25="","",IF(C25="✗","Skipped",IF(Q25>0,"Paid","Upcoming"))) | U25: =IF(A25="",0,IF(C25="✗",0,IF(L25<>"",L25,F25)))
A26: =IFERROR(SMALL(Calc!$B$2:$BB$61,21),"") | B26: =IF(A26="","",ROUND(MOD(A26,1)*1000,0)) | D26: =IF(A26="","",INT(A26)) | E26: =IF(B26="","",INDEX(Setup!$D$25:$D$84,B26)) | F26: =IF(B26="","",INDEX(Setup!$E$25:$E$84,B26)) | G26: =IF(B26="","",INDEX(Setup!$I$25:$I$84,B26)&"") | H26: =IF(B26="","",INDEX(Setup!$J$25:$J$84,B26)&"") | I26: =IF(B26="","",INDEX(Setup!$C$25:$C$84,B26)) | P26: =IF(A26="","",IF(K26<>"",K26,D26)) | Q26: =IF(A26="",0,IF(C26="✗",0,IF(OR(C26="✓",AND(Setup!$D$7="Yes",P26<=TODAY())),IF(L26<>"",L26,F26),0))) | R26: =IF(A26="","",IF(M26<>"",M26,G26)) | S26: =IF(A26="","",IF(N26<>"",N26,H26)) | T26: =IF(A26="","",IF(C26="✗","Skipped",IF(Q26>0,"Paid","Upcoming"))) | U26: =IF(A26="",0,IF(C26="✗",0,IF(L26<>"",L26,F26)))
A27: =IFERROR(SMALL(Calc!$B$2:$BB$61,22),"") | B27: =IF(A27="","",ROUND(MOD(A27,1)*1000,0)) | D27: =IF(A27="","",INT(A27)) | E27: =IF(B27="","",INDEX(Setup!$D$25:$D$84,B27)) | F27: =IF(B27="","",INDEX(Setup!$E$25:$E$84,B27)) | G27: =IF(B27="","",INDEX(Setup!$I$25:$I$84,B27)&"") | H27: =IF(B27="","",INDEX(Setup!$J$25:$J$84,B27)&"") | I27: =IF(B27="","",INDEX(Setup!$C$25:$C$84,B27)) | P27: =IF(A27="","",IF(K27<>"",K27,D27)) | Q27: =IF(A27="",0,IF(C27="✗",0,IF(OR(C27="✓",AND(Setup!$D$7="Yes",P27<=TODAY())),IF(L27<>"",L27,F27),0))) | R27: =IF(A27="","",IF(M27<>"",M27,G27)) | S27: =IF(A27="","",IF(N27<>"",N27,H27)) | T27: =IF(A27="","",IF(C27="✗","Skipped",IF(Q27>0,"Paid","Upcoming"))) | U27: =IF(A27="",0,IF(C27="✗",0,IF(L27<>"",L27,F27)))
A28: =IFERROR(SMALL(Calc!$B$2:$BB$61,23),"") | B28: =IF(A28="","",ROUND(MOD(A28,1)*1000,0)) | D28: =IF(A28="","",INT(A28)) | E28: =IF(B28="","",INDEX(Setup!$D$25:$D$84,B28)) | F28: =IF(B28="","",INDEX(Setup!$E$25:$E$84,B28)) | G28: =IF(B28="","",INDEX(Setup!$I$25:$I$84,B28)&"") | H28: =IF(B28="","",INDEX(Setup!$J$25:$J$84,B28)&"") | I28: =IF(B28="","",INDEX(Setup!$C$25:$C$84,B28)) | P28: =IF(A28="","",IF(K28<>"",K28,D28)) | Q28: =IF(A28="",0,IF(C28="✗",0,IF(OR(C28="✓",AND(Setup!$D$7="Yes",P28<=TODAY())),IF(L28<>"",L28,F28),0))) | R28: =IF(A28="","",IF(M28<>"",M28,G28)) | S28: =IF(A28="","",IF(N28<>"",N28,H28)) | T28: =IF(A28="","",IF(C28="✗","Skipped",IF(Q28>0,"Paid","Upcoming"))) | U28: =IF(A28="",0,IF(C28="✗",0,IF(L28<>"",L28,F28)))
A29: =IFERROR(SMALL(Calc!$B$2:$BB$61,24),"") | B29: =IF(A29="","",ROUND(MOD(A29,1)*1000,0)) | D29: =IF(A29="","",INT(A29)) | E29: =IF(B29="","",INDEX(Setup!$D$25:$D$84,B29)) | F29: =IF(B29="","",INDEX(Setup!$E$25:$E$84,B29)) | G29: =IF(B29="","",INDEX(Setup!$I$25:$I$84,B29)&"") | H29: =IF(B29="","",INDEX(Setup!$J$25:$J$84,B29)&"") | I29: =IF(B29="","",INDEX(Setup!$C$25:$C$84,B29)) | P29: =IF(A29="","",IF(K29<>"",K29,D29)) | Q29: =IF(A29="",0,IF(C29="✗",0,IF(OR(C29="✓",AND(Setup!$D$7="Yes",P29<=TODAY())),IF(L29<>"",L29,F29),0))) | R29: =IF(A29="","",IF(M29<>"",M29,G29)) | S29: =IF(A29="","",IF(N29<>"",N29,H29)) | T29: =IF(A29="","",IF(C29="✗","Skipped",IF(Q29>0,"Paid","Upcoming"))) | U29: =IF(A29="",0,IF(C29="✗",0,IF(L29<>"",L29,F29)))
A30: =IFERROR(SMALL(Calc!$B$2:$BB$61,25),"") | B30: =IF(A30="","",ROUND(MOD(A30,1)*1000,0)) | D30: =IF(A30="","",INT(A30)) | E30: =IF(B30="","",INDEX(Setup!$D$25:$D$84,B30)) | F30: =IF(B30="","",INDEX(Setup!$E$25:$E$84,B30)) | G30: =IF(B30="","",INDEX(Setup!$I$25:$I$84,B30)&"") | H30: =IF(B30="","",INDEX(Setup!$J$25:$J$84,B30)&"") | I30: =IF(B30="","",INDEX(Setup!$C$25:$C$84,B30)) | P30: =IF(A30="","",IF(K30<>"",K30,D30)) | Q30: =IF(A30="",0,IF(C30="✗",0,IF(OR(C30="✓",AND(Setup!$D$7="Yes",P30<=TODAY())),IF(L30<>"",L30,F30),0))) | R30: =IF(A30="","",IF(M30<>"",M30,G30)) | S30: =IF(A30="","",IF(N30<>"",N30,H30)) | T30: =IF(A30="","",IF(C30="✗","Skipped",IF(Q30>0,"Paid","Upcoming"))) | U30: =IF(A30="",0,IF(C30="✗",0,IF(L30<>"",L30,F30)))
A31: =IFERROR(SMALL(Calc!$B$2:$BB$61,26),"") | B31: =IF(A31="","",ROUND(MOD(A31,1)*1000,0)) | D31: =IF(A31="","",INT(A31)) | E31: =IF(B31="","",INDEX(Setup!$D$25:$D$84,B31)) | F31: =IF(B31="","",INDEX(Setup!$E$25:$E$84,B31)) | G31: =IF(B31="","",INDEX(Setup!$I$25:$I$84,B31)&"") | H31: =IF(B31="","",INDEX(Setup!$J$25:$J$84,B31)&"") | I31: =IF(B31="","",INDEX(Setup!$C$25:$C$84,B31)) | P31: =IF(A31="","",IF(K31<>"",K31,D31)) | Q31: =IF(A31="",0,IF(C31="✗",0,IF(OR(C31="✓",AND(Setup!$D$7="Yes",P31<=TODAY())),IF(L31<>"",L31,F31),0))) | R31: =IF(A31="","",IF(M31<>"",M31,G31)) | S31: =IF(A31="","",IF(N31<>"",N31,H31)) | T31: =IF(A31="","",IF(C31="✗","Skipped",IF(Q31>0,"Paid","Upcoming"))) | U31: =IF(A31="",0,IF(C31="✗",0,IF(L31<>"",L31,F31)))
A32: =IFERROR(SMALL(Calc!$B$2:$BB$61,27),"") | B32: =IF(A32="","",ROUND(MOD(A32,1)*1000,0)) | D32: =IF(A32="","",INT(A32)) | E32: =IF(B32="","",INDEX(Setup!$D$25:$D$84,B32)) | F32: =IF(B32="","",INDEX(Setup!$E$25:$E$84,B32)) | G32: =IF(B32="","",INDEX(Setup!$I$25:$I$84,B32)&"") | H32: =IF(B32="","",INDEX(Setup!$J$25:$J$84,B32)&"") | I32: =IF(B32="","",INDEX(Setup!$C$25:$C$84,B32)) | P32: =IF(A32="","",IF(K32<>"",K32,D32)) | Q32: =IF(A32="",0,IF(C32="✗",0,IF(OR(C32="✓",AND(Setup!$D$7="Yes",P32<=TODAY())),IF(L32<>"",L32,F32),0))) | R32: =IF(A32="","",IF(M32<>"",M32,G32)) | S32: =IF(A32="","",IF(N32<>"",N32,H32)) | T32: =IF(A32="","",IF(C32="✗","Skipped",IF(Q32>0,"Paid","Upcoming"))) | U32: =IF(A32="",0,IF(C32="✗",0,IF(L32<>"",L32,F32)))
A33: =IFERROR(SMALL(Calc!$B$2:$BB$61,28),"") | B33: =IF(A33="","",ROUND(MOD(A33,1)*1000,0)) | D33: =IF(A33="","",INT(A33)) | E33: =IF(B33="","",INDEX(Setup!$D$25:$D$84,B33)) | F33: =IF(B33="","",INDEX(Setup!$E$25:$E$84,B33)) | G33: =IF(B33="","",INDEX(Setup!$I$25:$I$84,B33)&"") | H33: =IF(B33="","",INDEX(Setup!$J$25:$J$84,B33)&"") | I33: =IF(B33="","",INDEX(Setup!$C$25:$C$84,B33)) | P33: =IF(A33="","",IF(K33<>"",K33,D33)) | Q33: =IF(A33="",0,IF(C33="✗",0,IF(OR(C33="✓",AND(Setup!$D$7="Yes",P33<=TODAY())),IF(L33<>"",L33,F33),0))) | R33: =IF(A33="","",IF(M33<>"",M33,G33)) | S33: =IF(A33="","",IF(N33<>"",N33,H33)) | T33: =IF(A33="","",IF(C33="✗","Skipped",IF(Q33>0,"Paid","Upcoming"))) | U33: =IF(A33="",0,IF(C33="✗",0,IF(L33<>"",L33,F33)))
A34: =IFERROR(SMALL(Calc!$B$2:$BB$61,29),"") | B34: =IF(A34="","",ROUND(MOD(A34,1)*1000,0)) | D34: =IF(A34="","",INT(A34)) | E34: =IF(B34="","",INDEX(Setup!$D$25:$D$84,B34)) | F34: =IF(B34="","",INDEX(Setup!$E$25:$E$84,B34)) | G34: =IF(B34="","",INDEX(Setup!$I$25:$I$84,B34)&"") | H34: =IF(B34="","",INDEX(Setup!$J$25:$J$84,B34)&"") | I34: =IF(B34="","",INDEX(Setup!$C$25:$C$84,B34)) | P34: =IF(A34="","",IF(K34<>"",K34,D34)) | Q34: =IF(A34="",0,IF(C34="✗",0,IF(OR(C34="✓",AND(Setup!$D$7="Yes",P34<=TODAY())),IF(L34<>"",L34,F34),0))) | R34: =IF(A34="","",IF(M34<>"",M34,G34)) | S34: =IF(A34="","",IF(N34<>"",N34,H34)) | T34: =IF(A34="","",IF(C34="✗","Skipped",IF(Q34>0,"Paid","Upcoming"))) | U34: =IF(A34="",0,IF(C34="✗",0,IF(L34<>"",L34,F34)))
A35: =IFERROR(SMALL(Calc!$B$2:$BB$61,30),"") | B35: =IF(A35="","",ROUND(MOD(A35,1)*1000,0)) | D35: =IF(A35="","",INT(A35)) | E35: =IF(B35="","",INDEX(Setup!$D$25:$D$84,B35)) | F35: =IF(B35="","",INDEX(Setup!$E$25:$E$84,B35)) | G35: =IF(B35="","",INDEX(Setup!$I$25:$I$84,B35)&"") | H35: =IF(B35="","",INDEX(Setup!$J$25:$J$84,B35)&"") | I35: =IF(B35="","",INDEX(Setup!$C$25:$C$84,B35)) | P35: =IF(A35="","",IF(K35<>"",K35,D35)) | Q35: =IF(A35="",0,IF(C35="✗",0,IF(OR(C35="✓",AND(Setup!$D$7="Yes",P35<=TODAY())),IF(L35<>"",L35,F35),0))) | R35: =IF(A35="","",IF(M35<>"",M35,G35)) | S35: =IF(A35="","",IF(N35<>"",N35,H35)) | T35: =IF(A35="","",IF(C35="✗","Skipped",IF(Q35>0,"Paid","Upcoming"))) | U35: =IF(A35="",0,IF(C35="✗",0,IF(L35<>"",L35,F35)))
A36: =IFERROR(SMALL(Calc!$B$2:$BB$61,31),"") | B36: =IF(A36="","",ROUND(MOD(A36,1)*1000,0)) | D36: =IF(A36="","",INT(A36)) | E36: =IF(B36="","",INDEX(Setup!$D$25:$D$84,B36)) | F36: =IF(B36="","",INDEX(Setup!$E$25:$E$84,B36)) | G36: =IF(B36="","",INDEX(Setup!$I$25:$I$84,B36)&"") | H36: =IF(B36="","",INDEX(Setup!$J$25:$J$84,B36)&"") | I36: =IF(B36="","",INDEX(Setup!$C$25:$C$84,B36)) | P36: =IF(A36="","",IF(K36<>"",K36,D36)) | Q36: =IF(A36="",0,IF(C36="✗",0,IF(OR(C36="✓",AND(Setup!$D$7="Yes",P36<=TODAY())),IF(L36<>"",L36,F36),0))) | R36: =IF(A36="","",IF(M36<>"",M36,G36)) | S36: =IF(A36="","",IF(N36<>"",N36,H36)) | T36: =IF(A36="","",IF(C36="✗","Skipped",IF(Q36>0,"Paid","Upcoming"))) | U36: =IF(A36="",0,IF(C36="✗",0,IF(L36<>"",L36,F36)))
A37: =IFERROR(SMALL(Calc!$B$2:$BB$61,32),"") | B37: =IF(A37="","",ROUND(MOD(A37,1)*1000,0)) | D37: =IF(A37="","",INT(A37)) | E37: =IF(B37="","",INDEX(Setup!$D$25:$D$84,B37)) | F37: =IF(B37="","",INDEX(Setup!$E$25:$E$84,B37)) | G37: =IF(B37="","",INDEX(Setup!$I$25:$I$84,B37)&"") | H37: =IF(B37="","",INDEX(Setup!$J$25:$J$84,B37)&"") | I37: =IF(B37="","",INDEX(Setup!$C$25:$C$84,B37)) | P37: =IF(A37="","",IF(K37<>"",K37,D37)) | Q37: =IF(A37="",0,IF(C37="✗",0,IF(OR(C37="✓",AND(Setup!$D$7="Yes",P37<=TODAY())),IF(L37<>"",L37,F37),0))) | R37: =IF(A37="","",IF(M37<>"",M37,G37)) | S37: =IF(A37="","",IF(N37<>"",N37,H37)) | T37: =IF(A37="","",IF(C37="✗","Skipped",IF(Q37>0,"Paid","Upcoming"))) | U37: =IF(A37="",0,IF(C37="✗",0,IF(L37<>"",L37,F37)))
A38: =IFERROR(SMALL(Calc!$B$2:$BB$61,33),"") | B38: =IF(A38="","",ROUND(MOD(A38,1)*1000,0)) | D38: =IF(A38="","",INT(A38)) | E38: =IF(B38="","",INDEX(Setup!$D$25:$D$84,B38)) | F38: =IF(B38="","",INDEX(Setup!$E$25:$E$84,B38)) | G38: =IF(B38="","",INDEX(Setup!$I$25:$I$84,B38)&"") | H38: =IF(B38="","",INDEX(Setup!$J$25:$J$84,B38)&"") | I38: =IF(B38="","",INDEX(Setup!$C$25:$C$84,B38)) | P38: =IF(A38="","",IF(K38<>"",K38,D38)) | Q38: =IF(A38="",0,IF(C38="✗",0,IF(OR(C38="✓",AND(Setup!$D$7="Yes",P38<=TODAY())),IF(L38<>"",L38,F38),0))) | R38: =IF(A38="","",IF(M38<>"",M38,G38)) | S38: =IF(A38="","",IF(N38<>"",N38,H38)) | T38: =IF(A38="","",IF(C38="✗","Skipped",IF(Q38>0,"Paid","Upcoming"))) | U38: =IF(A38="",0,IF(C38="✗",0,IF(L38<>"",L38,F38)))
A39: =IFERROR(SMALL(Calc!$B$2:$BB$61,34),"") | B39: =IF(A39="","",ROUND(MOD(A39,1)*1000,0)) | D39: =IF(A39="","",INT(A39)) | E39: =IF(B39="","",INDEX(Setup!$D$25:$D$84,B39)) | F39: =IF(B39="","",INDEX(Setup!$E$25:$E$84,B39)) | G39: =IF(B39="","",INDEX(Setup!$I$25:$I$84,B39)&"") | H39: =IF(B39="","",INDEX(Setup!$J$25:$J$84,B39)&"") | I39: =IF(B39="","",INDEX(Setup!$C$25:$C$84,B39)) | P39: =IF(A39="","",IF(K39<>"",K39,D39)) | Q39: =IF(A39="",0,IF(C39="✗",0,IF(OR(C39="✓",AND(Setup!$D$7="Yes",P39<=TODAY())),IF(L39<>"",L39,F39),0))) | R39: =IF(A39="","",IF(M39<>"",M39,G39)) | S39: =IF(A39="","",IF(N39<>"",N39,H39)) | T39: =IF(A39="","",IF(C39="✗","Skipped",IF(Q39>0,"Paid","Upcoming"))) | U39: =IF(A39="",0,IF(C39="✗",0,IF(L39<>"",L39,F39)))
A40: =IFERROR(SMALL(Calc!$B$2:$BB$61,35),"") | B40: =IF(A40="","",ROUND(MOD(A40,1)*1000,0)) | D40: =IF(A40="","",INT(A40)) | E40: =IF(B40="","",INDEX(Setup!$D$25:$D$84,B40)) | F40: =IF(B40="","",INDEX(Setup!$E$25:$E$84,B40)) | G40: =IF(B40="","",INDEX(Setup!$I$25:$I$84,B40)&"") | H40: =IF(B40="","",INDEX(Setup!$J$25:$J$84,B40)&"") | I40: =IF(B40="","",INDEX(Setup!$C$25:$C$84,B40)) | P40: =IF(A40="","",IF(K40<>"",K40,D40)) | Q40: =IF(A40="",0,IF(C40="✗",0,IF(OR(C40="✓",AND(Setup!$D$7="Yes",P40<=TODAY())),IF(L40<>"",L40,F40),0))) | R40: =IF(A40="","",IF(M40<>"",M40,G40)) | S40: =IF(A40="","",IF(N40<>"",N40,H40)) | T40: =IF(A40="","",IF(C40="✗","Skipped",IF(Q40>0,"Paid","Upcoming"))) | U40: =IF(A40="",0,IF(C40="✗",0,IF(L40<>"",L40,F40)))
A41: =IFERROR(SMALL(Calc!$B$2:$BB$61,36),"") | B41: =IF(A41="","",ROUND(MOD(A41,1)*1000,0)) | D41: =IF(A41="","",INT(A41)) | E41: =IF(B41="","",INDEX(Setup!$D$25:$D$84,B41)) | F41: =IF(B41="","",INDEX(Setup!$E$25:$E$84,B41)) | G41: =IF(B41="","",INDEX(Setup!$I$25:$I$84,B41)&"") | H41: =IF(B41="","",INDEX(Setup!$J$25:$J$84,B41)&"") | I41: =IF(B41="","",INDEX(Setup!$C$25:$C$84,B41)) | P41: =IF(A41="","",IF(K41<>"",K41,D41)) | Q41: =IF(A41="",0,IF(C41="✗",0,IF(OR(C41="✓",AND(Setup!$D$7="Yes",P41<=TODAY())),IF(L41<>"",L41,F41),0))) | R41: =IF(A41="","",IF(M41<>"",M41,G41)) | S41: =IF(A41="","",IF(N41<>"",N41,H41)) | T41: =IF(A41="","",IF(C41="✗","Skipped",IF(Q41>0,"Paid","Upcoming"))) | U41: =IF(A41="",0,IF(C41="✗",0,IF(L41<>"",L41,F41)))
A42: =IFERROR(SMALL(Calc!$B$2:$BB$61,37),"") | B42: =IF(A42="","",ROUND(MOD(A42,1)*1000,0)) | D42: =IF(A42="","",INT(A42)) | E42: =IF(B42="","",INDEX(Setup!$D$25:$D$84,B42)) | F42: =IF(B42="","",INDEX(Setup!$E$25:$E$84,B42)) | G42: =IF(B42="","",INDEX(Setup!$I$25:$I$84,B42)&"") | H42: =IF(B42="","",INDEX(Setup!$J$25:$J$84,B42)&"") | I42: =IF(B42="","",INDEX(Setup!$C$25:$C$84,B42)) | P42: =IF(A42="","",IF(K42<>"",K42,D42)) | Q42: =IF(A42="",0,IF(C42="✗",0,IF(OR(C42="✓",AND(Setup!$D$7="Yes",P42<=TODAY())),IF(L42<>"",L42,F42),0))) | R42: =IF(A42="","",IF(M42<>"",M42,G42)) | S42: =IF(A42="","",IF(N42<>"",N42,H42)) | T42: =IF(A42="","",IF(C42="✗","Skipped",IF(Q42>0,"Paid","Upcoming"))) | U42: =IF(A42="",0,IF(C42="✗",0,IF(L42<>"",L42,F42)))
A43: =IFERROR(SMALL(Calc!$B$2:$BB$61,38),"") | B43: =IF(A43="","",ROUND(MOD(A43,1)*1000,0)) | D43: =IF(A43="","",INT(A43)) | E43: =IF(B43="","",INDEX(Setup!$D$25:$D$84,B43)) | F43: =IF(B43="","",INDEX(Setup!$E$25:$E$84,B43)) | G43: =IF(B43="","",INDEX(Setup!$I$25:$I$84,B43)&"") | H43: =IF(B43="","",INDEX(Setup!$J$25:$J$84,B43)&"") | I43: =IF(B43="","",INDEX(Setup!$C$25:$C$84,B43)) | P43: =IF(A43="","",IF(K43<>"",K43,D43)) | Q43: =IF(A43="",0,IF(C43="✗",0,IF(OR(C43="✓",AND(Setup!$D$7="Yes",P43<=TODAY())),IF(L43<>"",L43,F43),0))) | R43: =IF(A43="","",IF(M43<>"",M43,G43)) | S43: =IF(A43="","",IF(N43<>"",N43,H43)) | T43: =IF(A43="","",IF(C43="✗","Skipped",IF(Q43>0,"Paid","Upcoming"))) | U43: =IF(A43="",0,IF(C43="✗",0,IF(L43<>"",L43,F43)))
A44: =IFERROR(SMALL(Calc!$B$2:$BB$61,39),"") | B44: =IF(A44="","",ROUND(MOD(A44,1)*1000,0)) | D44: =IF(A44="","",INT(A44)) | E44: =IF(B44="","",INDEX(Setup!$D$25:$D$84,B44)) | F44: =IF(B44="","",INDEX(Setup!$E$25:$E$84,B44)) | G44: =IF(B44="","",INDEX(Setup!$I$25:$I$84,B44)&"") | H44: =IF(B44="","",INDEX(Setup!$J$25:$J$84,B44)&"") | I44: =IF(B44="","",INDEX(Setup!$C$25:$C$84,B44)) | P44: =IF(A44="","",IF(K44<>"",K44,D44)) | Q44: =IF(A44="",0,IF(C44="✗",0,IF(OR(C44="✓",AND(Setup!$D$7="Yes",P44<=TODAY())),IF(L44<>"",L44,F44),0))) | R44: =IF(A44="","",IF(M44<>"",M44,G44)) | S44: =IF(A44="","",IF(N44<>"",N44,H44)) | T44: =IF(A44="","",IF(C44="✗","Skipped",IF(Q44>0,"Paid","Upcoming"))) | U44: =IF(A44="",0,IF(C44="✗",0,IF(L44<>"",L44,F44)))
A45: =IFERROR(SMALL(Calc!$B$2:$BB$61,40),"") | B45: =IF(A45="","",ROUND(MOD(A45,1)*1000,0)) | D45: =IF(A45="","",INT(A45)) | E45: =IF(B45="","",INDEX(Setup!$D$25:$D$84,B45)) | F45: =IF(B45="","",INDEX(Setup!$E$25:$E$84,B45)) | G45: =IF(B45="","",INDEX(Setup!$I$25:$I$84,B45)&"") | H45: =IF(B45="","",INDEX(Setup!$J$25:$J$84,B45)&"") | I45: =IF(B45="","",INDEX(Setup!$C$25:$C$84,B45)) | P45: =IF(A45="","",IF(K45<>"",K45,D45)) | Q45: =IF(A45="",0,IF(C45="✗",0,IF(OR(C45="✓",AND(Setup!$D$7="Yes",P45<=TODAY())),IF(L45<>"",L45,F45),0))) | R45: =IF(A45="","",IF(M45<>"",M45,G45)) | S45: =IF(A45="","",IF(N45<>"",N45,H45)) | T45: =IF(A45="","",IF(C45="✗","Skipped",IF(Q45>0,"Paid","Upcoming"))) | U45: =IF(A45="",0,IF(C45="✗",0,IF(L45<>"",L45,F45)))
A46: =IFERROR(SMALL(Calc!$B$2:$BB$61,41),"") | B46: =IF(A46="","",ROUND(MOD(A46,1)*1000,0)) | D46: =IF(A46="","",INT(A46)) | E46: =IF(B46="","",INDEX(Setup!$D$25:$D$84,B46)) | F46: =IF(B46="","",INDEX(Setup!$E$25:$E$84,B46)) | G46: =IF(B46="","",INDEX(Setup!$I$25:$I$84,B46)&"") | H46: =IF(B46="","",INDEX(Setup!$J$25:$J$84,B46)&"") | I46: =IF(B46="","",INDEX(Setup!$C$25:$C$84,B46)) | P46: =IF(A46="","",IF(K46<>"",K46,D46)) | Q46: =IF(A46="",0,IF(C46="✗",0,IF(OR(C46="✓",AND(Setup!$D$7="Yes",P46<=TODAY())),IF(L46<>"",L46,F46),0))) | R46: =IF(A46="","",IF(M46<>"",M46,G46)) | S46: =IF(A46="","",IF(N46<>"",N46,H46)) | T46: =IF(A46="","",IF(C46="✗","Skipped",IF(Q46>0,"Paid","Upcoming"))) | U46: =IF(A46="",0,IF(C46="✗",0,IF(L46<>"",L46,F46)))
A47: =IFERROR(SMALL(Calc!$B$2:$BB$61,42),"") | B47: =IF(A47="","",ROUND(MOD(A47,1)*1000,0)) | D47: =IF(A47="","",INT(A47)) | E47: =IF(B47="","",INDEX(Setup!$D$25:$D$84,B47)) | F47: =IF(B47="","",INDEX(Setup!$E$25:$E$84,B47)) | G47: =IF(B47="","",INDEX(Setup!$I$25:$I$84,B47)&"") | H47: =IF(B47="","",INDEX(Setup!$J$25:$J$84,B47)&"") | I47: =IF(B47="","",INDEX(Setup!$C$25:$C$84,B47)) | P47: =IF(A47="","",IF(K47<>"",K47,D47)) | Q47: =IF(A47="",0,IF(C47="✗",0,IF(OR(C47="✓",AND(Setup!$D$7="Yes",P47<=TODAY())),IF(L47<>"",L47,F47),0))) | R47: =IF(A47="","",IF(M47<>"",M47,G47)) | S47: =IF(A47="","",IF(N47<>"",N47,H47)) | T47: =IF(A47="","",IF(C47="✗","Skipped",IF(Q47>0,"Paid","Upcoming"))) | U47: =IF(A47="",0,IF(C47="✗",0,IF(L47<>"",L47,F47)))
A48: =IFERROR(SMALL(Calc!$B$2:$BB$61,43),"") | B48: =IF(A48="","",ROUND(MOD(A48,1)*1000,0)) | D48: =IF(A48="","",INT(A48)) | E48: =IF(B48="","",INDEX(Setup!$D$25:$D$84,B48)) | F48: =IF(B48="","",INDEX(Setup!$E$25:$E$84,B48)) | G48: =IF(B48="","",INDEX(Setup!$I$25:$I$84,B48)&"") | H48: =IF(B48="","",INDEX(Setup!$J$25:$J$84,B48)&"") | I48: =IF(B48="","",INDEX(Setup!$C$25:$C$84,B48)) | P48: =IF(A48="","",IF(K48<>"",K48,D48)) | Q48: =IF(A48="",0,IF(C48="✗",0,IF(OR(C48="✓",AND(Setup!$D$7="Yes",P48<=TODAY())),IF(L48<>"",L48,F48),0))) | R48: =IF(A48="","",IF(M48<>"",M48,G48)) | S48: =IF(A48="","",IF(N48<>"",N48,H48)) | T48: =IF(A48="","",IF(C48="✗","Skipped",IF(Q48>0,"Paid","Upcoming"))) | U48: =IF(A48="",0,IF(C48="✗",0,IF(L48<>"",L48,F48)))
A49: =IFERROR(SMALL(Calc!$B$2:$BB$61,44),"") | B49: =IF(A49="","",ROUND(MOD(A49,1)*1000,0)) | D49: =IF(A49="","",INT(A49)) | E49: =IF(B49="","",INDEX(Setup!$D$25:$D$84,B49)) | F49: =IF(B49="","",INDEX(Setup!$E$25:$E$84,B49)) | G49: =IF(B49="","",INDEX(Setup!$I$25:$I$84,B49)&"") | H49: =IF(B49="","",INDEX(Setup!$J$25:$J$84,B49)&"") | I49: =IF(B49="","",INDEX(Setup!$C$25:$C$84,B49)) | P49: =IF(A49="","",IF(K49<>"",K49,D49)) | Q49: =IF(A49="",0,IF(C49="✗",0,IF(OR(C49="✓",AND(Setup!$D$7="Yes",P49<=TODAY())),IF(L49<>"",L49,F49),0))) | R49: =IF(A49="","",IF(M49<>"",M49,G49)) | S49: =IF(A49="","",IF(N49<>"",N49,H49)) | T49: =IF(A49="","",IF(C49="✗","Skipped",IF(Q49>0,"Paid","Upcoming"))) | U49: =IF(A49="",0,IF(C49="✗",0,IF(L49<>"",L49,F49)))
A50: =IFERROR(SMALL(Calc!$B$2:$BB$61,45),"") | B50: =IF(A50="","",ROUND(MOD(A50,1)*1000,0)) | D50: =IF(A50="","",INT(A50)) | E50: =IF(B50="","",INDEX(Setup!$D$25:$D$84,B50)) | F50: =IF(B50="","",INDEX(Setup!$E$25:$E$84,B50)) | G50: =IF(B50="","",INDEX(Setup!$I$25:$I$84,B50)&"") | H50: =IF(B50="","",INDEX(Setup!$J$25:$J$84,B50)&"") | I50: =IF(B50="","",INDEX(Setup!$C$25:$C$84,B50)) | P50: =IF(A50="","",IF(K50<>"",K50,D50)) | Q50: =IF(A50="",0,IF(C50="✗",0,IF(OR(C50="✓",AND(Setup!$D$7="Yes",P50<=TODAY())),IF(L50<>"",L50,F50),0))) | R50: =IF(A50="","",IF(M50<>"",M50,G50)) | S50: =IF(A50="","",IF(N50<>"",N50,H50)) | T50: =IF(A50="","",IF(C50="✗","Skipped",IF(Q50>0,"Paid","Upcoming"))) | U50: =IF(A50="",0,IF(C50="✗",0,IF(L50<>"",L50,F50)))
A51: =IFERROR(SMALL(Calc!$B$2:$BB$61,46),"") | B51: =IF(A51="","",ROUND(MOD(A51,1)*1000,0)) | D51: =IF(A51="","",INT(A51)) | E51: =IF(B51="","",INDEX(Setup!$D$25:$D$84,B51)) | F51: =IF(B51="","",INDEX(Setup!$E$25:$E$84,B51)) | G51: =IF(B51="","",INDEX(Setup!$I$25:$I$84,B51)&"") | H51: =IF(B51="","",INDEX(Setup!$J$25:$J$84,B51)&"") | I51: =IF(B51="","",INDEX(Setup!$C$25:$C$84,B51)) | P51: =IF(A51="","",IF(K51<>"",K51,D51)) | Q51: =IF(A51="",0,IF(C51="✗",0,IF(OR(C51="✓",AND(Setup!$D$7="Yes",P51<=TODAY())),IF(L51<>"",L51,F51),0))) | R51: =IF(A51="","",IF(M51<>"",M51,G51)) | S51: =IF(A51="","",IF(N51<>"",N51,H51)) | T51: =IF(A51="","",IF(C51="✗","Skipped",IF(Q51>0,"Paid","Upcoming"))) | U51: =IF(A51="",0,IF(C51="✗",0,IF(L51<>"",L51,F51)))
A52: =IFERROR(SMALL(Calc!$B$2:$BB$61,47),"") | B52: =IF(A52="","",ROUND(MOD(A52,1)*1000,0)) | D52: =IF(A52="","",INT(A52)) | E52: =IF(B52="","",INDEX(Setup!$D$25:$D$84,B52)) | F52: =IF(B52="","",INDEX(Setup!$E$25:$E$84,B52)) | G52: =IF(B52="","",INDEX(Setup!$I$25:$I$84,B52)&"") | H52: =IF(B52="","",INDEX(Setup!$J$25:$J$84,B52)&"") | I52: =IF(B52="","",INDEX(Setup!$C$25:$C$84,B52)) | P52: =IF(A52="","",IF(K52<>"",K52,D52)) | Q52: =IF(A52="",0,IF(C52="✗",0,IF(OR(C52="✓",AND(Setup!$D$7="Yes",P52<=TODAY())),IF(L52<>"",L52,F52),0))) | R52: =IF(A52="","",IF(M52<>"",M52,G52)) | S52: =IF(A52="","",IF(N52<>"",N52,H52)) | T52: =IF(A52="","",IF(C52="✗","Skipped",IF(Q52>0,"Paid","Upcoming"))) | U52: =IF(A52="",0,IF(C52="✗",0,IF(L52<>"",L52,F52)))
A53: =IFERROR(SMALL(Calc!$B$2:$BB$61,48),"") | B53: =IF(A53="","",ROUND(MOD(A53,1)*1000,0)) | D53: =IF(A53="","",INT(A53)) | E53: =IF(B53="","",INDEX(Setup!$D$25:$D$84,B53)) | F53: =IF(B53="","",INDEX(Setup!$E$25:$E$84,B53)) | G53: =IF(B53="","",INDEX(Setup!$I$25:$I$84,B53)&"") | H53: =IF(B53="","",INDEX(Setup!$J$25:$J$84,B53)&"") | I53: =IF(B53="","",INDEX(Setup!$C$25:$C$84,B53)) | P53: =IF(A53="","",IF(K53<>"",K53,D53)) | Q53: =IF(A53="",0,IF(C53="✗",0,IF(OR(C53="✓",AND(Setup!$D$7="Yes",P53<=TODAY())),IF(L53<>"",L53,F53),0))) | R53: =IF(A53="","",IF(M53<>"",M53,G53)) | S53: =IF(A53="","",IF(N53<>"",N53,H53)) | T53: =IF(A53="","",IF(C53="✗","Skipped",IF(Q53>0,"Paid","Upcoming"))) | U53: =IF(A53="",0,IF(C53="✗",0,IF(L53<>"",L53,F53)))
A54: =IFERROR(SMALL(Calc!$B$2:$BB$61,49),"") | B54: =IF(A54="","",ROUND(MOD(A54,1)*1000,0)) | D54: =IF(A54="","",INT(A54)) | E54: =IF(B54="","",INDEX(Setup!$D$25:$D$84,B54)) | F54: =IF(B54="","",INDEX(Setup!$E$25:$E$84,B54)) | G54: =IF(B54="","",INDEX(Setup!$I$25:$I$84,B54)&"") | H54: =IF(B54="","",INDEX(Setup!$J$25:$J$84,B54)&"") | I54: =IF(B54="","",INDEX(Setup!$C$25:$C$84,B54)) | P54: =IF(A54="","",IF(K54<>"",K54,D54)) | Q54: =IF(A54="",0,IF(C54="✗",0,IF(OR(C54="✓",AND(Setup!$D$7="Yes",P54<=TODAY())),IF(L54<>"",L54,F54),0))) | R54: =IF(A54="","",IF(M54<>"",M54,G54)) | S54: =IF(A54="","",IF(N54<>"",N54,H54)) | T54: =IF(A54="","",IF(C54="✗","Skipped",IF(Q54>0,"Paid","Upcoming"))) | U54: =IF(A54="",0,IF(C54="✗",0,IF(L54<>"",L54,F54)))
A55: =IFERROR(SMALL(Calc!$B$2:$BB$61,50),"") | B55: =IF(A55="","",ROUND(MOD(A55,1)*1000,0)) | D55: =IF(A55="","",INT(A55)) | E55: =IF(B55="","",INDEX(Setup!$D$25:$D$84,B55)) | F55: =IF(B55="","",INDEX(Setup!$E$25:$E$84,B55)) | G55: =IF(B55="","",INDEX(Setup!$I$25:$I$84,B55)&"") | H55: =IF(B55="","",INDEX(Setup!$J$25:$J$84,B55)&"") | I55: =IF(B55="","",INDEX(Setup!$C$25:$C$84,B55)) | P55: =IF(A55="","",IF(K55<>"",K55,D55)) | Q55: =IF(A55="",0,IF(C55="✗",0,IF(OR(C55="✓",AND(Setup!$D$7="Yes",P55<=TODAY())),IF(L55<>"",L55,F55),0))) | R55: =IF(A55="","",IF(M55<>"",M55,G55)) | S55: =IF(A55="","",IF(N55<>"",N55,H55)) | T55: =IF(A55="","",IF(C55="✗","Skipped",IF(Q55>0,"Paid","Upcoming"))) | U55: =IF(A55="",0,IF(C55="✗",0,IF(L55<>"",L55,F55)))
A56: =IFERROR(SMALL(Calc!$B$2:$BB$61,51),"") | B56: =IF(A56="","",ROUND(MOD(A56,1)*1000,0)) | D56: =IF(A56="","",INT(A56)) | E56: =IF(B56="","",INDEX(Setup!$D$25:$D$84,B56)) | F56: =IF(B56="","",INDEX(Setup!$E$25:$E$84,B56)) | G56: =IF(B56="","",INDEX(Setup!$I$25:$I$84,B56)&"") | H56: =IF(B56="","",INDEX(Setup!$J$25:$J$84,B56)&"") | I56: =IF(B56="","",INDEX(Setup!$C$25:$C$84,B56)) | P56: =IF(A56="","",IF(K56<>"",K56,D56)) | Q56: =IF(A56="",0,IF(C56="✗",0,IF(OR(C56="✓",AND(Setup!$D$7="Yes",P56<=TODAY())),IF(L56<>"",L56,F56),0))) | R56: =IF(A56="","",IF(M56<>"",M56,G56)) | S56: =IF(A56="","",IF(N56<>"",N56,H56)) | T56: =IF(A56="","",IF(C56="✗","Skipped",IF(Q56>0,"Paid","Upcoming"))) | U56: =IF(A56="",0,IF(C56="✗",0,IF(L56<>"",L56,F56)))
A57: =IFERROR(SMALL(Calc!$B$2:$BB$61,52),"") | B57: =IF(A57="","",ROUND(MOD(A57,1)*1000,0)) | D57: =IF(A57="","",INT(A57)) | E57: =IF(B57="","",INDEX(Setup!$D$25:$D$84,B57)) | F57: =IF(B57="","",INDEX(Setup!$E$25:$E$84,B57)) | G57: =IF(B57="","",INDEX(Setup!$I$25:$I$84,B57)&"") | H57: =IF(B57="","",INDEX(Setup!$J$25:$J$84,B57)&"") | I57: =IF(B57="","",INDEX(Setup!$C$25:$C$84,B57)) | P57: =IF(A57="","",IF(K57<>"",K57,D57)) | Q57: =IF(A57="",0,IF(C57="✗",0,IF(OR(C57="✓",AND(Setup!$D$7="Yes",P57<=TODAY())),IF(L57<>"",L57,F57),0))) | R57: =IF(A57="","",IF(M57<>"",M57,G57)) | S57: =IF(A57="","",IF(N57<>"",N57,H57)) | T57: =IF(A57="","",IF(C57="✗","Skipped",IF(Q57>0,"Paid","Upcoming"))) | U57: =IF(A57="",0,IF(C57="✗",0,IF(L57<>"",L57,F57)))
A58: =IFERROR(SMALL(Calc!$B$2:$BB$61,53),"") | B58: =IF(A58="","",ROUND(MOD(A58,1)*1000,0)) | D58: =IF(A58="","",INT(A58)) | E58: =IF(B58="","",INDEX(Setup!$D$25:$D$84,B58)) | F58: =IF(B58="","",INDEX(Setup!$E$25:$E$84,B58)) | G58: =IF(B58="","",INDEX(Setup!$I$25:$I$84,B58)&"") | H58: =IF(B58="","",INDEX(Setup!$J$25:$J$84,B58)&"") | I58: =IF(B58="","",INDEX(Setup!$C$25:$C$84,B58)) | P58: =IF(A58="","",IF(K58<>"",K58,D58)) | Q58: =IF(A58="",0,IF(C58="✗",0,IF(OR(C58="✓",AND(Setup!$D$7="Yes",P58<=TODAY())),IF(L58<>"",L58,F58),0))) | R58: =IF(A58="","",IF(M58<>"",M58,G58)) | S58: =IF(A58="","",IF(N58<>"",N58,H58)) | T58: =IF(A58="","",IF(C58="✗","Skipped",IF(Q58>0,"Paid","Upcoming"))) | U58: =IF(A58="",0,IF(C58="✗",0,IF(L58<>"",L58,F58)))
A59: =IFERROR(SMALL(Calc!$B$2:$BB$61,54),"") | B59: =IF(A59="","",ROUND(MOD(A59,1)*1000,0)) | D59: =IF(A59="","",INT(A59)) | E59: =IF(B59="","",INDEX(Setup!$D$25:$D$84,B59)) | F59: =IF(B59="","",INDEX(Setup!$E$25:$E$84,B59)) | G59: =IF(B59="","",INDEX(Setup!$I$25:$I$84,B59)&"") | H59: =IF(B59="","",INDEX(Setup!$J$25:$J$84,B59)&"") | I59: =IF(B59="","",INDEX(Setup!$C$25:$C$84,B59)) | P59: =IF(A59="","",IF(K59<>"",K59,D59)) | Q59: =IF(A59="",0,IF(C59="✗",0,IF(OR(C59="✓",AND(Setup!$D$7="Yes",P59<=TODAY())),IF(L59<>"",L59,F59),0))) | R59: =IF(A59="","",IF(M59<>"",M59,G59)) | S59: =IF(A59="","",IF(N59<>"",N59,H59)) | T59: =IF(A59="","",IF(C59="✗","Skipped",IF(Q59>0,"Paid","Upcoming"))) | U59: =IF(A59="",0,IF(C59="✗",0,IF(L59<>"",L59,F59)))
A60: =IFERROR(SMALL(Calc!$B$2:$BB$61,55),"") | B60: =IF(A60="","",ROUND(MOD(A60,1)*1000,0)) | D60: =IF(A60="","",INT(A60)) | E60: =IF(B60="","",INDEX(Setup!$D$25:$D$84,B60)) | F60: =IF(B60="","",INDEX(Setup!$E$25:$E$84,B60)) | G60: =IF(B60="","",INDEX(Setup!$I$25:$I$84,B60)&"") | H60: =IF(B60="","",INDEX(Setup!$J$25:$J$84,B60)&"") | I60: =IF(B60="","",INDEX(Setup!$C$25:$C$84,B60)) | P60: =IF(A60="","",IF(K60<>"",K60,D60)) | Q60: =IF(A60="",0,IF(C60="✗",0,IF(OR(C60="✓",AND(Setup!$D$7="Yes",P60<=TODAY())),IF(L60<>"",L60,F60),0))) | R60: =IF(A60="","",IF(M60<>"",M60,G60)) | S60: =IF(A60="","",IF(N60<>"",N60,H60)) | T60: =IF(A60="","",IF(C60="✗","Skipped",IF(Q60>0,"Paid","Upcoming"))) | U60: =IF(A60="",0,IF(C60="✗",0,IF(L60<>"",L60,F60)))
A61: =IFERROR(SMALL(Calc!$B$2:$BB$61,56),"") | B61: =IF(A61="","",ROUND(MOD(A61,1)*1000,0)) | D61: =IF(A61="","",INT(A61)) | E61: =IF(B61="","",INDEX(Setup!$D$25:$D$84,B61)) | F61: =IF(B61="","",INDEX(Setup!$E$25:$E$84,B61)) | G61: =IF(B61="","",INDEX(Setup!$I$25:$I$84,B61)&"") | H61: =IF(B61="","",INDEX(Setup!$J$25:$J$84,B61)&"") | I61: =IF(B61="","",INDEX(Setup!$C$25:$C$84,B61)) | P61: =IF(A61="","",IF(K61<>"",K61,D61)) | Q61: =IF(A61="",0,IF(C61="✗",0,IF(OR(C61="✓",AND(Setup!$D$7="Yes",P61<=TODAY())),IF(L61<>"",L61,F61),0))) | R61: =IF(A61="","",IF(M61<>"",M61,G61)) | S61: =IF(A61="","",IF(N61<>"",N61,H61)) | T61: =IF(A61="","",IF(C61="✗","Skipped",IF(Q61>0,"Paid","Upcoming"))) | U61: =IF(A61="",0,IF(C61="✗",0,IF(L61<>"",L61,F61)))
A62: =IFERROR(SMALL(Calc!$B$2:$BB$61,57),"") | B62: =IF(A62="","",ROUND(MOD(A62,1)*1000,0)) | D62: =IF(A62="","",INT(A62)) | E62: =IF(B62="","",INDEX(Setup!$D$25:$D$84,B62)) | F62: =IF(B62="","",INDEX(Setup!$E$25:$E$84,B62)) | G62: =IF(B62="","",INDEX(Setup!$I$25:$I$84,B62)&"") | H62: =IF(B62="","",INDEX(Setup!$J$25:$J$84,B62)&"") | I62: =IF(B62="","",INDEX(Setup!$C$25:$C$84,B62)) | P62: =IF(A62="","",IF(K62<>"",K62,D62)) | Q62: =IF(A62="",0,IF(C62="✗",0,IF(OR(C62="✓",AND(Setup!$D$7="Yes",P62<=TODAY())),IF(L62<>"",L62,F62),0))) | R62: =IF(A62="","",IF(M62<>"",M62,G62)) | S62: =IF(A62="","",IF(N62<>"",N62,H62)) | T62: =IF(A62="","",IF(C62="✗","Skipped",IF(Q62>0,"Paid","Upcoming"))) | U62: =IF(A62="",0,IF(C62="✗",0,IF(L62<>"",L62,F62)))
A63: =IFERROR(SMALL(Calc!$B$2:$BB$61,58),"") | B63: =IF(A63="","",ROUND(MOD(A63,1)*1000,0)) | D63: =IF(A63="","",INT(A63)) | E63: =IF(B63="","",INDEX(Setup!$D$25:$D$84,B63)) | F63: =IF(B63="","",INDEX(Setup!$E$25:$E$84,B63)) | G63: =IF(B63="","",INDEX(Setup!$I$25:$I$84,B63)&"") | H63: =IF(B63="","",INDEX(Setup!$J$25:$J$84,B63)&"") | I63: =IF(B63="","",INDEX(Setup!$C$25:$C$84,B63)) | P63: =IF(A63="","",IF(K63<>"",K63,D63)) | Q63: =IF(A63="",0,IF(C63="✗",0,IF(OR(C63="✓",AND(Setup!$D$7="Yes",P63<=TODAY())),IF(L63<>"",L63,F63),0))) | R63: =IF(A63="","",IF(M63<>"",M63,G63)) | S63: =IF(A63="","",IF(N63<>"",N63,H63)) | T63: =IF(A63="","",IF(C63="✗","Skipped",IF(Q63>0,"Paid","Upcoming"))) | U63: =IF(A63="",0,IF(C63="✗",0,IF(L63<>"",L63,F63)))
A64: =IFERROR(SMALL(Calc!$B$2:$BB$61,59),"") | B64: =IF(A64="","",ROUND(MOD(A64,1)*1000,0)) | D64: =IF(A64="","",INT(A64)) | E64: =IF(B64="","",INDEX(Setup!$D$25:$D$84,B64)) | F64: =IF(B64="","",INDEX(Setup!$E$25:$E$84,B64)) | G64: =IF(B64="","",INDEX(Setup!$I$25:$I$84,B64)&"") | H64: =IF(B64="","",INDEX(Setup!$J$25:$J$84,B64)&"") | I64: =IF(B64="","",INDEX(Setup!$C$25:$C$84,B64)) | P64: =IF(A64="","",IF(K64<>"",K64,D64)) | Q64: =IF(A64="",0,IF(C64="✗",0,IF(OR(C64="✓",AND(Setup!$D$7="Yes",P64<=TODAY())),IF(L64<>"",L64,F64),0))) | R64: =IF(A64="","",IF(M64<>"",M64,G64)) | S64: =IF(A64="","",IF(N64<>"",N64,H64)) | T64: =IF(A64="","",IF(C64="✗","Skipped",IF(Q64>0,"Paid","Upcoming"))) | U64: =IF(A64="",0,IF(C64="✗",0,IF(L64<>"",L64,F64)))
A65: =IFERROR(SMALL(Calc!$B$2:$BB$61,60),"") | B65: =IF(A65="","",ROUND(MOD(A65,1)*1000,0)) | D65: =IF(A65="","",INT(A65)) | E65: =IF(B65="","",INDEX(Setup!$D$25:$D$84,B65)) | F65: =IF(B65="","",INDEX(Setup!$E$25:$E$84,B65)) | G65: =IF(B65="","",INDEX(Setup!$I$25:$I$84,B65)&"") | H65: =IF(B65="","",INDEX(Setup!$J$25:$J$84,B65)&"") | I65: =IF(B65="","",INDEX(Setup!$C$25:$C$84,B65)) | P65: =IF(A65="","",IF(K65<>"",K65,D65)) | Q65: =IF(A65="",0,IF(C65="✗",0,IF(OR(C65="✓",AND(Setup!$D$7="Yes",P65<=TODAY())),IF(L65<>"",L65,F65),0))) | R65: =IF(A65="","",IF(M65<>"",M65,G65)) | S65: =IF(A65="","",IF(N65<>"",N65,H65)) | T65: =IF(A65="","",IF(C65="✗","Skipped",IF(Q65>0,"Paid","Upcoming"))) | U65: =IF(A65="",0,IF(C65="✗",0,IF(L65<>"",L65,F65)))
A66: =IFERROR(SMALL(Calc!$B$2:$BB$61,61),"") | B66: =IF(A66="","",ROUND(MOD(A66,1)*1000,0)) | D66: =IF(A66="","",INT(A66)) | E66: =IF(B66="","",INDEX(Setup!$D$25:$D$84,B66)) | F66: =IF(B66="","",INDEX(Setup!$E$25:$E$84,B66)) | G66: =IF(B66="","",INDEX(Setup!$I$25:$I$84,B66)&"") | H66: =IF(B66="","",INDEX(Setup!$J$25:$J$84,B66)&"") | I66: =IF(B66="","",INDEX(Setup!$C$25:$C$84,B66)) | P66: =IF(A66="","",IF(K66<>"",K66,D66)) | Q66: =IF(A66="",0,IF(C66="✗",0,IF(OR(C66="✓",AND(Setup!$D$7="Yes",P66<=TODAY())),IF(L66<>"",L66,F66),0))) | R66: =IF(A66="","",IF(M66<>"",M66,G66)) | S66: =IF(A66="","",IF(N66<>"",N66,H66)) | T66: =IF(A66="","",IF(C66="✗","Skipped",IF(Q66>0,"Paid","Upcoming"))) | U66: =IF(A66="",0,IF(C66="✗",0,IF(L66<>"",L66,F66)))
A67: =IFERROR(SMALL(Calc!$B$2:$BB$61,62),"") | B67: =IF(A67="","",ROUND(MOD(A67,1)*1000,0)) | D67: =IF(A67="","",INT(A67)) | E67: =IF(B67="","",INDEX(Setup!$D$25:$D$84,B67)) | F67: =IF(B67="","",INDEX(Setup!$E$25:$E$84,B67)) | G67: =IF(B67="","",INDEX(Setup!$I$25:$I$84,B67)&"") | H67: =IF(B67="","",INDEX(Setup!$J$25:$J$84,B67)&"") | I67: =IF(B67="","",INDEX(Setup!$C$25:$C$84,B67)) | P67: =IF(A67="","",IF(K67<>"",K67,D67)) | Q67: =IF(A67="",0,IF(C67="✗",0,IF(OR(C67="✓",AND(Setup!$D$7="Yes",P67<=TODAY())),IF(L67<>"",L67,F67),0))) | R67: =IF(A67="","",IF(M67<>"",M67,G67)) | S67: =IF(A67="","",IF(N67<>"",N67,H67)) | T67: =IF(A67="","",IF(C67="✗","Skipped",IF(Q67>0,"Paid","Upcoming"))) | U67: =IF(A67="",0,IF(C67="✗",0,IF(L67<>"",L67,F67)))
A68: =IFERROR(SMALL(Calc!$B$2:$BB$61,63),"") | B68: =IF(A68="","",ROUND(MOD(A68,1)*1000,0)) | D68: =IF(A68="","",INT(A68)) | E68: =IF(B68="","",INDEX(Setup!$D$25:$D$84,B68)) | F68: =IF(B68="","",INDEX(Setup!$E$25:$E$84,B68)) | G68: =IF(B68="","",INDEX(Setup!$I$25:$I$84,B68)&"") | H68: =IF(B68="","",INDEX(Setup!$J$25:$J$84,B68)&"") | I68: =IF(B68="","",INDEX(Setup!$C$25:$C$84,B68)) | P68: =IF(A68="","",IF(K68<>"",K68,D68)) | Q68: =IF(A68="",0,IF(C68="✗",0,IF(OR(C68="✓",AND(Setup!$D$7="Yes",P68<=TODAY())),IF(L68<>"",L68,F68),0))) | R68: =IF(A68="","",IF(M68<>"",M68,G68)) | S68: =IF(A68="","",IF(N68<>"",N68,H68)) | T68: =IF(A68="","",IF(C68="✗","Skipped",IF(Q68>0,"Paid","Upcoming"))) | U68: =IF(A68="",0,IF(C68="✗",0,IF(L68<>"",L68,F68)))
A69: =IFERROR(SMALL(Calc!$B$2:$BB$61,64),"") | B69: =IF(A69="","",ROUND(MOD(A69,1)*1000,0)) | D69: =IF(A69="","",INT(A69)) | E69: =IF(B69="","",INDEX(Setup!$D$25:$D$84,B69)) | F69: =IF(B69="","",INDEX(Setup!$E$25:$E$84,B69)) | G69: =IF(B69="","",INDEX(Setup!$I$25:$I$84,B69)&"") | H69: =IF(B69="","",INDEX(Setup!$J$25:$J$84,B69)&"") | I69: =IF(B69="","",INDEX(Setup!$C$25:$C$84,B69)) | P69: =IF(A69="","",IF(K69<>"",K69,D69)) | Q69: =IF(A69="",0,IF(C69="✗",0,IF(OR(C69="✓",AND(Setup!$D$7="Yes",P69<=TODAY())),IF(L69<>"",L69,F69),0))) | R69: =IF(A69="","",IF(M69<>"",M69,G69)) | S69: =IF(A69="","",IF(N69<>"",N69,H69)) | T69: =IF(A69="","",IF(C69="✗","Skipped",IF(Q69>0,"Paid","Upcoming"))) | U69: =IF(A69="",0,IF(C69="✗",0,IF(L69<>"",L69,F69)))
A70: =IFERROR(SMALL(Calc!$B$2:$BB$61,65),"") | B70: =IF(A70="","",ROUND(MOD(A70,1)*1000,0)) | D70: =IF(A70="","",INT(A70)) | E70: =IF(B70="","",INDEX(Setup!$D$25:$D$84,B70)) | F70: =IF(B70="","",INDEX(Setup!$E$25:$E$84,B70)) | G70: =IF(B70="","",INDEX(Setup!$I$25:$I$84,B70)&"") | H70: =IF(B70="","",INDEX(Setup!$J$25:$J$84,B70)&"") | I70: =IF(B70="","",INDEX(Setup!$C$25:$C$84,B70)) | P70: =IF(A70="","",IF(K70<>"",K70,D70)) | Q70: =IF(A70="",0,IF(C70="✗",0,IF(OR(C70="✓",AND(Setup!$D$7="Yes",P70<=TODAY())),IF(L70<>"",L70,F70),0))) | R70: =IF(A70="","",IF(M70<>"",M70,G70)) | S70: =IF(A70="","",IF(N70<>"",N70,H70)) | T70: =IF(A70="","",IF(C70="✗","Skipped",IF(Q70>0,"Paid","Upcoming"))) | U70: =IF(A70="",0,IF(C70="✗",0,IF(L70<>"",L70,F70)))
A71: =IFERROR(SMALL(Calc!$B$2:$BB$61,66),"") | B71: =IF(A71="","",ROUND(MOD(A71,1)*1000,0)) | D71: =IF(A71="","",INT(A71)) | E71: =IF(B71="","",INDEX(Setup!$D$25:$D$84,B71)) | F71: =IF(B71="","",INDEX(Setup!$E$25:$E$84,B71)) | G71: =IF(B71="","",INDEX(Setup!$I$25:$I$84,B71)&"") | H71: =IF(B71="","",INDEX(Setup!$J$25:$J$84,B71)&"") | I71: =IF(B71="","",INDEX(Setup!$C$25:$C$84,B71)) | P71: =IF(A71="","",IF(K71<>"",K71,D71)) | Q71: =IF(A71="",0,IF(C71="✗",0,IF(OR(C71="✓",AND(Setup!$D$7="Yes",P71<=TODAY())),IF(L71<>"",L71,F71),0))) | R71: =IF(A71="","",IF(M71<>"",M71,G71)) | S71: =IF(A71="","",IF(N71<>"",N71,H71)) | T71: =IF(A71="","",IF(C71="✗","Skipped",IF(Q71>0,"Paid","Upcoming"))) | U71: =IF(A71="",0,IF(C71="✗",0,IF(L71<>"",L71,F71)))
A72: =IFERROR(SMALL(Calc!$B$2:$BB$61,67),"") | B72: =IF(A72="","",ROUND(MOD(A72,1)*1000,0)) | D72: =IF(A72="","",INT(A72)) | E72: =IF(B72="","",INDEX(Setup!$D$25:$D$84,B72)) | F72: =IF(B72="","",INDEX(Setup!$E$25:$E$84,B72)) | G72: =IF(B72="","",INDEX(Setup!$I$25:$I$84,B72)&"") | H72: =IF(B72="","",INDEX(Setup!$J$25:$J$84,B72)&"") | I72: =IF(B72="","",INDEX(Setup!$C$25:$C$84,B72)) | P72: =IF(A72="","",IF(K72<>"",K72,D72)) | Q72: =IF(A72="",0,IF(C72="✗",0,IF(OR(C72="✓",AND(Setup!$D$7="Yes",P72<=TODAY())),IF(L72<>"",L72,F72),0))) | R72: =IF(A72="","",IF(M72<>"",M72,G72)) | S72: =IF(A72="","",IF(N72<>"",N72,H72)) | T72: =IF(A72="","",IF(C72="✗","Skipped",IF(Q72>0,"Paid","Upcoming"))) | U72: =IF(A72="",0,IF(C72="✗",0,IF(L72<>"",L72,F72)))
A73: =IFERROR(SMALL(Calc!$B$2:$BB$61,68),"") | B73: =IF(A73="","",ROUND(MOD(A73,1)*1000,0)) | D73: =IF(A73="","",INT(A73)) | E73: =IF(B73="","",INDEX(Setup!$D$25:$D$84,B73)) | F73: =IF(B73="","",INDEX(Setup!$E$25:$E$84,B73)) | G73: =IF(B73="","",INDEX(Setup!$I$25:$I$84,B73)&"") | H73: =IF(B73="","",INDEX(Setup!$J$25:$J$84,B73)&"") | I73: =IF(B73="","",INDEX(Setup!$C$25:$C$84,B73)) | P73: =IF(A73="","",IF(K73<>"",K73,D73)) | Q73: =IF(A73="",0,IF(C73="✗",0,IF(OR(C73="✓",AND(Setup!$D$7="Yes",P73<=TODAY())),IF(L73<>"",L73,F73),0))) | R73: =IF(A73="","",IF(M73<>"",M73,G73)) | S73: =IF(A73="","",IF(N73<>"",N73,H73)) | T73: =IF(A73="","",IF(C73="✗","Skipped",IF(Q73>0,"Paid","Upcoming"))) | U73: =IF(A73="",0,IF(C73="✗",0,IF(L73<>"",L73,F73)))
A74: =IFERROR(SMALL(Calc!$B$2:$BB$61,69),"") | B74: =IF(A74="","",ROUND(MOD(A74,1)*1000,0)) | D74: =IF(A74="","",INT(A74)) | E74: =IF(B74="","",INDEX(Setup!$D$25:$D$84,B74)) | F74: =IF(B74="","",INDEX(Setup!$E$25:$E$84,B74)) | G74: =IF(B74="","",INDEX(Setup!$I$25:$I$84,B74)&"") | H74: =IF(B74="","",INDEX(Setup!$J$25:$J$84,B74)&"") | I74: =IF(B74="","",INDEX(Setup!$C$25:$C$84,B74)) | P74: =IF(A74="","",IF(K74<>"",K74,D74)) | Q74: =IF(A74="",0,IF(C74="✗",0,IF(OR(C74="✓",AND(Setup!$D$7="Yes",P74<=TODAY())),IF(L74<>"",L74,F74),0))) | R74: =IF(A74="","",IF(M74<>"",M74,G74)) | S74: =IF(A74="","",IF(N74<>"",N74,H74)) | T74: =IF(A74="","",IF(C74="✗","Skipped",IF(Q74>0,"Paid","Upcoming"))) | U74: =IF(A74="",0,IF(C74="✗",0,IF(L74<>"",L74,F74)))
A75: =IFERROR(SMALL(Calc!$B$2:$BB$61,70),"") | B75: =IF(A75="","",ROUND(MOD(A75,1)*1000,0)) | D75: =IF(A75="","",INT(A75)) | E75: =IF(B75="","",INDEX(Setup!$D$25:$D$84,B75)) | F75: =IF(B75="","",INDEX(Setup!$E$25:$E$84,B75)) | G75: =IF(B75="","",INDEX(Setup!$I$25:$I$84,B75)&"") | H75: =IF(B75="","",INDEX(Setup!$J$25:$J$84,B75)&"") | I75: =IF(B75="","",INDEX(Setup!$C$25:$C$84,B75)) | P75: =IF(A75="","",IF(K75<>"",K75,D75)) | Q75: =IF(A75="",0,IF(C75="✗",0,IF(OR(C75="✓",AND(Setup!$D$7="Yes",P75<=TODAY())),IF(L75<>"",L75,F75),0))) | R75: =IF(A75="","",IF(M75<>"",M75,G75)) | S75: =IF(A75="","",IF(N75<>"",N75,H75)) | T75: =IF(A75="","",IF(C75="✗","Skipped",IF(Q75>0,"Paid","Upcoming"))) | U75: =IF(A75="",0,IF(C75="✗",0,IF(L75<>"",L75,F75)))
A76: =IFERROR(SMALL(Calc!$B$2:$BB$61,71),"") | B76: =IF(A76="","",ROUND(MOD(A76,1)*1000,0)) | D76: =IF(A76="","",INT(A76)) | E76: =IF(B76="","",INDEX(Setup!$D$25:$D$84,B76)) | F76: =IF(B76="","",INDEX(Setup!$E$25:$E$84,B76)) | G76: =IF(B76="","",INDEX(Setup!$I$25:$I$84,B76)&"") | H76: =IF(B76="","",INDEX(Setup!$J$25:$J$84,B76)&"") | I76: =IF(B76="","",INDEX(Setup!$C$25:$C$84,B76)) | P76: =IF(A76="","",IF(K76<>"",K76,D76)) | Q76: =IF(A76="",0,IF(C76="✗",0,IF(OR(C76="✓",AND(Setup!$D$7="Yes",P76<=TODAY())),IF(L76<>"",L76,F76),0))) | R76: =IF(A76="","",IF(M76<>"",M76,G76)) | S76: =IF(A76="","",IF(N76<>"",N76,H76)) | T76: =IF(A76="","",IF(C76="✗","Skipped",IF(Q76>0,"Paid","Upcoming"))) | U76: =IF(A76="",0,IF(C76="✗",0,IF(L76<>"",L76,F76)))
A77: =IFERROR(SMALL(Calc!$B$2:$BB$61,72),"") | B77: =IF(A77="","",ROUND(MOD(A77,1)*1000,0)) | D77: =IF(A77="","",INT(A77)) | E77: =IF(B77="","",INDEX(Setup!$D$25:$D$84,B77)) | F77: =IF(B77="","",INDEX(Setup!$E$25:$E$84,B77)) | G77: =IF(B77="","",INDEX(Setup!$I$25:$I$84,B77)&"") | H77: =IF(B77="","",INDEX(Setup!$J$25:$J$84,B77)&"") | I77: =IF(B77="","",INDEX(Setup!$C$25:$C$84,B77)) | P77: =IF(A77="","",IF(K77<>"",K77,D77)) | Q77: =IF(A77="",0,IF(C77="✗",0,IF(OR(C77="✓",AND(Setup!$D$7="Yes",P77<=TODAY())),IF(L77<>"",L77,F77),0))) | R77: =IF(A77="","",IF(M77<>"",M77,G77)) | S77: =IF(A77="","",IF(N77<>"",N77,H77)) | T77: =IF(A77="","",IF(C77="✗","Skipped",IF(Q77>0,"Paid","Upcoming"))) | U77: =IF(A77="",0,IF(C77="✗",0,IF(L77<>"",L77,F77)))
A78: =IFERROR(SMALL(Calc!$B$2:$BB$61,73),"") | B78: =IF(A78="","",ROUND(MOD(A78,1)*1000,0)) | D78: =IF(A78="","",INT(A78)) | E78: =IF(B78="","",INDEX(Setup!$D$25:$D$84,B78)) | F78: =IF(B78="","",INDEX(Setup!$E$25:$E$84,B78)) | G78: =IF(B78="","",INDEX(Setup!$I$25:$I$84,B78)&"") | H78: =IF(B78="","",INDEX(Setup!$J$25:$J$84,B78)&"") | I78: =IF(B78="","",INDEX(Setup!$C$25:$C$84,B78)) | P78: =IF(A78="","",IF(K78<>"",K78,D78)) | Q78: =IF(A78="",0,IF(C78="✗",0,IF(OR(C78="✓",AND(Setup!$D$7="Yes",P78<=TODAY())),IF(L78<>"",L78,F78),0))) | R78: =IF(A78="","",IF(M78<>"",M78,G78)) | S78: =IF(A78="","",IF(N78<>"",N78,H78)) | T78: =IF(A78="","",IF(C78="✗","Skipped",IF(Q78>0,"Paid","Upcoming"))) | U78: =IF(A78="",0,IF(C78="✗",0,IF(L78<>"",L78,F78)))
A79: =IFERROR(SMALL(Calc!$B$2:$BB$61,74),"") | B79: =IF(A79="","",ROUND(MOD(A79,1)*1000,0)) | D79: =IF(A79="","",INT(A79)) | E79: =IF(B79="","",INDEX(Setup!$D$25:$D$84,B79)) | F79: =IF(B79="","",INDEX(Setup!$E$25:$E$84,B79)) | G79: =IF(B79="","",INDEX(Setup!$I$25:$I$84,B79)&"") | H79: =IF(B79="","",INDEX(Setup!$J$25:$J$84,B79)&"") | I79: =IF(B79="","",INDEX(Setup!$C$25:$C$84,B79)) | P79: =IF(A79="","",IF(K79<>"",K79,D79)) | Q79: =IF(A79="",0,IF(C79="✗",0,IF(OR(C79="✓",AND(Setup!$D$7="Yes",P79<=TODAY())),IF(L79<>"",L79,F79),0))) | R79: =IF(A79="","",IF(M79<>"",M79,G79)) | S79: =IF(A79="","",IF(N79<>"",N79,H79)) | T79: =IF(A79="","",IF(C79="✗","Skipped",IF(Q79>0,"Paid","Upcoming"))) | U79: =IF(A79="",0,IF(C79="✗",0,IF(L79<>"",L79,F79)))
A80: =IFERROR(SMALL(Calc!$B$2:$BB$61,75),"") | B80: =IF(A80="","",ROUND(MOD(A80,1)*1000,0)) | D80: =IF(A80="","",INT(A80)) | E80: =IF(B80="","",INDEX(Setup!$D$25:$D$84,B80)) | F80: =IF(B80="","",INDEX(Setup!$E$25:$E$84,B80)) | G80: =IF(B80="","",INDEX(Setup!$I$25:$I$84,B80)&"") | H80: =IF(B80="","",INDEX(Setup!$J$25:$J$84,B80)&"") | I80: =IF(B80="","",INDEX(Setup!$C$25:$C$84,B80)) | P80: =IF(A80="","",IF(K80<>"",K80,D80)) | Q80: =IF(A80="",0,IF(C80="✗",0,IF(OR(C80="✓",AND(Setup!$D$7="Yes",P80<=TODAY())),IF(L80<>"",L80,F80),0))) | R80: =IF(A80="","",IF(M80<>"",M80,G80)) | S80: =IF(A80="","",IF(N80<>"",N80,H80)) | T80: =IF(A80="","",IF(C80="✗","Skipped",IF(Q80>0,"Paid","Upcoming"))) | U80: =IF(A80="",0,IF(C80="✗",0,IF(L80<>"",L80,F80)))
A81: =IFERROR(SMALL(Calc!$B$2:$BB$61,76),"") | B81: =IF(A81="","",ROUND(MOD(A81,1)*1000,0)) | D81: =IF(A81="","",INT(A81)) | E81: =IF(B81="","",INDEX(Setup!$D$25:$D$84,B81)) | F81: =IF(B81="","",INDEX(Setup!$E$25:$E$84,B81)) | G81: =IF(B81="","",INDEX(Setup!$I$25:$I$84,B81)&"") | H81: =IF(B81="","",INDEX(Setup!$J$25:$J$84,B81)&"") | I81: =IF(B81="","",INDEX(Setup!$C$25:$C$84,B81)) | P81: =IF(A81="","",IF(K81<>"",K81,D81)) | Q81: =IF(A81="",0,IF(C81="✗",0,IF(OR(C81="✓",AND(Setup!$D$7="Yes",P81<=TODAY())),IF(L81<>"",L81,F81),0))) | R81: =IF(A81="","",IF(M81<>"",M81,G81)) | S81: =IF(A81="","",IF(N81<>"",N81,H81)) | T81: =IF(A81="","",IF(C81="✗","Skipped",IF(Q81>0,"Paid","Upcoming"))) | U81: =IF(A81="",0,IF(C81="✗",0,IF(L81<>"",L81,F81)))
A82: =IFERROR(SMALL(Calc!$B$2:$BB$61,77),"") | B82: =IF(A82="","",ROUND(MOD(A82,1)*1000,0)) | D82: =IF(A82="","",INT(A82)) | E82: =IF(B82="","",INDEX(Setup!$D$25:$D$84,B82)) | F82: =IF(B82="","",INDEX(Setup!$E$25:$E$84,B82)) | G82: =IF(B82="","",INDEX(Setup!$I$25:$I$84,B82)&"") | H82: =IF(B82="","",INDEX(Setup!$J$25:$J$84,B82)&"") | I82: =IF(B82="","",INDEX(Setup!$C$25:$C$84,B82)) | P82: =IF(A82="","",IF(K82<>"",K82,D82)) | Q82: =IF(A82="",0,IF(C82="✗",0,IF(OR(C82="✓",AND(Setup!$D$7="Yes",P82<=TODAY())),IF(L82<>"",L82,F82),0))) | R82: =IF(A82="","",IF(M82<>"",M82,G82)) | S82: =IF(A82="","",IF(N82<>"",N82,H82)) | T82: =IF(A82="","",IF(C82="✗","Skipped",IF(Q82>0,"Paid","Upcoming"))) | U82: =IF(A82="",0,IF(C82="✗",0,IF(L82<>"",L82,F82)))
A83: =IFERROR(SMALL(Calc!$B$2:$BB$61,78),"") | B83: =IF(A83="","",ROUND(MOD(A83,1)*1000,0)) | D83: =IF(A83="","",INT(A83)) | E83: =IF(B83="","",INDEX(Setup!$D$25:$D$84,B83)) | F83: =IF(B83="","",INDEX(Setup!$E$25:$E$84,B83)) | G83: =IF(B83="","",INDEX(Setup!$I$25:$I$84,B83)&"") | H83: =IF(B83="","",INDEX(Setup!$J$25:$J$84,B83)&"") | I83: =IF(B83="","",INDEX(Setup!$C$25:$C$84,B83)) | P83: =IF(A83="","",IF(K83<>"",K83,D83)) | Q83: =IF(A83="",0,IF(C83="✗",0,IF(OR(C83="✓",AND(Setup!$D$7="Yes",P83<=TODAY())),IF(L83<>"",L83,F83),0))) | R83: =IF(A83="","",IF(M83<>"",M83,G83)) | S83: =IF(A83="","",IF(N83<>"",N83,H83)) | T83: =IF(A83="","",IF(C83="✗","Skipped",IF(Q83>0,"Paid","Upcoming"))) | U83: =IF(A83="",0,IF(C83="✗",0,IF(L83<>"",L83,F83)))
A84: =IFERROR(SMALL(Calc!$B$2:$BB$61,79),"") | B84: =IF(A84="","",ROUND(MOD(A84,1)*1000,0)) | D84: =IF(A84="","",INT(A84)) | E84: =IF(B84="","",INDEX(Setup!$D$25:$D$84,B84)) | F84: =IF(B84="","",INDEX(Setup!$E$25:$E$84,B84)) | G84: =IF(B84="","",INDEX(Setup!$I$25:$I$84,B84)&"") | H84: =IF(B84="","",INDEX(Setup!$J$25:$J$84,B84)&"") | I84: =IF(B84="","",INDEX(Setup!$C$25:$C$84,B84)) | P84: =IF(A84="","",IF(K84<>"",K84,D84)) | Q84: =IF(A84="",0,IF(C84="✗",0,IF(OR(C84="✓",AND(Setup!$D$7="Yes",P84<=TODAY())),IF(L84<>"",L84,F84),0))) | R84: =IF(A84="","",IF(M84<>"",M84,G84)) | S84: =IF(A84="","",IF(N84<>"",N84,H84)) | T84: =IF(A84="","",IF(C84="✗","Skipped",IF(Q84>0,"Paid","Upcoming"))) | U84: =IF(A84="",0,IF(C84="✗",0,IF(L84<>"",L84,F84)))
A85: =IFERROR(SMALL(Calc!$B$2:$BB$61,80),"") | B85: =IF(A85="","",ROUND(MOD(A85,1)*1000,0)) | D85: =IF(A85="","",INT(A85)) | E85: =IF(B85="","",INDEX(Setup!$D$25:$D$84,B85)) | F85: =IF(B85="","",INDEX(Setup!$E$25:$E$84,B85)) | G85: =IF(B85="","",INDEX(Setup!$I$25:$I$84,B85)&"") | H85: =IF(B85="","",INDEX(Setup!$J$25:$J$84,B85)&"") | I85: =IF(B85="","",INDEX(Setup!$C$25:$C$84,B85)) | P85: =IF(A85="","",IF(K85<>"",K85,D85)) | Q85: =IF(A85="",0,IF(C85="✗",0,IF(OR(C85="✓",AND(Setup!$D$7="Yes",P85<=TODAY())),IF(L85<>"",L85,F85),0))) | R85: =IF(A85="","",IF(M85<>"",M85,G85)) | S85: =IF(A85="","",IF(N85<>"",N85,H85)) | T85: =IF(A85="","",IF(C85="✗","Skipped",IF(Q85>0,"Paid","Upcoming"))) | U85: =IF(A85="",0,IF(C85="✗",0,IF(L85<>"",L85,F85)))
A86: =IFERROR(SMALL(Calc!$B$2:$BB$61,81),"") | B86: =IF(A86="","",ROUND(MOD(A86,1)*1000,0)) | D86: =IF(A86="","",INT(A86)) | E86: =IF(B86="","",INDEX(Setup!$D$25:$D$84,B86)) | F86: =IF(B86="","",INDEX(Setup!$E$25:$E$84,B86)) | G86: =IF(B86="","",INDEX(Setup!$I$25:$I$84,B86)&"") | H86: =IF(B86="","",INDEX(Setup!$J$25:$J$84,B86)&"") | I86: =IF(B86="","",INDEX(Setup!$C$25:$C$84,B86)) | P86: =IF(A86="","",IF(K86<>"",K86,D86)) | Q86: =IF(A86="",0,IF(C86="✗",0,IF(OR(C86="✓",AND(Setup!$D$7="Yes",P86<=TODAY())),IF(L86<>"",L86,F86),0))) | R86: =IF(A86="","",IF(M86<>"",M86,G86)) | S86: =IF(A86="","",IF(N86<>"",N86,H86)) | T86: =IF(A86="","",IF(C86="✗","Skipped",IF(Q86>0,"Paid","Upcoming"))) | U86: =IF(A86="",0,IF(C86="✗",0,IF(L86<>"",L86,F86)))
A87: =IFERROR(SMALL(Calc!$B$2:$BB$61,82),"") | B87: =IF(A87="","",ROUND(MOD(A87,1)*1000,0)) | D87: =IF(A87="","",INT(A87)) | E87: =IF(B87="","",INDEX(Setup!$D$25:$D$84,B87)) | F87: =IF(B87="","",INDEX(Setup!$E$25:$E$84,B87)) | G87: =IF(B87="","",INDEX(Setup!$I$25:$I$84,B87)&"") | H87: =IF(B87="","",INDEX(Setup!$J$25:$J$84,B87)&"") | I87: =IF(B87="","",INDEX(Setup!$C$25:$C$84,B87)) | P87: =IF(A87="","",IF(K87<>"",K87,D87)) | Q87: =IF(A87="",0,IF(C87="✗",0,IF(OR(C87="✓",AND(Setup!$D$7="Yes",P87<=TODAY())),IF(L87<>"",L87,F87),0))) | R87: =IF(A87="","",IF(M87<>"",M87,G87)) | S87: =IF(A87="","",IF(N87<>"",N87,H87)) | T87: =IF(A87="","",IF(C87="✗","Skipped",IF(Q87>0,"Paid","Upcoming"))) | U87: =IF(A87="",0,IF(C87="✗",0,IF(L87<>"",L87,F87)))
A88: =IFERROR(SMALL(Calc!$B$2:$BB$61,83),"") | B88: =IF(A88="","",ROUND(MOD(A88,1)*1000,0)) | D88: =IF(A88="","",INT(A88)) | E88: =IF(B88="","",INDEX(Setup!$D$25:$D$84,B88)) | F88: =IF(B88="","",INDEX(Setup!$E$25:$E$84,B88)) | G88: =IF(B88="","",INDEX(Setup!$I$25:$I$84,B88)&"") | H88: =IF(B88="","",INDEX(Setup!$J$25:$J$84,B88)&"") | I88: =IF(B88="","",INDEX(Setup!$C$25:$C$84,B88)) | P88: =IF(A88="","",IF(K88<>"",K88,D88)) | Q88: =IF(A88="",0,IF(C88="✗",0,IF(OR(C88="✓",AND(Setup!$D$7="Yes",P88<=TODAY())),IF(L88<>"",L88,F88),0))) | R88: =IF(A88="","",IF(M88<>"",M88,G88)) | S88: =IF(A88="","",IF(N88<>"",N88,H88)) | T88: =IF(A88="","",IF(C88="✗","Skipped",IF(Q88>0,"Paid","Upcoming"))) | U88: =IF(A88="",0,IF(C88="✗",0,IF(L88<>"",L88,F88)))
A89: =IFERROR(SMALL(Calc!$B$2:$BB$61,84),"") | B89: =IF(A89="","",ROUND(MOD(A89,1)*1000,0)) | D89: =IF(A89="","",INT(A89)) | E89: =IF(B89="","",INDEX(Setup!$D$25:$D$84,B89)) | F89: =IF(B89="","",INDEX(Setup!$E$25:$E$84,B89)) | G89: =IF(B89="","",INDEX(Setup!$I$25:$I$84,B89)&"") | H89: =IF(B89="","",INDEX(Setup!$J$25:$J$84,B89)&"") | I89: =IF(B89="","",INDEX(Setup!$C$25:$C$84,B89)) | P89: =IF(A89="","",IF(K89<>"",K89,D89)) | Q89: =IF(A89="",0,IF(C89="✗",0,IF(OR(C89="✓",AND(Setup!$D$7="Yes",P89<=TODAY())),IF(L89<>"",L89,F89),0))) | R89: =IF(A89="","",IF(M89<>"",M89,G89)) | S89: =IF(A89="","",IF(N89<>"",N89,H89)) | T89: =IF(A89="","",IF(C89="✗","Skipped",IF(Q89>0,"Paid","Upcoming"))) | U89: =IF(A89="",0,IF(C89="✗",0,IF(L89<>"",L89,F89)))
A90: =IFERROR(SMALL(Calc!$B$2:$BB$61,85),"") | B90: =IF(A90="","",ROUND(MOD(A90,1)*1000,0)) | D90: =IF(A90="","",INT(A90)) | E90: =IF(B90="","",INDEX(Setup!$D$25:$D$84,B90)) | F90: =IF(B90="","",INDEX(Setup!$E$25:$E$84,B90)) | G90: =IF(B90="","",INDEX(Setup!$I$25:$I$84,B90)&"") | H90: =IF(B90="","",INDEX(Setup!$J$25:$J$84,B90)&"") | I90: =IF(B90="","",INDEX(Setup!$C$25:$C$84,B90)) | P90: =IF(A90="","",IF(K90<>"",K90,D90)) | Q90: =IF(A90="",0,IF(C90="✗",0,IF(OR(C90="✓",AND(Setup!$D$7="Yes",P90<=TODAY())),IF(L90<>"",L90,F90),0))) | R90: =IF(A90="","",IF(M90<>"",M90,G90)) | S90: =IF(A90="","",IF(N90<>"",N90,H90)) | T90: =IF(A90="","",IF(C90="✗","Skipped",IF(Q90>0,"Paid","Upcoming"))) | U90: =IF(A90="",0,IF(C90="✗",0,IF(L90<>"",L90,F90)))
A91: =IFERROR(SMALL(Calc!$B$2:$BB$61,86),"") | B91: =IF(A91="","",ROUND(MOD(A91,1)*1000,0)) | D91: =IF(A91="","",INT(A91)) | E91: =IF(B91="","",INDEX(Setup!$D$25:$D$84,B91)) | F91: =IF(B91="","",INDEX(Setup!$E$25:$E$84,B91)) | G91: =IF(B91="","",INDEX(Setup!$I$25:$I$84,B91)&"") | H91: =IF(B91="","",INDEX(Setup!$J$25:$J$84,B91)&"") | I91: =IF(B91="","",INDEX(Setup!$C$25:$C$84,B91)) | P91: =IF(A91="","",IF(K91<>"",K91,D91)) | Q91: =IF(A91="",0,IF(C91="✗",0,IF(OR(C91="✓",AND(Setup!$D$7="Yes",P91<=TODAY())),IF(L91<>"",L91,F91),0))) | R91: =IF(A91="","",IF(M91<>"",M91,G91)) | S91: =IF(A91="","",IF(N91<>"",N91,H91)) | T91: =IF(A91="","",IF(C91="✗","Skipped",IF(Q91>0,"Paid","Upcoming"))) | U91: =IF(A91="",0,IF(C91="✗",0,IF(L91<>"",L91,F91)))
A92: =IFERROR(SMALL(Calc!$B$2:$BB$61,87),"") | B92: =IF(A92="","",ROUND(MOD(A92,1)*1000,0)) | D92: =IF(A92="","",INT(A92)) | E92: =IF(B92="","",INDEX(Setup!$D$25:$D$84,B92)) | F92: =IF(B92="","",INDEX(Setup!$E$25:$E$84,B92)) | G92: =IF(B92="","",INDEX(Setup!$I$25:$I$84,B92)&"") | H92: =IF(B92="","",INDEX(Setup!$J$25:$J$84,B92)&"") | I92: =IF(B92="","",INDEX(Setup!$C$25:$C$84,B92)) | P92: =IF(A92="","",IF(K92<>"",K92,D92)) | Q92: =IF(A92="",0,IF(C92="✗",0,IF(OR(C92="✓",AND(Setup!$D$7="Yes",P92<=TODAY())),IF(L92<>"",L92,F92),0))) | R92: =IF(A92="","",IF(M92<>"",M92,G92)) | S92: =IF(A92="","",IF(N92<>"",N92,H92)) | T92: =IF(A92="","",IF(C92="✗","Skipped",IF(Q92>0,"Paid","Upcoming"))) | U92: =IF(A92="",0,IF(C92="✗",0,IF(L92<>"",L92,F92)))
A93: =IFERROR(SMALL(Calc!$B$2:$BB$61,88),"") | B93: =IF(A93="","",ROUND(MOD(A93,1)*1000,0)) | D93: =IF(A93="","",INT(A93)) | E93: =IF(B93="","",INDEX(Setup!$D$25:$D$84,B93)) | F93: =IF(B93="","",INDEX(Setup!$E$25:$E$84,B93)) | G93: =IF(B93="","",INDEX(Setup!$I$25:$I$84,B93)&"") | H93: =IF(B93="","",INDEX(Setup!$J$25:$J$84,B93)&"") | I93: =IF(B93="","",INDEX(Setup!$C$25:$C$84,B93)) | P93: =IF(A93="","",IF(K93<>"",K93,D93)) | Q93: =IF(A93="",0,IF(C93="✗",0,IF(OR(C93="✓",AND(Setup!$D$7="Yes",P93<=TODAY())),IF(L93<>"",L93,F93),0))) | R93: =IF(A93="","",IF(M93<>"",M93,G93)) | S93: =IF(A93="","",IF(N93<>"",N93,H93)) | T93: =IF(A93="","",IF(C93="✗","Skipped",IF(Q93>0,"Paid","Upcoming"))) | U93: =IF(A93="",0,IF(C93="✗",0,IF(L93<>"",L93,F93)))
A94: =IFERROR(SMALL(Calc!$B$2:$BB$61,89),"") | B94: =IF(A94="","",ROUND(MOD(A94,1)*1000,0)) | D94: =IF(A94="","",INT(A94)) | E94: =IF(B94="","",INDEX(Setup!$D$25:$D$84,B94)) | F94: =IF(B94="","",INDEX(Setup!$E$25:$E$84,B94)) | G94: =IF(B94="","",INDEX(Setup!$I$25:$I$84,B94)&"") | H94: =IF(B94="","",INDEX(Setup!$J$25:$J$84,B94)&"") | I94: =IF(B94="","",INDEX(Setup!$C$25:$C$84,B94)) | P94: =IF(A94="","",IF(K94<>"",K94,D94)) | Q94: =IF(A94="",0,IF(C94="✗",0,IF(OR(C94="✓",AND(Setup!$D$7="Yes",P94<=TODAY())),IF(L94<>"",L94,F94),0))) | R94: =IF(A94="","",IF(M94<>"",M94,G94)) | S94: =IF(A94="","",IF(N94<>"",N94,H94)) | T94: =IF(A94="","",IF(C94="✗","Skipped",IF(Q94>0,"Paid","Upcoming"))) | U94: =IF(A94="",0,IF(C94="✗",0,IF(L94<>"",L94,F94)))
A95: =IFERROR(SMALL(Calc!$B$2:$BB$61,90),"") | B95: =IF(A95="","",ROUND(MOD(A95,1)*1000,0)) | D95: =IF(A95="","",INT(A95)) | E95: =IF(B95="","",INDEX(Setup!$D$25:$D$84,B95)) | F95: =IF(B95="","",INDEX(Setup!$E$25:$E$84,B95)) | G95: =IF(B95="","",INDEX(Setup!$I$25:$I$84,B95)&"") | H95: =IF(B95="","",INDEX(Setup!$J$25:$J$84,B95)&"") | I95: =IF(B95="","",INDEX(Setup!$C$25:$C$84,B95)) | P95: =IF(A95="","",IF(K95<>"",K95,D95)) | Q95: =IF(A95="",0,IF(C95="✗",0,IF(OR(C95="✓",AND(Setup!$D$7="Yes",P95<=TODAY())),IF(L95<>"",L95,F95),0))) | R95: =IF(A95="","",IF(M95<>"",M95,G95)) | S95: =IF(A95="","",IF(N95<>"",N95,H95)) | T95: =IF(A95="","",IF(C95="✗","Skipped",IF(Q95>0,"Paid","Upcoming"))) | U95: =IF(A95="",0,IF(C95="✗",0,IF(L95<>"",L95,F95)))
A96: =IFERROR(SMALL(Calc!$B$2:$BB$61,91),"") | B96: =IF(A96="","",ROUND(MOD(A96,1)*1000,0)) | D96: =IF(A96="","",INT(A96)) | E96: =IF(B96="","",INDEX(Setup!$D$25:$D$84,B96)) | F96: =IF(B96="","",INDEX(Setup!$E$25:$E$84,B96)) | G96: =IF(B96="","",INDEX(Setup!$I$25:$I$84,B96)&"") | H96: =IF(B96="","",INDEX(Setup!$J$25:$J$84,B96)&"") | I96: =IF(B96="","",INDEX(Setup!$C$25:$C$84,B96)) | P96: =IF(A96="","",IF(K96<>"",K96,D96)) | Q96: =IF(A96="",0,IF(C96="✗",0,IF(OR(C96="✓",AND(Setup!$D$7="Yes",P96<=TODAY())),IF(L96<>"",L96,F96),0))) | R96: =IF(A96="","",IF(M96<>"",M96,G96)) | S96: =IF(A96="","",IF(N96<>"",N96,H96)) | T96: =IF(A96="","",IF(C96="✗","Skipped",IF(Q96>0,"Paid","Upcoming"))) | U96: =IF(A96="",0,IF(C96="✗",0,IF(L96<>"",L96,F96)))
A97: =IFERROR(SMALL(Calc!$B$2:$BB$61,92),"") | B97: =IF(A97="","",ROUND(MOD(A97,1)*1000,0)) | D97: =IF(A97="","",INT(A97)) | E97: =IF(B97="","",INDEX(Setup!$D$25:$D$84,B97)) | F97: =IF(B97="","",INDEX(Setup!$E$25:$E$84,B97)) | G97: =IF(B97="","",INDEX(Setup!$I$25:$I$84,B97)&"") | H97: =IF(B97="","",INDEX(Setup!$J$25:$J$84,B97)&"") | I97: =IF(B97="","",INDEX(Setup!$C$25:$C$84,B97)) | P97: =IF(A97="","",IF(K97<>"",K97,D97)) | Q97: =IF(A97="",0,IF(C97="✗",0,IF(OR(C97="✓",AND(Setup!$D$7="Yes",P97<=TODAY())),IF(L97<>"",L97,F97),0))) | R97: =IF(A97="","",IF(M97<>"",M97,G97)) | S97: =IF(A97="","",IF(N97<>"",N97,H97)) | T97: =IF(A97="","",IF(C97="✗","Skipped",IF(Q97>0,"Paid","Upcoming"))) | U97: =IF(A97="",0,IF(C97="✗",0,IF(L97<>"",L97,F97)))
A98: =IFERROR(SMALL(Calc!$B$2:$BB$61,93),"") | B98: =IF(A98="","",ROUND(MOD(A98,1)*1000,0)) | D98: =IF(A98="","",INT(A98)) | E98: =IF(B98="","",INDEX(Setup!$D$25:$D$84,B98)) | F98: =IF(B98="","",INDEX(Setup!$E$25:$E$84,B98)) | G98: =IF(B98="","",INDEX(Setup!$I$25:$I$84,B98)&"") | H98: =IF(B98="","",INDEX(Setup!$J$25:$J$84,B98)&"") | I98: =IF(B98="","",INDEX(Setup!$C$25:$C$84,B98)) | P98: =IF(A98="","",IF(K98<>"",K98,D98)) | Q98: =IF(A98="",0,IF(C98="✗",0,IF(OR(C98="✓",AND(Setup!$D$7="Yes",P98<=TODAY())),IF(L98<>"",L98,F98),0))) | R98: =IF(A98="","",IF(M98<>"",M98,G98)) | S98: =IF(A98="","",IF(N98<>"",N98,H98)) | T98: =IF(A98="","",IF(C98="✗","Skipped",IF(Q98>0,"Paid","Upcoming"))) | U98: =IF(A98="",0,IF(C98="✗",0,IF(L98<>"",L98,F98)))
A99: =IFERROR(SMALL(Calc!$B$2:$BB$61,94),"") | B99: =IF(A99="","",ROUND(MOD(A99,1)*1000,0)) | D99: =IF(A99="","",INT(A99)) | E99: =IF(B99="","",INDEX(Setup!$D$25:$D$84,B99)) | F99: =IF(B99="","",INDEX(Setup!$E$25:$E$84,B99)) | G99: =IF(B99="","",INDEX(Setup!$I$25:$I$84,B99)&"") | H99: =IF(B99="","",INDEX(Setup!$J$25:$J$84,B99)&"") | I99: =IF(B99="","",INDEX(Setup!$C$25:$C$84,B99)) | P99: =IF(A99="","",IF(K99<>"",K99,D99)) | Q99: =IF(A99="",0,IF(C99="✗",0,IF(OR(C99="✓",AND(Setup!$D$7="Yes",P99<=TODAY())),IF(L99<>"",L99,F99),0))) | R99: =IF(A99="","",IF(M99<>"",M99,G99)) | S99: =IF(A99="","",IF(N99<>"",N99,H99)) | T99: =IF(A99="","",IF(C99="✗","Skipped",IF(Q99>0,"Paid","Upcoming"))) | U99: =IF(A99="",0,IF(C99="✗",0,IF(L99<>"",L99,F99)))
A100: =IFERROR(SMALL(Calc!$B$2:$BB$61,95),"") | B100: =IF(A100="","",ROUND(MOD(A100,1)*1000,0)) | D100: =IF(A100="","",INT(A100)) | E100: =IF(B100="","",INDEX(Setup!$D$25:$D$84,B100)) | F100: =IF(B100="","",INDEX(Setup!$E$25:$E$84,B100)) | G100: =IF(B100="","",INDEX(Setup!$I$25:$I$84,B100)&"") | H100: =IF(B100="","",INDEX(Setup!$J$25:$J$84,B100)&"") | I100: =IF(B100="","",INDEX(Setup!$C$25:$C$84,B100)) | P100: =IF(A100="","",IF(K100<>"",K100,D100)) | Q100: =IF(A100="",0,IF(C100="✗",0,IF(OR(C100="✓",AND(Setup!$D$7="Yes",P100<=TODAY())),IF(L100<>"",L100,F100),0))) | R100: =IF(A100="","",IF(M100<>"",M100,G100)) | S100: =IF(A100="","",IF(N100<>"",N100,H100)) | T100: =IF(A100="","",IF(C100="✗","Skipped",IF(Q100>0,"Paid","Upcoming"))) | U100: =IF(A100="",0,IF(C100="✗",0,IF(L100<>"",L100,F100)))
A101: =IFERROR(SMALL(Calc!$B$2:$BB$61,96),"") | B101: =IF(A101="","",ROUND(MOD(A101,1)*1000,0)) | D101: =IF(A101="","",INT(A101)) | E101: =IF(B101="","",INDEX(Setup!$D$25:$D$84,B101)) | F101: =IF(B101="","",INDEX(Setup!$E$25:$E$84,B101)) | G101: =IF(B101="","",INDEX(Setup!$I$25:$I$84,B101)&"") | H101: =IF(B101="","",INDEX(Setup!$J$25:$J$84,B101)&"") | I101: =IF(B101="","",INDEX(Setup!$C$25:$C$84,B101)) | P101: =IF(A101="","",IF(K101<>"",K101,D101)) | Q101: =IF(A101="",0,IF(C101="✗",0,IF(OR(C101="✓",AND(Setup!$D$7="Yes",P101<=TODAY())),IF(L101<>"",L101,F101),0))) | R101: =IF(A101="","",IF(M101<>"",M101,G101)) | S101: =IF(A101="","",IF(N101<>"",N101,H101)) | T101: =IF(A101="","",IF(C101="✗","Skipped",IF(Q101>0,"Paid","Upcoming"))) | U101: =IF(A101="",0,IF(C101="✗",0,IF(L101<>"",L101,F101)))
...

Sheet Manual Log
B2: MANUAL LOG
B3: Log variable expenses, irregular income, one-off bills and money transfers here (or paste from your bank). Category 'Transfer' moves money between accounts only.
B4: MANUAL LOG
B5: DATE | C5: CATEGORY | D5: SUB-CATEGORY | E5: AMOUNT | F5: FROM ACCOUNT | G5: TO ACCOUNT | H5: DESCRIPTION
B6: 46024 | C6: Variable Exp | D6: Groceries | E6: 53.16 | F6: Checking 2 | G6: N/A
B7: 46024 | C7: Variable Exp | D7: Groceries | E7: 123.55 | F7: Credit Card 1 | G7: N/A
B8: 46024 | C8: Variable Exp | D8: Pets | E8: 68.29 | F8: Credit Card 1 | G8: N/A
B9: 46025 | C9: Variable Exp | D9: Groceries | E9: 67.86 | F9: Checking 2 | G9: N/A
B10: 46026 | C10: Variable Exp | D10: Eating Out | E10: 56.97 | F10: Credit Card 2 | G10: N/A
B11: 46027 | C11: Variable Exp | D11: School | E11: 113.99 | F11: Checking 2 | G11: N/A
B12: 46030 | C12: Variable Exp | D12: Eating Out | E12: 21.12 | F12: Credit Card 2 | G12: N/A
B13: 46030 | C13: Variable Exp | D13: Eating Out | E13: 60.25 | F13: Credit Card 1 | G13: N/A
B14: 46032 | C14: Variable Exp | D14: Eating Out | E14: 46.08 | F14: Credit Card 1 | G14: N/A
B15: 46033 | C15: Variable Exp | D15: Gifts | E15: 68.67 | F15: Checking 2 | G15: N/A
B16: 46033 | C16: Variable Exp | D16: Groceries | E16: 135.05 | F16: Checking 2 | G16: N/A
B17: 46033 | C17: Variable Exp | D17: Transportation | E17: 62.83 | F17: Checking 1 | G17: N/A
... B30: 46045 | C30: Variable Exp | D30: Transportation | E30: 65.09 | F30: Credit Card 1 | G30: N/A
B31: 46047 | C31: Transfer | E31: 300 | F31: Checking 2 | G31: Checking 1 | H31: Move to main account
B32: 46047 | C32: Variable Exp | D32: Entertainment | E32: 35.71 | F32: Checking 2 | G32: N/A
B33: 46047 | C33: Variable Exp | D33: Hair/Beauty | E33: 46.74 | F33: Checking 1 | G33: N/A
B34: 46049 | C34: Variable Exp | D34: Other | E34: 13.74 | F34: Checking 1 | G34: N/A
B35: 46054 | C35: Variable Exp | D35: Groceries | E35: 134.36 | F35: Checking 1 | G35: N/A
B36: 46055 | C36: Variable Exp | D36: Eating Out | E36: 32.62 | F36: Checking 1 | G36: N/A
B37: 46055 | C37: Variable Exp | D37: Groceries | E37: 114.46 | F37: Checking 1 | G37: N/A
B38: 46056 | C38: Variable Exp | D38: Eating Out | E38: 29.15 | F38: Checking 2 | G38: N/A
B39: 46058 | C39: Variable Exp | D39: Eating Out | E39: 67.47 | F39: Checking 2 | G39: N/A
B40: 46058 | C40: Variable Exp | D40: Shopping | E40: 34.54 | F40: Credit Card 2 | G40: N/A
B41: 46058 | C41: Variable Exp | D41: Transportation | E41: 61.07 | F41: Credit Card 1 | G41: N/A
B42: 46059 | C42: Variable Exp | D42: Groceries | E42: 103.04 | F42: Checking 2 | G42: N/A
B43: 46060 | C43: Variable Exp | D43: Pets | E43: 28.03 | F43: Credit Card 2 | G43: N/A
... B61: 46076 | C61: Variable Exp | D61: Shopping | E61: 72.76 | F61: Checking 1 | G61: N/A
B62: 46078 | C62: Transfer | E62: 300 | F62: Checking 2 | G62: Checking 1 | H62: Move to main account
B63: 46080 | C63: Variable Exp | D63: Eating Out | E63: 46.84 | F63: Checking 1 | G63: N/A
B64: 46082 | C64: Variable Exp | D64: Transportation | E64: 65.56 | F64: Checking 2 | G64: N/A
B65: 46085 | C65: Variable Exp | D65: Groceries | E65: 125.65 | F65: Checking 2 | G65: N/A
B66: 46086 | C66: Variable Exp | D66: Eating Out | E66: 64.23 | F66: Credit Card 1 | G66: N/A
B67: 46086 | C67: Variable Exp | D67: Groceries | E67: 54.71 | F67: Checking 1 | G67: N/A
B68: 46086 | C68: Variable Exp | D68: Groceries | E68: 105.27 | F68: Checking 1 | G68: N/A
B69: 46087 | C69: Variable Exp | D69: Eating Out | E69: 41.83 | F69: Credit Card 2 | G69: N/A
B70: 46088 | C70: Variable Exp | D70: School | E70: 73.44 | F70: Credit Card 1 | G70: N/A
B71: 46089 | C71: Variable Exp | D71: School | E71: 72.31 | F71: Checking 1 | G71: N/A
B72: 46090 | C72: Variable Exp | D72: Transportation | E72: 38.71 | F72: Checking 1 | G72: N/A
B73: 46093 | C73: Variable Exp | D73: Transportation | E73: 33.62 | F73: Credit Card 1 | G73: N/A
B74: 46094 | C74: Variable Exp | D74: Gifts | E74: 74.76 | F74: Credit Card 2 | G74: N/A
... B80: 46098 | C80: Variable Exp | D80: Entertainment | E80: 44.64 | F80: Credit Card 1 | G80: N/A
B81: 46099 | C81: Income | D81: Freelance Job | E81: 1150 | F81: N/A | G81: Checking 1 | H81: Logo project
B82: 46099 | C82: Variable Exp | D82: Shopping | E82: 87.28 | F82: Checking 1 | G82: N/A
B83: 46101 | C83: Variable Exp | D83: Groceries | E83: 79.6 | F83: Credit Card 1 | G83: N/A
B84: 46102 | C84: Variable Exp | D84: Shopping | E84: 50.65 | F84: Credit Card 2 | G84: N/A
B85: 46104 | C85: Variable Exp | D85: Eating Out | E85: 74.64 | F85: Checking 1 | G85: N/A
B86: 46105 | C86: Variable Exp | D86: Eating Out | E86: 35.74 | F86: Credit Card 2 | G86: N/A
B87: 46105 | C87: Variable Exp | D87: Entertainment | E87: 60.17 | F87: Credit Card 2 | G87: N/A
B88: 46106 | C88: Transfer | E88: 300 | F88: Checking 2 | G88: Checking 1 | H88: Move to main account
B89: 46106 | C89: Variable Exp | D89: Eating Out | E89: 53.38 | F89: Credit Card 1 | G89: N/A
B90: 46107 | C90: Variable Exp | D90: Hair/Beauty | E90: 49.29 | F90: Credit Card 1 | G90: N/A
B91: 46107 | C91: Variable Exp | D91: Other | E91: 35.43 | F91: Credit Card 1 | G91: N/A
B92: 46107 | C92: Variable Exp | D92: Shopping | E92: 52.53 | F92: Checking 2 | G92: N/A
B93: 46109 | C93: Variable Exp | D93: Groceries | E93: 64.76 | F93: Checking 2 | G93: N/A
B94: 46113 | C94: Variable Exp | D94: Eating Out | E94: 71.56 | F94: Credit Card 1 | G94: N/A
B95: 46113 | C95: Variable Exp | D95: Groceries | E95: 59.36 | F95: Checking 2 | G95: N/A
B96: 46114 | C96: Variable Exp | D96: Shopping | E96: 129.65 | F96: Checking 1 | G96: N/A
B97: 46118 | C97: Variable Exp | D97: Transportation | E97: 36.37 | F97: Credit Card 1 | G97: N/A
B98: 46120 | C98: Variable Exp | D98: Pets | E98: 33.61 | F98: Credit Card 1 | G98: N/A
B99: 46121 | C99: Variable Exp | D99: Eating Out | E99: 32.26 | F99: Credit Card 2 | G99: N/A
B100: 46126 | C100: Variable Exp | D100: Eating Out | E100: 84.1 | F100: Credit Card 2 | G100: N/A
... B113: 46136 | C113: Variable Exp | D113: Groceries | E113: 60.09 | F113: Credit Card 2 | G113: N/A
B114: 46137 | C114: Transfer | E114: 300 | F114: Checking 2 | G114: Checking 1 | H114: Move to main account
B115: 46137 | C115: Variable Exp | D115: Hair/Beauty | E115: 32.93 | F115: Checking 2 | G115: N/A
B116: 46137 | C116: Variable Exp | D116: Shopping | E116: 92.44 | F116: Checking 1 | G116: N/A
B117: 46138 | C117: Variable Exp | D117: Groceries | E117: 107.31 | F117: Checking 2 | G117: N/A
B118: 46138 | C118: Variable Exp | D118: Groceries | E118: 134.89 | F118: Checking 2 | G118: N/A
B119: 46138 | C119: Variable Exp | D119: School | E119: 99.88 | F119: Credit Card 1 | G119: N/A
B120: 46139 | C120: Variable Exp | D120: Eating Out | E120: 76.55 | F120: Credit Card 1 | G120: N/A
B121: 46139 | C121: Variable Exp | D121: Entertainment | E121: 65.89 | F121: Credit Card 2 | G121: N/A
B122: 46140 | C122: Variable Exp | D122: Transportation | E122: 49.81 | F122: Credit Card 2 | G122: N/A
B123: 46143 | C123: Variable Exp | D123: Entertainment | E123: 36.9 | F123: Checking 2 | G123: N/A
B124: 46143 | C124: Variable Exp | D124: Other | E124: 35.38 | F124: Checking 1 | G124: N/A
B125: 46144 | C125: Variable Exp | D125: Gifts | E125: 75.97 | F125: Credit Card 2 | G125: N/A
B126: 46145 | C126: Variable Exp | D126: Groceries | E126: 65.21 | F126: Checking 1 | G126: N/A
... B145: 46165 | C145: Variable Exp | D145: Shopping | E145: 74.63 | F145: Checking 2 | G145: N/A
B146: 46167 | C146: Transfer | E146: 300 | F146: Checking 2 | G146: Checking 1 | H146: Move to main account
B147: 46167 | C147: Variable Exp | D147: School | E147: 46.34 | F147: Credit Card 2 | G147: N/A
B148: 46168 | C148: Variable Exp | D148: Eating Out | E148: 26.2 | F148: Credit Card 2 | G148: N/A
B149: 46168 | C149: Variable Exp | D149: Transportation | E149: 40.28 | F149: Credit Card 1 | G149: N/A
B150: 46169 | C150: Variable Exp | D150: Groceries | E150: 87.52 | F150: Checking 2 | G150: N/A
B151: 46169 | C151: Variable Exp | D151: School | E151: 68 | F151: Checking 1 | G151: N/A
B152: 46175 | C152: Variable Exp | D152: Pets | E152: 45.68 | F152: Credit Card 2 | G152: N/A
B153: 46176 | C153: Variable Exp | D153: Groceries | E153: 70.12 | F153: Credit Card 1 | G153: N/A
B154: 46176 | C154: Variable Exp | D154: Groceries | E154: 102.78 | F154: Credit Card 2 | G154: N/A
B155: 46177 | C155: Variable Exp | D155: Shopping | E155: 100.71 | F155: Checking 2 | G155: N/A
B156: 46179 | C156: Variable Exp | D156: Groceries | E156: 69.88 | F156: Credit Card 2 | G156: N/A
B157: 46180 | C157: Variable Exp | D157: Eating Out | E157: 80.46 | F157: Checking 1 | G157: N/A
B158: 46180 | C158: Variable Exp | D158: Other | E158: 24.26 | F158: Credit Card 1 | G158: N/A
... B173: 46190 | C173: Variable Exp | D173: Shopping | E173: 79.6 | F173: Checking 2 | G173: N/A
B174: 46191 | C174: Income | D174: Freelance Job | E174: 1150 | F174: N/A | G174: Checking 1 | H174: Logo project
B175: 46193 | C175: Variable Exp | D175: School | E175: 51.8 | F175: Checking 1 | G175: N/A
B176: 46194 | C176: Variable Exp | D176: Transportation | E176: 63.34 | F176: Checking 1 | G176: N/A
B177: 46195 | C177: Variable Exp | D177: School | E177: 105.71 | F177: Checking 1 | G177: N/A
B178: 46195 | C178: Variable Exp | D178: Shopping | E178: 81.93 | F178: Checking 2 | G178: N/A
B179: 46197 | C179: Variable Exp | D179: Eating Out | E179: 51.88 | F179: Credit Card 2 | G179: N/A
...

Sheet Accounts
B2: ACCOUNTS
B3: Balances update from paid items in Payments + everything in the Manual Log.
B4: ACCOUNT BALANCES
B5: ACCOUNT | C5: OPENING | D5: MONEY IN | E5: MONEY OUT | F5: CURRENT BALANCE
B6: =IF(Setup!F6="","",Setup!F6) | C6: =IF(B6="","",Setup!G6) | D6: =IF(B6="","",SUMIFS(Payments!$Q$6:$Q$1205,Payments!$S$6:$S$1205,B6)+SUMIFS('Manual Log'!$E$6:$E$1005,'Manual Log'!$G$6:$G$1005,B6)) | E6: =IF(B6="","",SUMIFS(Payments!$Q$6:$Q$1205,Payments!$R$6:$R$1205,B6)+SUMIFS('Manual Log'!$E$6:$E$1005,'Manual Log'!$F$6:$F$1005,B6)) | F6: =IF(B6="","",C6+D6-E6)
B7: =IF(Setup!F7="","",Setup!F7) | C7: =IF(B7="","",Setup!G7) | D7: =IF(B7="","",SUMIFS(Payments!$Q$6:$Q$1205,Payments!$S$6:$S$1205,B7)+SUMIFS('Manual Log'!$E$6:$E$1005,'Manual Log'!$G$6:$G$1005,B7)) | E7: =IF(B7="","",SUMIFS(Payments!$Q$6:$Q$1205,Payments!$R$6:$R$1205,B7)+SUMIFS('Manual Log'!$E$6:$E$1005,'Manual Log'!$F$6:$F$1005,B7)) | F7: =IF(B7="","",C7+D7-E7)
B8: =IF(Setup!F8="","",Setup!F8) | C8: =IF(B8="","",Setup!G8) | D8: =IF(B8="","",SUMIFS(Payments!$Q$6:$Q$1205,Payments!$S$6:$S$1205,B8)+SUMIFS('Manual Log'!$E$6:$E$1005,'Manual Log'!$G$6:$G$1005,B8)) | E8: =IF(B8="","",SUMIFS(Payments!$Q$6:$Q$1205,Payments!$R$6:$R$1205,B8)+SUMIFS('Manual Log'!$E$6:$E$1005,'Manual Log'!$F$6:$F$1005,B8)) | F8: =IF(B8="","",C8+D8-E8)
B9: =IF(Setup!F9="","",Setup!F9) | C9: =IF(B9="","",Setup!G9) | D9: =IF(B9="","",SUMIFS(Payments!$Q$6:$Q$1205,Payments!$S$6:$S$1205,B9)+SUMIFS('Manual Log'!$E$6:$E$1005,'Manual Log'!$G$6:$G$1005,B9)) | E9: =IF(B9="","",SUMIFS(Payments!$Q$6:$Q$1205,Payments!$R$6:$R$1205,B9)+SUMIFS('Manual Log'!$E$6:$E$1005,'Manual Log'!$F$6:$F$1005,B9)) | F9: =IF(B9="","",C9+D9-E9)
B10: =IF(Setup!F10="","",Setup!F10) | C10: =IF(B10="","",Setup!G10) | D10: =IF(B10="","",SUMIFS(Payments!$Q$6:$Q$1205,Payments!$S$6:$S$1205,B10)+SUMIFS('Manual Log'!$E$6:$E$1005,'Manual Log'!$G$6:$G$1005,B10)) | E10: =IF(B10="","",SUMIFS(Payments!$Q$6:$Q$1205,Payments!$R$6:$R$1205,B10)+SUMIFS('Manual Log'!$E$6:$E$1005,'Manual Log'!$F$6:$F$1005,B10)) | F10: =IF(B10="","",C10+D10-E10)
B11: =IF(Setup!F11="","",Setup!F11) | C11: =IF(B11="","",Setup!G11) | D11: =IF(B11="","",SUMIFS(Payments!$Q$6:$Q$1205,Payments!$S$6:$S$1205,B11)+SUMIFS('Manual Log'!$E$6:$E$1005,'Manual Log'!$G$6:$G$1005,B11)) | E11: =IF(B11="","",SUMIFS(Payments!$Q$6:$Q$1205,Payments!$R$6:$R$1205,B11)+SUMIFS('Manual Log'!$E$6:$E$1005,'Manual Log'!$F$6:$F$1005,B11)) | F11: =IF(B11="","",C11+D11-E11)
B12: =IF(Setup!F12="","",Setup!F12) | C12: =IF(B12="","",Setup!G12) | D12: =IF(B12="","",SUMIFS(Payments!$Q$6:$Q$1205,Payments!$S$6:$S$1205,B12)+SUMIFS('Manual Log'!$E$6:$E$1005,'Manual Log'!$G$6:$G$1005,B12)) | E12: =IF(B12="","",SUMIFS(Payments!$Q$6:$Q$1205,Payments!$R$6:$R$1205,B12)+SUMIFS('Manual Log'!$E$6:$E$1005,'Manual Log'!$F$6:$F$1005,B12)) | F12: =IF(B12="","",C12+D12-E12)
B13: =IF(Setup!F13="","",Setup!F13) | C13: =IF(B13="","",Setup!G13) | D13: =IF(B13="","",SUMIFS(Payments!$Q$6:$Q$1205,Payments!$S$6:$S$1205,B13)+SUMIFS('Manual Log'!$E$6:$E$1005,'Manual Log'!$G$6:$G$1005,B13)) | E13: =IF(B13="","",SUMIFS(Payments!$Q$6:$Q$1205,Payments!$R$6:$R$1205,B13)+SUMIFS('Manual Log'!$E$6:$E$1005,'Manual Log'!$F$6:$F$1005,B13)) | F13: =IF(B13="","",C13+D13-E13)
B14: =IF(Setup!F14="","",Setup!F14) | C14: =IF(B14="","",Setup!G14) | D14: =IF(B14="","",SUMIFS(Payments!$Q$6:$Q$1205,Payments!$S$6:$S$1205,B14)+SUMIFS('Manual Log'!$E$6:$E$1005,'Manual Log'!$G$6:$G$1005,B14)) | E14: =IF(B14="","",SUMIFS(Payments!$Q$6:$Q$1205,Payments!$R$6:$R$1205,B14)+SUMIFS('Manual Log'!$E$6:$E$1005,'Manual Log'!$F$6:$F$1005,B14)) | F14: =IF(B14="","",C14+D14-E14)
B15: =IF(Setup!F15="","",Setup!F15) | C15: =IF(B15="","",Setup!G15) | D15: =IF(B15="","",SUMIFS(Payments!$Q$6:$Q$1205,Payments!$S$6:$S$1205,B15)+SUMIFS('Manual Log'!$E$6:$E$1005,'Manual Log'!$G$6:$G$1005,B15)) | E15: =IF(B15="","",SUMIFS(Payments!$Q$6:$Q$1205,Payments!$R$6:$R$1205,B15)+SUMIFS('Manual Log'!$E$6:$E$1005,'Manual Log'!$F$6:$F$1005,B15)) | F15: =IF(B15="","",C15+D15-E15)
B16: =IF(Setup!F16="","",Setup!F16) | C16: =IF(B16="","",Setup!G16) | D16: =IF(B16="","",SUMIFS(Payments!$Q$6:$Q$1205,Payments!$S$6:$S$1205,B16)+SUMIFS('Manual Log'!$E$6:$E$1005,'Manual Log'!$G$6:$G$1005,B16)) | E16: =IF(B16="","",SUMIFS(Payments!$Q$6:$Q$1205,Payments!$R$6:$R$1205,B16)+SUMIFS('Manual Log'!$E$6:$E$1005,'Manual Log'!$F$6:$F$1005,B16)) | F16: =IF(B16="","",C16+D16-E16)
B17: =IF(Setup!F17="","",Setup!F17) | C17: =IF(B17="","",Setup!G17) | D17: =IF(B17="","",SUMIFS(Payments!$Q$6:$Q$1205,Payments!$S$6:$S$1205,B17)+SUMIFS('Manual Log'!$E$6:$E$1005,'Manual Log'!$G$6:$G$1005,B17)) | E17: =IF(B17="","",SUMIFS(Payments!$Q$6:$Q$1205,Payments!$R$6:$R$1205,B17)+SUMIFS('Manual Log'!$E$6:$E$1005,'Manual Log'!$F$6:$F$1005,B17)) | F17: =IF(B17="","",C17+D17-E17)
B18: NET WORTH | C18: =SUM(C6:C17) | D18: =SUM(D6:D17) | E18: =SUM(E6:E17) | F18: =SUM(F6:F17)

Sheet Dashboard
B2: BUDGET DASHBOARD | G2: PERIOD SUMMARY | L2: INCOME | Q2: SAVINGS
B3: =UPPER(C5)&" DASHBOARD" | I3: BUDGET | J3: ACTUAL | L3: =J5 | N3: BUDGET | O3: PROGRESS | Q3: =J7 | S3: BUDGET | T3: PROGRESS
B4: =TEXT(C6,"d mmm yyyy")&" – "&TEXT(C7,"d mmm yyyy") | G4: Start balance | I4: =C10 | J4: =C10 | N4: =I5 | O4: =IFERROR(J5/I5,0) | S4: =I7 | T4: =IFERROR(J7/I7,0)
B5: Budget period | C5: Monthly | G5: + Total income | I5: =C14 | J5: =D14
B6: Start date | C6: 46266 | G6: – Total expenses | I6: =SUM(C16:C19) | J6: =SUM(D16:D19) | L6: EXPENSES | Q6: LEFT TO SPEND
B7: End date | C7: =IF(C5="Custom",IF(C8="",C6,C8),IF(C5="Weekly",C6+6,IF(C5="Bi-weekly",C6+13,IF(C5="4-weekly",C6+27,IF(C5="Monthly",EDATE(C6,1)-1,IF(C5="Quarterly",EDATE(C6,3)-1,IF(C5="6-month",EDATE(C6,6)-1,EDATE(C6,12)-1))))))) | G7: – Total savings | I7: =C15 | J7: =D15 | L7: =J6 | N7: BUDGET | O7: PROGRESS | Q7: =J9 | S7: BUDGET | T7: PROGRESS
B8: Custom end date | D8: ← only for 'Custom' | G8: End balance | I8: =I4+I5-I6-I7 | J8: =J4+J5-J6-J7 | N8: =I6 | O8: =IFERROR(J6/I6,0) | S8: =I9 | T8: =IFERROR(J9/I9,0)
B9: Start balance override | D9: ← leave blank to roll over | G9: Left to spend | I9: =I5-I6-I7 | J9: =J5-J6-J7
B10: Start balance | C10: =IF(C9<>"",C9,Setup!$D$6+SUMIFS(Payments!$Q$6:$Q$1205,Payments!$I$6:$I$1205,"Income",Payments!$P$6:$P$1205,">="&Setup!$D$5,Payments!$P$6:$P$1205,"<"&C6)-SUMIFS(Payments!$Q$6:$Q$1205,Payments!$I$6:$I$1205,"<>Income",Payments!$I$6:$I$1205,"<>Transfer",Payments!$P$6:$P$1205,">="&Setup!$D$5,Payments!$P$6:$P$1205,"<"&C6)+SUMIFS('Manual Log'!$E$6:$E$1005,'Manual Log'!$C$6:$C$1005,"Income",'Manual Log'!$B$6:$B$1005,">="&Setup!$D$5,'Manual Log'!$B$6:$B$1005,"<"&C6)-SUMIFS('Manual Log'!$E$6:$E$1005,'Manual Log'!$C$6:$C$1005,"<>Income",'Manual Log'!$C$6:$C$1005,"<>Transfer",'Manual Log'!$B$6:$B$1005,">="&Setup!$D$5,'Manual Log'!$B$6:$B$1005,"<"&C6))
B12: BUDGET vs ACTUAL | G12: BUDGET vs ACTUAL | L12: EXPENSES BREAKDOWN | Q12: VARIABLE EXPENSES
B13: CATEGORY | C13: BUDGET | D13: ACTUAL | E13: PROGRESS
B14: Income | C14: =C30 | D14: =D30 | E14: =IFERROR(D14/C14,0)
B15: Savings | C15: =H30 | D15: =I30 | E15: =IFERROR(D15/C15,0)
B16: Bills | C16: =M30 | D16: =N30 | E16: =IFERROR(D16/C16,0)
B17: Debt | C17: =R30 | D17: =S30 | E17: =IFERROR(D17/C17,0)
B18: Subscriptions | C18: =C51 | D18: =D51 | E18: =IFERROR(D18/C18,0)
B19: Variable Exp. | C19: =H51 | D19: =I51 | E19: =IFERROR(D19/C19,0)
B20: REMAINING BUDGET (expenses) | E20: =SUM(C16:C19)-SUM(D16:D19)
B22: Pink text = over budget (expenses) or below target (income & savings).
B23: Actual = paid items in Payments + Manual Log entries in this period.
B27: INCOME | G27: SAVINGS | L27: BILLS | Q27: DEBT
B28: =D30 | G28: =I30 | L28: =N30 | Q28: =S30
B29: SUB-CATEGORY | C29: BUDGET | D29: ACTUAL | E29: DIFF | G29: SUB-CATEGORY | H29: BUDGET | I29: ACTUAL | J29: DIFF | L29: SUB-CATEGORY | M29: BUDGET | N29: ACTUAL | O29: REMAINING | Q29: SUB-CATEGORY | R29: BUDGET | S29: ACTUAL | T29: REMAINING | V29: =MAX(1,ROUNDUP(($C$7-$C$6+1)/31,0))
B30: TOTAL | C30: =SUM(C31:C40) | D30: =SUM(D31:D40) | E30: =SUM(E31:E40) | G30: TOTAL | H30: =SUM(H31:H40) | I30: =SUM(I31:I40) | J30: =SUM(J31:J40) | L30: TOTAL | M30: =SUM(M31:M45) | N30: =SUM(N31:N45) | O30: =SUM(O31:O45) | Q30: TOTAL | R30: =SUM(R31:R40) | S30: =SUM(S31:S40) | T30: =SUM(T31:T40)
B31: =IF(AC31="","",INDEX(Setup!$D$25:$D$84,AC31)) | C31: =IF(AC31="","",COUNTIFS(INDEX(Calc!$B$2:$BB$61,AC31,0),">="&$C$6,INDEX(Calc!$B$2:$BB$61,AC31,0),"<"&($C$7+1))*INDEX(Setup!$E$25:$E$84,AC31)) | D31: =IF(B31="","",SUMIFS(Payments!$Q$6:$Q$1205,Payments!$I$6:$I$1205,"Income",Payments!$E$6:$E$1205,B31,Payments!$P$6:$P$1205,">="&$C$6,Payments!$P$6:$P$1205,"<="&$C$7)+SUMIFS('Manual Log'!$E$6:$E$1005,'Manual Log'!$C$6:$C$1005,"Income",'Manual Log'!$D$6:$D$1005,B31,'Manual Log'!$B$6:$B$1005,">="&$C$6,'Manual Log'!$B$6:$B$1005,"<="&$C$7)) | E31: =IF(B31="","",D31-C31) | G31: =IF(AD31="","",INDEX(Setup!$D$25:$D$84,AD31)) | H31: =IF(AD31="","",COUNTIFS(INDEX(Calc!$B$2:$BB$61,AD31,0),">="&$C$6,INDEX(Calc!$B$2:$BB$61,AD31,0),"<"&($C$7+1))*INDEX(Setup!$E$25:$E$84,AD31)) | I31: =IF(G31="","",SUMIFS(Payments!$Q$6:$Q$1205,Payments!$I$6:$I$1205,"Savings",Payments!$E$6:$E$1205,G31,Payments!$P$6:$P$1205,">="&$C$6,Payments!$P$6:$P$1205,"<="&$C$7)+SUMIFS('Manual Log'!$E$6:$E$1005,'Manual Log'!$C$6:$C$1005,"Savings",'Manual Log'!$D$6:$D$1005,G31,'Manual Log'!$B$6:$B$1005,">="&$C$6,'Manual Log'!$B$6:$B$1005,"<="&$C$7)) | J31: =IF(G31="","",I31-H31) | L31: =IF(AE31="","",INDEX(Setup!$D$25:$D$84,AE31)) | M31: =IF(AE31="","",COUNTIFS(INDEX(Calc!$B$2:$BB$61,AE31,0),">="&$C$6,INDEX(Calc!$B$2:$BB$61,AE31,0),"<"&($C$7+1))*INDEX(Setup!$E$25:$E$84,AE31)) | N31: =IF(L31="","",SUMIFS(Payments!$Q$6:$Q$1205,Payments!$I$6:$I$1205,"Bills",Payments!$E$6:$E$1205,L31,Payments!$P$6:$P$1205,">="&$C$6,Payments!$P$6:$P$1205,"<="&$C$7)+SUMIFS('Manual Log'!$E$6:$E$1005,'Manual Log'!$C$6:$C$1005,"Bills",'Manual Log'!$D$6:$D$1005,L31,'Manual Log'!$B$6:$B$1005,">="&$C$6,'Manual Log'!$B$6:$B$1005,"<="&$C$7)) | O31: =IF(L31="","",M31-N31) | Q31: =IF(AF31="","",INDEX(Setup!$D$25:$D$84,AF31)) | R31: =IF(AF31="","",COUNTIFS(INDEX(Calc!$B$2:$BB$61,AF31,0),">="&$C$6,INDEX(Calc!$B$2:$BB$61,AF31,0),"<"&($C$7+1))*INDEX(Setup!$E$25:$E$84,AF31)) | S31: =IF(Q31="","",SUMIFS(Payments!$Q$6:$Q$1205,Payments!$I$6:$I$1205,"Debt",Payments!$E$6:$E$1205,Q31,Payments!$P$6:$P$1205,">="&$C$6,Payments!$P$6:$P$1205,"<="&$C$7)+SUMIFS('Manual Log'!$E$6:$E$1005,'Manual Log'!$C$6:$C$1005,"Debt",'Manual Log'!$D$6:$D$1005,Q31,'Manual Log'!$B$6:$B$1005,">="&$C$6,'Manual Log'!$B$6:$B$1005,"<="&$C$7)) | T31: =IF(Q31="","",R31-S31) | V31: =IF($C$6+0*$V$29>$C$7,"",$C$6+0*$V$29) | W31: =IF(V31="","",SUMIFS(Payments!$Q$6:$Q$1205,Payments!$I$6:$I$1205,"<>Income",Payments!$I$6:$I$1205,"<>Savings",Payments!$P$6:$P$1205,">="&V31,Payments!$P$6:$P$1205,"<"&(V31+$V$29),Payments!$P$6:$P$1205,"<="&$C$7)+SUMIFS('Manual Log'!$E$6:$E$1005,'Manual Log'!$C$6:$C$1005,"<>Income",'Manual Log'!$C$6:$C$1005,"<>Savings",'Manual Log'!$C$6:$C$1005,"<>Transfer",'Manual Log'!$B$6:$B$1005,">="&V31,'Manual Log'!$B$6:$B$1005,"<"&(V31+$V$29),'Manual Log'!$B$6:$B$1005,"<="&$C$7)) | X31: =IF(V31="","",TEXT(V31,"ddd d mmm")) | Y31: =L31 | Z31: =N31 | AA31: =IF(OR(Y31="",N(Z31)<=0),"",Z31+ROW()/1000000) | AC31: =IFERROR(MATCH("Income|1",Setup!$L$25:$L$84,0),"") | AD31: =IFERROR(MATCH("Savings|1",Setup!$L$25:$L$84,0),"") | AE31: =IFERROR(MATCH("Bills|1",Setup!$L$25:$L$84,0),"") | AF31: =IFERROR(MATCH("Debt|1",Setup!$L$25:$L$84,0),"")
B32: =IF(AC32="","",INDEX(Setup!$D$25:$D$84,AC32)) | C32: =IF(AC32="","",COUNTIFS(INDEX(Calc!$B$2:$BB$61,AC32,0),">="&$C$6,INDEX(Calc!$B$2:$BB$61,AC32,0),"<"&($C$7+1))*INDEX(Setup!$E$25:$E$84,AC32)) | D32: =IF(B32="","",SUMIFS(Payments!$Q$6:$Q$1205,Payments!$I$6:$I$1205,"Income",Payments!$E$6:$E$1205,B32,Payments!$P$6:$P$1205,">="&$C$6,Payments!$P$6:$P$1205,"<="&$C$7)+SUMIFS('Manual Log'!$E$6:$E$1005,'Manual Log'!$C$6:$C$1005,"Income",'Manual Log'!$D$6:$D$1005,B32,'Manual Log'!$B$6:$B$1005,">="&$C$6,'Manual Log'!$B$6:$B$1005,"<="&$C$7)) | E32: =IF(B32="","",D32-C32) | G32: =IF(AD32="","",INDEX(Setup!$D$25:$D$84,AD32)) | H32: =IF(AD32="","",COUNTIFS(INDEX(Calc!$B$2:$BB$61,AD32,0),">="&$C$6,INDEX(Calc!$B$2:$BB$61,AD32,0),"<"&($C$7+1))*INDEX(Setup!$E$25:$E$84,AD32)) | I32: =IF(G32="","",SUMIFS(Payments!$Q$6:$Q$1205,Payments!$I$6:$I$1205,"Savings",Payments!$E$6:$E$1205,G32,Payments!$P$6:$P$1205,">="&$C$6,Payments!$P$6:$P$1205,"<="&$C$7)+SUMIFS('Manual Log'!$E$6:$E$1005,'Manual Log'!$C$6:$C$1005,"Savings",'Manual Log'!$D$6:$D$1005,G32,'Manual Log'!$B$6:$B$1005,">="&$C$6,'Manual Log'!$B$6:$B$1005,"<="&$C$7)) | J32: =IF(G32="","",I32-H32) | L32: =IF(AE32="","",INDEX(Setup!$D$25:$D$84,AE32)) | M32: =IF(AE32="","",COUNTIFS(INDEX(Calc!$B$2:$BB$61,AE32,0),">="&$C$6,INDEX(Calc!$B$2:$BB$61,AE32,0),"<"&($C$7+1))*INDEX(Setup!$E$25:$E$84,AE32)) | N32: =IF(L32="","",SUMIFS(Payments!$Q$6:$Q$1205,Payments!$I$6:$I$1205,"Bills",Payments!$E$6:$E$1205,L32,Payments!$P$6:$P$1205,">="&$C$6,Payments!$P$6:$P$1205,"<="&$C$7)+SUMIFS('Manual Log'!$E$6:$E$1005,'Manual Log'!$C$6:$C$1005,"Bills",'Manual Log'!$D$6:$D$1005,L32,'Manual Log'!$B$6:$B$1005,">="&$C$6,'Manual Log'!$B$6:$B$1005,"<="&$C$7)) | O32: =IF(L32="","",M32-N32) | Q32: =IF(AF32="","",INDEX(Setup!$D$25:$D$84,AF32)) | R32: =IF(AF32="","",COUNTIFS(INDEX(Calc!$B$2:$BB$61,AF32,0),">="&$C$6,INDEX(Calc!$B$2:$BB$61,AF32,0),"<"&($C$7+1))*INDEX(Setup!$E$25:$E$84,AF32)) | S32: =IF(Q32="","",SUMIFS(Payments!$Q$6:$Q$1205,Payments!$I$6:$I$1205,"Debt",Payments!$E$6:$E$1205,Q32,Payments!$P$6:$P$1205,">="&$C$6,Payments!$P$6:$P$1205,"<="&$C$7)+SUMIFS('Manual Log'!$E$6:$E$1005,'Manual Log'!$C$6:$C$1005,"Debt",'Manual Log'!$D$6:$D$1005,Q32,'Manual Log'!$B$6:$B$1005,">="&$C$6,'Manual Log'!$B$6:$B$1005,"<="&$C$7)) | T32: =IF(Q32="","",R32-S32) | V32: =IF($C$6+1*$V$29>$C$7,"",$C$6+1*$V$29) | W32: =IF(V32="","",SUMIFS(Payments!$Q$6:$Q$1205,Payments!$I$6:$I$1205,"<>Income",Payments!$I$6:$I$1205,"<>Savings",Payments!$P$6:$P$1205,">="&V32,Payments!$P$6:$P$1205,"<"&(V32+$V$29),Payments!$P$6:$P$1205,"<="&$C$7)+SUMIFS('Manual Log'!$E$6:$E$1005,'Manual Log'!$C$6:$C$1005,"<>Income",'Manual Log'!$C$6:$C$1005,"<>Savings",'Manual Log'!$C$6:$C$1005,"<>Transfer",'Manual Log'!$B$6:$B$1005,">="&V32,'Manual Log'!$B$6:$B$1005,"<"&(V32+$V$29),'Manual Log'!$B$6:$B$1005,"<="&$C$7)) | X32: =IF(V32="","",TEXT(V32,"ddd d mmm")) | Y32: =L32 | Z32: =N32 | AA32: =IF(OR(Y32="",N(Z32)<=0),"",Z32+ROW()/1000000) | AC32: =IFERROR(MATCH("Income|2",Setup!$L$25:$L$84,0),"") | AD32: =IFERROR(MATCH("Savings|2",Setup!$L$25:$L$84,0),"") | AE32: =IFERROR(MATCH("Bills|2",Setup!$L$25:$L$84,0),"") | AF32: =IFERROR(MATCH("Debt|2",Setup!$L$25:$L$84,0),"")
B33: =IF(AC33="","",INDEX(Setup!$D$25:$D$84,AC33)) | C33: =IF(AC33="","",COUNTIFS(INDEX(Calc!$B$2:$BB$61,AC33,0),">="&$C$6,INDEX(Calc!$B$2:$BB$61,AC33,0),"<"&($C$7+1))*INDEX(Setup!$E$25:$E$84,AC33)) | D33: =IF(B33="","",SUMIFS(Payments!$Q$6:$Q$1205,Payments!$I$6:$I$1205,"Income",Payments!$E$6:$E$1205,B33,Payments!$P$6:$P$1205,">="&$C$6,Payments!$P$6:$P$1205,"<="&$C$7)+SUMIFS('Manual Log'!$E$6:$E$1005,'Manual Log'!$C$6:$C$1005,"Income",'Manual Log'!$D$6:$D$1005,B33,'Manual Log'!$B$6:$B$1005,">="&$C$6,'Manual Log'!$B$6:$B$1005,"<="&$C$7)) | E33: =IF(B33="","",D33-C33) | G33: =IF(AD33="","",INDEX(Setup!$D$25:$D$84,AD33)) | H33: =IF(AD33="","",COUNTIFS(INDEX(Calc!$B$2:$BB$61,AD33,0),">="&$C$6,INDEX(Calc!$B$2:$BB$61,AD33,0),"<"&($C$7+1))*INDEX(Setup!$E$25:$E$84,AD33)) | I33: =IF(G33="","",SUMIFS(Payments!$Q$6:$Q$1205,Payments!$I$6:$I$1205,"Savings",Payments!$E$6:$E$1205,G33,Payments!$P$6:$P$1205,">="&$C$6,Payments!$P$6:$P$1205,"<="&$C$7)+SUMIFS('Manual Log'!$E$6:$E$1005,'Manual Log'!$C$6:$C$1005,"Savings",'Manual Log'!$D$6:$D$1005,G33,'Manual Log'!$B$6:$B$1005,">="&$C$6,'Manual Log'!$B$6:$B$1005,"<="&$C$7)) | J33: =IF(G33="","",I33-H33) | L33: =IF(AE33="","",INDEX(Setup!$D$25:$D$84,AE33)) | M33: =IF(AE33="","",COUNTIFS(INDEX(Calc!$B$2:$BB$61,AE33,0),">="&$C$6,INDEX(Calc!$B$2:$BB$61,AE33,0),"<"&($C$7+1))*INDEX(Setup!$E$25:$E$84,AE33)) | N33: =IF(L33="","",SUMIFS(Payments!$Q$6:$Q$1205,Payments!$I$6:$I$1205,"Bills",Payments!$E$6:$E$1205,L33,Payments!$P$6:$P$1205,">="&$C$6,Payments!$P$6:$P$1205,"<="&$C$7)+SUMIFS('Manual Log'!$E$6:$E$1005,'Manual Log'!$C$6:$C$1005,"Bills",'Manual Log'!$D$6:$D$1005,L33,'Manual Log'!$B$6:$B$1005,">="&$C$6,'Manual Log'!$B$6:$B$1005,"<="&$C$7)) | O33: =IF(L33="","",M33-N33) | Q33: =IF(AF33="","",INDEX(Setup!$D$25:$D$84,AF33)) | R33: =IF(AF33="","",COUNTIFS(INDEX(Calc!$B$2:$BB$61,AF33,0),">="&$C$6,INDEX(Calc!$B$2:$BB$61,AF33,0),"<"&($C$7+1))*INDEX(Setup!$E$25:$E$84,AF33)) | S33: =IF(Q33="","",SUMIFS(Payments!$Q$6:$Q$1205,Payments!$I$6:$I$1205,"Debt",Payments!$E$6:$E$1205,Q33,Payments!$P$6:$P$1205,">="&$C$6,Payments!$P$6:$P$1205,"<="&$C$7)+SUMIFS('Manual Log'!$E$6:$E$1005,'Manual Log'!$C$6:$C$1005,"Debt",'Manual Log'!$D$6:$D$1005,Q33,'Manual Log'!$B$6:$B$1005,">="&$C$6,'Manual Log'!$B$6:$B$1005,"<="&$C$7)) | T33: =IF(Q33="","",R33-S33) | V33: =IF($C$6+2*$V$29>$C$7,"",$C$6+2*$V$29) | W33: =IF(V33="","",SUMIFS(Payments!$Q$6:$Q$1205,Payments!$I$6:$I$1205,"<>Income",Payments!$I$6:$I$1205,"<>Savings",Payments!$P$6:$P$1205,">="&V33,Payments!$P$6:$P$1205,"<"&(V33+$V$29),Payments!$P$6:$P$1205,"<="&$C$7)+SUMIFS('Manual Log'!$E$6:$E$1005,'Manual Log'!$C$6:$C$1005,"<>Income",'Manual Log'!$C$6:$C$1005,"<>Savings",'Manual Log'!$C$6:$C$1005,"<>Transfer",'Manual Log'!$B$6:$B$1005,">="&V33,'Manual Log'!$B$6:$B$1005,"<"&(V33+$V$29),'Manual Log'!$B$6:$B$1005,"<="&$C$7)) | X33: =IF(V33="","",TEXT(V33,"ddd d mmm")) | Y33: =L33 | Z33: =N33 | AA33: =IF(OR(Y33="",N(Z33)<=0),"",Z33+ROW()/1000000) | AC33: =IFERROR(MATCH("Income|3",Setup!$L$25:$L$84,0),"") | AD33: =IFERROR(MATCH("Savings|3",Setup!$L$25:$L$84,0),"") | AE33: =IFERROR(MATCH("Bills|3",Setup!$L$25:$L$84,0),"") | AF33: =IFERROR(MATCH("Debt|3",Setup!$L$25:$L$84,0),"")
B34: =IF(AC34="","",INDEX(Setup!$D$25:$D$84,AC34)) | C34: =IF(AC34="","",COUNTIFS(INDEX(Calc!$B$2:$BB$61,AC34,0),">="&$C$6,INDEX(Calc!$B$2:$BB$61,AC34,0),"<"&($C$7+1))*INDEX(Setup!$E$25:$E$84,AC34)) | D34: =IF(B34="","",SUMIFS(Payments!$Q$6:$Q$1205,Payments!$I$6:$I$1205,"Income",Payments!$E$6:$E$1205,B34,Payments!$P$6:$P$1205,">="&$C$6,Payments!$P$6:$P$1205,"<="&$C$7)+SUMIFS('Manual Log'!$E$6:$E$1005,'Manual Log'!$C$6:$C$1005,"Income",'Manual Log'!$D$6:$D$1005,B34,'Manual Log'!$B$6:$B$1005,">="&$C$6,'Manual Log'!$B$6:$B$1005,"<="&$C$7)) | E34: =IF(B34="","",D34-C34) | G34: =IF(AD34="","",INDEX(Setup!$D$25:$D$84,AD34)) | H34: =IF(AD34="","",COUNTIFS(INDEX(Calc!$B$2:$BB$61,AD34,0),">="&$C$6,INDEX(Calc!$B$2:$BB$61,AD34,0),"<"&($C$7+1))*INDEX(Setup!$E$25:$E$84,AD34)) | I34: =IF(G34="","",SUMIFS(Payments!$Q$6:$Q$1205,Payments!$I$6:$I$1205,"Savings",Payments!$E$6:$E$1205,G34,Payments!$P$6:$P$1205,">="&$C$6,Payments!$P$6:$P$1205,"<="&$C$7)+SUMIFS('Manual Log'!$E$6:$E$1005,'Manual Log'!$C$6:$C$1005,"Savings",'Manual Log'!$D$6:$D$1005,G34,'Manual Log'!$B$6:$B$1005,">="&$C$6,'Manual Log'!$B$6:$B$1005,"<="&$C$7)) | J34: =IF(G34="","",I34-H34) | L34: =IF(AE34="","",INDEX(Setup!$D$25:$D$84,AE34)) | M34: =IF(AE34="","",COUNTIFS(INDEX(Calc!$B$2:$BB$61,AE34,0),">="&$C$6,INDEX(Calc!$B$2:$BB$61,AE34,0),"<"&($C$7+1))*INDEX(Setup!$E$25:$E$84,AE34)) | N34: =IF(L34="","",SUMIFS(Payments!$Q$6:$Q$1205,Payments!$I$6:$I$1205,"Bills",Payments!$E$6:$E$1205,L34,Payments!$P$6:$P$1205,">="&$C$6,Payments!$P$6:$P$1205,"<="&$C$7)+SUMIFS('Manual Log'!$E$6:$E$1005,'Manual Log'!$C$6:$C$1005,"Bills",'Manual Log'!$D$6:$D$1005,L34,'Manual Log'!$B$6:$B$1005,">="&$C$6,'Manual Log'!$B$6:$B$1005,"<="&$C$7)) | O34: =IF(L34="","",M34-N34) | Q34: =IF(AF34="","",INDEX(Setup!$D$25:$D$84,AF34)) | R34: =IF(AF34="","",COUNTIFS(INDEX(Calc!$B$2:$BB$61,AF34,0),">="&$C$6,INDEX(Calc!$B$2:$BB$61,AF34,0),"<"&($C$7+1))*INDEX(Setup!$E$25:$E$84,AF34)) | S34: =IF(Q34="","",SUMIFS(Payments!$Q$6:$Q$1205,Payments!$I$6:$I$1205,"Debt",Payments!$E$6:$E$1205,Q34,Payments!$P$6:$P$1205,">="&$C$6,Payments!$P$6:$P$1205,"<="&$C$7)+SUMIFS('Manual Log'!$E$6:$E$1005,'Manual Log'!$C$6:$C$1005,"Debt",'Manual Log'!$D$6:$D$1005,Q34,'Manual Log'!$B$6:$B$1005,">="&$C$6,'Manual Log'!$B$6:$B$1005,"<="&$C$7)) | T34: =IF(Q34="","",R34-S34) | V34: =IF($C$6+3*$V$29>$C$7,"",$C$6+3*$V$29) | W34: =IF(V34="","",SUMIFS(Payments!$Q$6:$Q$1205,Payments!$I$6:$I$1205,"<>Income",Payments!$I$6:$I$1205,"<>Savings",Payments!$P$6:$P$1205,">="&V34,Payments!$P$6:$P$1205,"<"&(V34+$V$29),Payments!$P$6:$P$1205,"<="&$C$7)+SUMIFS('Manual Log'!$E$6:$E$1005,'Manual Log'!$C$6:$C$1005,"<>Income",'Manual Log'!$C$6:$C$1005,"<>Savings",'Manual Log'!$C$6:$C$1005,"<>Transfer",'Manual Log'!$B$6:$B$1005,">="&V34,'Manual Log'!$B$6:$B$1005,"<"&(V34+$V$29),'Manual Log'!$B$6:$B$1005,"<="&$C$7)) | X34: =IF(V34="","",TEXT(V34,"ddd d mmm")) | Y34: =L34 | Z34: =N34 | AA34: =IF(OR(Y34="",N(Z34)<=0),"",Z34+ROW()/1000000) | AC34: =IFERROR(MATCH("Income|4",Setup!$L$25:$L$84,0),"") | AD34: =IFERROR(MATCH("Savings|4",Setup!$L$25:$L$84,0),"") | AE34: =IFERROR(MATCH("Bills|4",Setup!$L$25:$L$84,0),"") | AF34: =IFERROR(MATCH("Debt|4",Setup!$L$25:$L$84,0),"")
B35: =IF(AC35="","",INDEX(Setup!$D$25:$D$84,AC35)) | C35: =IF(AC35="","",COUNTIFS(INDEX(Calc!$B$2:$BB$61,AC35,0),">="&$C$6,INDEX(Calc!$B$2:$BB$61,AC35,0),"<"&($C$7+1))*INDEX(Setup!$E$25:$E$84,AC35)) | D35: =IF(B35="","",SUMIFS(Payments!$Q$6:$Q$1205,Payments!$I$6:$I$1205,"Income",Payments!$E$6:$E$1205,B35,Payments!$P$6:$P$1205,">="&$C$6,Payments!$P$6:$P$1205,"<="&$C$7)+SUMIFS('Manual Log'!$E$6:$E$1005,'Manual Log'!$C$6:$C$1005,"Income",'Manual Log'!$D$6:$D$1005,B35,'Manual Log'!$B$6:$B$1005,">="&$C$6,'Manual Log'!$B$6:$B$1005,"<="&$C$7)) | E35: =IF(B35="","",D35-C35) | G35: =IF(AD35="","",INDEX(Setup!$D$25:$D$84,AD35)) | H35: =IF(AD35="","",COUNTIFS(INDEX(Calc!$B$2:$BB$61,AD35,0),">="&$C$6,INDEX(Calc!$B$2:$BB$61,AD35,0),"<"&($C$7+1))*INDEX(Setup!$E$25:$E$84,AD35)) | I35: =IF(G35="","",SUMIFS(Payments!$Q$6:$Q$1205,Payments!$I$6:$I$1205,"Savings",Payments!$E$6:$E$1205,G35,Payments!$P$6:$P$1205,">="&$C$6,Payments!$P$6:$P$1205,"<="&$C$7)+SUMIFS('Manual Log'!$E$6:$E$1005,'Manual Log'!$C$6:$C$1005,"Savings",'Manual Log'!$D$6:$D$1005,G35,'Manual Log'!$B$6:$B$1005,">="&$C$6,'Manual Log'!$B$6:$B$1005,"<="&$C$7)) | J35: =IF(G35="","",I35-H35) | L35: =IF(AE35="","",INDEX(Setup!$D$25:$D$84,AE35)) | M35: =IF(AE35="","",COUNTIFS(INDEX(Calc!$B$2:$BB$61,AE35,0),">="&$C$6,INDEX(Calc!$B$2:$BB$61,AE35,0),"<"&($C$7+1))*INDEX(Setup!$E$25:$E$84,AE35)) | N35: =IF(L35="","",SUMIFS(Payments!$Q$6:$Q$1205,Payments!$I$6:$I$1205,"Bills",Payments!$E$6:$E$1205,L35,Payments!$P$6:$P$1205,">="&$C$6,Payments!$P$6:$P$1205,"<="&$C$7)+SUMIFS('Manual Log'!$E$6:$E$1005,'Manual Log'!$C$6:$C$1005,"Bills",'Manual Log'!$D$6:$D$1005,L35,'Manual Log'!$B$6:$B$1005,">="&$C$6,'Manual Log'!$B$6:$B$1005,"<="&$C$7)) | O35: =IF(L35="","",M35-N35) | Q35: =IF(AF35="","",INDEX(Setup!$D$25:$D$84,AF35)) | R35: =IF(AF35="","",COUNTIFS(INDEX(Calc!$B$2:$BB$61,AF35,0),">="&$C$6,INDEX(Calc!$B$2:$BB$61,AF35,0),"<"&($C$7+1))*INDEX(Setup!$E$25:$E$84,AF35)) | S35: =IF(Q35="","",SUMIFS(Payments!$Q$6:$Q$1205,Payments!$I$6:$I$1205,"Debt",Payments!$E$6:$E$1205,Q35,Payments!$P$6:$P$1205,">="&$C$6,Payments!$P$6:$P$1205,"<="&$C$7)+SUMIFS('Manual Log'!$E$6:$E$1005,'Manual Log'!$C$6:$C$1005,"Debt",'Manual Log'!$D$6:$D$1005,Q35,'Manual Log'!$B$6:$B$1005,">="&$C$6,'Manual Log'!$B$6:$B$1005,"<="&$C$7)) | T35: =IF(Q35="","",R35-S35) | V35: =IF($C$6+4*$V$29>$C$7,"",$C$6+4*$V$29) | W35: =IF(V35="","",SUMIFS(Payments!$Q$6:$Q$1205,Payments!$I$6:$I$1205,"<>Income",Payments!$I$6:$I$1205,"<>Savings",Payments!$P$6:$P$1205,">="&V35,Payments!$P$6:$P$1205,"<"&(V35+$V$29),Payments!$P$6:$P$1205,"<="&$C$7)+SUMIFS('Manual Log'!$E$6:$E$1005,'Manual Log'!$C$6:$C$1005,"<>Income",'Manual Log'!$C$6:$C$1005,"<>Savings",'Manual Log'!$C$6:$C$1005,"<>Transfer",'Manual Log'!$B$6:$B$1005,">="&V35,'Manual Log'!$B$6:$B$1005,"<"&(V35+$V$29),'Manual Log'!$B$6:$B$1005,"<="&$C$7)) | X35: =IF(V35="","",TEXT(V35,"ddd d mmm")) | Y35: =L35 | Z35: =N35 | AA35: =IF(OR(Y35="",N(Z35)<=0),"",Z35+ROW()/1000000) | AC35: =IFERROR(MATCH("Income|5",Setup!$L$25:$L$84,0),"") | AD35: =IFERROR(MATCH("Savings|5",Setup!$L$25:$L$84,0),"") | AE35: =IFERROR(MATCH("Bills|5",Setup!$L$25:$L$84,0),"") | AF35: =IFERROR(MATCH("Debt|5",Setup!$L$25:$L$84,0),"")
B36: =IF(AC36="","",INDEX(Setup!$D$25:$D$84,AC36)) | C36: =IF(AC36="","",COUNTIFS(INDEX(Calc!$B$2:$BB$61,AC36,0),">="&$C$6,INDEX(Calc!$B$2:$BB$61,AC36,0),"<"&($C$7+1))*INDEX(Setup!$E$25:$E$84,AC36)) | D36: =IF(B36="","",SUMIFS(Payments!$Q$6:$Q$1205,Payments!$I$6:$I$1205,"Income",Payments!$E$6:$E$1205,B36,Payments!$P$6:$P$1205,">="&$C$6,Payments!$P$6:$P$1205,"<="&$C$7)+SUMIFS('Manual Log'!$E$6:$E$1005,'Manual Log'!$C$6:$C$1005,"Income",'Manual Log'!$D$6:$D$1005,B36,'Manual Log'!$B$6:$B$1005,">="&$C$6,'Manual Log'!$B$6:$B$1005,"<="&$C$7)) | E36: =IF(B36="","",D36-C36) | G36: =IF(AD36="","",INDEX(Setup!$D$25:$D$84,AD36)) | H36: =IF(AD36="","",COUNTIFS(INDEX(Calc!$B$2:$BB$61,AD36,0),">="&$C$6,INDEX(Calc!$B$2:$BB$61,AD36,0),"<"&($C$7+1))*INDEX(Setup!$E$25:$E$84,AD36)) | I36: =IF(G36="","",SUMIFS(Payments!$Q$6:$Q$1205,Payments!$I$6:$I$1205,"Savings",Payments!$E$6:$E$1205,G36,Payments!$P$6:$P$1205,">="&$C$6,Payments!$P$6:$P$1205,"<="&$C$7)+SUMIFS('Manual Log'!$E$6:$E$1005,'Manual Log'!$C$6:$C$1005,"Savings",'Manual Log'!$D$6:$D$1005,G36,'Manual Log'!$B$6:$B$1005,">="&$C$6,'Manual Log'!$B$6:$B$1005,"<="&$C$7)) | J36: =IF(G36="","",I36-H36) | L36: =IF(AE36="","",INDEX(Setup!$D$25:$D$84,AE36)) | M36: =IF(AE36="","",COUNTIFS(INDEX(Calc!$B$2:$BB$61,AE36,0),">="&$C$6,INDEX(Calc!$B$2:$BB$61,AE36,0),"<"&($C$7+1))*INDEX(Setup!$E$25:$E$84,AE36)) | N36: =IF(L36="","",SUMIFS(Payments!$Q$6:$Q$1205,Payments!$I$6:$I$1205,"Bills",Payments!$E$6:$E$1205,L36,Payments!$P$6:$P$1205,">="&$C$6,Payments!$P$6:$P$1205,"<="&$C$7)+SUMIFS('Manual Log'!$E$6:$E$1005,'Manual Log'!$C$6:$C$1005,"Bills",'Manual Log'!$D$6:$D$1005,L36,'Manual Log'!$B$6:$B$1005,">="&$C$6,'Manual Log'!$B$6:$B$1005,"<="&$C$7)) | O36: =IF(L36="","",M36-N36) | Q36: =IF(AF36="","",INDEX(Setup!$D$25:$D$84,AF36)) | R36: =IF(AF36="","",COUNTIFS(INDEX(Calc!$B$2:$BB$61,AF36,0),">="&$C$6,INDEX(Calc!$B$2:$BB$61,AF36,0),"<"&($C$7+1))*INDEX(Setup!$E$25:$E$84,AF36)) | S36: =IF(Q36="","",SUMIFS(Payments!$Q$6:$Q$1205,Payments!$I$6:$I$1205,"Debt",Payments!$E$6:$E$1205,Q36,Payments!$P$6:$P$1205,">="&$C$6,Payments!$P$6:$P$1205,"<="&$C$7)+SUMIFS('Manual Log'!$E$6:$E$1005,'Manual Log'!$C$6:$C$1005,"Debt",'Manual Log'!$D$6:$D$1005,Q36,'Manual Log'!$B$6:$B$1005,">="&$C$6,'Manual Log'!$B$6:$B$1005,"<="&$C$7)) | T36: =IF(Q36="","",R36-S36) | V36: =IF($C$6+5*$V$29>$C$7,"",$C$6+5*$V$29) | W36: =IF(V36="","",SUMIFS(Payments!$Q$6:$Q$1205,Payments!$I$6:$I$1205,"<>Income",Payments!$I$6:$I$1205,"<>Savings",Payments!$P$6:$P$1205,">="&V36,Payments!$P$6:$P$1205,"<"&(V36+$V$29),Payments!$P$6:$P$1205,"<="&$C$7)+SUMIFS('Manual Log'!$E$6:$E$1005,'Manual Log'!$C$6:$C$1005,"<>Income",'Manual Log'!$C$6:$C$1005,"<>Savings",'Manual Log'!$C$6:$C$1005,"<>Transfer",'Manual Log'!$B$6:$B$1005,">="&V36,'Manual Log'!$B$6:$B$1005,"<"&(V36+$V$29),'Manual Log'!$B$6:$B$1005,"<="&$C$7)) | X36: =IF(V36="","",TEXT(V36,"ddd d mmm")) | Y36: =L36 | Z36: =N36 | AA36: =IF(OR(Y36="",N(Z36)<=0),"",Z36+ROW()/1000000) | AC36: =IFERROR(MATCH("Income|6",Setup!$L$25:$L$84,0),"") | AD36: =IFERROR(MATCH("Savings|6",Setup!$L$25:$L$84,0),"") | AE36: =IFERROR(MATCH("Bills|6",Setup!$L$25:$L$84,0),"") | AF36: =IFERROR(MATCH("Debt|6",Setup!$L$25:$L$84,0),"")
B37: =IF(AC37="","",INDEX(Setup!$D$25:$D$84,AC37)) | C37: =IF(AC37="","",COUNTIFS(INDEX(Calc!$B$2:$BB$61,AC37,0),">="&$C$6,INDEX(Calc!$B$2:$BB$61,AC37,0),"<"&($C$7+1))*INDEX(Setup!$E$25:$E$84,AC37)) | D37: =IF(B37="","",SUMIFS(Payments!$Q$6:$Q$1205,Payments!$I$6:$I$1205,"Income",Payments!$E$6:$E$1205,B37,Payments!$P$6:$P$1205,">="&$C$6,Payments!$P$6:$P$1205,"<="&$C$7)+SUMIFS('Manual Log'!$E$6:$E$1005,'Manual Log'!$C$6:$C$1005,"Income",'Manual Log'!$D$6:$D$1005,B37,'Manual Log'!$B$6:$B$1005,">="&$C$6,'Manual Log'!$B$6:$B$1005,"<="&$C$7)) | E37: =IF(B37="","",D37-C37) | G37: =IF(AD37="","",INDEX(Setup!$D$25:$D$84,AD37)) | H37: =IF(AD37="","",COUNTIFS(INDEX(Calc!$B$2:$BB$61,AD37,0),">="&$C$6,INDEX(Calc!$B$2:$BB$61,AD37,0),"<"&($C$7+1))*INDEX(Setup!$E$25:$E$84,AD37)) | I37: =IF(G37="","",SUMIFS(Payments!$Q$6:$Q$1205,Payments!$I$6:$I$1205,"Savings",Payments!$E$6:$E$1205,G37,Payments!$P$6:$P$1205,">="&$C$6,Payments!$P$6:$P$1205,"<="&$C$7)+SUMIFS('Manual Log'!$E$6:$E$1005,'Manual Log'!$C$6:$C$1005,"Savings",'Manual Log'!$D$6:$D$1005,G37,'Manual Log'!$B$6:$B$1005,">="&$C$6,'Manual Log'!$B$6:$B$1005,"<="&$C$7)) | J37: =IF(G37="","",I37-H37) | L37: =IF(AE37="","",INDEX(Setup!$D$25:$D$84,AE37)) | M37: =IF(AE37="","",COUNTIFS(INDEX(Calc!$B$2:$BB$61,AE37,0),">="&$C$6,INDEX(Calc!$B$2:$BB$61,AE37,0),"<"&($C$7+1))*INDEX(Setup!$E$25:$E$84,AE37)) | N37: =IF(L37="","",SUMIFS(Payments!$Q$6:$Q$1205,Payments!$I$6:$I$1205,"Bills",Payments!$E$6:$E$1205,L37,Payments!$P$6:$P$1205,">="&$C$6,Payments!$P$6:$P$1205,"<="&$C$7)+SUMIFS('Manual Log'!$E$6:$E$1005,'Manual Log'!$C$6:$C$1005,"Bills",'Manual Log'!$D$6:$D$1005,L37,'Manual Log'!$B$6:$B$1005,">="&$C$6,'Manual Log'!$B$6:$B$1005,"<="&$C$7)) | O37: =IF(L37="","",M37-N37) | Q37: =IF(AF37="","",INDEX(Setup!$D$25:$D$84,AF37)) | R37: =IF(AF37="","",COUNTIFS(INDEX(Calc!$B$2:$BB$61,AF37,0),">="&$C$6,INDEX(Calc!$B$2:$BB$61,AF37,0),"<"&($C$7+1))*INDEX(Setup!$E$25:$E$84,AF37)) | S37: =IF(Q37="","",SUMIFS(Payments!$Q$6:$Q$1205,Payments!$I$6:$I$1205,"Debt",Payments!$E$6:$E$1205,Q37,Payments!$P$6:$P$1205,">="&$C$6,Payments!$P$6:$P$1205,"<="&$C$7)+SUMIFS('Manual Log'!$E$6:$E$1005,'Manual Log'!$C$6:$C$1005,"Debt",'Manual Log'!$D$6:$D$1005,Q37,'Manual Log'!$B$6:$B$1005,">="&$C$6,'Manual Log'!$B$6:$B$1005,"<="&$C$7)) | T37: =IF(Q37="","",R37-S37) | V37: =IF($C$6+6*$V$29>$C$7,"",$C$6+6*$V$29) | W37: =IF(V37="","",SUMIFS(Payments!$Q$6:$Q$1205,Payments!$I$6:$I$1205,"<>Income",Payments!$I$6:$I$1205,"<>Savings",Payments!$P$6:$P$1205,">="&V37,Payments!$P$6:$P$1205,"<"&(V37+$V$29),Payments!$P$6:$P$1205,"<="&$C$7)+SUMIFS('Manual Log'!$E$6:$E$1005,'Manual Log'!$C$6:$C$1005,"<>Income",'Manual Log'!$C$6:$C$1005,"<>Savings",'Manual Log'!$C$6:$C$1005,"<>Transfer",'Manual Log'!$B$6:$B$1005,">="&V37,'Manual Log'!$B$6:$B$1005,"<"&(V37+$V$29),'Manual Log'!$B$6:$B$1005,"<="&$C$7)) | X37: =IF(V37="","",TEXT(V37,"ddd d mmm")) | Y37: =L37 | Z37: =N37 | AA37: =IF(OR(Y37="",N(Z37)<=0),"",Z37+ROW()/1000000) | AC37: =IFERROR(MATCH("Income|7",Setup!$L$25:$L$84,0),"") | AD37: =IFERROR(MATCH("Savings|7",Setup!$L$25:$L$84,0),"") | AE37: =IFERROR(MATCH("Bills|7",Setup!$L$25:$L$84,0),"") | AF37: =IFERROR(MATCH("Debt|7",Setup!$L$25:$L$84,0),"")
B38: =IF(AC38="","",INDEX(Setup!$D$25:$D$84,AC38)) | C38: =IF(AC38="","",COUNTIFS(INDEX(Calc!$B$2:$BB$61,AC38,0),">="&$C$6,INDEX(Calc!$B$2:$BB$61,AC38,0),"<"&($C$7+1))*INDEX(Setup!$E$25:$E$84,AC38)) | D38: =IF(B38="","",SUMIFS(Payments!$Q$6:$Q$1205,Payments!$I$6:$I$1205,"Income",Payments!$E$6:$E$1205,B38,Payments!$P$6:$P$1205,">="&$C$6,Payments!$P$6:$P$1205,"<="&$C$7)+SUMIFS('Manual Log'!$E$6:$E$1005,'Manual Log'!$C$6:$C$1005,"Income",'Manual Log'!$D$6:$D$1005,B38,'Manual Log'!$B$6:$B$1005,">="&$C$6,'Manual Log'!$B$6:$B$1005,"<="&$C$7)) | E38: =IF(B38="","",D38-C38) | G38: =IF(AD38="","",INDEX(Setup!$D$25:$D$84,AD38)) | H38: =IF(AD38="","",COUNTIFS(INDEX(Calc!$B$2:$BB$61,AD38,0),">="&$C$6,INDEX(Calc!$B$2:$BB$61,AD38,0),"<"&($C$7+1))*INDEX(Setup!$E$25:$E$84,AD38)) | I38: =IF(G38="","",SUMIFS(Payments!$Q$6:$Q$1205,Payments!$I$6:$I$1205,"Savings",Payments!$E$6:$E$1205,G38,Payments!$P$6:$P$1205,">="&$C$6,Payments!$P$6:$P$1205,"<="&$C$7)+SUMIFS('Manual Log'!$E$6:$E$1005,'Manual Log'!$C$6:$C$1005,"Savings",'Manual Log'!$D$6:$D$1005,G38,'Manual Log'!$B$6:$B$1005,">="&$C$6,'Manual Log'!$B$6:$B$1005,"<="&$C$7)) | J38: =IF(G38="","",I38-H38) | L38: =IF(AE38="","",INDEX(Setup!$D$25:$D$84,AE38)) | M38: =IF(AE38="","",COUNTIFS(INDEX(Calc!$B$2:$BB$61,AE38,0),">="&$C$6,INDEX(Calc!$B$2:$BB$61,AE38,0),"<"&($C$7+1))*INDEX(Setup!$E$25:$E$84,AE38)) | N38: =IF(L38="","",SUMIFS(Payments!$Q$6:$Q$1205,Payments!$I$6:$I$1205,"Bills",Payments!$E$6:$E$1205,L38,Payments!$P$6:$P$1205,">="&$C$6,Payments!$P$6:$P$1205,"<="&$C$7)+SUMIFS('Manual Log'!$E$6:$E$1005,'Manual Log'!$C$6:$C$1005,"Bills",'Manual Log'!$D$6:$D$1005,L38,'Manual Log'!$B$6:$B$1005,">="&$C$6,'Manual Log'!$B$6:$B$1005,"<="&$C$7)) | O38: =IF(L38="","",M38-N38) | Q38: =IF(AF38="","",INDEX(Setup!$D$25:$D$84,AF38)) | R38: =IF(AF38="","",COUNTIFS(INDEX(Calc!$B$2:$BB$61,AF38,0),">="&$C$6,INDEX(Calc!$B$2:$BB$61,AF38,0),"<"&($C$7+1))*INDEX(Setup!$E$25:$E$84,AF38)) | S38: =IF(Q38="","",SUMIFS(Payments!$Q$6:$Q$1205,Payments!$I$6:$I$1205,"Debt",Payments!$E$6:$E$1205,Q38,Payments!$P$6:$P$1205,">="&$C$6,Payments!$P$6:$P$1205,"<="&$C$7)+SUMIFS('Manual Log'!$E$6:$E$1005,'Manual Log'!$C$6:$C$1005,"Debt",'Manual Log'!$D$6:$D$1005,Q38,'Manual Log'!$B$6:$B$1005,">="&$C$6,'Manual Log'!$B$6:$B$1005,"<="&$C$7)) | T38: =IF(Q38="","",R38-S38) | V38: =IF($C$6+7*$V$29>$C$7,"",$C$6+7*$V$29) | W38: =IF(V38="","",SUMIFS(Payments!$Q$6:$Q$1205,Payments!$I$6:$I$1205,"<>Income",Payments!$I$6:$I$1205,"<>Savings",Payments!$P$6:$P$1205,">="&V38,Payments!$P$6:$P$1205,"<"&(V38+$V$29),Payments!$P$6:$P$1205,"<="&$C$7)+SUMIFS('Manual Log'!$E$6:$E$1005,'Manual Log'!$C$6:$C$1005,"<>Income",'Manual Log'!$C$6:$C$1005,"<>Savings",'Manual Log'!$C$6:$C$1005,"<>Transfer",'Manual Log'!$B$6:$B$1005,">="&V38,'Manual Log'!$B$6:$B$1005,"<"&(V38+$V$29),'Manual Log'!$B$6:$B$1005,"<="&$C$7)) | X38: =IF(V38="","",TEXT(V38,"ddd d mmm")) | Y38: =L38 | Z38: =N38 | AA38: =IF(OR(Y38="",N(Z38)<=0),"",Z38+ROW()/1000000) | AC38: =IFERROR(MATCH("Income|8",Setup!$L$25:$L$84,0),"") | AD38: =IFERROR(MATCH("Savings|8",Setup!$L$25:$L$84,0),"") | AE38: =IFERROR(MATCH("Bills|8",Setup!$L$25:$L$84,0),"") | AF38: =IFERROR(MATCH("Debt|8",Setup!$L$25:$L$84,0),"")
B39: =IF(AC39="","",INDEX(Setup!$D$25:$D$84,AC39)) | C39: =IF(AC39="","",COUNTIFS(INDEX(Calc!$B$2:$BB$61,AC39,0),">="&$C$6,INDEX(Calc!$B$2:$BB$61,AC39,0),"<"&($C$7+1))*INDEX(Setup!$E$25:$E$84,AC39)) | D39: =IF(B39="","",SUMIFS(Payments!$Q$6:$Q$1205,Payments!$I$6:$I$1205,"Income",Payments!$E$6:$E$1205,B39,Payments!$P$6:$P$1205,">="&$C$6,Payments!$P$6:$P$1205,"<="&$C$7)+SUMIFS('Manual Log'!$E$6:$E$1005,'Manual Log'!$C$6:$C$1005,"Income",'Manual Log'!$D$6:$D$1005,B39,'Manual Log'!$B$6:$B$1005,">="&$C$6,'Manual Log'!$B$6:$B$1005,"<="&$C$7)) | E39: =IF(B39="","",D39-C39) | G39: =IF(AD39="","",INDEX(Setup!$D$25:$D$84,AD39)) | H39: =IF(AD39="","",COUNTIFS(INDEX(Calc!$B$2:$BB$61,AD39,0),">="&$C$6,INDEX(Calc!$B$2:$BB$61,AD39,0),"<"&($C$7+1))*INDEX(Setup!$E$25:$E$84,AD39)) | I39: =IF(G39="","",SUMIFS(Payments!$Q$6:$Q$1205,Payments!$I$6:$I$1205,"Savings",Payments!$E$6:$E$1205,G39,Payments!$P$6:$P$1205,">="&$C$6,Payments!$P$6:$P$1205,"<="&$C$7)+SUMIFS('Manual Log'!$E$6:$E$1005,'Manual Log'!$C$6:$C$1005,"Savings",'Manual Log'!$D$6:$D$1005,G39,'Manual Log'!$B$6:$B$1005,">="&$C$6,'Manual Log'!$B$6:$B$1005,"<="&$C$7)) | J39: =IF(G39="","",I39-H39) | L39: =IF(AE39="","",INDEX(Setup!$D$25:$D$84,AE39)) | M39: =IF(AE39="","",COUNTIFS(INDEX(Calc!$B$2:$BB$61,AE39,0),">="&$C$6,INDEX(Calc!$B$2:$BB$61,AE39,0),"<"&($C$7+1))*INDEX(Setup!$E$25:$E$84,AE39)) | N39: =IF(L39="","",SUMIFS(Payments!$Q$6:$Q$1205,Payments!$I$6:$I$1205,"Bills",Payments!$E$6:$E$1205,L39,Payments!$P$6:$P$1205,">="&$C$6,Payments!$P$6:$P$1205,"<="&$C$7)+SUMIFS('Manual Log'!$E$6:$E$1005,'Manual Log'!$C$6:$C$1005,"Bills",'Manual Log'!$D$6:$D$1005,L39,'Manual Log'!$B$6:$B$1005,">="&$C$6,'Manual Log'!$B$6:$B$1005,"<="&$C$7)) | O39: =IF(L39="","",M39-N39) | Q39: =IF(AF39="","",INDEX(Setup!$D$25:$D$84,AF39)) | R39: =IF(AF39="","",COUNTIFS(INDEX(Calc!$B$2:$BB$61,AF39,0),">="&$C$6,INDEX(Calc!$B$2:$BB$61,AF39,0),"<"&($C$7+1))*INDEX(Setup!$E$25:$E$84,AF39)) | S39: =IF(Q39="","",SUMIFS(Payments!$Q$6:$Q$1205,Payments!$I$6:$I$1205,"Debt",Payments!$E$6:$E$1205,Q39,Payments!$P$6:$P$1205,">="&$C$6,Payments!$P$6:$P$1205,"<="&$C$7)+SUMIFS('Manual Log'!$E$6:$E$1005,'Manual Log'!$C$6:$C$1005,"Debt",'Manual Log'!$D$6:$D$1005,Q39,'Manual Log'!$B$6:$B$1005,">="&$C$6,'Manual Log'!$B$6:$B$1005,"<="&$C$7)) | T39: =IF(Q39="","",R39-S39) | V39: =IF($C$6+8*$V$29>$C$7,"",$C$6+8*$V$29) | W39: =IF(V39="","",SUMIFS(Payments!$Q$6:$Q$1205,Payments!$I$6:$I$1205,"<>Income",Payments!$I$6:$I$1205,"<>Savings",Payments!$P$6:$P$1205,">="&V39,Payments!$P$6:$P$1205,"<"&(V39+$V$29),Payments!$P$6:$P$1205,"<="&$C$7)+SUMIFS('Manual Log'!$E$6:$E$1005,'Manual Log'!$C$6:$C$1005,"<>Income",'Manual Log'!$C$6:$C$1005,"<>Savings",'Manual Log'!$C$6:$C$1005,"<>Transfer",'Manual Log'!$B$6:$B$1005,">="&V39,'Manual Log'!$B$6:$B$1005,"<"&(V39+$V$29),'Manual Log'!$B$6:$B$1005,"<="&$C$7)) | X39: =IF(V39="","",TEXT(V39,"ddd d mmm")) | Y39: =L39 | Z39: =N39 | AA39: =IF(OR(Y39="",N(Z39)<=0),"",Z39+ROW()/1000000) | AC39: =IFERROR(MATCH("Income|9",Setup!$L$25:$L$84,0),"") | AD39: =IFERROR(MATCH("Savings|9",Setup!$L$25:$L$84,0),"") | AE39: =IFERROR(MATCH("Bills|9",Setup!$L$25:$L$84,0),"") | AF39: =IFERROR(MATCH("Debt|9",Setup!$L$25:$L$84,0),"")
B40: =IF(AC40="","",INDEX(Setup!$D$25:$D$84,AC40)) | C40: =IF(AC40="","",COUNTIFS(INDEX(Calc!$B$2:$BB$61,AC40,0),">="&$C$6,INDEX(Calc!$B$2:$BB$61,AC40,0),"<"&($C$7+1))*INDEX(Setup!$E$25:$E$84,AC40)) | D40: =IF(B40="","",SUMIFS(Payments!$Q$6:$Q$1205,Payments!$I$6:$I$1205,"Income",Payments!$E$6:$E$1205,B40,Payments!$P$6:$P$1205,">="&$C$6,Payments!$P$6:$P$1205,"<="&$C$7)+SUMIFS('Manual Log'!$E$6:$E$1005,'Manual Log'!$C$6:$C$1005,"Income",'Manual Log'!$D$6:$D$1005,B40,'Manual Log'!$B$6:$B$1005,">="&$C$6,'Manual Log'!$B$6:$B$1005,"<="&$C$7)) | E40: =IF(B40="","",D40-C40) | G40: =IF(AD40="","",INDEX(Setup!$D$25:$D$84,AD40)) | H40: =IF(AD40="","",COUNTIFS(INDEX(Calc!$B$2:$BB$61,AD40,0),">="&$C$6,INDEX(Calc!$B$2:$BB$61,AD40,0),"<"&($C$7+1))*INDEX(Setup!$E$25:$E$84,AD40)) | I40: =IF(G40="","",SUMIFS(Payments!$Q$6:$Q$1205,Payments!$I$6:$I$1205,"Savings",Payments!$E$6:$E$1205,G40,Payments!$P$6:$P$1205,">="&$C$6,Payments!$P$6:$P$1205,"<="&$C$7)+SUMIFS('Manual Log'!$E$6:$E$1005,'Manual Log'!$C$6:$C$1005,"Savings",'Manual Log'!$D$6:$D$1005,G40,'Manual Log'!$B$6:$B$1005,">="&$C$6,'Manual Log'!$B$6:$B$1005,"<="&$C$7)) | J40: =IF(G40="","",I40-H40) | L40: =IF(AE40="","",INDEX(Setup!$D$25:$D$84,AE40)) | M40: =IF(AE40="","",COUNTIFS(INDEX(Calc!$B$2:$BB$61,AE40,0),">="&$C$6,INDEX(Calc!$B$2:$BB$61,AE40,0),"<"&($C$7+1))*INDEX(Setup!$E$25:$E$84,AE40)) | N40: =IF(L40="","",SUMIFS(Payments!$Q$6:$Q$1205,Payments!$I$6:$I$1205,"Bills",Payments!$E$6:$E$1205,L40,Payments!$P$6:$P$1205,">="&$C$6,Payments!$P$6:$P$1205,"<="&$C$7)+SUMIFS('Manual Log'!$E$6:$E$1005,'Manual Log'!$C$6:$C$1005,"Bills",'Manual Log'!$D$6:$D$1005,L40,'Manual Log'!$B$6:$B$1005,">="&$C$6,'Manual Log'!$B$6:$B$1005,"<="&$C$7)) | O40: =IF(L40="","",M40-N40) | Q40: =IF(AF40="","",INDEX(Setup!$D$25:$D$84,AF40)) | R40: =IF(AF40="","",COUNTIFS(INDEX(Calc!$B$2:$BB$61,AF40,0),">="&$C$6,INDEX(Calc!$B$2:$BB$61,AF40,0),"<"&($C$7+1))*INDEX(Setup!$E$25:$E$84,AF40)) | S40: =IF(Q40="","",SUMIFS(Payments!$Q$6:$Q$1205,Payments!$I$6:$I$1205,"Debt",Payments!$E$6:$E$1205,Q40,Payments!$P$6:$P$1205,">="&$C$6,Payments!$P$6:$P$1205,"<="&$C$7)+SUMIFS('Manual Log'!$E$6:$E$1005,'Manual Log'!$C$6:$C$1005,"Debt",'Manual Log'!$D$6:$D$1005,Q40,'Manual Log'!$B$6:$B$1005,">="&$C$6,'Manual Log'!$B$6:$B$1005,"<="&$C$7)) | T40: =IF(Q40="","",R40-S40) | V40: =IF($C$6+9*$V$29>$C$7,"",$C$6+9*$V$29) | W40: =IF(V40="","",SUMIFS(Payments!$Q$6:$Q$1205,Payments!$I$6:$I$1205,"<>Income",Payments!$I$6:$I$1205,"<>Savings",Payments!$P$6:$P$1205,">="&V40,Payments!$P$6:$P$1205,"<"&(V40+$V$29),Payments!$P$6:$P$1205,"<="&$C$7)+SUMIFS('Manual Log'!$E$6:$E$1005,'Manual Log'!$C$6:$C$1005,"<>Income",'Manual Log'!$C$6:$C$1005,"<>Savings",'Manual Log'!$C$6:$C$1005,"<>Transfer",'Manual Log'!$B$6:$B$1005,">="&V40,'Manual Log'!$B$6:$B$1005,"<"&(V40+$V$29),'Manual Log'!$B$6:$B$1005,"<="&$C$7)) | X40: =IF(V40="","",TEXT(V40,"ddd d mmm")) | Y40: =L40 | Z40: =N40 | AA40: =IF(OR(Y40="",N(Z40)<=0),"",Z40+ROW()/1000000) | AC40: =IFERROR(MATCH("Income|10",Setup!$L$25:$L$84,0),"") | AD40: =IFERROR(MATCH("Savings|10",Setup!$L$25:$L$84,0),"") | AE40: =IFERROR(MATCH("Bills|10",Setup!$L$25:$L$84,0),"") | AF40: =IFERROR(MATCH("Debt|10",Setup!$L$25:$L$84,0),"")
L41: =IF(AE41="","",INDEX(Setup!$D$25:$D$84,AE41)) | M41: =IF(AE41="","",COUNTIFS(INDEX(Calc!$B$2:$BB$61,AE41,0),">="&$C$6,INDEX(Calc!$B$2:$BB$61,AE41,0),"<"&($C$7+1))*INDEX(Setup!$E$25:$E$84,AE41)) | N41: =IF(L41="","",SUMIFS(Payments!$Q$6:$Q$1205,Payments!$I$6:$I$1205,"Bills",Payments!$E$6:$E$1205,L41,Payments!$P$6:$P$1205,">="&$C$6,Payments!$P$6:$P$1205,"<="&$C$7)+SUMIFS('Manual Log'!$E$6:$E$1005,'Manual Log'!$C$6:$C$1005,"Bills",'Manual Log'!$D$6:$D$1005,L41,'Manual Log'!$B$6:$B$1005,">="&$C$6,'Manual Log'!$B$6:$B$1005,"<="&$C$7)) | O41: =IF(L41="","",M41-N41) | V41: =IF($C$6+10*$V$29>$C$7,"",$C$6+10*$V$29) | W41: =IF(V41="","",SUMIFS(Payments!$Q$6:$Q$1205,Payments!$I$6:$I$1205,"<>Income",Payments!$I$6:$I$1205,"<>Savings",Payments!$P$6:$P$1205,">="&V41,Payments!$P$6:$P$1205,"<"&(V41+$V$29),Payments!$P$6:$P$1205,"<="&$C$7)+SUMIFS('Manual Log'!$E$6:$E$1005,'Manual Log'!$C$6:$C$1005,"<>Income",'Manual Log'!$C$6:$C$1005,"<>Savings",'Manual Log'!$C$6:$C$1005,"<>Transfer",'Manual Log'!$B$6:$B$1005,">="&V41,'Manual Log'!$B$6:$B$1005,"<"&(V41+$V$29),'Manual Log'!$B$6:$B$1005,"<="&$C$7)) | X41: =IF(V41="","",TEXT(V41,"ddd d mmm")) | Y41: =L41 | Z41: =N41 | AA41: =IF(OR(Y41="",N(Z41)<=0),"",Z41+ROW()/1000000) | AE41: =IFERROR(MATCH("Bills|11",Setup!$L$25:$L$84,0),"")
L42: =IF(AE42="","",INDEX(Setup!$D$25:$D$84,AE42)) | M42: =IF(AE42="","",COUNTIFS(INDEX(Calc!$B$2:$BB$61,AE42,0),">="&$C$6,INDEX(Calc!$B$2:$BB$61,AE42,0),"<"&($C$7+1))*INDEX(Setup!$E$25:$E$84,AE42)) | N42: =IF(L42="","",SUMIFS(Payments!$Q$6:$Q$1205,Payments!$I$6:$I$1205,"Bills",Payments!$E$6:$E$1205,L42,Payments!$P$6:$P$1205,">="&$C$6,Payments!$P$6:$P$1205,"<="&$C$7)+SUMIFS('Manual Log'!$E$6:$E$1005,'Manual Log'!$C$6:$C$1005,"Bills",'Manual Log'!$D$6:$D$1005,L42,'Manual Log'!$B$6:$B$1005,">="&$C$6,'Manual Log'!$B$6:$B$1005,"<="&$C$7)) | O42: =IF(L42="","",M42-N42) | V42: =IF($C$6+11*$V$29>$C$7,"",$C$6+11*$V$29) | W42: =IF(V42="","",SUMIFS(Payments!$Q$6:$Q$1205,Payments!$I$6:$I$1205,"<>Income",Payments!$I$6:$I$1205,"<>Savings",Payments!$P$6:$P$1205,">="&V42,Payments!$P$6:$P$1205,"<"&(V42+$V$29),Payments!$P$6:$P$1205,"<="&$C$7)+SUMIFS('Manual Log'!$E$6:$E$1005,'Manual Log'!$C$6:$C$1005,"<>Income",'Manual Log'!$C$6:$C$1005,"<>Savings",'Manual Log'!$C$6:$C$1005,"<>Transfer",'Manual Log'!$B$6:$B$1005,">="&V42,'Manual Log'!$B$6:$B$1005,"<"&(V42+$V$29),'Manual Log'!$B$6:$B$1005,"<="&$C$7)) | X42: =IF(V42="","",TEXT(V42,"ddd d mmm")) | Y42: =L42 | Z42: =N42 | AA42: =IF(OR(Y42="",N(Z42)<=0),"",Z42+ROW()/1000000) | AE42: =IFERROR(MATCH("Bills|12",Setup!$L$25:$L$84,0),"")
L43: =IF(AE43="","",INDEX(Setup!$D$25:$D$84,AE43)) | M43: =IF(AE43="","",COUNTIFS(INDEX(Calc!$B$2:$BB$61,AE43,0),">="&$C$6,INDEX(Calc!$B$2:$BB$61,AE43,0),"<"&($C$7+1))*INDEX(Setup!$E$25:$E$84,AE43)) | N43: =IF(L43="","",SUMIFS(Payments!$Q$6:$Q$1205,Payments!$I$6:$I$1205,"Bills",Payments!$E$6:$E$1205,L43,Payments!$P$6:$P$1205,">="&$C$6,Payments!$P$6:$P$1205,"<="&$C$7)+SUMIFS('Manual Log'!$E$6:$E$1005,'Manual Log'!$C$6:$C$1005,"Bills",'Manual Log'!$D$6:$D$1005,L43,'Manual Log'!$B$6:$B$1005,">="&$C$6,'Manual Log'!$B$6:$B$1005,"<="&$C$7)) | O43: =IF(L43="","",M43-N43) | V43: =IF($C$6+12*$V$29>$C$7,"",$C$6+12*$V$29) | W43: =IF(V43="","",SUMIFS(Payments!$Q$6:$Q$1205,Payments!$I$6:$I$1205,"<>Income",Payments!$I$6:$I$1205,"<>Savings",Payments!$P$6:$P$1205,">="&V43,Payments!$P$6:$P$1205,"<"&(V43+$V$29),Payments!$P$6:$P$1205,"<="&$C$7)+SUMIFS('Manual Log'!$E$6:$E$1005,'Manual Log'!$C$6:$C$1005,"<>Income",'Manual Log'!$C$6:$C$1005,"<>Savings",'Manual Log'!$C$6:$C$1005,"<>Transfer",'Manual Log'!$B$6:$B$1005,">="&V43,'Manual Log'!$B$6:$B$1005,"<"&(V43+$V$29),'Manual Log'!$B$6:$B$1005,"<="&$C$7)) | X43: =IF(V43="","",TEXT(V43,"ddd d mmm")) | Y43: =L43 | Z43: =N43 | AA43: =IF(OR(Y43="",N(Z43)<=0),"",Z43+ROW()/1000000) | AE43: =IFERROR(MATCH("Bills|13",Setup!$L$25:$L$84,0),"")
L44: =IF(AE44="","",INDEX(Setup!$D$25:$D$84,AE44)) | M44: =IF(AE44="","",COUNTIFS(INDEX(Calc!$B$2:$BB$61,AE44,0),">="&$C$6,INDEX(Calc!$B$2:$BB$61,AE44,0),"<"&($C$7+1))*INDEX(Setup!$E$25:$E$84,AE44)) | N44: =IF(L44="","",SUMIFS(Payments!$Q$6:$Q$1205,Payments!$I$6:$I$1205,"Bills",Payments!$E$6:$E$1205,L44,Payments!$P$6:$P$1205,">="&$C$6,Payments!$P$6:$P$1205,"<="&$C$7)+SUMIFS('Manual Log'!$E$6:$E$1005,'Manual Log'!$C$6:$C$1005,"Bills",'Manual Log'!$D$6:$D$1005,L44,'Manual Log'!$B$6:$B$1005,">="&$C$6,'Manual Log'!$B$6:$B$1005,"<="&$C$7)) | O44: =IF(L44="","",M44-N44) | V44: =IF($C$6+13*$V$29>$C$7,"",$C$6+13*$V$29) | W44: =IF(V44="","",SUMIFS(Payments!$Q$6:$Q$1205,Payments!$I$6:$I$1205,"<>Income",Payments!$I$6:$I$1205,"<>Savings",Payments!$P$6:$P$1205,">="&V44,Payments!$P$6:$P$1205,"<"&(V44+$V$29),Payments!$P$6:$P$1205,"<="&$C$7)+SUMIFS('Manual Log'!$E$6:$E$1005,'Manual Log'!$C$6:$C$1005,"<>Income",'Manual Log'!$C$6:$C$1005,"<>Savings",'Manual Log'!$C$6:$C$1005,"<>Transfer",'Manual Log'!$B$6:$B$1005,">="&V44,'Manual Log'!$B$6:$B$1005,"<"&(V44+$V$29),'Manual Log'!$B$6:$B$1005,"<="&$C$7)) | X44: =IF(V44="","",TEXT(V44,"ddd d mmm")) | Y44: =L44 | Z44: =N44 | AA44: =IF(OR(Y44="",N(Z44)<=0),"",Z44+ROW()/1000000) | AE44: =IFERROR(MATCH("Bills|14",Setup!$L$25:$L$84,0),"")
L45: =IF(AE45="","",INDEX(Setup!$D$25:$D$84,AE45)) | M45: =IF(AE45="","",COUNTIFS(INDEX(Calc!$B$2:$BB$61,AE45,0),">="&$C$6,INDEX(Calc!$B$2:$BB$61,AE45,0),"<"&($C$7+1))*INDEX(Setup!$E$25:$E$84,AE45)) | N45: =IF(L45="","",SUMIFS(Payments!$Q$6:$Q$1205,Payments!$I$6:$I$1205,"Bills",Payments!$E$6:$E$1205,L45,Payments!$P$6:$P$1205,">="&$C$6,Payments!$P$6:$P$1205,"<="&$C$7)+SUMIFS('Manual Log'!$E$6:$E$1005,'Manual Log'!$C$6:$C$1005,"Bills",'Manual Log'!$D$6:$D$1005,L45,'Manual Log'!$B$6:$B$1005,">="&$C$6,'Manual Log'!$B$6:$B$1005,"<="&$C$7)) | O45: =IF(L45="","",M45-N45) | V45: =IF($C$6+14*$V$29>$C$7,"",$C$6+14*$V$29) | W45: =IF(V45="","",SUMIFS(Payments!$Q$6:$Q$1205,Payments!$I$6:$I$1205,"<>Income",Payments!$I$6:$I$1205,"<>Savings",Payments!$P$6:$P$1205,">="&V45,Payments!$P$6:$P$1205,"<"&(V45+$V$29),Payments!$P$6:$P$1205,"<="&$C$7)+SUMIFS('Manual Log'!$E$6:$E$1005,'Manual Log'!$C$6:$C$1005,"<>Income",'Manual Log'!$C$6:$C$1005,"<>Savings",'Manual Log'!$C$6:$C$1005,"<>Transfer",'Manual Log'!$B$6:$B$1005,">="&V45,'Manual Log'!$B$6:$B$1005,"<"&(V45+$V$29),'Manual Log'!$B$6:$B$1005,"<="&$C$7)) | X45: =IF(V45="","",TEXT(V45,"ddd d mmm")) | Y45: =L45 | Z45: =N45 | AA45: =IF(OR(Y45="",N(Z45)<=0),"",Z45+ROW()/1000000) | AE45: =IFERROR(MATCH("Bills|15",Setup!$L$25:$L$84,0),"")
V46: =IF($C$6+15*$V$29>$C$7,"",$C$6+15*$V$29) | W46: =IF(V46="","",SUMIFS(Payments!$Q$6:$Q$1205,Payments!$I$6:$I$1205,"<>Income",Payments!$I$6:$I$1205,"<>Savings",Payments!$P$6:$P$1205,">="&V46,Payments!$P$6:$P$1205,"<"&(V46+$V$29),Payments!$P$6:$P$1205,"<="&$C$7)+SUMIFS('Manual Log'!$E$6:$E$1005,'Manual Log'!$C$6:$C$1005,"<>Income",'Manual Log'!$C$6:$C$1005,"<>Savings",'Manual Log'!$C$6:$C$1005,"<>Transfer",'Manual Log'!$B$6:$B$1005,">="&V46,'Manual Log'!$B$6:$B$1005,"<"&(V46+$V$29),'Manual Log'!$B$6:$B$1005,"<="&$C$7)) | X46: =IF(V46="","",TEXT(V46,"ddd d mmm")) | Y46: =Q31 | Z46: =S31 | AA46: =IF(OR(Y46="",N(Z46)<=0),"",Z46+ROW()/1000000)
V47: =IF($C$6+16*$V$29>$C$7,"",$C$6+16*$V$29) | W47: =IF(V47="","",SUMIFS(Payments!$Q$6:$Q$1205,Payments!$I$6:$I$1205,"<>Income",Payments!$I$6:$I$1205,"<>Savings",Payments!$P$6:$P$1205,">="&V47,Payments!$P$6:$P$1205,"<"&(V47+$V$29),Payments!$P$6:$P$1205,"<="&$C$7)+SUMIFS('Manual Log'!$E$6:$E$1005,'Manual Log'!$C$6:$C$1005,"<>Income",'Manual Log'!$C$6:$C$1005,"<>Savings",'Manual Log'!$C$6:$C$1005,"<>Transfer",'Manual Log'!$B$6:$B$1005,">="&V47,'Manual Log'!$B$6:$B$1005,"<"&(V47+$V$29),'Manual Log'!$B$6:$B$1005,"<="&$C$7)) | X47: =IF(V47="","",TEXT(V47,"ddd d mmm")) | Y47: =Q32 | Z47: =S32 | AA47: =IF(OR(Y47="",N(Z47)<=0),"",Z47+ROW()/1000000)
B48: SUBSCRIPTIONS | G48: VARIABLE EXPENSES | L48: HIGHEST TO LOWEST EXPENSES | Q48: DAILY SPENDING | V48: =IF($C$6+17*$V$29>$C$7,"",$C$6+17*$V$29) | W48: =IF(V48="","",SUMIFS(Payments!$Q$6:$Q$1205,Payments!$I$6:$I$1205,"<>Income",Payments!$I$6:$I$1205,"<>Savings",Payments!$P$6:$P$1205,">="&V48,Payments!$P$6:$P$1205,"<"&(V48+$V$29),Payments!$P$6:$P$1205,"<="&$C$7)+SUMIFS('Manual Log'!$E$6:$E$1005,'Manual Log'!$C$6:$C$1005,"<>Income",'Manual Log'!$C$6:$C$1005,"<>Savings",'Manual Log'!$C$6:$C$1005,"<>Transfer",'Manual Log'!$B$6:$B$1005,">="&V48,'Manual Log'!$B$6:$B$1005,"<"&(V48+$V$29),'Manual Log'!$B$6:$B$1005,"<="&$C$7)) | X48: =IF(V48="","",TEXT(V48,"ddd d mmm")) | Y48: =Q33 | Z48: =S33 | AA48: =IF(OR(Y48="",N(Z48)<=0),"",Z48+ROW()/1000000)
B49: =D51 | G49: =I51 | L49: =J6 | V49: =IF($C$6+18*$V$29>$C$7,"",$C$6+18*$V$29) | W49: =IF(V49="","",SUMIFS(Payments!$Q$6:$Q$1205,Payments!$I$6:$I$1205,"<>Income",Payments!$I$6:$I$1205,"<>Savings",Payments!$P$6:$P$1205,">="&V49,Payments!$P$6:$P$1205,"<"&(V49+$V$29),Payments!$P$6:$P$1205,"<="&$C$7)+SUMIFS('Manual Log'!$E$6:$E$1005,'Manual Log'!$C$6:$C$1005,"<>Income",'Manual Log'!$C$6:$C$1005,"<>Savings",'Manual Log'!$C$6:$C$1005,"<>Transfer",'Manual Log'!$B$6:$B$1005,">="&V49,'Manual Log'!$B$6:$B$1005,"<"&(V49+$V$29),'Manual Log'!$B$6:$B$1005,"<="&$C$7)) | X49: =IF(V49="","",TEXT(V49,"ddd d mmm")) | Y49: =Q34 | Z49: =S34 | AA49: =IF(OR(Y49="",N(Z49)<=0),"",Z49+ROW()/1000000)
B50: SUB-CATEGORY | C50: BUDGET | D50: ACTUAL | E50: REMAINING | G50: SUB-CATEGORY | H50: BUDGET | I50: ACTUAL | J50: REMAINING | L50: CATEGORY | M50: AMOUNT | N50: % OF TOTAL | V50: =IF($C$6+19*$V$29>$C$7,"",$C$6+19*$V$29) | W50: =IF(V50="","",SUMIFS(Payments!$Q$6:$Q$1205,Payments!$I$6:$I$1205,"<>Income",Payments!$I$6:$I$1205,"<>Savings",Payments!$P$6:$P$1205,">="&V50,Payments!$P$6:$P$1205,"<"&(V50+$V$29),Payments!$P$6:$P$1205,"<="&$C$7)+SUMIFS('Manual Log'!$E$6:$E$1005,'Manual Log'!$C$6:$C$1005,"<>Income",'Manual Log'!$C$6:$C$1005,"<>Savings",'Manual Log'!$C$6:$C$1005,"<>Transfer",'Manual Log'!$B$6:$B$1005,">="&V50,'Manual Log'!$B$6:$B$1005,"<"&(V50+$V$29),'Manual Log'!$B$6:$B$1005,"<="&$C$7)) | X50: =IF(V50="","",TEXT(V50,"ddd d mmm")) | Y50: =Q35 | Z50: =S35 | AA50: =IF(OR(Y50="",N(Z50)<=0),"",Z50+ROW()/1000000)
B51: TOTAL | C51: =SUM(C52:C61) | D51: =SUM(D52:D61) | E51: =SUM(E52:E61) | G51: TOTAL | H51: =SUM(H52:H66) | I51: =SUM(I52:I66) | J51: =SUM(J52:J66) | L51: =IFERROR(INDEX($Y$31:$Y$80,MATCH(LARGE($AA$31:$AA$80,1),$AA$31:$AA$80,0)),"") | M51: =IFERROR(INDEX($Z$31:$Z$80,MATCH(LARGE($AA$31:$AA$80,1),$AA$31:$AA$80,0)),"") | N51: =IFERROR(M51/$J$6,"") | V51: =IF($C$6+20*$V$29>$C$7,"",$C$6+20*$V$29) | W51: =IF(V51="","",SUMIFS(Payments!$Q$6:$Q$1205,Payments!$I$6:$I$1205,"<>Income",Payments!$I$6:$I$1205,"<>Savings",Payments!$P$6:$P$1205,">="&V51,Payments!$P$6:$P$1205,"<"&(V51+$V$29),Payments!$P$6:$P$1205,"<="&$C$7)+SUMIFS('Manual Log'!$E$6:$E$1005,'Manual Log'!$C$6:$C$1005,"<>Income",'Manual Log'!$C$6:$C$1005,"<>Savings",'Manual Log'!$C$6:$C$1005,"<>Transfer",'Manual Log'!$B$6:$B$1005,">="&V51,'Manual Log'!$B$6:$B$1005,"<"&(V51+$V$29),'Manual Log'!$B$6:$B$1005,"<="&$C$7)) | X51: =IF(V51="","",TEXT(V51,"ddd d mmm")) | Y51: =Q36 | Z51: =S36 | AA51: =IF(OR(Y51="",N(Z51)<=0),"",Z51+ROW()/1000000)
B52: =IF(AG52="","",INDEX(Setup!$D$25:$D$84,AG52)) | C52: =IF(AG52="","",COUNTIFS(INDEX(Calc!$B$2:$BB$61,AG52,0),">="&$C$6,INDEX(Calc!$B$2:$BB$61,AG52,0),"<"&($C$7+1))*INDEX(Setup!$E$25:$E$84,AG52)) | D52: =IF(B52="","",SUMIFS(Payments!$Q$6:$Q$1205,Payments!$I$6:$I$1205,"Subscriptions",Payments!$E$6:$E$1205,B52,Payments!$P$6:$P$1205,">="&$C$6,Payments!$P$6:$P$1205,"<="&$C$7)+SUMIFS('Manual Log'!$E$6:$E$1005,'Manual Log'!$C$6:$C$1005,"Subscriptions",'Manual Log'!$D$6:$D$1005,B52,'Manual Log'!$B$6:$B$1005,">="&$C$6,'Manual Log'!$B$6:$B$1005,"<="&$C$7)) | E52: =IF(B52="","",C52-D52) | G52: =IF(Setup!$I$6="","",Setup!$I$6) | H52: =IF(G52="","",IF($C$5="Monthly",Setup!$J$6,Setup!$J$6*($C$7-$C$6+1)*12/365)) | I52: =IF(G52="","",SUMIFS(Payments!$Q$6:$Q$1205,Payments!$I$6:$I$1205,"Variable Exp",Payments!$E$6:$E$1205,G52,Payments!$P$6:$P$1205,">="&$C$6,Payments!$P$6:$P$1205,"<="&$C$7)+SUMIFS('Manual Log'!$E$6:$E$1005,'Manual Log'!$C$6:$C$1005,"Variable Exp",'Manual Log'!$D$6:$D$1005,G52,'Manual Log'!$B$6:$B$1005,">="&$C$6,'Manual Log'!$B$6:$B$1005,"<="&$C$7)) | J52: =IF(G52="","",H52-I52) | L52: =IFERROR(INDEX($Y$31:$Y$80,MATCH(LARGE($AA$31:$AA$80,2),$AA$31:$AA$80,0)),"") | M52: =IFERROR(INDEX($Z$31:$Z$80,MATCH(LARGE($AA$31:$AA$80,2),$AA$31:$AA$80,0)),"") | N52: =IFERROR(M52/$J$6,"") | V52: =IF($C$6+21*$V$29>$C$7,"",$C$6+21*$V$29) | W52: =IF(V52="","",SUMIFS(Payments!$Q$6:$Q$1205,Payments!$I$6:$I$1205,"<>Income",Payments!$I$6:$I$1205,"<>Savings",Payments!$P$6:$P$1205,">="&V52,Payments!$P$6:$P$1205,"<"&(V52+$V$29),Payments!$P$6:$P$1205,"<="&$C$7)+SUMIFS('Manual Log'!$E$6:$E$1005,'Manual Log'!$C$6:$C$1005,"<>Income",'Manual Log'!$C$6:$C$1005,"<>Savings",'Manual Log'!$C$6:$C$1005,"<>Transfer",'Manual Log'!$B$6:$B$1005,">="&V52,'Manual Log'!$B$6:$B$1005,"<"&(V52+$V$29),'Manual Log'!$B$6:$B$1005,"<="&$C$7)) | X52: =IF(V52="","",TEXT(V52,"ddd d mmm")) | Y52: =Q37 | Z52: =S37 | AA52: =IF(OR(Y52="",N(Z52)<=0),"",Z52+ROW()/1000000) | AG52: =IFERROR(MATCH("Subscriptions|1",Setup!$L$25:$L$84,0),"")
B53: =IF(AG53="","",INDEX(Setup!$D$25:$D$84,AG53)) | C53: =IF(AG53="","",COUNTIFS(INDEX(Calc!$B$2:$BB$61,AG53,0),">="&$C$6,INDEX(Calc!$B$2:$BB$61,AG53,0),"<"&($C$7+1))*INDEX(Setup!$E$25:$E$84,AG53)) | D53: =IF(B53="","",SUMIFS(Payments!$Q$6:$Q$1205,Payments!$I$6:$I$1205,"Subscriptions",Payments!$E$6:$E$1205,B53,Payments!$P$6:$P$1205,">="&$C$6,Payments!$P$6:$P$1205,"<="&$C$7)+SUMIFS('Manual Log'!$E$6:$E$1005,'Manual Log'!$C$6:$C$1005,"Subscriptions",'Manual Log'!$D$6:$D$1005,B53,'Manual Log'!$B$6:$B$1005,">="&$C$6,'Manual Log'!$B$6:$B$1005,"<="&$C$7)) | E53: =IF(B53="","",C53-D53) | G53: =IF(Setup!$I$7="","",Setup!$I$7) | H53: =IF(G53="","",IF($C$5="Monthly",Setup!$J$7,Setup!$J$7*($C$7-$C$6+1)*12/365)) | I53: =IF(G53="","",SUMIFS(Payments!$Q$6:$Q$1205,Payments!$I$6:$I$1205,"Variable Exp",Payments!$E$6:$E$1205,G53,Payments!$P$6:$P$1205,">="&$C$6,Payments!$P$6:$P$1205,"<="&$C$7)+SUMIFS('Manual Log'!$E$6:$E$1005,'Manual Log'!$C$6:$C$1005,"Variable Exp",'Manual Log'!$D$6:$D$1005,G53,'Manual Log'!$B$6:$B$1005,">="&$C$6,'Manual Log'!$B$6:$B$1005,"<="&$C$7)) | J53: =IF(G53="","",H53-I53) | L53: =IFERROR(INDEX($Y$31:$Y$80,MATCH(LARGE($AA$31:$AA$80,3),$AA$31:$AA$80,0)),"") | M53: =IFERROR(INDEX($Z$31:$Z$80,MATCH(LARGE($AA$31:$AA$80,3),$AA$31:$AA$80,0)),"") | N53: =IFERROR(M53/$J$6,"") | V53: =IF($C$6+22*$V$29>$C$7,"",$C$6+22*$V$29) | W53: =IF(V53="","",SUMIFS(Payments!$Q$6:$Q$1205,Payments!$I$6:$I$1205,"<>Income",Payments!$I$6:$I$1205,"<>Savings",Payments!$P$6:$P$1205,">="&V53,Payments!$P$6:$P$1205,"<"&(V53+$V$29),Payments!$P$6:$P$1205,"<="&$C$7)+SUMIFS('Manual Log'!$E$6:$E$1005,'Manual Log'!$C$6:$C$1005,"<>Income",'Manual Log'!$C$6:$C$1005,"<>Savings",'Manual Log'!$C$6:$C$1005,"<>Transfer",'Manual Log'!$B$6:$B$1005,">="&V53,'Manual Log'!$B$6:$B$1005,"<"&(V53+$V$29),'Manual Log'!$B$6:$B$1005,"<="&$C$7)) | X53: =IF(V53="","",TEXT(V53,"ddd d mmm")) | Y53: =Q38 | Z53: =S38 | AA53: =IF(OR(Y53="",N(Z53)<=0),"",Z53+ROW()/1000000) | AG53: =IFERROR(MATCH("Subscriptions|2",Setup!$L$25:$L$84,0),"")
B54: =IF(AG54="","",INDEX(Setup!$D$25:$D$84,AG54)) | C54: =IF(AG54="","",COUNTIFS(INDEX(Calc!$B$2:$BB$61,AG54,0),">="&$C$6,INDEX(Calc!$B$2:$BB$61,AG54,0),"<"&($C$7+1))*INDEX(Setup!$E$25:$E$84,AG54)) | D54: =IF(B54="","",SUMIFS(Payments!$Q$6:$Q$1205,Payments!$I$6:$I$1205,"Subscriptions",Payments!$E$6:$E$1205,B54,Payments!$P$6:$P$1205,">="&$C$6,Payments!$P$6:$P$1205,"<="&$C$7)+SUMIFS('Manual Log'!$E$6:$E$1005,'Manual Log'!$C$6:$C$1005,"Subscriptions",'Manual Log'!$D$6:$D$1005,B54,'Manual Log'!$B$6:$B$1005,">="&$C$6,'Manual Log'!$B$6:$B$1005,"<="&$C$7)) | E54: =IF(B54="","",C54-D54) | G54: =IF(Setup!$I$8="","",Setup!$I$8) | H54: =IF(G54="","",IF($C$5="Monthly",Setup!$J$8,Setup!$J$8*($C$7-$C$6+1)*12/365)) | I54: =IF(G54="","",SUMIFS(Payments!$Q$6:$Q$1205,Payments!$I$6:$I$1205,"Variable Exp",Payments!$E$6:$E$1205,G54,Payments!$P$6:$P$1205,">="&$C$6,Payments!$P$6:$P$1205,"<="&$C$7)+SUMIFS('Manual Log'!$E$6:$E$1005,'Manual Log'!$C$6:$C$1005,"Variable Exp",'Manual Log'!$D$6:$D$1005,G54,'Manual Log'!$B$6:$B$1005,">="&$C$6,'Manual Log'!$B$6:$B$1005,"<="&$C$7)) | J54: =IF(G54="","",H54-I54) | L54: =IFERROR(INDEX($Y$31:$Y$80,MATCH(LARGE($AA$31:$AA$80,4),$AA$31:$AA$80,0)),"") | M54: =IFERROR(INDEX($Z$31:$Z$80,MATCH(LARGE($AA$31:$AA$80,4),$AA$31:$AA$80,0)),"") | N54: =IFERROR(M54/$J$6,"") | V54: =IF($C$6+23*$V$29>$C$7,"",$C$6+23*$V$29) | W54: =IF(V54="","",SUMIFS(Payments!$Q$6:$Q$1205,Payments!$I$6:$I$1205,"<>Income",Payments!$I$6:$I$1205,"<>Savings",Payments!$P$6:$P$1205,">="&V54,Payments!$P$6:$P$1205,"<"&(V54+$V$29),Payments!$P$6:$P$1205,"<="&$C$7)+SUMIFS('Manual Log'!$E$6:$E$1005,'Manual Log'!$C$6:$C$1005,"<>Income",'Manual Log'!$C$6:$C$1005,"<>Savings",'Manual Log'!$C$6:$C$1005,"<>Transfer",'Manual Log'!$B$6:$B$1005,">="&V54,'Manual Log'!$B$6:$B$1005,"<"&(V54+$V$29),'Manual Log'!$B$6:$B$1005,"<="&$C$7)) | X54: =IF(V54="","",TEXT(V54,"ddd d mmm")) | Y54: =Q39 | Z54: =S39 | AA54: =IF(OR(Y54="",N(Z54)<=0),"",Z54+ROW()/1000000) | AG54: =IFERROR(MATCH("Subscriptions|3",Setup!$L$25:$L$84,0),"")
B55: =IF(AG55="","",INDEX(Setup!$D$25:$D$84,AG55)) | C55: =IF(AG55="","",COUNTIFS(INDEX(Calc!$B$2:$BB$61,AG55,0),">="&$C$6,INDEX(Calc!$B$2:$BB$61,AG55,0),"<"&($C$7+1))*INDEX(Setup!$E$25:$E$84,AG55)) | D55: =IF(B55="","",SUMIFS(Payments!$Q$6:$Q$1205,Payments!$I$6:$I$1205,"Subscriptions",Payments!$E$6:$E$1205,B55,Payments!$P$6:$P$1205,">="&$C$6,Payments!$P$6:$P$1205,"<="&$C$7)+SUMIFS('Manual Log'!$E$6:$E$1005,'Manual Log'!$C$6:$C$1005,"Subscriptions",'Manual Log'!$D$6:$D$1005,B55,'Manual Log'!$B$6:$B$1005,">="&$C$6,'Manual Log'!$B$6:$B$1005,"<="&$C$7)) | E55: =IF(B55="","",C55-D55) | G55: =IF(Setup!$I$9="","",Setup!$I$9) | H55: =IF(G55="","",IF($C$5="Monthly",Setup!$J$9,Setup!$J$9*($C$7-$C$6+1)*12/365)) | I55: =IF(G55="","",SUMIFS(Payments!$Q$6:$Q$1205,Payments!$I$6:$I$1205,"Variable Exp",Payments!$E$6:$E$1205,G55,Payments!$P$6:$P$1205,">="&$C$6,Payments!$P$6:$P$1205,"<="&$C$7)+SUMIFS('Manual Log'!$E$6:$E$1005,'Manual Log'!$C$6:$C$1005,"Variable Exp",'Manual Log'!$D$6:$D$1005,G55,'Manual Log'!$B$6:$B$1005,">="&$C$6,'Manual Log'!$B$6:$B$1005,"<="&$C$7)) | J55: =IF(G55="","",H55-I55) | L55: =IFERROR(INDEX($Y$31:$Y$80,MATCH(LARGE($AA$31:$AA$80,5),$AA$31:$AA$80,0)),"") | M55: =IFERROR(INDEX($Z$31:$Z$80,MATCH(LARGE($AA$31:$AA$80,5),$AA$31:$AA$80,0)),"") | N55: =IFERROR(M55/$J$6,"") | V55: =IF($C$6+24*$V$29>$C$7,"",$C$6+24*$V$29) | W55: =IF(V55="","",SUMIFS(Payments!$Q$6:$Q$1205,Payments!$I$6:$I$1205,"<>Income",Payments!$I$6:$I$1205,"<>Savings",Payments!$P$6:$P$1205,">="&V55,Payments!$P$6:$P$1205,"<"&(V55+$V$29),Payments!$P$6:$P$1205,"<="&$C$7)+SUMIFS('Manual Log'!$E$6:$E$1005,'Manual Log'!$C$6:$C$1005,"<>Income",'Manual Log'!$C$6:$C$1005,"<>Savings",'Manual Log'!$C$6:$C$1005,"<>Transfer",'Manual Log'!$B$6:$B$1005,">="&V55,'Manual Log'!$B$6:$B$1005,"<"&(V55+$V$29),'Manual Log'!$B$6:$B$1005,"<="&$C$7)) | X55: =IF(V55="","",TEXT(V55,"ddd d mmm")) | Y55: =Q40 | Z55: =S40 | AA55: =IF(OR(Y55="",N(Z55)<=0),"",Z55+ROW()/1000000) | AG55: =IFERROR(MATCH("Subscriptions|4",Setup!$L$25:$L$84,0),"")
B56: =IF(AG56="","",INDEX(Setup!$D$25:$D$84,AG56)) | C56: =IF(AG56="","",COUNTIFS(INDEX(Calc!$B$2:$BB$61,AG56,0),">="&$C$6,INDEX(Calc!$B$2:$BB$61,AG56,0),"<"&($C$7+1))*INDEX(Setup!$E$25:$E$84,AG56)) | D56: =IF(B56="","",SUMIFS(Payments!$Q$6:$Q$1205,Payments!$I$6:$I$1205,"Subscriptions",Payments!$E$6:$E$1205,B56,Payments!$P$6:$P$1205,">="&$C$6,Payments!$P$6:$P$1205,"<="&$C$7)+SUMIFS('Manual Log'!$E$6:$E$1005,'Manual Log'!$C$6:$C$1005,"Subscriptions",'Manual Log'!$D$6:$D$1005,B56,'Manual Log'!$B$6:$B$1005,">="&$C$6,'Manual Log'!$B$6:$B$1005,"<="&$C$7)) | E56: =IF(B56="","",C56-D56) | G56: =IF(Setup!$I$10="","",Setup!$I$10) | H56: =IF(G56="","",IF($C$5="Monthly",Setup!$J$10,Setup!$J$10*($C$7-$C$6+1)*12/365)) | I56: =IF(G56="","",SUMIFS(Payments!$Q$6:$Q$1205,Payments!$I$6:$I$1205,"Variable Exp",Payments!$E$6:$E$1205,G56,Payments!$P$6:$P$1205,">="&$C$6,Payments!$P$6:$P$1205,"<="&$C$7)+SUMIFS('Manual Log'!$E$6:$E$1005,'Manual Log'!$C$6:$C$1005,"Variable Exp",'Manual Log'!$D$6:$D$1005,G56,'Manual Log'!$B$6:$B$1005,">="&$C$6,'Manual Log'!$B$6:$B$1005,"<="&$C$7)) | J56: =IF(G56="","",H56-I56) | L56: =IFERROR(INDEX($Y$31:$Y$80,MATCH(LARGE($AA$31:$AA$80,6),$AA$31:$AA$80,0)),"") | M56: =IFERROR(INDEX($Z$31:$Z$80,MATCH(LARGE($AA$31:$AA$80,6),$AA$31:$AA$80,0)),"") | N56: =IFERROR(M56/$J$6,"") | V56: =IF($C$6+25*$V$29>$C$7,"",$C$6+25*$V$29) | W56: =IF(V56="","",SUMIFS(Payments!$Q$6:$Q$1205,Payments!$I$6:$I$1205,"<>Income",Payments!$I$6:$I$1205,"<>Savings",Payments!$P$6:$P$1205,">="&V56,Payments!$P$6:$P$1205,"<"&(V56+$V$29),Payments!$P$6:$P$1205,"<="&$C$7)+SUMIFS('Manual Log'!$E$6:$E$1005,'Manual Log'!$C$6:$C$1005,"<>Income",'Manual Log'!$C$6:$C$1005,"<>Savings",'Manual Log'!$C$6:$C$1005,"<>Transfer",'Manual Log'!$B$6:$B$1005,">="&V56,'Manual Log'!$B$6:$B$1005,"<"&(V56+$V$29),'Manual Log'!$B$6:$B$1005,"<="&$C$7)) | X56: =IF(V56="","",TEXT(V56,"ddd d mmm")) | Y56: =B52 | Z56: =D52 | AA56: =IF(OR(Y56="",N(Z56)<=0),"",Z56+ROW()/1000000) | AG56: =IFERROR(MATCH("Subscriptions|5",Setup!$L$25:$L$84,0),"")
B57: =IF(AG57="","",INDEX(Setup!$D$25:$D$84,AG57)) | C57: =IF(AG57="","",COUNTIFS(INDEX(Calc!$B$2:$BB$61,AG57,0),">="&$C$6,INDEX(Calc!$B$2:$BB$61,AG57,0),"<"&($C$7+1))*INDEX(Setup!$E$25:$E$84,AG57)) | D57: =IF(B57="","",SUMIFS(Payments!$Q$6:$Q$1205,Payments!$I$6:$I$1205,"Subscriptions",Payments!$E$6:$E$1205,B57,Payments!$P$6:$P$1205,">="&$C$6,Payments!$P$6:$P$1205,"<="&$C$7)+SUMIFS('Manual Log'!$E$6:$E$1005,'Manual Log'!$C$6:$C$1005,"Subscriptions",'Manual Log'!$D$6:$D$1005,B57,'Manual Log'!$B$6:$B$1005,">="&$C$6,'Manual Log'!$B$6:$B$1005,"<="&$C$7)) | E57: =IF(B57="","",C57-D57) | G57: =IF(Setup!$I$11="","",Setup!$I$11) | H57: =IF(G57="","",IF($C$5="Monthly",Setup!$J$11,Setup!$J$11*($C$7-$C$6+1)*12/365)) | I57: =IF(G57="","",SUMIFS(Payments!$Q$6:$Q$1205,Payments!$I$6:$I$1205,"Variable Exp",Payments!$E$6:$E$1205,G57,Payments!$P$6:$P$1205,">="&$C$6,Payments!$P$6:$P$1205,"<="&$C$7)+SUMIFS('Manual Log'!$E$6:$E$1005,'Manual Log'!$C$6:$C$1005,"Variable Exp",'Manual Log'!$D$6:$D$1005,G57,'Manual Log'!$B$6:$B$1005,">="&$C$6,'Manual Log'!$B$6:$B$1005,"<="&$C$7)) | J57: =IF(G57="","",H57-I57) | L57: =IFERROR(INDEX($Y$31:$Y$80,MATCH(LARGE($AA$31:$AA$80,7),$AA$31:$AA$80,0)),"") | M57: =IFERROR(INDEX($Z$31:$Z$80,MATCH(LARGE($AA$31:$AA$80,7),$AA$31:$AA$80,0)),"") | N57: =IFERROR(M57/$J$6,"") | V57: =IF($C$6+26*$V$29>$C$7,"",$C$6+26*$V$29) | W57: =IF(V57="","",SUMIFS(Payments!$Q$6:$Q$1205,Payments!$I$6:$I$1205,"<>Income",Payments!$I$6:$I$1205,"<>Savings",Payments!$P$6:$P$1205,">="&V57,Payments!$P$6:$P$1205,"<"&(V57+$V$29),Payments!$P$6:$P$1205,"<="&$C$7)+SUMIFS('Manual Log'!$E$6:$E$1005,'Manual Log'!$C$6:$C$1005,"<>Income",'Manual Log'!$C$6:$C$1005,"<>Savings",'Manual Log'!$C$6:$C$1005,"<>Transfer",'Manual Log'!$B$6:$B$1005,">="&V57,'Manual Log'!$B$6:$B$1005,"<"&(V57+$V$29),'Manual Log'!$B$6:$B$1005,"<="&$C$7)) | X57: =IF(V57="","",TEXT(V57,"ddd d mmm")) | Y57: =B53 | Z57: =D53 | AA57: =IF(OR(Y57="",N(Z57)<=0),"",Z57+ROW()/1000000) | AG57: =IFERROR(MATCH("Subscriptions|6",Setup!$L$25:$L$84,0),"")
B58: =IF(AG58="","",INDEX(Setup!$D$25:$D$84,AG58)) | C58: =IF(AG58="","",COUNTIFS(INDEX(Calc!$B$2:$BB$61,AG58,0),">="&$C$6,INDEX(Calc!$B$2:$BB$61,AG58,0),"<"&($C$7+1))*INDEX(Setup!$E$25:$E$84,AG58)) | D58: =IF(B58="","",SUMIFS(Payments!$Q$6:$Q$1205,Payments!$I$6:$I$1205,"Subscriptions",Payments!$E$6:$E$1205,B58,Payments!$P$6:$P$1205,">="&$C$6,Payments!$P$6:$P$1205,"<="&$C$7)+SUMIFS('Manual Log'!$E$6:$E$1005,'Manual Log'!$C$6:$C$1005,"Subscriptions",'Manual Log'!$D$6:$D$1005,B58,'Manual Log'!$B$6:$B$1005,">="&$C$6,'Manual Log'!$B$6:$B$1005,"<="&$C$7)) | E58: =IF(B58="","",C58-D58) | G58: =IF(Setup!$I$12="","",Setup!$I$12) | H58: =IF(G58="","",IF($C$5="Monthly",Setup!$J$12,Setup!$J$12*($C$7-$C$6+1)*12/365)) | I58: =IF(G58="","",SUMIFS(Payments!$Q$6:$Q$1205,Payments!$I$6:$I$1205,"Variable Exp",Payments!$E$6:$E$1205,G58,Payments!$P$6:$P$1205,">="&$C$6,Payments!$P$6:$P$1205,"<="&$C$7)+SUMIFS('Manual Log'!$E$6:$E$1005,'Manual Log'!$C$6:$C$1005,"Variable Exp",'Manual Log'!$D$6:$D$1005,G58,'Manual Log'!$B$6:$B$1005,">="&$C$6,'Manual Log'!$B$6:$B$1005,"<="&$C$7)) | J58: =IF(G58="","",H58-I58) | L58: =IFERROR(INDEX($Y$31:$Y$80,MATCH(LARGE($AA$31:$AA$80,8),$AA$31:$AA$80,0)),"") | M58: =IFERROR(INDEX($Z$31:$Z$80,MATCH(LARGE($AA$31:$AA$80,8),$AA$31:$AA$80,0)),"") | N58: =IFERROR(M58/$J$6,"") | V58: =IF($C$6+27*$V$29>$C$7,"",$C$6+27*$V$29) | W58: =IF(V58="","",SUMIFS(Payments!$Q$6:$Q$1205,Payments!$I$6:$I$1205,"<>Income",Payments!$I$6:$I$1205,"<>Savings",Payments!$P$6:$P$1205,">="&V58,Payments!$P$6:$P$1205,"<"&(V58+$V$29),Payments!$P$6:$P$1205,"<="&$C$7)+SUMIFS('Manual Log'!$E$6:$E$1005,'Manual Log'!$C$6:$C$1005,"<>Income",'Manual Log'!$C$6:$C$1005,"<>Savings",'Manual Log'!$C$6:$C$1005,"<>Transfer",'Manual Log'!$B$6:$B$1005,">="&V58,'Manual Log'!$B$6:$B$1005,"<"&(V58+$V$29),'Manual Log'!$B$6:$B$1005,"<="&$C$7)) | X58: =IF(V58="","",TEXT(V58,"ddd d mmm")) | Y58: =B54 | Z58: =D54 | AA58: =IF(OR(Y58="",N(Z58)<=0),"",Z58+ROW()/1000000) | AG58: =IFERROR(MATCH("Subscriptions|7",Setup!$L$25:$L$84,0),"")
B59: =IF(AG59="","",INDEX(Setup!$D$25:$D$84,AG59)) | C59: =IF(AG59="","",COUNTIFS(INDEX(Calc!$B$2:$BB$61,AG59,0),">="&$C$6,INDEX(Calc!$B$2:$BB$61,AG59,0),"<"&($C$7+1))*INDEX(Setup!$E$25:$E$84,AG59)) | D59: =IF(B59="","",SUMIFS(Payments!$Q$6:$Q$1205,Payments!$I$6:$I$1205,"Subscriptions",Payments!$E$6:$E$1205,B59,Payments!$P$6:$P$1205,">="&$C$6,Payments!$P$6:$P$1205,"<="&$C$7)+SUMIFS('Manual Log'!$E$6:$E$1005,'Manual Log'!$C$6:$C$1005,"Subscriptions",'Manual Log'!$D$6:$D$1005,B59,'Manual Log'!$B$6:$B$1005,">="&$C$6,'Manual Log'!$B$6:$B$1005,"<="&$C$7)) | E59: =IF(B59="","",C59-D59) | G59: =IF(Setup!$I$13="","",Setup!$I$13) | H59: =IF(G59="","",IF($C$5="Monthly",Setup!$J$13,Setup!$J$13*($C$7-$C$6+1)*12/365)) | I59: =IF(G59="","",SUMIFS(Payments!$Q$6:$Q$1205,Payments!$I$6:$I$1205,"Variable Exp",Payments!$E$6:$E$1205,G59,Payments!$P$6:$P$1205,">="&$C$6,Payments!$P$6:$P$1205,"<="&$C$7)+SUMIFS('Manual Log'!$E$6:$E$1005,'Manual Log'!$C$6:$C$1005,"Variable Exp",'Manual Log'!$D$6:$D$1005,G59,'Manual Log'!$B$6:$B$1005,">="&$C$6,'Manual Log'!$B$6:$B$1005,"<="&$C$7)) | J59: =IF(G59="","",H59-I59) | L59: =IFERROR(INDEX($Y$31:$Y$80,MATCH(LARGE($AA$31:$AA$80,9),$AA$31:$AA$80,0)),"") | M59: =IFERROR(INDEX($Z$31:$Z$80,MATCH(LARGE($AA$31:$AA$80,9),$AA$31:$AA$80,0)),"") | N59: =IFERROR(M59/$J$6,"") | V59: =IF($C$6+28*$V$29>$C$7,"",$C$6+28*$V$29) | W59: =IF(V59="","",SUMIFS(Payments!$Q$6:$Q$1205,Payments!$I$6:$I$1205,"<>Income",Payments!$I$6:$I$1205,"<>Savings",Payments!$P$6:$P$1205,">="&V59,Payments!$P$6:$P$1205,"<"&(V59+$V$29),Payments!$P$6:$P$1205,"<="&$C$7)+SUMIFS('Manual Log'!$E$6:$E$1005,'Manual Log'!$C$6:$C$1005,"<>Income",'Manual Log'!$C$6:$C$1005,"<>Savings",'Manual Log'!$C$6:$C$1005,"<>Transfer",'Manual Log'!$B$6:$B$1005,">="&V59,'Manual Log'!$B$6:$B$1005,"<"&(V59+$V$29),'Manual Log'!$B$6:$B$1005,"<="&$C$7)) | X59: =IF(V59="","",TEXT(V59,"ddd d mmm")) | Y59: =B55 | Z59: =D55 | AA59: =IF(OR(Y59="",N(Z59)<=0),"",Z59+ROW()/1000000) | AG59: =IFERROR(MATCH("Subscriptions|8",Setup!$L$25:$L$84,0),"")
B60: =IF(AG60="","",INDEX(Setup!$D$25:$D$84,AG60)) | C60: =IF(AG60="","",COUNTIFS(INDEX(Calc!$B$2:$BB$61,AG60,0),">="&$C$6,INDEX(Calc!$B$2:$BB$61,AG60,0),"<"&($C$7+1))*INDEX(Setup!$E$25:$E$84,AG60)) | D60: =IF(B60="","",SUMIFS(Payments!$Q$6:$Q$1205,Payments!$I$6:$I$1205,"Subscriptions",Payments!$E$6:$E$1205,B60,Payments!$P$6:$P$1205,">="&$C$6,Payments!$P$6:$P$1205,"<="&$C$7)+SUMIFS('Manual Log'!$E$6:$E$1005,'Manual Log'!$C$6:$C$1005,"Subscriptions",'Manual Log'!$D$6:$D$1005,B60,'Manual Log'!$B$6:$B$1005,">="&$C$6,'Manual Log'!$B$6:$B$1005,"<="&$C$7)) | E60: =IF(B60="","",C60-D60) | G60: =IF(Setup!$I$14="","",Setup!$I$14) | H60: =IF(G60="","",IF($C$5="Monthly",Setup!$J$14,Setup!$J$14*($C$7-$C$6+1)*12/365)) | I60: =IF(G60="","",SUMIFS(Payments!$Q$6:$Q$1205,Payments!$I$6:$I$1205,"Variable Exp",Payments!$E$6:$E$1205,G60,Payments!$P$6:$P$1205,">="&$C$6,Payments!$P$6:$P$1205,"<="&$C$7)+SUMIFS('Manual Log'!$E$6:$E$1005,'Manual Log'!$C$6:$C$1005,"Variable Exp",'Manual Log'!$D$6:$D$1005,G60,'Manual Log'!$B$6:$B$1005,">="&$C$6,'Manual Log'!$B$6:$B$1005,"<="&$C$7)) | J60: =IF(G60="","",H60-I60) | L60: =IFERROR(INDEX($Y$31:$Y$80,MATCH(LARGE($AA$31:$AA$80,10),$AA$31:$AA$80,0)),"") | M60: =IFERROR(INDEX($Z$31:$Z$80,MATCH(LARGE($AA$31:$AA$80,10),$AA$31:$AA$80,0)),"") | N60: =IFERROR(M60/$J$6,"") | V60: =IF($C$6+29*$V$29>$C$7,"",$C$6+29*$V$29) | W60: =IF(V60="","",SUMIFS(Payments!$Q$6:$Q$1205,Payments!$I$6:$I$1205,"<>Income",Payments!$I$6:$I$1205,"<>Savings",Payments!$P$6:$P$1205,">="&V60,Payments!$P$6:$P$1205,"<"&(V60+$V$29),Payments!$P$6:$P$1205,"<="&$C$7)+SUMIFS('Manual Log'!$E$6:$E$1005,'Manual Log'!$C$6:$C$1005,"<>Income",'Manual Log'!$C$6:$C$1005,"<>Savings",'Manual Log'!$C$6:$C$1005,"<>Transfer",'Manual Log'!$B$6:$B$1005,">="&V60,'Manual Log'!$B$6:$B$1005,"<"&(V60+$V$29),'Manual Log'!$B$6:$B$1005,"<="&$C$7)) | X60: =IF(V60="","",TEXT(V60,"ddd d mmm")) | Y60: =B56 | Z60: =D56 | AA60: =IF(OR(Y60="",N(Z60)<=0),"",Z60+ROW()/1000000) | AG60: =IFERROR(MATCH("Subscriptions|9",Setup!$L$25:$L$84,0),"")
B61: =IF(AG61="","",INDEX(Setup!$D$25:$D$84,AG61)) | C61: =IF(AG61="","",COUNTIFS(INDEX(Calc!$B$2:$BB$61,AG61,0),">="&$C$6,INDEX(Calc!$B$2:$BB$61,AG61,0),"<"&($C$7+1))*INDEX(Setup!$E$25:$E$84,AG61)) | D61: =IF(B61="","",SUMIFS(Payments!$Q$6:$Q$1205,Payments!$I$6:$I$1205,"Subscriptions",Payments!$E$6:$E$1205,B61,Payments!$P$6:$P$1205,">="&$C$6,Payments!$P$6:$P$1205,"<="&$C$7)+SUMIFS('Manual Log'!$E$6:$E$1005,'Manual Log'!$C$6:$C$1005,"Subscriptions",'Manual Log'!$D$6:$D$1005,B61,'Manual Log'!$B$6:$B$1005,">="&$C$6,'Manual Log'!$B$6:$B$1005,"<="&$C$7)) | E61: =IF(B61="","",C61-D61) | G61: =IF(Setup!$I$15="","",Setup!$I$15) | H61: =IF(G61="","",IF($C$5="Monthly",Setup!$J$15,Setup!$J$15*($C$7-$C$6+1)*12/365)) | I61: =IF(G61="","",SUMIFS(Payments!$Q$6:$Q$1205,Payments!$I$6:$I$1205,"Variable Exp",Payments!$E$6:$E$1205,G61,Payments!$P$6:$P$1205,">="&$C$6,Payments!$P$6:$P$1205,"<="&$C$7)+SUMIFS('Manual Log'!$E$6:$E$1005,'Manual Log'!$C$6:$C$1005,"Variable Exp",'Manual Log'!$D$6:$D$1005,G61,'Manual Log'!$B$6:$B$1005,">="&$C$6,'Manual Log'!$B$6:$B$1005,"<="&$C$7)) | J61: =IF(G61="","",H61-I61) | V61: =IF($C$6+30*$V$29>$C$7,"",$C$6+30*$V$29) | W61: =IF(V61="","",SUMIFS(Payments!$Q$6:$Q$1205,Payments!$I$6:$I$1205,"<>Income",Payments!$I$6:$I$1205,"<>Savings",Payments!$P$6:$P$1205,">="&V61,Payments!$P$6:$P$1205,"<"&(V61+$V$29),Payments!$P$6:$P$1205,"<="&$C$7)+SUMIFS('Manual Log'!$E$6:$E$1005,'Manual Log'!$C$6:$C$1005,"<>Income",'Manual Log'!$C$6:$C$1005,"<>Savings",'Manual Log'!$C$6:$C$1005,"<>Transfer",'Manual Log'!$B$6:$B$1005,">="&V61,'Manual Log'!$B$6:$B$1005,"<"&(V61+$V$29),'Manual Log'!$B$6:$B$1005,"<="&$C$7)) | X61: =IF(V61="","",TEXT(V61,"ddd d mmm")) | Y61: =B57 | Z61: =D57 | AA61: =IF(OR(Y61="",N(Z61)<=0),"",Z61+ROW()/1000000) | AG61: =IFERROR(MATCH("Subscriptions|10",Setup!$L$25:$L$84,0),"")
G62: =IF(Setup!$I$16="","",Setup!$I$16) | H62: =IF(G62="","",IF($C$5="Monthly",Setup!$J$16,Setup!$J$16*($C$7-$C$6+1)*12/365)) | I62: =IF(G62="","",SUMIFS(Payments!$Q$6:$Q$1205,Payments!$I$6:$I$1205,"Variable Exp",Payments!$E$6:$E$1205,G62,Payments!$P$6:$P$1205,">="&$C$6,Payments!$P$6:$P$1205,"<="&$C$7)+SUMIFS('Manual Log'!$E$6:$E$1005,'Manual Log'!$C$6:$C$1005,"Variable Exp",'Manual Log'!$D$6:$D$1005,G62,'Manual Log'!$B$6:$B$1005,">="&$C$6,'Manual Log'!$B$6:$B$1005,"<="&$C$7)) | J62: =IF(G62="","",H62-I62) | Y62: =B58 | Z62: =D58 | AA62: =IF(OR(Y62="",N(Z62)<=0),"",Z62+ROW()/1000000)
G63: =IF(Setup!$I$17="","",Setup!$I$17) | H63: =IF(G63="","",IF($C$5="Monthly",Setup!$J$17,Setup!$J$17*($C$7-$C$6+1)*12/365)) | I63: =IF(G63="","",SUMIFS(Payments!$Q$6:$Q$1205,Payments!$I$6:$I$1205,"Variable Exp",Payments!$E$6:$E$1205,G63,Payments!$P$6:$P$1205,">="&$C$6,Payments!$P$6:$P$1205,"<="&$C$7)+SUMIFS('Manual Log'!$E$6:$E$1005,'Manual Log'!$C$6:$C$1005,"Variable Exp",'Manual Log'!$D$6:$D$1005,G63,'Manual Log'!$B$6:$B$1005,">="&$C$6,'Manual Log'!$B$6:$B$1005,"<="&$C$7)) | J63: =IF(G63="","",H63-I63) | Y63: =B59 | Z63: =D59 | AA63: =IF(OR(Y63="",N(Z63)<=0),"",Z63+ROW()/1000000)
G64: =IF(Setup!$I$18="","",Setup!$I$18) | H64: =IF(G64="","",IF($C$5="Monthly",Setup!$J$18,Setup!$J$18*($C$7-$C$6+1)*12/365)) | I64: =IF(G64="","",SUMIFS(Payments!$Q$6:$Q$1205,Payments!$I$6:$I$1205,"Variable Exp",Payments!$E$6:$E$1205,G64,Payments!$P$6:$P$1205,">="&$C$6,Payments!$P$6:$P$1205,"<="&$C$7)+SUMIFS('Manual Log'!$E$6:$E$1005,'Manual Log'!$C$6:$C$1005,"Variable Exp",'Manual Log'!$D$6:$D$1005,G64,'Manual Log'!$B$6:$B$1005,">="&$C$6,'Manual Log'!$B$6:$B$1005,"<="&$C$7)) | J64: =IF(G64="","",H64-I64) | Y64: =B60 | Z64: =D60 | AA64: =IF(OR(Y64="",N(Z64)<=0),"",Z64+ROW()/1000000)
G65: =IF(Setup!$I$19="","",Setup!$I$19) | H65: =IF(G65="","",IF($C$5="Monthly",Setup!$J$19,Setup!$J$19*($C$7-$C$6+1)*12/365)) | I65: =IF(G65="","",SUMIFS(Payments!$Q$6:$Q$1205,Payments!$I$6:$I$1205,"Variable Exp",Payments!$E$6:$E$1205,G65,Payments!$P$6:$P$1205,">="&$C$6,Payments!$P$6:$P$1205,"<="&$C$7)+SUMIFS('Manual Log'!$E$6:$E$1005,'Manual Log'!$C$6:$C$1005,"Variable Exp",'Manual Log'!$D$6:$D$1005,G65,'Manual Log'!$B$6:$B$1005,">="&$C$6,'Manual Log'!$B$6:$B$1005,"<="&$C$7)) | J65: =IF(G65="","",H65-I65) | Y65: =B61 | Z65: =D61 | AA65: =IF(OR(Y65="",N(Z65)<=0),"",Z65+ROW()/1000000)
G66: =IF(Setup!$I$20="","",Setup!$I$20) | H66: =IF(G66="","",IF($C$5="Monthly",Setup!$J$20,Setup!$J$20*($C$7-$C$6+1)*12/365)) | I66: =IF(G66="","",SUMIFS(Payments!$Q$6:$Q$1205,Payments!$I$6:$I$1205,"Variable Exp",Payments!$E$6:$E$1205,G66,Payments!$P$6:$P$1205,">="&$C$6,Payments!$P$6:$P$1205,"<="&$C$7)+SUMIFS('Manual Log'!$E$6:$E$1005,'Manual Log'!$C$6:$C$1005,"Variable Exp",'Manual Log'!$D$6:$D$1005,G66,'Manual Log'!$B$6:$B$1005,">="&$C$6,'Manual Log'!$B$6:$B$1005,"<="&$C$7)) | J66: =IF(G66="","",H66-I66) | Y66: =G52 | Z66: =I52 | AA66: =IF(OR(Y66="",N(Z66)<=0),"",Z66+ROW()/1000000)
Y67: =G53 | Z67: =I53 | AA67: =IF(OR(Y67="",N(Z67)<=0),"",Z67+ROW()/1000000)
Y68: =G54 | Z68: =I54 | AA68: =IF(OR(Y68="",N(Z68)<=0),"",Z68+ROW()/1000000)
Y69: =G55 | Z69: =I55 | AA69: =IF(OR(Y69="",N(Z69)<=0),"",Z69+ROW()/1000000)
Y70: =G56 | Z70: =I56 | AA70: =IF(OR(Y70="",N(Z70)<=0),"",Z70+ROW()/1000000)
Y71: =G57 | Z71: =I57 | AA71: =IF(OR(Y71="",N(Z71)<=0),"",Z71+ROW()/1000000)
Y72: =G58 | Z72: =I58 | AA72: =IF(OR(Y72="",N(Z72)<=0),"",Z72+ROW()/1000000)
Y73: =G59 | Z73: =I59 | AA73: =IF(OR(Y73="",N(Z73)<=0),"",Z73+ROW()/1000000)
Y74: =G60 | Z74: =I60 | AA74: =IF(OR(Y74="",N(Z74)<=0),"",Z74+ROW()/1000000)
Y75: =G61 | Z75: =I61 | AA75: =IF(OR(Y75="",N(Z75)<=0),"",Z75+ROW()/1000000)
Y76: =G62 | Z76: =I62 | AA76: =IF(OR(Y76="",N(Z76)<=0),"",Z76+ROW()/1000000)
Y77: =G63 | Z77: =I63 | AA77: =IF(OR(Y77="",N(Z77)<=0),"",Z77+ROW()/1000000)
Y78: =G64 | Z78: =I64 | AA78: =IF(OR(Y78="",N(Z78)<=0),"",Z78+ROW()/1000000)
... Y80: =G66 | Z80: =I66 | AA80: =IF(OR(Y80="",N(Z80)<=0),"",Z80+ROW()/1000000)

Sheet Jan
B2: MONTHLY DASHBOARD | G2: MONTHLY SUMMARY | L2: INCOME | Q2: SAVINGS
B3: =TEXT(C6,"mmmm yyyy") | I3: BUDGET | J3: ACTUAL | L3: =J5 | N3: BUDGET | O3: PROGRESS | Q3: =J7 | S3: BUDGET | T3: PROGRESS
B4: Set the budget start date on the Setup sheet. | G4: Start balance | I4: =C10 | J4: =C10 | N4: =I5 | O4: =IFERROR(J5/I5,0) | S4: =I7 | T4: =IFERROR(J7/I7,0)
B5: Month # | C5: 1 | G5: + Total income | I5: =C14 | J5: =D14
B6: Start date | C6: =EDATE(Setup!$D$5,C5-1) | G6: – Total expenses | I6: =SUM(C16:C19) | J6: =SUM(D16:D19) | L6: EXPENSES | Q6: LEFT TO SPEND
B7: End date | C7: =EDATE(C6,1)-1 | G7: – Total savings | I7: =C15 | J7: =D15 | L7: =J6 | N7: BUDGET | O7: PROGRESS | Q7: =J9 | S7: BUDGET | T7: PROGRESS
B8: Days | C8: =C7-C6+1 | G8: End balance | I8: =I4+I5-I6-I7 | J8: =J4+J5-J6-J7 | N8: =I6 | O8: =IFERROR(J6/I6,0) | S8: =I9 | T8: =IFERROR(J9/I9,0)
B9: Start balance override | D9: ← leave blank to roll over | G9: Left to spend | I9: =I5-I6-I7 | J9: =J5-J6-J7
B10: Start balance | C10: =IF(C9<>"",C9,Setup!$D$6)
B12: BUDGET vs ACTUAL | G12: BUDGET vs ACTUAL | L12: EXPENSES BREAKDOWN | Q12: VARIABLE EXPENSES
B13: CATEGORY | C13: BUDGET | D13: ACTUAL | E13: PROGRESS
B14: Income | C14: =C30 | D14: =D30 | E14: =IFERROR(D14/C14,0)
B15: Savings | C15: =H30 | D15: =I30 | E15: =IFERROR(D15/C15,0)
B16: Bills | C16: =M30 | D16: =N30 | E16: =IFERROR(D16/C16,0)
B17: Debt | C17: =R30 | D17: =S30 | E17: =IFERROR(D17/C17,0)
B18: Subscriptions | C18: =C51 | D18: =D51 | E18: =IFERROR(D18/C18,0)
B19: Variable Exp. | C19: =H51 | D19: =I51 | E19: =IFERROR(D19/C19,0)
B20: REMAINING BUDGET (expenses) | E20: =SUM(C16:C19)-SUM(D16:D19)
B22: Pink text = over budget (expenses) or below target (income & savings).
B23: Actual = paid items in Payments + Manual Log entries in this period.
B27: INCOME | G27: SAVINGS | L27: BILLS | Q27: DEBT
B28: =D30 | G28: =I30 | L28: =N30 | Q28: =S30
B29: SUB-CATEGORY | C29: BUDGET | D29: ACTUAL | E29: DIFF | G29: SUB-CATEGORY | H29: BUDGET | I29: ACTUAL | J29: DIFF | L29: SUB-CATEGORY | M29: BUDGET | N29: ACTUAL | O29: REMAINING | Q29: SUB-CATEGORY | R29: BUDGET | S29: ACTUAL | T29: REMAINING | V29: =MAX(1,ROUNDUP(($C$7-$C$6+1)/31,0))
B30: TOTAL | C30: =SUM(C31:C40) | D30: =SUM(D31:D40) | E30: =SUM(E31:E40) | G30: TOTAL | H30: =SUM(H31:H40) | I30: =SUM(I31:I40) | J30: =SUM(J31:J40) | L30: TOTAL | M30: =SUM(M31:M45) | N30: =SUM(N31:N45) | O30: =SUM(O31:O45) | Q30: TOTAL | R30: =SUM(R31:R40) | S30: =SUM(S31:S40) | T30: =SUM(T31:T40)
B31: =IF(AC31="","",INDEX(Setup!$D$25:$D$84,AC31)) | C31: =IF(AC31="","",COUNTIFS(INDEX(Calc!$B$2:$BB$61,AC31,0),">="&$C$6,INDEX(Calc!$B$2:$BB$61,AC31,0),"<"&($C$7+1))*INDEX(Setup!$E$25:$E$84,AC31)) | D31: =IF(B31="","",SUMIFS(Payments!$Q$6:$Q$1205,Payments!$I$6:$I$1205,"Income",Payments!$E$6:$E$1205,B31,Payments!$P$6:$P$1205,">="&$C$6,Payments!$P$6:$P$1205,"<="&$C$7)+SUMIFS('Manual Log'!$E$6:$E$1005,'Manual Log'!$C$6:$C$1005,"Income",'Manual Log'!$D$6:$D$1005,B31,'Manual Log'!$B$6:$B$1005,">="&$C$6,'Manual Log'!$B$6:$B$1005,"<="&$C$7)) | E31: =IF(B31="","",D31-C31) | G31: =IF(AD31="","",INDEX(Setup!$D$25:$D$84,AD31)) | H31: =IF(AD31="","",COUNTIFS(INDEX(Calc!$B$2:$BB$61,AD31,0),">="&$C$6,INDEX(Calc!$B$2:$BB$61,AD31,0),"<"&($C$7+1))*INDEX(Setup!$E$25:$E$84,AD31)) | I31: =IF(G31="","",SUMIFS(Payments!$Q$6:$Q$1205,Payments!$I$6:$I$1205,"Savings",Payments!$E$6:$E$1205,G31,Payments!$P$6:$P$1205,">="&$C$6,Payments!$P$6:$P$1205,"<="&$C$7)+SUMIFS('Manual Log'!$E$6:$E$1005,'Manual Log'!$C$6:$C$1005,"Savings",'Manual Log'!$D$6:$D$1005,G31,'Manual Log'!$B$6:$B$1005,">="&$C$6,'Manual Log'!$B$6:$B$1005,"<="&$C$7)) | J31: =IF(G31="","",I31-H31) | L31: =IF(AE31="","",INDEX(Setup!$D$25:$D$84,AE31)) | M31: =IF(AE31="","",COUNTIFS(INDEX(Calc!$B$2:$BB$61,AE31,0),">="&$C$6,INDEX(Calc!$B$2:$BB$61,AE31,0),"<"&($C$7+1))*INDEX(Setup!$E$25:$E$84,AE31)) | N31: =IF(L31="","",SUMIFS(Payments!$Q$6:$Q$1205,Payments!$I$6:$I$1205,"Bills",Payments!$E$6:$E$1205,L31,Payments!$P$6:$P$1205,">="&$C$6,Payments!$P$6:$P$1205,"<="&$C$7)+SUMIFS('Manual Log'!$E$6:$E$1005,'Manual Log'!$C$6:$C$1005,"Bills",'Manual Log'!$D$6:$D$1005,L31,'Manual Log'!$B$6:$B$1005,">="&$C$6,'Manual Log'!$B$6:$B$1005,"<="&$C$7)) | O31: =IF(L31="","",M31-N31) | Q31: =IF(AF31="","",INDEX(Setup!$D$25:$D$84,AF31)) | R31: =IF(AF31="","",COUNTIFS(INDEX(Calc!$B$2:$BB$61,AF31,0),">="&$C$6,INDEX(Calc!$B$2:$BB$61,AF31,0),"<"&($C$7+1))*INDEX(Setup!$E$25:$E$84,AF31)) | S31: =IF(Q31="","",SUMIFS(Payments!$Q$6:$Q$1205,Payments!$I$6:$I$1205,"Debt",Payments!$E$6:$E$1205,Q31,Payments!$P$6:$P$1205,">="&$C$6,Payments!$P$6:$P$1205,"<="&$C$7)+SUMIFS('Manual Log'!$E$6:$E$1005,'Manual Log'!$C$6:$C$1005,"Debt",'Manual Log'!$D$6:$D$1005,Q31,'Manual Log'!$B$6:$B$1005,">="&$C$6,'Manual Log'!$B$6:$B$1005,"<="&$C$7)) | T31: =IF(Q31="","",R31-S31) | V31: =IF($C$6+0*$V$29>$C$7,"",$C$6+0*$V$29) | W31: =IF(V31="","",SUMIFS(Payments!$Q$6:$Q$1205,Payments!$I$6:$I$1205,"<>Income",Payments!$I$6:$I$1205,"<>Savings",Payments!$P$6:$P$1205,">="&V31,Payments!$P$6:$P$1205,"<"&(V31+$V$29),Payments!$P$6:$P$1205,"<="&$C$7)+SUMIFS('Manual Log'!$E$6:$E$1005,'Manual Log'!$C$6:$C$1005,"<>Income",'Manual Log'!$C$6:$C$1005,"<>Savings",'Manual Log'!$C$6:$C$1005,"<>Transfer",'Manual Log'!$B$6:$B$1005,">="&V31,'Manual Log'!$B$6:$B$1005,"<"&(V31+$V$29),'Manual Log'!$B$6:$B$1005,"<="&$C$7)) | X31: =IF(V31="","",TEXT(V31,"ddd d mmm")) | Y31: =L31 | Z31: =N31 | AA31: =IF(OR(Y31="",N(Z31)<=0),"",Z31+ROW()/1000000) | AC31: =IFERROR(MATCH("Income|1",Setup!$L$25:$L$84,0),"") | AD31: =IFERROR(MATCH("Savings|1",Setup!$L$25:$L$84,0),"") | AE31: =IFERROR(MATCH("Bills|1",Setup!$L$25:$L$84,0),"") | AF31: =IFERROR(MATCH("Debt|1",Setup!$L$25:$L$84,0),"")
B32: =IF(AC32="","",INDEX(Setup!$D$25:$D$84,AC32)) | C32: =IF(AC32="","",COUNTIFS(INDEX(Calc!$B$2:$BB$61,AC32,0),">="&$C$6,INDEX(Calc!$B$2:$BB$61,AC32,0),"<"&($C$7+1))*INDEX(Setup!$E$25:$E$84,AC32)) | D32: =IF(B32="","",SUMIFS(Payments!$Q$6:$Q$1205,Payments!$I$6:$I$1205,"Income",Payments!$E$6:$E$1205,B32,Payments!$P$6:$P$1205,">="&$C$6,Payments!$P$6:$P$1205,"<="&$C$7)+SUMIFS('Manual Log'!$E$6:$E$1005,'Manual Log'!$C$6:$C$1005,"Income",'Manual Log'!$D$6:$D$1005,B32,'Manual Log'!$B$6:$B$1005,">="&$C$6,'Manual Log'!$B$6:$B$1005,"<="&$C$7)) | E32: =IF(B32="","",D32-C32) | G32: =IF(AD32="","",INDEX(Setup!$D$25:$D$84,AD32)) | H32: =IF(AD32="","",COUNTIFS(INDEX(Calc!$B$2:$BB$61,AD32,0),">="&$C$6,INDEX(Calc!$B$2:$BB$61,AD32,0),"<"&($C$7+1))*INDEX(Setup!$E$25:$E$84,AD32)) | I32: =IF(G32="","",SUMIFS(Payments!$Q$6:$Q$1205,Payments!$I$6:$I$1205,"Savings",Payments!$E$6:$E$1205,G32,Payments!$P$6:$P$1205,">="&$C$6,Payments!$P$6:$P$1205,"<="&$C$7)+SUMIFS('Manual Log'!$E$6:$E$1005,'Manual Log'!$C$6:$C$1005,"Savings",'Manual Log'!$D$6:$D$1005,G32,'Manual Log'!$B$6:$B$1005,">="&$C$6,'Manual Log'!$B$6:$B$1005,"<="&$C$7)) | J32: =IF(G32="","",I32-H32) | L32: =IF(AE32="","",INDEX(Setup!$D$25:$D$84,AE32)) | M32: =IF(AE32="","",COUNTIFS(INDEX(Calc!$B$2:$BB$61,AE32,0),">="&$C$6,INDEX(Calc!$B$2:$BB$61,AE32,0),"<"&($C$7+1))*INDEX(Setup!$E$25:$E$84,AE32)) | N32: =IF(L32="","",SUMIFS(Payments!$Q$6:$Q$1205,Payments!$I$6:$I$1205,"Bills",Payments!$E$6:$E$1205,L32,Payments!$P$6:$P$1205,">="&$C$6,Payments!$P$6:$P$1205,"<="&$C$7)+SUMIFS('Manual Log'!$E$6:$E$1005,'Manual Log'!$C$6:$C$1005,"Bills",'Manual Log'!$D$6:$D$1005,L32,'Manual Log'!$B$6:$B$1005,">="&$C$6,'Manual Log'!$B$6:$B$1005,"<="&$C$7)) | O32: =IF(L32="","",M32-N32) | Q32: =IF(AF32="","",INDEX(Setup!$D$25:$D$84,AF32)) | R32: =IF(AF32="","",COUNTIFS(INDEX(Calc!$B$2:$BB$61,AF32,0),">="&$C$6,INDEX(Calc!$B$2:$BB$61,AF32,0),"<"&($C$7+1))*INDEX(Setup!$E$25:$E$84,AF32)) | S32: =IF(Q32="","",SUMIFS(Payments!$Q$6:$Q$1205,Payments!$I$6:$I$1205,"Debt",Payments!$E$6:$E$1205,Q32,Payments!$P$6:$P$1205,">="&$C$6,Payments!$P$6:$P$1205,"<="&$C$7)+SUMIFS('Manual Log'!$E$6:$E$1005,'Manual Log'!$C$6:$C$1005,"Debt",'Manual Log'!$D$6:$D$1005,Q32,'Manual Log'!$B$6:$B$1005,">="&$C$6,'Manual Log'!$B$6:$B$1005,"<="&$C$7)) | T32: =IF(Q32="","",R32-S32) | V32: =IF($C$6+1*$V$29>$C$7,"",$C$6+1*$V$29) | W32: =IF(V32="","",SUMIFS(Payments!$Q$6:$Q$1205,Payments!$I$6:$I$1205,"<>Income",Payments!$I$6:$I$1205,"<>Savings",Payments!$P$6:$P$1205,">="&V32,Payments!$P$6:$P$1205,"<"&(V32+$V$29),Payments!$P$6:$P$1205,"<="&$C$7)+SUMIFS('Manual Log'!$E$6:$E$1005,'Manual Log'!$C$6:$C$1005,"<>Income",'Manual Log'!$C$6:$C$1005,"<>Savings",'Manual Log'!$C$6:$C$1005,"<>Transfer",'Manual Log'!$B$6:$B$1005,">="&V32,'Manual Log'!$B$6:$B$1005,"<"&(V32+$V$29),'Manual Log'!$B$6:$B$1005,"<="&$C$7)) | X32: =IF(V32="","",TEXT(V32,"ddd d mmm")) | Y32: =L32 | Z32: =N32 | AA32: =IF(OR(Y32="",N(Z32)<=0),"",Z32+ROW()/1000000) | AC32: =IFERROR(MATCH("Income|2",Setup!$L$25:$L$84,0),"") | AD32: =IFERROR(MATCH("Savings|2",Setup!$L$25:$L$84,0),"") | AE32: =IFERROR(MATCH("Bills|2",Setup!$L$25:$L$84,0),"") | AF32: =IFERROR(MATCH("Debt|2",Setup!$L$25:$L$84,0),"")
B33: =IF(AC33="","",INDEX(Setup!$D$25:$D$84,AC33)) | C33: =IF(AC33="","",COUNTIFS(INDEX(Calc!$B$2:$BB$61,AC33,0),">="&$C$6,INDEX(Calc!$B$2:$BB$61,AC33,0),"<"&($C$7+1))*INDEX(Setup!$E$25:$E$84,AC33)) | D33: =IF(B33="","",SUMIFS(Payments!$Q$6:$Q$1205,Payments!$I$6:$I$1205,"Income",Payments!$E$6:$E$1205,B33,Payments!$P$6:$P$1205,">="&$C$6,Payments!$P$6:$P$1205,"<="&$C$7)+SUMIFS('Manual Log'!$E$6:$E$1005,'Manual Log'!$C$6:$C$1005,"Income",'Manual Log'!$D$6:$D$1005,B33,'Manual Log'!$B$6:$B$1005,">="&$C$6,'Manual Log'!$B$6:$B$1005,"<="&$C$7)) | E33: =IF(B33="","",D33-C33) | G33: =IF(AD33="","",INDEX(Setup!$D$25:$D$84,AD33)) | H33: =IF(AD33="","",COUNTIFS(INDEX(Calc!$B$2:$BB$61,AD33,0),">="&$C$6,INDEX(Calc!$B$2:$BB$61,AD33,0),"<"&($C$7+1))*INDEX(Setup!$E$25:$E$84,AD33)) | I33: =IF(G33="","",SUMIFS(Payments!$Q$6:$Q$1205,Payments!$I$6:$I$1205,"Savings",Payments!$E$6:$E$1205,G33,Payments!$P$6:$P$1205,">="&$C$6,Payments!$P$6:$P$1205,"<="&$C$7)+SUMIFS('Manual Log'!$E$6:$E$1005,'Manual Log'!$C$6:$C$1005,"Savings",'Manual Log'!$D$6:$D$1005,G33,'Manual Log'!$B$6:$B$1005,">="&$C$6,'Manual Log'!$B$6:$B$1005,"<="&$C$7)) | J33: =IF(G33="","",I33-H33) | L33: =IF(AE33="","",INDEX(Setup!$D$25:$D$84,AE33)) | M33: =IF(AE33="","",COUNTIFS(INDEX(Calc!$B$2:$BB$61,AE33,0),">="&$C$6,INDEX(Calc!$B$2:$BB$61,AE33,0),"<"&($C$7+1))*INDEX(Setup!$E$25:$E$84,AE33)) | N33: =IF(L33="","",SUMIFS(Payments!$Q$6:$Q$1205,Payments!$I$6:$I$1205,"Bills",Payments!$E$6:$E$1205,L33,Payments!$P$6:$P$1205,">="&$C$6,Payments!$P$6:$P$1205,"<="&$C$7)+SUMIFS('Manual Log'!$E$6:$E$1005,'Manual Log'!$C$6:$C$1005,"Bills",'Manual Log'!$D$6:$D$1005,L33,'Manual Log'!$B$6:$B$1005,">="&$C$6,'Manual Log'!$B$6:$B$1005,"<="&$C$7)) | O33: =IF(L33="","",M33-N33) | Q33: =IF(AF33="","",INDEX(Setup!$D$25:$D$84,AF33)) | R33: =IF(AF33="","",COUNTIFS(INDEX(Calc!$B$2:$BB$61,AF33,0),">="&$C$6,INDEX(Calc!$B$2:$BB$61,AF33,0),"<"&($C$7+1))*INDEX(Setup!$E$25:$E$84,AF33)) | S33: =IF(Q33="","",SUMIFS(Payments!$Q$6:$Q$1205,Payments!$I$6:$I$1205,"Debt",Payments!$E$6:$E$1205,Q33,Payments!$P$6:$P$1205,">="&$C$6,Payments!$P$6:$P$1205,"<="&$C$7)+SUMIFS('Manual Log'!$E$6:$E$1005,'Manual Log'!$C$6:$C$1005,"Debt",'Manual Log'!$D$6:$D$1005,Q33,'Manual Log'!$B$6:$B$1005,">="&$C$6,'Manual Log'!$B$6:$B$1005,"<="&$C$7)) | T33: =IF(Q33="","",R33-S33) | V33: =IF($C$6+2*$V$29>$C$7,"",$C$6+2*$V$29) | W33: =IF(V33="","",SUMIFS(Payments!$Q$6:$Q$1205,Payments!$I$6:$I$1205,"<>Income",Payments!$I$6:$I$1205,"<>Savings",Payments!$P$6:$P$1205,">="&V33,Payments!$P$6:$P$1205,"<"&(V33+$V$29),Payments!$P$6:$P$1205,"<="&$C$7)+SUMIFS('Manual Log'!$E$6:$E$1005,'Manual Log'!$C$6:$C$1005,"<>Income",'Manual Log'!$C$6:$C$1005,"<>Savings",'Manual Log'!$C$6:$C$1005,"<>Transfer",'Manual Log'!$B$6:$B$1005,">="&V33,'Manual Log'!$B$6:$B$1005,"<"&(V33+$V$29),'Manual Log'!$B$6:$B$1005,"<="&$C$7)) | X33: =IF(V33="","",TEXT(V33,"ddd d mmm")) | Y33: =L33 | Z33: =N33 | AA33: =IF(OR(Y33="",N(Z33)<=0),"",Z33+ROW()/1000000) | AC33: =IFERROR(MATCH("Income|3",Setup!$L$25:$L$84,0),"") | AD33: =IFERROR(MATCH("Savings|3",Setup!$L$25:$L$84,0),"") | AE33: =IFERROR(MATCH("Bills|3",Setup!$L$25:$L$84,0),"") | AF33: =IFERROR(MATCH("Debt|3",Setup!$L$25:$L$84,0),"")
B34: =IF(AC34="","",INDEX(Setup!$D$25:$D$84,AC34)) | C34: =IF(AC34="","",COUNTIFS(INDEX(Calc!$B$2:$BB$61,AC34,0),">="&$C$6,INDEX(Calc!$B$2:$BB$61,AC34,0),"<"&($C$7+1))*INDEX(Setup!$E$25:$E$84,AC34)) | D34: =IF(B34="","",SUMIFS(Payments!$Q$6:$Q$1205,Payments!$I$6:$I$1205,"Income",Payments!$E$6:$E$1205,B34,Payments!$P$6:$P$1205,">="&$C$6,Payments!$P$6:$P$1205,"<="&$C$7)+SUMIFS('Manual Log'!$E$6:$E$1005,'Manual Log'!$C$6:$C$1005,"Income",'Manual Log'!$D$6:$D$1005,B34,'Manual Log'!$B$6:$B$1005,">="&$C$6,'Manual Log'!$B$6:$B$1005,"<="&$C$7)) | E34: =IF(B34="","",D34-C34) | G34: =IF(AD34="","",INDEX(Setup!$D$25:$D$84,AD34)) | H34: =IF(AD34="","",COUNTIFS(INDEX(Calc!$B$2:$BB$61,AD34,0),">="&$C$6,INDEX(Calc!$B$2:$BB$61,AD34,0),"<"&($C$7+1))*INDEX(Setup!$E$25:$E$84,AD34)) | I34: =IF(G34="","",SUMIFS(Payments!$Q$6:$Q$1205,Payments!$I$6:$I$1205,"Savings",Payments!$E$6:$E$1205,G34,Payments!$P$6:$P$1205,">="&$C$6,Payments!$P$6:$P$1205,"<="&$C$7)+SUMIFS('Manual Log'!$E$6:$E$1005,'Manual Log'!$C$6:$C$1005,"Savings",'Manual Log'!$D$6:$D$1005,G34,'Manual Log'!$B$6:$B$1005,">="&$C$6,'Manual Log'!$B$6:$B$1005,"<="&$C$7)) | J34: =IF(G34="","",I34-H34) | L34: =IF(AE34="","",INDEX(Setup!$D$25:$D$84,AE34)) | M34: =IF(AE34="","",COUNTIFS(INDEX(Calc!$B$2:$BB$61,AE34,0),">="&$C$6,INDEX(Calc!$B$2:$BB$61,AE34,0),"<"&($C$7+1))*INDEX(Setup!$E$25:$E$84,AE34)) | N34: =IF(L34="","",SUMIFS(Payments!$Q$6:$Q$1205,Payments!$I$6:$I$1205,"Bills",Payments!$E$6:$E$1205,L34,Payments!$P$6:$P$1205,">="&$C$6,Payments!$P$6:$P$1205,"<="&$C$7)+SUMIFS('Manual Log'!$E$6:$E$1005,'Manual Log'!$C$6:$C$1005,"Bills",'Manual Log'!$D$6:$D$1005,L34,'Manual Log'!$B$6:$B$1005,">="&$C$6,'Manual Log'!$B$6:$B$1005,"<="&$C$7)) | O34: =IF(L34="","",M34-N34) | Q34: =IF(AF34="","",INDEX(Setup!$D$25:$D$84,AF34)) | R34: =IF(AF34="","",COUNTIFS(INDEX(Calc!$B$2:$BB$61,AF34,0),">="&$C$6,INDEX(Calc!$B$2:$BB$61,AF34,0),"<"&($C$7+1))*INDEX(Setup!$E$25:$E$84,AF34)) | S34: =IF(Q34="","",SUMIFS(Payments!$Q$6:$Q$1205,Payments!$I$6:$I$1205,"Debt",Payments!$E$6:$E$1205,Q34,Payments!$P$6:$P$1205,">="&$C$6,Payments!$P$6:$P$1205,"<="&$C$7)+SUMIFS('Manual Log'!$E$6:$E$1005,'Manual Log'!$C$6:$C$1005,"Debt",'Manual Log'!$D$6:$D$1005,Q34,'Manual Log'!$B$6:$B$1005,">="&$C$6,'Manual Log'!$B$6:$B$1005,"<="&$C$7)) | T34: =IF(Q34="","",R34-S34) | V34: =IF($C$6+3*$V$29>$C$7,"",$C$6+3*$V$29) | W34: =IF(V34="","",SUMIFS(Payments!$Q$6:$Q$1205,Payments!$I$6:$I$1205,"<>Income",Payments!$I$6:$I$1205,"<>Savings",Payments!$P$6:$P$1205,">="&V34,Payments!$P$6:$P$1205,"<"&(V34+$V$29),Payments!$P$6:$P$1205,"<="&$C$7)+SUMIFS('Manual Log'!$E$6:$E$1005,'Manual Log'!$C$6:$C$1005,"<>Income",'Manual Log'!$C$6:$C$1005,"<>Savings",'Manual Log'!$C$6:$C$1005,"<>Transfer",'Manual Log'!$B$6:$B$1005,">="&V34,'Manual Log'!$B$6:$B$1005,"<"&(V34+$V$29),'Manual Log'!$B$6:$B$1005,"<="&$C$7)) | X34: =IF(V34="","",TEXT(V34,"ddd d mmm")) | Y34: =L34 | Z34: =N34 | AA34: =IF(OR(Y34="",N(Z34)<=0),"",Z34+ROW()/1000000) | AC34: =IFERROR(MATCH("Income|4",Setup!$L$25:$L$84,0),"") | AD34: =IFERROR(MATCH("Savings|4",Setup!$L$25:$L$84,0),"") | AE34: =IFERROR(MATCH("Bills|4",Setup!$L$25:$L$84,0),"") | AF34: =IFERROR(MATCH("Debt|4",Setup!$L$25:$L$84,0),"")
B35: =IF(AC35="","",INDEX(Setup!$D$25:$D$84,AC35)) | C35: =IF(AC35="","",COUNTIFS(INDEX(Calc!$B$2:$BB$61,AC35,0),">="&$C$6,INDEX(Calc!$B$2:$BB$61,AC35,0),"<"&($C$7+1))*INDEX(Setup!$E$25:$E$84,AC35)) | D35: =IF(B35="","",SUMIFS(Payments!$Q$6:$Q$1205,Payments!$I$6:$I$1205,"Income",Payments!$E$6:$E$1205,B35,Payments!$P$6:$P$1205,">="&$C$6,Payments!$P$6:$P$1205,"<="&$C$7)+SUMIFS('Manual Log'!$E$6:$E$1005,'Manual Log'!$C$6:$C$1005,"Income",'Manual Log'!$D$6:$D$1005,B35,'Manual Log'!$B$6:$B$1005,">="&$C$6,'Manual Log'!$B$6:$B$1005,"<="&$C$7)) | E35: =IF(B35="","",D35-C35) | G35: =IF(AD35="","",INDEX(Setup!$D$25:$D$84,AD35)) | H35: =IF(AD35="","",COUNTIFS(INDEX(Calc!$B$2:$BB$61,AD35,0),">="&$C$6,INDEX(Calc!$B$2:$BB$61,AD35,0),"<"&($C$7+1))*INDEX(Setup!$E$25:$E$84,AD35)) | I35: =IF(G35="","",SUMIFS(Payments!$Q$6:$Q$1205,Payments!$I$6:$I$1205,"Savings",Payments!$E$6:$E$1205,G35,Payments!$P$6:$P$1205,">="&$C$6,Payments!$P$6:$P$1205,"<="&$C$7)+SUMIFS('Manual Log'!$E$6:$E$1005,'Manual Log'!$C$6:$C$1005,"Savings",'Manual Log'!$D$6:$D$1005,G35,'Manual Log'!$B$6:$B$1005,">="&$C$6,'Manual Log'!$B$6:$B$1005,"<="&$C$7)) | J35: =IF(G35="","",I35-H35) | L35: =IF(AE35="","",INDEX(Setup!$D$25:$D$84,AE35)) | M35: =IF(AE35="","",COUNTIFS(INDEX(Calc!$B$2:$BB$61,AE35,0),">="&$C$6,INDEX(Calc!$B$2:$BB$61,AE35,0),"<"&($C$7+1))*INDEX(Setup!$E$25:$E$84,AE35)) | N35: =IF(L35="","",SUMIFS(Payments!$Q$6:$Q$1205,Payments!$I$6:$I$1205,"Bills",Payments!$E$6:$E$1205,L35,Payments!$P$6:$P$1205,">="&$C$6,Payments!$P$6:$P$1205,"<="&$C$7)+SUMIFS('Manual Log'!$E$6:$E$1005,'Manual Log'!$C$6:$C$1005,"Bills",'Manual Log'!$D$6:$D$1005,L35,'Manual Log'!$B$6:$B$1005,">="&$C$6,'Manual Log'!$B$6:$B$1005,"<="&$C$7)) | O35: =IF(L35="","",M35-N35) | Q35: =IF(AF35="","",INDEX(Setup!$D$25:$D$84,AF35)) | R35: =IF(AF35="","",COUNTIFS(INDEX(Calc!$B$2:$BB$61,AF35,0),">="&$C$6,INDEX(Calc!$B$2:$BB$61,AF35,0),"<"&($C$7+1))*INDEX(Setup!$E$25:$E$84,AF35)) | S35: =IF(Q35="","",SUMIFS(Payments!$Q$6:$Q$1205,Payments!$I$6:$I$1205,"Debt",Payments!$E$6:$E$1205,Q35,Payments!$P$6:$P$1205,">="&$C$6,Payments!$P$6:$P$1205,"<="&$C$7)+SUMIFS('Manual Log'!$E$6:$E$1005,'Manual Log'!$C$6:$C$1005,"Debt",'Manual Log'!$D$6:$D$1005,Q35,'Manual Log'!$B$6:$B$1005,">="&$C$6,'Manual Log'!$B$6:$B$1005,"<="&$C$7)) | T35: =IF(Q35="","",R35-S35) | V35: =IF($C$6+4*$V$29>$C$7,"",$C$6+4*$V$29) | W35: =IF(V35="","",SUMIFS(Payments!$Q$6:$Q$1205,Payments!$I$6:$I$1205,"<>Income",Payments!$I$6:$I$1205,"<>Savings",Payments!$P$6:$P$1205,">="&V35,Payments!$P$6:$P$1205,"<"&(V35+$V$29),Payments!$P$6:$P$1205,"<="&$C$7)+SUMIFS('Manual Log'!$E$6:$E$1005,'Manual Log'!$C$6:$C$1005,"<>Income",'Manual Log'!$C$6:$C$1005,"<>Savings",'Manual Log'!$C$6:$C$1005,"<>Transfer",'Manual Log'!$B$6:$B$1005,">="&V35,'Manual Log'!$B$6:$B$1005,"<"&(V35+$V$29),'Manual Log'!$B$6:$B$1005,"<="&$C$7)) | X35: =IF(V35="","",TEXT(V35,"ddd d mmm")) | Y35: =L35 | Z35: =N35 | AA35: =IF(OR(Y35="",N(Z35)<=0),"",Z35+ROW()/1000000) | AC35: =IFERROR(MATCH("Income|5",Setup!$L$25:$L$84,0),"") | AD35: =IFERROR(MATCH("Savings|5",Setup!$L$25:$L$84,0),"") | AE35: =IFERROR(MATCH("Bills|5",Setup!$L$25:$L$84,0),"") | AF35: =IFERROR(MATCH("Debt|5",Setup!$L$25:$L$84,0),"")
B36: =IF(AC36="","",INDEX(Setup!$D$25:$D$84,AC36)) | C36: =IF(AC36="","",COUNTIFS(INDEX(Calc!$B$2:$BB$61,AC36,0),">="&$C$6,INDEX(Calc!$B$2:$BB$61,AC36,0),"<"&($C$7+1))*INDEX(Setup!$E$25:$E$84,AC36)) | D36: =IF(B36="","",SUMIFS(Payments!$Q$6:$Q$1205,Payments!$I$6:$I$1205,"Income",Payments!$E$6:$E$1205,B36,Payments!$P$6:$P$1205,">="&$C$6,Payments!$P$6:$P$1205,"<="&$C$7)+SUMIFS('Manual Log'!$E$6:$E$1005,'Manual Log'!$C$6:$C$1005,"Income",'Manual Log'!$D$6:$D$1005,B36,'Manual Log'!$B$6:$B$1005,">="&$C$6,'Manual Log'!$B$6:$B$1005,"<="&$C$7)) | E36: =IF(B36="","",D36-C36) | G36: =IF(AD36="","",INDEX(Setup!$D$25:$D$84,AD36)) | H36: =IF(AD36="","",COUNTIFS(INDEX(Calc!$B$2:$BB$61,AD36,0),">="&$C$6,INDEX(Calc!$B$2:$BB$61,AD36,0),"<"&($C$7+1))*INDEX(Setup!$E$25:$E$84,AD36)) | I36: =IF(G36="","",SUMIFS(Payments!$Q$6:$Q$1205,Payments!$I$6:$I$1205,"Savings",Payments!$E$6:$E$1205,G36,Payments!$P$6:$P$1205,">="&$C$6,Payments!$P$6:$P$1205,"<="&$C$7)+SUMIFS('Manual Log'!$E$6:$E$1005,'Manual Log'!$C$6:$C$1005,"Savings",'Manual Log'!$D$6:$D$1005,G36,'Manual Log'!$B$6:$B$1005,">="&$C$6,'Manual Log'!$B$6:$B$1005,"<="&$C$7)) | J36: =IF(G36="","",I36-H36) | L36: =IF(AE36="","",INDEX(Setup!$D$25:$D$84,AE36)) | M36: =IF(AE36="","",COUNTIFS(INDEX(Calc!$B$2:$BB$61,AE36,0),">="&$C$6,INDEX(Calc!$B$2:$BB$61,AE36,0),"<"&($C$7+1))*INDEX(Setup!$E$25:$E$84,AE36)) | N36: =IF(L36="","",SUMIFS(Payments!$Q$6:$Q$1205,Payments!$I$6:$I$1205,"Bills",Payments!$E$6:$E$1205,L36,Payments!$P$6:$P$1205,">="&$C$6,Payments!$P$6:$P$1205,"<="&$C$7)+SUMIFS('Manual Log'!$E$6:$E$1005,'Manual Log'!$C$6:$C$1005,"Bills",'Manual Log'!$D$6:$D$1005,L36,'Manual Log'!$B$6:$B$1005,">="&$C$6,'Manual Log'!$B$6:$B$1005,"<="&$C$7)) | O36: =IF(L36="","",M36-N36) | Q36: =IF(AF36="","",INDEX(Setup!$D$25:$D$84,AF36)) | R36: =IF(AF36="","",COUNTIFS(INDEX(Calc!$B$2:$BB$61,AF36,0),">="&$C$6,INDEX(Calc!$B$2:$BB$61,AF36,0),"<"&($C$7+1))*INDEX(Setup!$E$25:$E$84,AF36)) | S36: =IF(Q36="","",SUMIFS(Payments!$Q$6:$Q$1205,Payments!$I$6:$I$1205,"Debt",Payments!$E$6:$E$1205,Q36,Payments!$P$6:$P$1205,">="&$C$6,Payments!$P$6:$P$1205,"<="&$C$7)+SUMIFS('Manual Log'!$E$6:$E$1005,'Manual Log'!$C$6:$C$1005,"Debt",'Manual Log'!$D$6:$D$1005,Q36,'Manual Log'!$B$6:$B$1005,">="&$C$6,'Manual Log'!$B$6:$B$1005,"<="&$C$7)) | T36: =IF(Q36="","",R36-S36) | V36: =IF($C$6+5*$V$29>$C$7,"",$C$6+5*$V$29) | W36: =IF(V36="","",SUMIFS(Payments!$Q$6:$Q$1205,Payments!$I$6:$I$1205,"<>Income",Payments!$I$6:$I$1205,"<>Savings",Payments!$P$6:$P$1205,">="&V36,Payments!$P$6:$P$1205,"<"&(V36+$V$29),Payments!$P$6:$P$1205,"<="&$C$7)+SUMIFS('Manual Log'!$E$6:$E$1005,'Manual Log'!$C$6:$C$1005,"<>Income",'Manual Log'!$C$6:$C$1005,"<>Savings",'Manual Log'!$C$6:$C$1005,"<>Transfer",'Manual Log'!$B$6:$B$1005,">="&V36,'Manual Log'!$B$6:$B$1005,"<"&(V36+$V$29),'Manual Log'!$B$6:$B$1005,"<="&$C$7)) | X36: =IF(V36="","",TEXT(V36,"ddd d mmm")) | Y36: =L36 | Z36: =N36 | AA36: =IF(OR(Y36="",N(Z36)<=0),"",Z36+ROW()/1000000) | AC36: =IFERROR(MATCH("Income|6",Setup!$L$25:$L$84,0),"") | AD36: =IFERROR(MATCH("Savings|6",Setup!$L$25:$L$84,0),"") | AE36: =IFERROR(MATCH("Bills|6",Setup!$L$25:$L$84,0),"") | AF36: =IFERROR(MATCH("Debt|6",Setup!$L$25:$L$84,0),"")
B37: =IF(AC37="","",INDEX(Setup!$D$25:$D$84,AC37)) | C37: =IF(AC37="","",COUNTIFS(INDEX(Calc!$B$2:$BB$61,AC37,0),">="&$C$6,INDEX(Calc!$B$2:$BB$61,AC37,0),"<"&($C$7+1))*INDEX(Setup!$E$25:$E$84,AC37)) | D37: =IF(B37="","",SUMIFS(Payments!$Q$6:$Q$1205,Payments!$I$6:$I$1205,"Income",Payments!$E$6:$E$1205,B37,Payments!$P$6:$P$1205,">="&$C$6,Payments!$P$6:$P$1205,"<="&$C$7)+SUMIFS('Manual Log'!$E$6:$E$1005,'Manual Log'!$C$6:$C$1005,"Income",'Manual Log'!$D$6:$D$1005,B37,'Manual Log'!$B$6:$B$1005,">="&$C$6,'Manual Log'!$B$6:$B$1005,"<="&$C$7)) | E37: =IF(B37="","",D37-C37) | G37: =IF(AD37="","",INDEX(Setup!$D$25:$D$84,AD37)) | H37: =IF(AD37="","",COUNTIFS(INDEX(Calc!$B$2:$BB$61,AD37,0),">="&$C$6,INDEX(Calc!$B$2:$BB$61,AD37,0),"<"&($C$7+1))*INDEX(Setup!$E$25:$E$84,AD37)) | I37: =IF(G37="","",SUMIFS(Payments!$Q$6:$Q$1205,Payments!$I$6:$I$1205,"Savings",Payments!$E$6:$E$1205,G37,Payments!$P$6:$P$1205,">="&$C$6,Payments!$P$6:$P$1205,"<="&$C$7)+SUMIFS('Manual Log'!$E$6:$E$1005,'Manual Log'!$C$6:$C$1005,"Savings",'Manual Log'!$D$6:$D$1005,G37,'Manual Log'!$B$6:$B$1005,">="&$C$6,'Manual Log'!$B$6:$B$1005,"<="&$C$7)) | J37: =IF(G37="","",I37-H37) | L37: =IF(AE37="","",INDEX(Setup!$D$25:$D$84,AE37)) | M37: =IF(AE37="","",COUNTIFS(INDEX(Calc!$B$2:$BB$61,AE37,0),">="&$C$6,INDEX(Calc!$B$2:$BB$61,AE37,0),"<"&($C$7+1))*INDEX(Setup!$E$25:$E$84,AE37)) | N37: =IF(L37="","",SUMIFS(Payments!$Q$6:$Q$1205,Payments!$I$6:$I$1205,"Bills",Payments!$E$6:$E$1205,L37,Payments!$P$6:$P$1205,">="&$C$6,Payments!$P$6:$P$1205,"<="&$C$7)+SUMIFS('Manual Log'!$E$6:$E$1005,'Manual Log'!$C$6:$C$1005,"Bills",'Manual Log'!$D$6:$D$1005,L37,'Manual Log'!$B$6:$B$1005,">="&$C$6,'Manual Log'!$B$6:$B$1005,"<="&$C$7)) | O37: =IF(L37="","",M37-N37) | Q37: =IF(AF37="","",INDEX(Setup!$D$25:$D$84,AF37)) | R37: =IF(AF37="","",COUNTIFS(INDEX(Calc!$B$2:$BB$61,AF37,0),">="&$C$6,INDEX(Calc!$B$2:$BB$61,AF37,0),"<"&($C$7+1))*INDEX(Setup!$E$25:$E$84,AF37)) | S37: =IF(Q37="","",SUMIFS(Payments!$Q$6:$Q$1205,Payments!$I$6:$I$1205,"Debt",Payments!$E$6:$E$1205,Q37,Payments!$P$6:$P$1205,">="&$C$6,Payments!$P$6:$P$1205,"<="&$C$7)+SUMIFS('Manual Log'!$E$6:$E$1005,'Manual Log'!$C$6:$C$1005,"Debt",'Manual Log'!$D$6:$D$1005,Q37,'Manual Log'!$B$6:$B$1005,">="&$C$6,'Manual Log'!$B$6:$B$1005,"<="&$C$7)) | T37: =IF(Q37="","",R37-S37) | V37: =IF($C$6+6*$V$29>$C$7,"",$C$6+6*$V$29) | W37: =IF(V37="","",SUMIFS(Payments!$Q$6:$Q$1205,Payments!$I$6:$I$1205,"<>Income",Payments!$I$6:$I$1205,"<>Savings",Payments!$P$6:$P$1205,">="&V37,Payments!$P$6:$P$1205,"<"&(V37+$V$29),Payments!$P$6:$P$1205,"<="&$C$7)+SUMIFS('Manual Log'!$E$6:$E$1005,'Manual Log'!$C$6:$C$1005,"<>Income",'Manual Log'!$C$6:$C$1005,"<>Savings",'Manual Log'!$C$6:$C$1005,"<>Transfer",'Manual Log'!$B$6:$B$1005,">="&V37,'Manual Log'!$B$6:$B$1005,"<"&(V37+$V$29),'Manual Log'!$B$6:$B$1005,"<="&$C$7)) | X37: =IF(V37="","",TEXT(V37,"ddd d mmm")) | Y37: =L37 | Z37: =N37 | AA37: =IF(OR(Y37="",N(Z37)<=0),"",Z37+ROW()/1000000) | AC37: =IFERROR(MATCH("Income|7",Setup!$L$25:$L$84,0),"") | AD37: =IFERROR(MATCH("Savings|7",Setup!$L$25:$L$84,0),"") | AE37: =IFERROR(MATCH("Bills|7",Setup!$L$25:$L$84,0),"") | AF37: =IFERROR(MATCH("Debt|7",Setup!$L$25:$L$84,0),"")
